Workbook
Name \A: #REF!
Name \B: #REF!
Name \C: #REF!
Name \D: #REF!
Name \E: #REF!
Name \F: #REF!
Name \G: #REF!
Name \H: #REF!
Name \I: #REF!
Name \J: #REF!
Name \P: #REF!
Name \Q: #REF!
Name \R: #REF!
Name \S: #REF!
Name \X: #REF!
Name \Z: #REF!
Name _1___0Yazdırma_Al: #REF!
Name _1_0Yazdırma_Al: #REF!
Name _108CROMO: #REF!
Name _15___0Yazdırma_Al: #REF!
Name _16___0Yazdırma_Al: #REF!
Name _2____Yazdırma_Al: #REF!
Name _2Yazdırma_Al: #REF!
Name _4_0Yazdırma_Al: #REF!
Name _5_0Yazdırma_Al: #REF!
Name _6Yazdırma_Al: #REF!
Name _9._Analysis_of_net_debt: #REF!
Name _ANG1: #REF!
Name _ANG2: #REF!
Name _ANG3: #REF!
Name _ANG4: #REF!
Name _c: #REF!
Name _DAT1: #REF!
Name _DAT11: #REF!
Name _DAT3: #REF!
Name _DAT4: #REF!
Name _DAT5: #REF!
Name _DAT9: #REF!
Name _pan1: #REF!
Name _par1: #REF!
Name _PY1: #REF!
Name _PY2: #REF!
Name _tab3: #REF!
Name _Typ7: "Cost Centre"
Name _Typ8: "Expense/Income"
Name a: {"Werkdp_excl",#N/A,FALSE,"WERKdp"}
Name AAA: #REF!
Name aaaaaa: #REF!
Name Abweichung: #REF!
Name ACCCODE: #REF!
Name ACCCODE2: #REF!
Name actual: #REF!
Name ali: #REF!
Name ALUMINUM: #REF!
Name AMG: #REF!
Name ANGKEM1: #REF!
Name ANGKEM11: #REF!
Name ANGKEM12: #REF!
Name ANGKEM13: #REF!
Name ANGKEM14: #REF!

Sheet _com.sap.ip.bi.xl.hiddensheet

Sheet Finansal Raporlama AY
C3: AYLIK
C4: bin Avro | D4: Ciro | G4: Brüt Kar | J4: EBITDA | M4: Net Kar
D5: Gerçekleşme | E5: Bütçe - Gerçekleşme Fark | F5: % Değişim | G5: Gerçekleşme | H5: Bütçe - Gerçekleşme Fark | I5: % Değişim | J5: Gerçekleşme | K5: Bütçe - Gerçekleşme Fark | L5: % Değişim | M5: Gerçekleşme | N5: Bütçe - Gerçekleşme Fark | O5: % Değişim
C6: Toplam | D6: =SUM(D7:D14) | E6: =SUM(E7:E14) | F6: =(D6/(D6-E6))-1 | G6: =SUM(G7:G14) | H6: =SUM(H7:H14) | I6: =(G6/(G6-H6))-1 | J6: =SUM(J7:J14) | K6: =SUM(K7:K14) | L6: =(J6/(J6-K6))-1 | M6: =SUM(M7:M14) | N6: =SUM(N7:N14) | O6: =(M6/(M6-N6))-1
C7: İnci Holding | D7: ='A -Döviz'!AD9/1000 | E7: =('A -Döviz'!AD9-'A -Döviz'!AC9)/1000 | F7: =(D7/(D7-E7))-1 | G7: =('A -Döviz'!AD36)/1000 | H7: =('A -Döviz'!AD36-'A -Döviz'!AC36)/1000 | I7: =(G7/(G7-H7))-1 | J7: ='A -Döviz'!AD139/1000 | K7: =('A -Döviz'!AD139-'A -Döviz'!AC139)/1000 | L7: =(J7/(J7-K7))-1 | M7: ='A -Döviz'!AD215/1000 | N7: =('A -Döviz'!AD215-'A -Döviz'!AC215)/1000 | O7: =(M7/(M7-N7))-1
C8: ISM | D8: ='A -Döviz'!AD10/1000 | E8: =('A -Döviz'!AD10-'A -Döviz'!AC10)/1000 | F8: =(D8/(D8-E8))-1 | G8: =('A -Döviz'!AD37)/1000 | H8: =('A -Döviz'!AD37-'A -Döviz'!AC37)/1000 | I8: =(G8/(G8-H8))-1 | J8: ='A -Döviz'!AD140/1000 | K8: =('A -Döviz'!AD140-'A -Döviz'!AC140)/1000 | L8: =((J8/(J8-K8))-1) | M8: ='A -Döviz'!AD216/1000 | N8: =('A -Döviz'!AD216-'A -Döviz'!AC216)/1000 | O8: =((M8/(M8-N8))-1)
C9: İncitaş | D9: ='A -Döviz'!AD11/1000 | E9: =('A -Döviz'!AD11-'A -Döviz'!AC11)/1000 | F9: =(D9/(D9-E9))-1 | G9: =('A -Döviz'!AD38)/1000 | H9: =('A -Döviz'!AD38-'A -Döviz'!AC38)/1000 | I9: =(G9/(G9-H9))-1 | J9: ='A -Döviz'!AD141/1000 | K9: =('A -Döviz'!AD141-'A -Döviz'!AC141)/1000 | L9: =((J9/(J9-K9))-1) | M9: ='A -Döviz'!AD217/1000 | N9: =('A -Döviz'!AD217-'A -Döviz'!AC217)/1000 | O9: =((M9/(M9-N9))-1)
C10: İnci GS Yuasa | D10: ='A -Döviz'!AD12/1000 | E10: =('A -Döviz'!AD12-'A -Döviz'!AC12)/1000 | F10: =(D10/(D10-E10))-1 | G10: =('A -Döviz'!AD39)/1000 | H10: =('A -Döviz'!AD39-'A -Döviz'!AC39)/1000 | I10: =(G10/(G10-H10))-1 | J10: ='A -Döviz'!AD142/1000 | K10: =('A -Döviz'!AD142-'A -Döviz'!AC142)/1000 | L10: =(J10/(J10-K10))-1 | M10: ='A -Döviz'!AD218/1000 | N10: =('A -Döviz'!AD218-'A -Döviz'!AC218)/1000 | O10: =((M10/(M10-N10))-1)
C11: Yusen İnci Loj. | D11: ='A -Döviz'!AD13/1000 | E11: =('A -Döviz'!AD13-'A -Döviz'!AC13)/1000 | F11: =(D11/(D11-E11))-1 | G11: =('A -Döviz'!AD40)/1000 | H11: =('A -Döviz'!AD40-'A -Döviz'!AC40)/1000 | I11: =(G11/(G11-H11))-1 | J11: ='A -Döviz'!AD143/1000 | K11: =('A -Döviz'!AD143-'A -Döviz'!AC143)/1000 | L11: =(J11/(J11-K11))-1 | M11: ='A -Döviz'!AD219/1000 | N11: =('A -Döviz'!AD219-'A -Döviz'!AC219)/1000 | O11: =(M11/(M11-N11))-1
C12: Jantaş | D12: ='A -Döviz'!AD14/1000 | E12: =('A -Döviz'!AD14-'A -Döviz'!AC14)/1000 | F12: =(D12/(D12-E12))-1 | G12: =('A -Döviz'!AD41)/1000 | H12: =('A -Döviz'!AD41-'A -Döviz'!AC41)/1000 | I12: =(G12/(G12-H12))-1 | J12: ='A -Döviz'!AD144/1000 | K12: =('A -Döviz'!AD144-'A -Döviz'!AC144)/1000 | L12: =(J12/(J12-K12))-1 | M12: ='A -Döviz'!AD220/1000 | N12: =('A -Döviz'!AD220-'A -Döviz'!AC220)/1000 | O12: =(M12/(M12-N12))-1
C13: Çelik | D13: ='A -Döviz'!AD15/1000 | E13: =('A -Döviz'!AD15-'A -Döviz'!AC15)/1000 | F13: =(D13/(D13-E13))-1 | G13: =('A -Döviz'!AD42)/1000 | H13: =('A -Döviz'!AD42-'A -Döviz'!AC42)/1000 | I13: =(G13/(G13-H13))-1 | J13: ='A -Döviz'!AD145/1000 | K13: =('A -Döviz'!AD145-'A -Döviz'!AC145)/1000 | L13: =(J13/(J13-K13))-1 | M13: ='A -Döviz'!AD221/1000 | N13: =('A -Döviz'!AD221-'A -Döviz'!AC221)/1000 | O13: =(M13/(M13-N13))-1
C14: Alüminyum | D14: ='A -Döviz'!AD16/1000 | E14: =('A -Döviz'!AD16-'A -Döviz'!AC16)/1000 | F14: =(D14/(D14-E14))-1 | G14: =('A -Döviz'!AD43)/1000 | H14: =('A -Döviz'!AD43-'A -Döviz'!AC43)/1000 | I14: =(G14/(G14-H14))-1 | J14: ='A -Döviz'!AD146/1000 | K14: =('A -Döviz'!AD146-'A -Döviz'!AC146)/1000 | L14: =(J14/(J14-K14))-1 | M14: ='A -Döviz'!AD222/1000 | N14: =('A -Döviz'!AD222-'A -Döviz'!AC222)/1000 | O14: =(M14/(M14-N14))-1
C17: bin Avro | D17: Vergi | G17: Operasyonel Nakit | J17: Serbest Nakit | M17: Net Nakit
D18: Gerçekleşme | E18: Bütçe - Gerçekleşme Fark | F18: % Değişim | G18: Gerçekleşme | H18: Bütçe - Gerçekleşme Fark | I18: % Değişim | J18: Gerçekleşme | K18: Bütçe - Gerçekleşme Fark | L18: % Değişim | M18: Gerçekleşme | N18: Bütçe - Gerçekleşme Fark | O18: % Değişim
C19: Toplam | D19: =SUM(D20:D27) | E19: =SUM(E20:E27) | F19: =(D19/(D19-E19)) | G19: =SUM(G20:G27) | H19: =SUM(H20:H27) | I19: =((G19/(G19-H19))-1) | J19: =SUM(J20:J27) | K19: =SUM(K20:K27) | L19: =((J19/(J19-K19))-1) | M19: =SUM(M20:M27) | N19: =SUM(N20:N27) | O19: =(M19/(M19-N19))-1
C20: İnci Holding | D20: ='A -Döviz'!AA202/1000 | E20: =('A -Döviz'!AA202-'A -Döviz'!Z202)/1000 | F20: =-((D20/(D20-E20))-1) | G20: ='A -Döviz'!AA291/1000 | H20: =('A -Döviz'!AA291-'A -Döviz'!Z291)/1000 | I20: =((G20/(G20-H20))-1) | J20: ='A -Döviz'!AA304/1000 | K20: =('A -Döviz'!AA304-'A -Döviz'!Z304)/1000 | L20: =((J20/(J20-K20))-1) | M20: ='A -Döviz'!AA265/1000 | N20: =('A -Döviz'!AA265-'A -Döviz'!Z265)/1000 | O20: =(M20/(M20-N20))-1
C21: ISM | D21: ='A -Döviz'!AA203/1000 | E21: =('A -Döviz'!AA203-'A -Döviz'!Z203)/1000 | F21: =-((D21/(D21-E21))-1) | G21: ='A -Döviz'!AA292/1000 | H21: =('A -Döviz'!AA292-'A -Döviz'!Z292)/1000 | I21: =((G21/(G21-H21))-1) | J21: ='A -Döviz'!AA305/1000 | K21: =('A -Döviz'!AA305-'A -Döviz'!Z305)/1000 | L21: =((J21/(J21-K21))-1) | M21: ='A -Döviz'!AA266/1000 | N21: =('A -Döviz'!AA266-'A -Döviz'!Z266)/1000 | O21: =-((M21/(M21-N21))-1)
C22: İncitaş | D22: ='A -Döviz'!AA204/1000 | E22: =('A -Döviz'!AA204-'A -Döviz'!Z204)/1000 | F22: =-IFERROR((D22/(D22-E22))-1,0) | G22: ='A -Döviz'!AA293/1000 | H22: =('A -Döviz'!AA293-'A -Döviz'!Z293)/1000 | I22: =((G22/(G22-H22))-1) | J22: ='A -Döviz'!AA306/1000 | K22: =('A -Döviz'!AA306-'A -Döviz'!Z306)/1000 | L22: =((J22/(J22-K22))-1) | M22: ='A -Döviz'!AA267/1000 | N22: =('A -Döviz'!AA267-'A -Döviz'!Z267)/1000 | O22: =-((M22/(M22-N22))-1)
C23: İnci GS Yuasa | D23: ='A -Döviz'!AA205/1000 | E23: =('A -Döviz'!AA205-'A -Döviz'!Z205)/1000 | F23: 0 | G23: ='A -Döviz'!AA294/1000 | H23: =('A -Döviz'!AA294-'A -Döviz'!Z294)/1000 | I23: =((G23/(G23-H23))-1) | J23: ='A -Döviz'!AA307/1000 | K23: =('A -Döviz'!AA307-'A -Döviz'!Z307)/1000 | L23: =-((J23/(J23-K23))) | M23: ='A -Döviz'!AA268/1000 | N23: =('A -Döviz'!AA268-'A -Döviz'!Z268)/1000 | O23: =-((M23/(M23-N23))-1)
C24: Yusen İnci Loj. | D24: ='A -Döviz'!AA206/1000 | E24: =('A -Döviz'!AA206-'A -Döviz'!Z206)/1000 | F24: =-((D24/(D24-E24))-1) | G24: ='A -Döviz'!AA295/1000 | H24: =('A -Döviz'!AA295-'A -Döviz'!Z295)/1000 | I24: =(G24/(G24-H24))-1 | J24: ='A -Döviz'!AA308/1000 | K24: =('A -Döviz'!AA308-'A -Döviz'!Z308)/1000 | L24: =(J24/(J24-K24))-1 | M24: ='A -Döviz'!AA269/1000 | N24: =('A -Döviz'!AA269-'A -Döviz'!Z269)/1000 | O24: =(M24/(M24-N24))-1
C25: Jantaş | D25: ='A -Döviz'!AA207/1000 | E25: =('A -Döviz'!AA207-'A -Döviz'!Z207)/1000 | F25: =-((D25/(D25-E25))-1) | G25: ='A -Döviz'!AA296/1000 | H25: =('A -Döviz'!AA296-'A -Döviz'!Z296)/1000 | I25: =((G25/(G25-H25))-1) | J25: ='A -Döviz'!AA309/1000 | K25: =('A -Döviz'!AA309-'A -Döviz'!Z309)/1000 | L25: =((J25/(J25-K25))-1) | M25: ='A -Döviz'!AA270/1000 | N25: =('A -Döviz'!AA270-'A -Döviz'!Z270)/1000 | O25: =(M25/(M25-N25))-1
C26: Çelik | D26: ='A -Döviz'!AA208/1000 | E26: =('A -Döviz'!AA208-'A -Döviz'!Z208)/1000 | F26: =-((D26/(D26-E26))-1) | G26: ='A -Döviz'!AA297/1000 | H26: =('A -Döviz'!AA297-'A -Döviz'!Z297)/1000 | I26: =((G26/(G26-H26))-1) | J26: ='A -Döviz'!AA310/1000 | K26: =('A -Döviz'!AA310-'A -Döviz'!Z310)/1000 | L26: =((J26/(J26-K26))-1) | M26: ='A -Döviz'!AA271/1000 | N26: =('A -Döviz'!AA271-'A -Döviz'!Z271)/1000 | O26: =(M26/(M26-N26))-1
C27: Alüminyum | D27: ='A -Döviz'!AA209/1000 | E27: =('A -Döviz'!AA209-'A -Döviz'!Z209)/1000 | F27: =-((D27/(D27-E27))-1) | G27: ='A -Döviz'!AA298/1000 | H27: =('A -Döviz'!AA298-'A -Döviz'!Z298)/1000 | I27: =((G27/(G27-H27))-1) | J27: ='A -Döviz'!AA311/1000 | K27: =('A -Döviz'!AA311-'A -Döviz'!Z311)/1000 | L27: =((J27/(J27-K27))-1) | M27: ='A -Döviz'!AA272/1000 | N27: =('A -Döviz'!AA272-'A -Döviz'!Z272)/1000 | O27: =(M27/(M27-N27))-1
D30: Faaliyet Giderleri Marjı | F30: Brüt Kar Marjı | H30: EBITDA Marjı | J30: Net Kar Marjı | L30: Operasyonel Nakit Marjı | N30: Serbest Nakit Marjı
D31: Gerçekleşme | E31: Bütçe - Gerçekleşme Fark | F31: Gerçekleşme | G31: Bütçe - Gerçekleşme Fark | H31: Gerçekleşme | I31: Bütçe - Gerçekleşme Fark | J31: Gerçekleşme | K31: Bütçe - Gerçekleşme Fark | L31: Gerçekleşme | M31: Bütçe - Gerçekleşme Fark | N31: Gerçekleşme | O31: Bütçe - Gerçekleşme Fark
C33: İnci Holding | D33: ='A -Döviz'!AA102 | E33: =-('A -Döviz'!AA102-'A -Döviz'!Z102) | F33: ='A -Döviz'!AA79 | G33: ='A -Döviz'!AA79-'A -Döviz'!Z79 | H33: ='A -Döviz'!AA150 | I33: ='A -Döviz'!AA150-'A -Döviz'!Z150 | J33: ='A -Döviz'!AA226 | K33: ='A -Döviz'!AA226-'A -Döviz'!Z226 | L33: ='A -Döviz'!AA291/'A -Döviz'!AA9 | M33: =L33-('A -Döviz'!Z291/'A -Döviz'!Z9) | N33: ='A -Döviz'!AA304/'A -Döviz'!AA9 | O33: =N33-'A -Döviz'!Z304/'A -Döviz'!Z9
C34: ISM | D34: ='A -Döviz'!AA103 | E34: =-('A -Döviz'!AA103-'A -Döviz'!Z103) | F34: ='A -Döviz'!AA80 | G34: ='A -Döviz'!AA80-'A -Döviz'!Z80 | H34: ='A -Döviz'!AA151 | I34: ='A -Döviz'!AA151-'A -Döviz'!Z151 | J34: ='A -Döviz'!AA227 | K34: ='A -Döviz'!AA227-'A -Döviz'!Z227 | L34: ='A -Döviz'!AA292/'A -Döviz'!AA10 | M34: =L34-('A -Döviz'!Z292/'A -Döviz'!Z10) | N34: ='A -Döviz'!AA305/'A -Döviz'!AA10 | O34: =N34-'A -Döviz'!Z305/'A -Döviz'!Z10
C35: İncitaş | D35: ='A -Döviz'!AA104 | E35: =-('A -Döviz'!AA104-'A -Döviz'!Z104) | F35: ='A -Döviz'!AA81 | G35: ='A -Döviz'!AA81-'A -Döviz'!Z81 | H35: ='A -Döviz'!AA152 | I35: ='A -Döviz'!AA152-'A -Döviz'!Z152 | J35: ='A -Döviz'!AA228 | K35: ='A -Döviz'!AA228-'A -Döviz'!Z228 | L35: ='A -Döviz'!AA293/'A -Döviz'!AA11 | M35: =L35-('A -Döviz'!Z293/'A -Döviz'!Z11) | N35: ='A -Döviz'!AA306/'A -Döviz'!AA11 | O35: =N35-'A -Döviz'!Z306/'A -Döviz'!Z11
C36: İnci GS Yuasa | D36: ='A -Döviz'!AA105 | E36: =-('A -Döviz'!AA105-'A -Döviz'!Z105) | F36: ='A -Döviz'!AA82 | G36: ='A -Döviz'!AA82-'A -Döviz'!Z82 | H36: ='A -Döviz'!AA153 | I36: ='A -Döviz'!AA153-'A -Döviz'!Z153 | J36: ='A -Döviz'!AA229 | K36: ='A -Döviz'!AA229-'A -Döviz'!Z229 | L36: ='A -Döviz'!AA294/'A -Döviz'!AA12 | M36: =L36-('A -Döviz'!Z294/'A -Döviz'!Z12) | N36: ='A -Döviz'!AA307/'A -Döviz'!AA12 | O36: =N36-'A -Döviz'!Z307/'A -Döviz'!Z12
C37: Yusen İnci Loj. | D37: ='A -Döviz'!AA106 | E37: =-('A -Döviz'!AA106-'A -Döviz'!Z106) | F37: ='A -Döviz'!AA83 | G37: ='A -Döviz'!AA83-'A -Döviz'!Z83 | H37: ='A -Döviz'!AA154 | I37: ='A -Döviz'!AA154-'A -Döviz'!Z154 | J37: ='A -Döviz'!AA230 | K37: ='A -Döviz'!AA230-'A -Döviz'!Z230 | L37: ='A -Döviz'!AA295/'A -Döviz'!AA13 | M37: =L37-('A -Döviz'!Z295/'A -Döviz'!Z13) | N37: ='A -Döviz'!AA308/'A -Döviz'!AA13 | O37: =N37-'A -Döviz'!Z308/'A -Döviz'!Z13
C38: Jantaş | D38: ='A -Döviz'!AA107 | E38: =-('A -Döviz'!AA107-'A -Döviz'!Z107) | F38: ='A -Döviz'!AA84 | G38: ='A -Döviz'!AA84-'A -Döviz'!Z84 | H38: ='A -Döviz'!AA155 | I38: ='A -Döviz'!AA155-'A -Döviz'!Z155 | J38: ='A -Döviz'!AA231 | K38: ='A -Döviz'!AA231-'A -Döviz'!Z231 | L38: ='A -Döviz'!AA296/'A -Döviz'!AA14 | M38: =L38-('A -Döviz'!Z296/'A -Döviz'!Z14) | N38: ='A -Döviz'!AA309/'A -Döviz'!AA14 | O38: =N38-'A -Döviz'!Z309/'A -Döviz'!Z14
C39: Çelik | D39: ='A -Döviz'!AA108 | E39: =-('A -Döviz'!AA108-'A -Döviz'!Z108) | F39: ='A -Döviz'!AA85 | G39: ='A -Döviz'!AA85-'A -Döviz'!Z85 | H39: ='A -Döviz'!AA156 | I39: ='A -Döviz'!AA156-'A -Döviz'!Z156 | J39: ='A -Döviz'!AA232 | K39: ='A -Döviz'!AA232-'A -Döviz'!Z232 | L39: ='A -Döviz'!AA297/'A -Döviz'!AA15 | M39: =L39-('A -Döviz'!Z297/'A -Döviz'!Z15) | N39: ='A -Döviz'!AA310/'A -Döviz'!AA15 | O39: =N39-'A -Döviz'!Z310/'A -Döviz'!Z15
C40: Alüminyum | D40: ='A -Döviz'!AA109 | E40: =-('A -Döviz'!AA109-'A -Döviz'!Z109) | F40: ='A -Döviz'!AA86 | G40: ='A -Döviz'!AA86-'A -Döviz'!Z86 | H40: ='A -Döviz'!AA157 | I40: ='A -Döviz'!AA157-'A -Döviz'!Z157 | J40: ='A -Döviz'!AA233 | K40: ='A -Döviz'!AA233-'A -Döviz'!Z233 | L40: ='A -Döviz'!AA298/'A -Döviz'!AA16 | M40: =L40-('A -Döviz'!Z298/'A -Döviz'!Z16) | N40: ='A -Döviz'!AA311/'A -Döviz'!AA16 | O40: =N40-'A -Döviz'!Z311/'A -Döviz'!Z16
D64: Ciro | G64: EBITDA | K64: Net Kar
D65: Gerçekleşme | E65: % | G65: Gerçekleşme | I65: % | K65: Gerçekleşme | M65: %
C66: Ciro | D66: 55 | G66: 55 | K66: 55
C67: Adet | D67: 12 | E67: =D67/$D$66 | G67: 12 | H67: =G67/$D$66 | K67: 12 | M67: =K67/$K$66
C68: Fiyat | D68: 9 | E68: =D68/$D$66 | G68: 9 | H68: =G68/$D$66 | K68: 9 | M68: =K68/$K$66
C69: Miks | D69: 8 | E69: =D69/$D$66 | G69: 8 | H69: =G69/$D$66 | K69: 8 | M69: =K69/$K$66
C70: Ham Madde | D70: 5 | E70: =D70/$D$66 | G70: 5 | H70: =G70/$D$66 | K70: 5 | M70: =K70/$K$66
C71: Enerji | D71: 4 | E71: =D71/$D$66 | G71: 4 | H71: =G71/$D$66 | K71: 4 | M71: =K71/$K$66
C72: Döviz | D72: 3 | E72: =D72/$D$66 | G72: 3 | H72: =G72/$D$66 | K72: 3 | M72: =K72/$K$66
C73: Enflasyon | D73: 3 | E73: =D73/$D$66 | G73: 3 | H73: =G73/$D$66 | K73: 3 | M73: =K73/$K$66

Sheet Finansal Raporlama KÜM
C3: KÜMÜLATİF
C4: bin Avro | D4: Ciro | G4: Brüt Kar | J4: EBITDA | M4: Net Kar
D5: Gerçekleşme | E5: Bütçe - Gerçekleşme Fark | F5: % Değişim | G5: Gerçekleşme | H5: Bütçe - Gerçekleşme Fark | I5: % Değişim | J5: Gerçekleşme | K5: Bütçe - Gerçekleşme Fark | L5: % Değişim | M5: Gerçekleşme | N5: Bütçe - Gerçekleşme Fark | O5: % Değişim
C6: Toplam | D6: =SUM(D7:D14) | E6: =SUM(E7:E14) | F6: =(D6/(D6-E6))-1 | G6: =SUM(G7:G14) | H6: =SUM(H7:H14) | I6: =(G6/(G6-H6))-1 | J6: =SUM(J7:J14) | K6: =SUM(K7:K14) | L6: =(J6/(J6-K6))-1 | M6: =SUM(M7:M14) | N6: =SUM(N7:N14) | O6: =(M6/(M6-N6))-1
C7: İnci Holding | D7: ='C-Döviz'!AJ9/1000 | E7: =('C-Döviz'!AJ9-'C-Döviz'!Z9)/1000 | F7: =(D7/(D7-E7))-1 | G7: =('C-Döviz'!AJ36)/1000 | H7: =('C-Döviz'!AJ36-'C-Döviz'!Z36)/1000 | I7: =(G7/(G7-H7))-1 | J7: ='C-Döviz'!AJ139/1000 | K7: =('C-Döviz'!AJ139-'C-Döviz'!Z139)/1000 | L7: =(J7/(J7-K7))-1 | M7: ='C-Döviz'!AJ215/1000 | N7: =('C-Döviz'!AJ215-'C-Döviz'!Z215)/1000 | O7: =(M7/(M7-N7))-1
C8: ISM | D8: ='C-Döviz'!AJ10/1000 | E8: =('C-Döviz'!AJ10-'C-Döviz'!Z10)/1000 | F8: =(D8/(D8-E8))-1 | G8: =('C-Döviz'!AJ37)/1000 | H8: =('C-Döviz'!AJ37-'C-Döviz'!Z37)/1000 | I8: =(G8/(G8-H8))-1 | J8: ='C-Döviz'!AJ140/1000 | K8: =('C-Döviz'!AJ140-'C-Döviz'!Z140)/1000 | L8: =(J8/(J8-K8))-1 | M8: ='C-Döviz'!AJ216/1000 | N8: =('C-Döviz'!AJ216-'C-Döviz'!Z216)/1000 | O8: =(M8/(M8-N8))-1
C9: İncitaş | D9: ='C-Döviz'!AJ11/1000 | E9: =('C-Döviz'!AJ11-'C-Döviz'!Z11)/1000 | F9: =(D9/(D9-E9))-1 | G9: =('C-Döviz'!AJ38)/1000 | H9: =('C-Döviz'!AJ38-'C-Döviz'!Z38)/1000 | I9: =(G9/(G9-H9))-1 | J9: ='C-Döviz'!AJ141/1000 | K9: =('C-Döviz'!AJ141-'C-Döviz'!Z141)/1000 | L9: =((J9/(J9-K9))-1) | M9: ='C-Döviz'!AJ217/1000 | N9: =('C-Döviz'!AJ217-'C-Döviz'!Z217)/1000 | O9: =-((M9/(M9-N9))-1)
C10: İnci GS Yuasa | D10: ='C-Döviz'!AJ12/1000 | E10: =('C-Döviz'!AJ12-'C-Döviz'!Z12)/1000 | F10: =(D10/(D10-E10))-1 | G10: =('C-Döviz'!AJ39)/1000 | H10: =('C-Döviz'!AJ39-'C-Döviz'!Z39)/1000 | I10: =(G10/(G10-H10))-1 | J10: ='C-Döviz'!AJ142/1000 | K10: =('C-Döviz'!AJ142-'C-Döviz'!Z142)/1000 | L10: =(J10/(J10-K10))-1 | M10: ='C-Döviz'!AJ218/1000 | N10: =('C-Döviz'!AJ218-'C-Döviz'!Z218)/1000 | O10: =-((M10/(M10-N10))-1)
C11: Yusen İnci Loj. | D11: ='C-Döviz'!AJ13/1000 | E11: =('C-Döviz'!AJ13-'C-Döviz'!Z13)/1000 | F11: =(D11/(D11-E11))-1 | G11: =('C-Döviz'!AJ40)/1000 | H11: =('C-Döviz'!AJ40-'C-Döviz'!Z40)/1000 | I11: =(G11/(G11-H11))-1 | J11: ='C-Döviz'!AJ143/1000 | K11: =('C-Döviz'!AJ143-'C-Döviz'!Z143)/1000 | L11: =(J11/(J11-K11))-1 | M11: ='C-Döviz'!AJ219/1000 | N11: =('C-Döviz'!AJ219-'C-Döviz'!Z219)/1000 | O11: =(M11/(M11-N11))-1
C12: Jantaş | D12: ='C-Döviz'!AJ14/1000 | E12: =('C-Döviz'!AJ14-'C-Döviz'!Z14)/1000 | F12: =(D12/(D12-E12))-1 | G12: =('C-Döviz'!AJ41)/1000 | H12: =('C-Döviz'!AJ41-'C-Döviz'!Z41)/1000 | I12: =(G12/(G12-H12))-1 | J12: ='C-Döviz'!AJ144/1000 | K12: =('C-Döviz'!AJ144-'C-Döviz'!Z144)/1000 | L12: =(J12/(J12-K12))-1 | M12: ='C-Döviz'!AJ220/1000 | N12: =('C-Döviz'!AJ220-'C-Döviz'!Z220)/1000 | O12: =(M12/(M12-N12))-1
C13: Çelik | D13: ='C-Döviz'!AJ15/1000 | E13: =('C-Döviz'!AJ15-'C-Döviz'!Z15)/1000 | F13: =(D13/(D13-E13))-1 | G13: =('C-Döviz'!AJ42)/1000 | H13: =('C-Döviz'!AJ42-'C-Döviz'!Z42)/1000 | I13: =(G13/(G13-H13))-1 | J13: ='C-Döviz'!AJ145/1000 | K13: =('C-Döviz'!AJ145-'C-Döviz'!Z145)/1000 | L13: =(J13/(J13-K13))-1 | M13: ='C-Döviz'!AJ221/1000 | N13: =('C-Döviz'!AJ221-'C-Döviz'!Z221)/1000 | O13: =(M13/(M13-N13))-1
C14: Alüminyum | D14: ='C-Döviz'!AJ16/1000 | E14: =('C-Döviz'!AJ16-'C-Döviz'!Z16)/1000 | F14: =(D14/(D14-E14))-1 | G14: =('C-Döviz'!AJ43)/1000 | H14: =('C-Döviz'!AJ43-'C-Döviz'!Z43)/1000 | I14: =(G14/(G14-H14))-1 | J14: ='C-Döviz'!AJ146/1000 | K14: =('C-Döviz'!AJ146-'C-Döviz'!Z146)/1000 | L14: =(J14/(J14-K14))-1 | M14: ='C-Döviz'!AJ222/1000 | N14: =('C-Döviz'!AJ222-'C-Döviz'!Z222)/1000 | O14: =(M14/(M14-N14))-1
C17: bin Avro | D17: Vergi | G17: Operasyonel Nakit | J17: Serbest Nakit | M17: Net Nakit
D18: Gerçekleşme | E18: Bütçe - Gerçekleşme Fark | F18: % Değişim | G18: Gerçekleşme | H18: Bütçe - Gerçekleşme Fark | I18: % Değişim | J18: Gerçekleşme | K18: Bütçe - Gerçekleşme Fark | L18: % Değişim | M18: Gerçekleşme | N18: Bütçe - Gerçekleşme Fark | O18: % Değişim
C19: Toplam | D19: =SUM(D20:D27) | E19: =SUM(E20:E27) | F19: =(D19/(D19-E19))-1 | G19: =SUM(G20:G27) | H19: =SUM(H20:H27) | I19: =((G19/(G19-H19))-1) | J19: =SUM(J20:J27) | K19: =SUM(K20:K27) | L19: =((J19/(J19-K19))-1) | M19: =SUM(M20:M27) | N19: =SUM(N20:N27) | O19: =(M19/(M19-N19))-1
C20: İnci Holding | D20: ='C-Döviz'!AJ202/1000 | E20: =('C-Döviz'!AJ202-'C-Döviz'!Z202)/1000 | F20: =-((D20/(D20-E20))-1) | G20: ='C-Döviz'!AJ291/1000 | H20: =('C-Döviz'!AA291-'C-Döviz'!Z291)/1000 | I20: =(G20/(G20-H20))-1 | J20: ='C-Döviz'!AJ304/1000 | K20: =('C-Döviz'!AA304-'C-Döviz'!Z304)/1000 | L20: =(J20/(J20-K20))-1 | M20: ='C-Döviz'!AA265/1000 | N20: =M20-'C-Döviz'!Z265/1000 | O20: =(M20/(M20-N20))-1
C21: ISM | D21: ='C-Döviz'!AJ203/1000 | E21: =('C-Döviz'!AJ203-'C-Döviz'!Z203)/1000 | F21: =-((D21/(D21-E21))-1) | G21: ='C-Döviz'!AJ292/1000 | H21: =('C-Döviz'!AA292-'C-Döviz'!Z292)/1000 | I21: =((G21/(G21-H21))-1) | J21: ='C-Döviz'!AJ305/1000 | K21: =('C-Döviz'!AA305-'C-Döviz'!Z305)/1000 | L21: =((J21/(J21-K21))-1) | M21: ='C-Döviz'!AA266/1000 | N21: =M21-'C-Döviz'!Z266/1000 | O21: =-((M21/(M21-N21))-1)
C22: İncitaş | D22: ='C-Döviz'!AJ204/1000 | E22: =('C-Döviz'!AJ204-'C-Döviz'!Z204)/1000 | F22: =-((D22/(D22-E22))-1) | G22: ='C-Döviz'!AJ293/1000 | H22: =('C-Döviz'!AA293-'C-Döviz'!Z293)/1000 | I22: =-((G22/(G22-H22))-1) | J22: ='C-Döviz'!AJ306/1000 | K22: =('C-Döviz'!AA306-'C-Döviz'!Z306)/1000 | L22: =-((J22/(J22-K22))-1) | M22: ='C-Döviz'!AA267/1000 | N22: =M22-'C-Döviz'!Z267/1000 | O22: =-((M22/(M22-N22))-1)
C23: İnci GS Yuasa | D23: ='C-Döviz'!AJ205/1000 | E23: =('C-Döviz'!AJ205-'C-Döviz'!Z205)/1000 | F23: 0 | G23: ='C-Döviz'!AJ294/1000 | H23: =('C-Döviz'!AA294-'C-Döviz'!Z294)/1000 | I23: =((G23/(G23-H23))-1) | J23: ='C-Döviz'!AJ307/1000 | K23: =('C-Döviz'!AA307-'C-Döviz'!Z307)/1000 | L23: =((J23/(J23-K23))-1) | M23: ='C-Döviz'!AA268/1000 | N23: =M23-'C-Döviz'!Z268/1000 | O23: =-(M23/(M23-N23))-1
C24: Yusen İnci Loj. | D24: ='C-Döviz'!AJ206/1000 | E24: =('C-Döviz'!AJ206-'C-Döviz'!Z206)/1000 | F24: =-((D24/(D24-E24))-1) | G24: ='C-Döviz'!AJ295/1000 | H24: =('C-Döviz'!AA295-'C-Döviz'!Z295)/1000 | I24: =((G24/(G24-H24))-1) | J24: ='C-Döviz'!AJ308/1000 | K24: =('C-Döviz'!AA308-'C-Döviz'!Z308)/1000 | L24: =(J24/(J24-K24))-1 | M24: ='C-Döviz'!AA269/1000 | N24: =M24-'C-Döviz'!Z269/1000 | O24: =(M24/(M24-N24))-1
C25: Jantaş | D25: ='C-Döviz'!AJ207/1000 | E25: =('C-Döviz'!AJ207-'C-Döviz'!Z207)/1000 | F25: =-((D25/(D25-E25))-1) | G25: ='C-Döviz'!AJ296/1000 | H25: =('C-Döviz'!AA296-'C-Döviz'!Z296)/1000 | I25: =((G25/(G25-H25))-1) | J25: ='C-Döviz'!AJ309/1000 | K25: =('C-Döviz'!AA309-'C-Döviz'!Z309)/1000 | L25: =((J25/(J25-K25))-1) | M25: ='C-Döviz'!AA270/1000 | N25: =M25-'C-Döviz'!Z270/1000 | O25: =(M25/(M25-N25))-1
C26: Çelik | D26: ='C-Döviz'!AJ208/1000 | E26: =('C-Döviz'!AJ208-'C-Döviz'!Z208)/1000 | F26: =-((D26/(D26-E26))-1) | G26: ='C-Döviz'!AJ297/1000 | H26: =('C-Döviz'!AA297-'C-Döviz'!Z297)/1000 | I26: =((G26/(G26-H26))-1) | J26: ='C-Döviz'!AJ310/1000 | K26: =('C-Döviz'!AA310-'C-Döviz'!Z310)/1000 | L26: =(J26/(J26-K26))-1 | M26: ='C-Döviz'!AA271/1000 | N26: =M26-'C-Döviz'!Z271/1000 | O26: =(M26/(M26-N26))-1
C27: Alüminyum | D27: ='C-Döviz'!AJ209/1000 | E27: =('C-Döviz'!AJ209-'C-Döviz'!Z209)/1000 | F27: =((D27/(D27-E27))-1) | G27: ='C-Döviz'!AJ298/1000 | H27: =('C-Döviz'!AA298-'C-Döviz'!Z298)/1000 | I27: =((G27/(G27-H27))-1) | J27: ='C-Döviz'!AJ311/1000 | K27: =('C-Döviz'!AA311-'C-Döviz'!Z311)/1000 | L27: =((J27/(J27-K27))-1) | M27: ='C-Döviz'!AA272/1000 | N27: =M27-'C-Döviz'!Z272/1000 | O27: =(M27/(M27-N27))-1
D30: Faaliyet Giderleri Marjı | F30: Brüt Kar Marjı | H30: EBITDA Marjı | J30: Net Kar Marjı | L30: Operasyonel Nakit Marjı | N30: Serbest Nakit Marjı
D31: Gerçekleşme | E31: Bütçe - Gerçekleşme Fark | F31: Gerçekleşme | G31: Bütçe - Gerçekleşme Fark | H31: Gerçekleşme | I31: Bütçe - Gerçekleşme Fark | J31: Gerçekleşme | K31: Bütçe - Gerçekleşme Fark | L31: Gerçekleşme | M31: Bütçe - Gerçekleşme Fark | N31: Gerçekleşme | O31: Bütçe - Gerçekleşme Fark
C33: İnci Holding | D33: ='C-Döviz'!AJ102 | E33: =-('C-Döviz'!AA102-'C-Döviz'!Z102) | F33: ='C-Döviz'!AJ79 | G33: ='C-Döviz'!AA79-'C-Döviz'!Z79 | H33: ='C-Döviz'!AJ150 | I33: ='C-Döviz'!AA150-'C-Döviz'!Z150 | J33: ='C-Döviz'!AJ226 | K33: ='C-Döviz'!AA226-'C-Döviz'!Z226 | L33: ='C-Döviz'!AJ291/'C-Döviz'!AJ9 | M33: =L33-('C-Döviz'!Z291/'C-Döviz'!Z9) | N33: ='C-Döviz'!AJ304/'C-Döviz'!AJ9 | O33: =N33-('C-Döviz'!Z304/'C-Döviz'!Z9)
C34: ISM | D34: ='C-Döviz'!AJ103 | E34: =-('C-Döviz'!AA103-'C-Döviz'!Z103) | F34: ='C-Döviz'!AJ80 | G34: ='C-Döviz'!AA80-'C-Döviz'!Z80 | H34: ='C-Döviz'!AJ151 | I34: ='C-Döviz'!AA151-'C-Döviz'!Z151 | J34: ='C-Döviz'!AJ227 | K34: ='C-Döviz'!AA227-'C-Döviz'!Z227 | L34: ='C-Döviz'!AJ292/'C-Döviz'!AJ10 | M34: =L34-('C-Döviz'!Z292/'C-Döviz'!Z10) | N34: ='C-Döviz'!AJ305/'C-Döviz'!AJ10 | O34: =N34-('C-Döviz'!Z305/'C-Döviz'!Z10)
C35: İncitaş | D35: ='C-Döviz'!AJ104 | E35: =-('C-Döviz'!AA104-'C-Döviz'!Z104) | F35: ='C-Döviz'!AJ81 | G35: ='C-Döviz'!AA81-'C-Döviz'!Z81 | H35: ='C-Döviz'!AJ152 | I35: ='C-Döviz'!AA152-'C-Döviz'!Z152 | J35: ='C-Döviz'!AJ228 | K35: ='C-Döviz'!AA228-'C-Döviz'!Z228 | L35: ='C-Döviz'!AJ293/'C-Döviz'!AJ11 | M35: =L35-('C-Döviz'!Z293/'C-Döviz'!Z11) | N35: ='C-Döviz'!AJ306/'C-Döviz'!AJ11 | O35: =N35-('C-Döviz'!Z306/'C-Döviz'!Z11)
C36: İnci GS Yuasa | D36: ='C-Döviz'!AJ105 | E36: =-('C-Döviz'!AA105-'C-Döviz'!Z105) | F36: ='C-Döviz'!AJ82 | G36: ='C-Döviz'!AA82-'C-Döviz'!Z82 | H36: ='C-Döviz'!AJ153 | I36: ='C-Döviz'!AA153-'C-Döviz'!Z153 | J36: ='C-Döviz'!AJ229 | K36: ='C-Döviz'!AA229-'C-Döviz'!Z229 | L36: ='C-Döviz'!AJ294/'C-Döviz'!AJ12 | M36: =L36-('C-Döviz'!Z294/'C-Döviz'!Z12) | N36: ='C-Döviz'!AJ307/'C-Döviz'!AJ12 | O36: =N36-('C-Döviz'!Z307/'C-Döviz'!Z12)
C37: Yusen İnci Loj. | D37: ='C-Döviz'!AJ106 | E37: =-('C-Döviz'!AA106-'C-Döviz'!Z106) | F37: ='C-Döviz'!AJ83 | G37: ='C-Döviz'!AA83-'C-Döviz'!Z83 | H37: ='C-Döviz'!AJ154 | I37: ='C-Döviz'!AA154-'C-Döviz'!Z154 | J37: ='C-Döviz'!AJ230 | K37: ='C-Döviz'!AA230-'C-Döviz'!Z230 | L37: ='C-Döviz'!AJ295/'C-Döviz'!AJ13 | M37: =L37-('C-Döviz'!Z295/'C-Döviz'!Z13) | N37: ='C-Döviz'!AJ308/'C-Döviz'!AJ13 | O37: =N37-('C-Döviz'!Z308/'C-Döviz'!Z13)
C38: Jantaş | D38: ='C-Döviz'!AJ107 | E38: =-('C-Döviz'!AA107-'C-Döviz'!Z107) | F38: ='C-Döviz'!AJ84 | G38: ='C-Döviz'!AA84-'C-Döviz'!Z84 | H38: ='C-Döviz'!AJ155 | I38: ='C-Döviz'!AA155-'C-Döviz'!Z155 | J38: ='C-Döviz'!AJ231 | K38: ='C-Döviz'!AA231-'C-Döviz'!Z231 | L38: ='C-Döviz'!AJ296/'C-Döviz'!AJ14 | M38: =L38-('C-Döviz'!Z296/'C-Döviz'!Z14) | N38: ='C-Döviz'!AJ309/'C-Döviz'!AJ14 | O38: =N38-('C-Döviz'!Z309/'C-Döviz'!Z14)
C39: Çelik | D39: ='C-Döviz'!AJ108 | E39: =-('C-Döviz'!AA108-'C-Döviz'!Z108) | F39: ='C-Döviz'!AJ85 | G39: ='C-Döviz'!AA85-'C-Döviz'!Z85 | H39: ='C-Döviz'!AJ156 | I39: ='C-Döviz'!AA156-'C-Döviz'!Z156 | J39: ='C-Döviz'!AJ232 | K39: ='C-Döviz'!AA232-'C-Döviz'!Z232 | L39: ='C-Döviz'!AJ297/'C-Döviz'!AJ15 | M39: =L39-('C-Döviz'!Z297/'C-Döviz'!Z15) | N39: ='C-Döviz'!AJ310/'C-Döviz'!AJ15 | O39: =N39-('C-Döviz'!Z310/'C-Döviz'!Z15)
C40: Alüminyum | D40: ='C-Döviz'!AJ109 | E40: =-('C-Döviz'!AA109-'C-Döviz'!Z109) | F40: ='C-Döviz'!AJ86 | G40: ='C-Döviz'!AA86-'C-Döviz'!Z86 | H40: ='C-Döviz'!AJ157 | I40: ='C-Döviz'!AA157-'C-Döviz'!Z157 | J40: ='C-Döviz'!AJ233 | K40: ='C-Döviz'!AA233-'C-Döviz'!Z233 | L40: ='C-Döviz'!AJ298/'C-Döviz'!AJ16 | M40: =L40-('C-Döviz'!Z298/'C-Döviz'!Z16) | N40: ='C-Döviz'!AJ311/'C-Döviz'!AJ16 | O40: =N40-('C-Döviz'!Z311/'C-Döviz'!Z16)
D64: Ciro | G64: EBITDA | K64: Net Kar
D65: Gerçekleşme | E65: % | G65: Gerçekleşme | I65: % | K65: Gerçekleşme | M65: %
C66: Ciro | D66: 55 | G66: 55 | K66: 55
C67: Adet | D67: 12 | E67: =D67/$D$66 | G67: 12 | H67: =G67/$D$66 | K67: 12 | M67: =K67/$K$66
C68: Fiyat | D68: 9 | E68: =D68/$D$66 | G68: 9 | H68: =G68/$D$66 | K68: 9 | M68: =K68/$K$66
C69: Miks | D69: 8 | E69: =D69/$D$66 | G69: 8 | H69: =G69/$D$66 | K69: 8 | M69: =K69/$K$66
C70: Ham Madde | D70: 5 | E70: =D70/$D$66 | G70: 5 | H70: =G70/$D$66 | K70: 5 | M70: =K70/$K$66
C71: Enerji | D71: 4 | E71: =D71/$D$66 | G71: 4 | H71: =G71/$D$66 | K71: 4 | M71: =K71/$K$66
C72: Döviz | D72: 3 | E72: =D72/$D$66 | G72: 3 | H72: =G72/$D$66 | K72: 3 | M72: =K72/$K$66
C73: Enflasyon | D73: 3 | E73: =D73/$D$66 | G73: 3 | H73: =G73/$D$66 | K73: 3 | M73: =K73/$K$66

Sheet Finansal Raporlama Tahmin
C3: KÜMÜLATİF | D3: Ciro | I3: Brüt Kar | N3: EBITDA | S3: Net Kar
C4: bin Avro
D5: Temmuz Tahmin | E5: Ağustos Tahmin | F5: Eylül Tahmin | G5: Bütçe - Tahmin Fark | H5: % Değişim | I5: Temmuz Tahmin | J5: Ağustos Tahmin | K5: Eylül Tahmin | L5: Bütçe - Tahmin Fark | M5: % Değişim | N5: Temmuz Tahmin | O5: Ağustos Tahmin | P5: Eylül Tahmin | Q5: Bütçe - Tahmin Fark | R5: % Değişim | S5: Temmuz Tahmin | T5: Ağustos Tahmin | U5: Eylül Tahmin | V5: Bütçe - Tahmin Fark | W5: % Değişim
C6: Toplam | D6: =SUM(D7:D14) | E6: =SUM(E7:E14) | F6: =SUM(F7:F14) | G6: =SUM(G7:G14) | H6: =(F6/(F6-G6))-1 | I6: =SUM(I7:I14) | J6: =SUM(J7:J14) | K6: =SUM(K7:K14) | L6: =SUM(L7:L14) | M6: =(K6/(K6-L6))-1 | N6: =SUM(N7:N14) | O6: =SUM(O7:O14) | P6: =SUM(P7:P14) | Q6: =SUM(Q7:Q14) | R6: =(P6/(P6-Q6))-1 | S6: =SUM(S7:S14) | T6: =SUM(T7:T14) | U6: =SUM(U7:U14) | V6: =SUM(V7:V14) | W6: =(U6/(U6-V6))-1
C7: İnci Holding | D7: ='Tahmin Data'!O4/1000 | E7: ='Tahmin Data'!Q4/1000 | F7: ='Tahmin Data'!S4/1000 | G7: =F7-'C-Döviz'!AI9/1000 | H7: =(F7/(F7-G7))-1 | I7: ='Tahmin Data'!O20/1000 | J7: ='Tahmin Data'!Q20/1000 | K7: ='Tahmin Data'!S20/1000 | L7: =K7-'C-Döviz'!AI36/1000 | M7: =(K7/(K7-L7))-1 | N7: ='Tahmin Data'!M60/1000 | O7: ='Tahmin Data'!Q60/1000 | P7: ='Tahmin Data'!S60/1000 | Q7: =P7-'C-Döviz'!AI139/1000 | R7: =(P7/(P7-Q7))-1 | S7: ='Tahmin Data'!O100/1000 | T7: ='Tahmin Data'!Q100/1000 | U7: ='Tahmin Data'!S100/1000 | V7: =U7-'C-Döviz'!AI215/1000 | W7: =(U7/(U7-V7))-1
C8: ISM | D8: ='Tahmin Data'!O6/1000 | E8: ='Tahmin Data'!Q6/1000 | F8: ='Tahmin Data'!S6/1000 | G8: =F8-'C-Döviz'!AI10/1000 | H8: =(F8/(F8-G8))-1 | I8: ='Tahmin Data'!O22/1000 | J8: ='Tahmin Data'!Q22/1000 | K8: ='Tahmin Data'!S22/1000 | L8: =K8-'C-Döviz'!AI37/1000 | M8: =(K8/(K8-L8))-1 | N8: ='Tahmin Data'!O62/1000 | O8: ='Tahmin Data'!Q62/1000 | P8: ='Tahmin Data'!S62/1000 | Q8: =P8-'C-Döviz'!AI140/1000 | R8: =(P8/(P8-Q8))-1 | S8: ='Tahmin Data'!O102/1000 | T8: ='Tahmin Data'!Q102/1000 | U8: ='Tahmin Data'!S102/1000 | V8: =U8-'C-Döviz'!AI216/1000 | W8: =(U8/(U8-V8))-1
C9: İncitaş | D9: ='Tahmin Data'!O5/1000 | E9: ='Tahmin Data'!Q5/1000 | F9: ='Tahmin Data'!S5/1000 | G9: =F9-'C-Döviz'!AI11/1000 | H9: =(F9/(F9-G9))-1 | I9: ='Tahmin Data'!O21/1000 | J9: ='Tahmin Data'!Q21/1000 | K9: ='Tahmin Data'!S21/1000 | L9: =K9-'C-Döviz'!AI38/1000 | M9: =(K9/(K9-L9))-1 | N9: ='Tahmin Data'!O61/1000 | O9: ='Tahmin Data'!Q61/1000 | P9: ='Tahmin Data'!S61/1000 | Q9: =P9-'C-Döviz'!AI141/1000 | R9: =(P9/(P9-Q9))-1 | S9: ='Tahmin Data'!O101/1000 | T9: ='Tahmin Data'!Q101/1000 | U9: ='Tahmin Data'!S101/1000 | V9: =U9-'C-Döviz'!AI217/1000 | W9: =(U9/(U9-V9))-1
C10: İnci GS Yuasa | D10: ='Tahmin Data'!O3/1000 | E10: ='Tahmin Data'!Q3/1000 | F10: ='Tahmin Data'!S3/1000 | G10: =F10-'C-Döviz'!AI12/1000 | H10: =(F10/(F10-G10))-1 | I10: ='Tahmin Data'!O19/1000 | J10: ='Tahmin Data'!Q19/1000 | K10: ='Tahmin Data'!S19/1000 | L10: =K10-'C-Döviz'!AI39/1000 | M10: =(K10/(K10-L10))-1 | N10: ='Tahmin Data'!O59/1000 | O10: ='Tahmin Data'!Q59/1000 | P10: ='Tahmin Data'!S59/1000 | Q10: =P10-'C-Döviz'!AI142/1000 | R10: =(P10/(P10-Q10))-1 | S10: ='Tahmin Data'!O99/1000 | T10: ='Tahmin Data'!Q99/1000 | U10: ='Tahmin Data'!S99/1000 | V10: =U10-'C-Döviz'!AI218/1000 | W10: =(U10/(U10-V10))-1
C11: Yusen İnci Loj. | D11: ='Tahmin Data'!O10/1000 | E11: ='Tahmin Data'!Q10/1000 | F11: ='Tahmin Data'!S10/1000 | G11: =F11-'C-Döviz'!AI13/1000 | H11: =(F11/(F11-G11))-1 | I11: ='Tahmin Data'!O26/1000 | J11: ='Tahmin Data'!Q26/1000 | K11: ='Tahmin Data'!S26/1000 | L11: =K11-'C-Döviz'!AI40/1000 | M11: =(K11/(K11-L11))-1 | N11: ='Tahmin Data'!O66/1000 | O11: ='Tahmin Data'!Q66/1000 | P11: ='Tahmin Data'!S66/1000 | Q11: =P11-'C-Döviz'!AI143/1000 | R11: =(P11/(P11-Q11))-1 | S11: ='Tahmin Data'!O106/1000 | T11: ='Tahmin Data'!Q106/1000 | U11: ='Tahmin Data'!S106/1000 | V11: =U11-'C-Döviz'!AI219/1000 | W11: =(U11/(U11-V11))-1
C12: Jantaş | D12: ='Tahmin Data'!O9/1000 | E12: ='Tahmin Data'!Q9/1000 | F12: ='Tahmin Data'!S9/1000 | G12: =F12-'C-Döviz'!AI14/1000 | H12: =(F12/(F12-G12))-1 | I12: ='Tahmin Data'!O25/1000 | J12: ='Tahmin Data'!Q25/1000 | K12: ='Tahmin Data'!S25/1000 | L12: =K12-'C-Döviz'!AI41/1000 | M12: =(K12/(K12-L12))-1 | N12: ='Tahmin Data'!O65/1000 | O12: ='Tahmin Data'!Q65/1000 | P12: ='Tahmin Data'!S65/1000 | Q12: =P12-'C-Döviz'!AI144/1000 | R12: =(P12/(P12-Q12))-1 | S12: ='Tahmin Data'!O105/1000 | T12: ='Tahmin Data'!Q105/1000 | U12: ='Tahmin Data'!S105/1000 | V12: =U12-'C-Döviz'!AI220/1000 | W12: =(U12/(U12-V12))-1
C13: Çelik | D13: ='Tahmin Data'!O8/1000 | E13: ='Tahmin Data'!Q8/1000 | F13: ='Tahmin Data'!S8/1000 | G13: =F13-'C-Döviz'!AI15/1000 | H13: =(F13/(F13-G13))-1 | I13: ='Tahmin Data'!O24/1000 | J13: ='Tahmin Data'!Q24/1000 | K13: ='Tahmin Data'!S24/1000 | L13: =K13-'C-Döviz'!AI42/1000 | M13: =(K13/(K13-L13))-1 | N13: ='Tahmin Data'!O64/1000 | O13: ='Tahmin Data'!Q64/1000 | P13: ='Tahmin Data'!S64/1000 | Q13: =P13-'C-Döviz'!AI145/1000 | R13: =(P13/(P13-Q13))-1 | S13: ='Tahmin Data'!O104/1000 | T13: ='Tahmin Data'!Q104/1000 | U13: ='Tahmin Data'!S104/1000 | V13: =U13-'C-Döviz'!AI221/1000 | W13: =(U13/(U13-V13))-1
C14: Alüminyum | D14: ='Tahmin Data'!O7/1000 | E14: ='Tahmin Data'!Q7/1000 | F14: ='Tahmin Data'!S7/1000 | G14: =F14-'C-Döviz'!AI16/1000 | H14: =(F14/(F14-G14))-1 | I14: ='Tahmin Data'!O23/1000 | J14: ='Tahmin Data'!Q23/1000 | K14: ='Tahmin Data'!S23/1000 | L14: =K14-'C-Döviz'!AI43/1000 | M14: =(K14/(K14-L14))-1 | N14: ='Tahmin Data'!O63/1000 | O14: ='Tahmin Data'!Q63/1000 | P14: ='Tahmin Data'!S63/1000 | Q14: =P14-'C-Döviz'!AI146/1000 | R14: =(P14/(P14-Q14))-1 | S14: ='Tahmin Data'!O103/1000 | T14: ='Tahmin Data'!Q103/1000 | U14: ='Tahmin Data'!S103/1000 | V14: =U14-'C-Döviz'!AI222/1000 | W14: =(U14/(U14-V14))-1
D16: Vergi | I16: Operasyonel Nakit | N16: Serbest Nakit
C17: bin Avro
D18: Temmuz Tahmin | E18: Ağustos Tahmin | F18: Eylül Tahmin | G18: Bütçe - Tahmin Fark | H18: % Değişim | I18: Temmuz Tahmin | J18: Ağustos Tahmin | K18: Eylül Tahmin | L18: Bütçe - Tahmin Fark | M18: % Değişim | N18: Temmuz Tahmin | O18: Ağustos Tahmin | P18: Eylül Tahmin | Q18: Bütçe - Tahmin Fark | R18: % Değişim
C19: Toplam | D19: =SUM(D20:D27) | E19: =SUM(E20:E27) | F19: =SUM(F20:F27) | G19: =SUM(G20:G27) | H19: =(F19/(F19-G19))-1 | I19: =SUM(I20:I27) | J19: =SUM(J20:J27) | K19: =SUM(K20:K27) | L19: =SUM(L20:L27) | M19: =(K19/(K19-L19))-1 | N19: =SUM(N20:N27) | O19: =SUM(O20:O27) | P19: =SUM(P20:P27) | Q19: =SUM(Q20:Q27) | R19: =(P19/(P19-Q19))-1
C20: İnci Holding | D20: ='Tahmin Data'!O92/1000 | E20: ='Tahmin Data'!Q92/1000 | F20: ='Tahmin Data'!S92/1000 | G20: =F20-('C-Döviz'!AI202/-1000) | H20: =(F20/(F20-G20))-1 | I20: ='Tahmin Data'!O140/1000 | J20: ='Tahmin Data'!Q140/1000 | K20: ='Tahmin Data'!S140/1000 | L20: =K20-('C-Döviz'!AI291/1000) | M20: =(K20/(K20-L20))-1 | N20: ='Tahmin Data'!O148/1000 | O20: ='Tahmin Data'!Q148/1000 | P20: ='Tahmin Data'!S148/1000 | Q20: =P20-('C-Döviz'!AI304/1000) | R20: =(P20/(P20-Q20))-1
C21: ISM | D21: ='Tahmin Data'!O94/1000 | E21: ='Tahmin Data'!Q94/1000 | F21: ='Tahmin Data'!S94/1000 | G21: =F21-('C-Döviz'!AI203/-1000) | H21: =(F21/(F21-G21))-1 | I21: ='Tahmin Data'!O142/1000 | J21: ='Tahmin Data'!Q142/1000 | K21: ='Tahmin Data'!S142/1000 | L21: =K21-('C-Döviz'!AI292/1000) | M21: =(K21/(K21-L21))-1 | N21: ='Tahmin Data'!O150/1000 | O21: ='Tahmin Data'!Q150/1000 | P21: ='Tahmin Data'!S150/1000 | Q21: =P21-('C-Döviz'!AI305/1000) | R21: =(P21/(P21-Q21))-1
C22: İncitaş | D22: ='Tahmin Data'!O93/1000 | E22: ='Tahmin Data'!Q93/1000 | F22: ='Tahmin Data'!S93/1000 | G22: =F22-('C-Döviz'!AI204/-1000) | H22: =(F22/(F22-G22))-1 | I22: ='Tahmin Data'!O141/1000 | J22: ='Tahmin Data'!Q141/1000 | K22: ='Tahmin Data'!S141/1000 | L22: =K22-('C-Döviz'!AI293/1000) | M22: =-(K22/(K22-L22)) | N22: ='Tahmin Data'!O149/1000 | O22: ='Tahmin Data'!Q149/1000 | P22: ='Tahmin Data'!S149/1000 | Q22: =P22-('C-Döviz'!AI306/1000) | R22: =-(P22/(P22-Q22))
C23: İnci GS Yuasa | D23: ='Tahmin Data'!O91/1000 | E23: ='Tahmin Data'!Q91/1000 | F23: ='Tahmin Data'!S91/1000 | G23: =F23-('C-Döviz'!AI205/-1000) | H23: 0 | I23: ='Tahmin Data'!O139/1000 | J23: ='Tahmin Data'!Q139/1000 | K23: ='Tahmin Data'!S139/1000 | L23: =K23-('C-Döviz'!AI294/1000) | M23: =(K23/(K23-L23))-1 | N23: ='Tahmin Data'!O147/1000 | O23: ='Tahmin Data'!Q147/1000 | P23: ='Tahmin Data'!S147/1000 | Q23: =P23-('C-Döviz'!AI307/1000) | R23: =-(P23/(P23-Q23))
C24: Yusen İnci Loj. | D24: ='Tahmin Data'!O98/1000 | E24: ='Tahmin Data'!Q98/1000 | F24: ='Tahmin Data'!S98/1000 | G24: =F24-('C-Döviz'!AI206/-1000) | H24: =(F24/(F24-G24))-1 | I24: ='Tahmin Data'!O146/1000 | J24: ='Tahmin Data'!Q146/1000 | K24: ='Tahmin Data'!S146/1000 | L24: =K24-('C-Döviz'!AI295/1000) | M24: =(K24/(K24-L24))-1 | N24: ='Tahmin Data'!O154/1000 | O24: ='Tahmin Data'!Q154/1000 | P24: ='Tahmin Data'!S154/1000 | Q24: =P24-('C-Döviz'!AI308/1000) | R24: =(P24/(P24-Q24))-1
C25: Jantaş | D25: ='Tahmin Data'!O97/1000 | E25: ='Tahmin Data'!Q97/1000 | F25: ='Tahmin Data'!S97/1000 | G25: =F25-('C-Döviz'!AI207/-1000) | H25: =(F25/(F25-G25))-1 | I25: ='Tahmin Data'!O145/1000 | J25: ='Tahmin Data'!Q145/1000 | K25: ='Tahmin Data'!S145/1000 | L25: =K25-('C-Döviz'!AI296/1000) | M25: =(K25/(K25-L25))-1 | N25: ='Tahmin Data'!O153/1000 | O25: ='Tahmin Data'!Q153/1000 | P25: ='Tahmin Data'!S153/1000 | Q25: =P25-('C-Döviz'!AI309/1000) | R25: =(P25/(P25-Q25))-1
C26: Çelik | D26: ='Tahmin Data'!O96/1000 | E26: ='Tahmin Data'!Q96/1000 | F26: ='Tahmin Data'!S96/1000 | G26: =F26-('C-Döviz'!AI208/-1000) | H26: =(F26/(F26-G26))-1 | I26: ='Tahmin Data'!O144/1000 | J26: ='Tahmin Data'!Q144/1000 | K26: ='Tahmin Data'!S144/1000 | L26: =K26-('C-Döviz'!AI297/1000) | M26: =(K26/(K26-L26))-1 | N26: ='Tahmin Data'!O152/1000 | O26: ='Tahmin Data'!Q152/1000 | P26: ='Tahmin Data'!S152/1000 | Q26: =P26-('C-Döviz'!AI310/1000) | R26: =(P26/(P26-Q26))-1
C27: Alüminyum | D27: ='Tahmin Data'!O95/1000 | E27: ='Tahmin Data'!Q95/1000 | F27: ='Tahmin Data'!S95/1000 | G27: =F27-('C-Döviz'!AI209/-1000) | H27: =(F27/(F27-G27))-1 | I27: ='Tahmin Data'!O143/1000 | J27: ='Tahmin Data'!Q143/1000 | K27: ='Tahmin Data'!S143/1000 | L27: =K27-('C-Döviz'!AI298/1000) | M27: =(K27/(K27-L27))-1 | N27: ='Tahmin Data'!O151/1000 | O27: ='Tahmin Data'!Q151/1000 | P27: ='Tahmin Data'!S151/1000 | Q27: =P27-('C-Döviz'!AI311/1000) | R27: =(P27/(P27-Q27))-1
D30: Faaliyet Giderleri Marjı | H30: Brüt Kar Marjı | L30: EBITDA Marjı
C31: bin Avro
D32: Temmuz Tahmin | E32: Ağustos Tahmin | F32: Eylül Tahmin | G32: Bütçe - Tahmin Fark | H32: Temmuz Tahmin | I32: Ağustos Tahmin | J32: Eylül Tahmin | K32: Bütçe - Tahmin Fark | L32: Temmuz Tahmin | M32: Ağustos Tahmin | N32: Eylül Tahmin | O32: Bütçe - Tahmin Fark
C34: İnci Holding | D34: ='Tahmin Data'!O28/1000/D7*-1 | E34: ='Tahmin Data'!Q28/1000/E7*-1 | F34: ='Tahmin Data'!S28/1000/F7*-1 | G34: =-(F34-'C-Döviz'!AI102) | H34: =I7/D7 | I34: =J7/E7 | J34: =K7/F7 | K34: =J34-'C-Döviz'!AI79 | L34: =N7/D7 | M34: =O7/E7 | N34: =P7/F7 | O34: =N34-'C-Döviz'!AI150
C35: ISM | D35: ='Tahmin Data'!O30/1000/D8*-1 | E35: ='Tahmin Data'!Q30/1000/E8*-1 | F35: ='Tahmin Data'!S30/1000/F8*-1 | G35: =-(F35-'C-Döviz'!AI103) | H35: =I8/D8 | I35: =J8/E8 | J35: =K8/F8 | K35: =J35-'C-Döviz'!AI80 | L35: =N8/D8 | M35: =O8/E8 | N35: =P8/F8 | O35: =N35-'C-Döviz'!AI151
C36: İncitaş | D36: ='Tahmin Data'!O29/1000/D9*-1 | E36: ='Tahmin Data'!Q29/1000/E9*-1 | F36: ='Tahmin Data'!S29/1000/F9*-1 | G36: =-(F36-'C-Döviz'!AI104) | H36: =I9/D9 | I36: =J9/E9 | J36: =K9/F9 | K36: =J36-'C-Döviz'!AI81 | L36: =N9/D9 | M36: =O9/E9 | N36: =P9/F9 | O36: =N36-'C-Döviz'!AI152
C37: İnci GS Yuasa | D37: ='Tahmin Data'!O27/1000/D10*-1 | E37: ='Tahmin Data'!Q27/1000/E10*-1 | F37: ='Tahmin Data'!S27/1000/F10*-1 | G37: =-(F37-'C-Döviz'!AI105) | H37: =I10/D10 | I37: =J10/E10 | J37: =K10/F10 | K37: =J37-'C-Döviz'!AI82 | L37: =N10/D10 | M37: =O10/E10 | N37: =P10/F10 | O37: =N37-'C-Döviz'!AI153
C38: Yusen İnci Loj. | D38: ='Tahmin Data'!O34/1000/D11*-1 | E38: ='Tahmin Data'!Q34/1000/E11*-1 | F38: ='Tahmin Data'!S34/1000/F11*-1 | G38: =-(F38-'C-Döviz'!AI106) | H38: =I11/D11 | I38: =J11/E11 | J38: =K11/F11 | K38: =J38-'C-Döviz'!AI83 | L38: =N11/D11 | M38: =O11/E11 | N38: =P11/F11 | O38: =N38-'C-Döviz'!AI154
C39: Jantaş | D39: ='Tahmin Data'!O33/1000/D12*-1 | E39: ='Tahmin Data'!Q33/1000/E12*-1 | F39: ='Tahmin Data'!S33/1000/F12*-1 | G39: =-(F39-'C-Döviz'!AI107) | H39: =I12/D12 | I39: =J12/E12 | J39: =K12/F12 | K39: =J39-'C-Döviz'!AI84 | L39: =N12/D12 | M39: =O12/E12 | N39: =P12/F12 | O39: =N39-'C-Döviz'!AI155
C40: Çelik | D40: ='Tahmin Data'!O32/1000/D13*-1 | E40: ='Tahmin Data'!Q32/1000/E13*-1 | F40: ='Tahmin Data'!S32/1000/F13*-1 | G40: =-(F40-'C-Döviz'!AI108) | H40: =I13/D13 | I40: =J13/E13 | J40: =K13/F13 | K40: =J40-'C-Döviz'!AI85 | L40: =N13/D13 | M40: =O13/E13 | N40: =P13/F13 | O40: =N40-'C-Döviz'!AI156
C41: Alüminyum | D41: ='Tahmin Data'!O31/1000/D14*-1 | E41: ='Tahmin Data'!Q31/1000/E14*-1 | F41: ='Tahmin Data'!S31/1000/F14*-1 | G41: =-(F41-'C-Döviz'!AI109) | H41: =I14/D14 | I41: =J14/E14 | J41: =K14/F14 | K41: =J41-'C-Döviz'!AI86 | L41: =N14/D14 | M41: =O14/E14 | N41: =P14/F14 | O41: =N41-'C-Döviz'!AI157
D43: Net Kar Marjı | H43: Operasyonel Nakit Marjı | L43: Serbest Nakit Marjı
C44: bin Avro
D45: Temmuz Tahmin | E45: Ağustos Tahmin | F45: Eylül Tahmin | G45: Bütçe - Tahmin Fark | H45: Temmuz Tahmin | I45: Ağustos Tahmin | J45: Eylül Tahmin | K45: Bütçe - Tahmin Fark | L45: Temmuz Tahmin | M45: Ağustos Tahmin | N45: Eylül Tahmin | O45: Bütçe - Tahmin Fark
C47: İnci Holding | D47: =S7/D7 | E47: =T7/E7 | F47: =U7/F7 | G47: =F47-'C-Döviz'!AI226 | H47: =I20/D7 | I47: =J20/E7 | J47: =K20/F7 | K47: =J47-('C-Döviz'!AI291/'C-Döviz'!AI9) | L47: =N20/D7 | M47: =O20/E7 | N47: =P20/F7 | O47: =N47-'C-Döviz'!AI304/'C-Döviz'!AI9
C48: ISM | D48: =S8/D8 | E48: =T8/E8 | F48: =U8/F8 | G48: =F48-'C-Döviz'!AI227 | H48: =I21/D8 | I48: =J21/E8 | J48: =K21/F8 | K48: =J48-('C-Döviz'!AI292/'C-Döviz'!AI10) | L48: =N21/D8 | M48: =O21/E8 | N48: =P21/F8 | O48: =N48-'C-Döviz'!AI305/'C-Döviz'!AI10
C49: İncitaş | D49: =S9/D9 | E49: =T9/E9 | F49: =U9/F9 | G49: =F49-'C-Döviz'!AI228 | H49: =I22/D9 | I49: =J22/E9 | J49: =K22/F9 | K49: =J49-('C-Döviz'!AI293/'C-Döviz'!AI11) | L49: =N22/D9 | M49: =O22/E9 | N49: =P22/F9 | O49: =N49-'C-Döviz'!AI306/'C-Döviz'!AI11
C50: İnci GS Yuasa | D50: =S10/D10 | E50: =T10/E10 | F50: =U10/F10 | G50: =F50-'C-Döviz'!AI229 | H50: =I23/D10 | I50: =J23/E10 | J50: =K23/F10 | K50: =J50-('C-Döviz'!AI294/'C-Döviz'!AI12) | L50: =N23/D10 | M50: =O23/E10 | N50: =P23/F10 | O50: =N50-'C-Döviz'!AI307/'C-Döviz'!AI12
C51: Yusen İnci Loj. | D51: =S11/D11 | E51: =T11/E11 | F51: =U11/F11 | G51: =F51-'C-Döviz'!AI230 | H51: =I24/D11 | I51: =J24/E11 | J51: =K24/F11 | K51: =J51-('C-Döviz'!AI295/'C-Döviz'!AI13) | L51: =N24/D11 | M51: =O24/E11 | N51: =P24/F11 | O51: =N51-'C-Döviz'!AI308/'C-Döviz'!AI13
C52: Jantaş | D52: =S12/D12 | E52: =T12/E12 | F52: =U12/F12 | G52: =F52-'C-Döviz'!AI231 | H52: =I25/D12 | I52: =J25/E12 | J52: =K25/F12 | K52: =J52-('C-Döviz'!AI296/'C-Döviz'!AI14) | L52: =N25/D12 | M52: =O25/E12 | N52: =P25/F12 | O52: =N52-'C-Döviz'!AI309/'C-Döviz'!AI14
C53: Çelik | D53: =S13/D13 | E53: =T13/E13 | F53: =U13/F13 | G53: =F53-'C-Döviz'!AI232 | H53: =I26/D13 | I53: =J26/E13 | J53: =K26/F13 | K53: =J53-('C-Döviz'!AI297/'C-Döviz'!AI15) | L53: =N26/D13 | M53: =O26/E13 | N53: =P26/F13 | O53: =N53-'C-Döviz'!AI310/'C-Döviz'!AI15
C54: Alüminyum | D54: =S14/D14 | E54: =T14/E14 | F54: =U14/F14 | G54: =F54-'C-Döviz'!AI233 | H54: =I27/D14 | I54: =J27/E14 | J54: =K27/F14 | K54: =J54-('C-Döviz'!AI298/'C-Döviz'!AI16) | L54: =N27/D14 | M54: =O27/E14 | N54: =P27/F14 | O54: =N54-'C-Döviz'!AI311/'C-Döviz'!AI16
D65: Ciro | H65: EBITDA | M65: Net Kar
D66: Gerçekleşme | E66: % | H66: Gerçekleşme | J66: % | M66: Gerçekleşme | O66: %
C67: Ciro | D67: 55 | H67: 55 | M67: 55
C68: Adet | D68: 12 | E68: =D68/$D$67 | H68: 12 | I68: =H68/$D$67 | M68: 12 | O68: =M68/$M$67
C69: Fiyat | D69: 9 | E69: =D69/$D$67 | H69: 9 | I69: =H69/$D$67 | M69: 9 | O69: =M69/$M$67
C70: Miks | D70: 8 | E70: =D70/$D$67 | H70: 8 | I70: =H70/$D$67 | M70: 8 | O70: =M70/$M$67
C71: Ham Madde | D71: 5 | E71: =D71/$D$67 | H71: 5 | I71: =H71/$D$67 | M71: 5 | O71: =M71/$M$67
C72: Enerji | D72: 4 | E72: =D72/$D$67 | H72: 4 | I72: =H72/$D$67 | M72: 4 | O72: =M72/$M$67
C73: Döviz | D73: 3 | E73: =D73/$D$67 | H73: 3 | I73: =H73/$D$67 | M73: 3 | O73: =M73/$M$67
C74: Enflasyon | D74: 3 | E74: =D74/$D$67 | H74: 3 | I74: =H74/$D$67 | M74: 3 | O74: =M74/$M$67

Sheet A -Döviz
A1: ='A-TRY'!A1 | B1: OCAK | E1: ŞUBAT | H1: MART | K1: NİSAN | N1: MAYIS | Q1: HAZİRAN | T1: TEMMUZ | W1: AĞUSTOS | Z1: EYLÜL | AC1: EKİM | AF1: KASIM | AI1: ARALIK
B2: Budget | C2: Actual | E2: Budget | F2: Actual | H2: Budget | I2: Actual | K2: Budget | L2: Actual | N2: Budget | O2: Actual | Q2: Budget | R2: Actual | T2: Budget | U2: Actual | W2: Budget | X2: Actual | Z2: Budget | AA2: Actual | AC2: Budget | AD2: Actual | AF2: Budget | AG2: Actual | AI2: Budget | AJ2: Actual | AL2: Difference | AM2: Variance % | AO2: Budget | AP2: Actual
A3: Eur Kapanış | B3: ='Bütçe aylık-TL'!$B$2 | C3: ='gerç aylık-tl'!$B$2 | E3: ='Bütçe aylık-TL'!$C$2 | F3: ='gerç aylık-tl'!$C$2 | H3: ='Bütçe aylık-TL'!$D$2 | I3: ='gerç aylık-tl'!$D$2 | K3: ='Bütçe aylık-TL'!$E$2 | L3: ='gerç aylık-tl'!$E$2 | N3: ='Bütçe aylık-TL'!$F$2 | O3: ='gerç aylık-tl'!$F$2 | Q3: ='Bütçe aylık-TL'!$G$2 | R3: ='gerç aylık-tl'!$G$2 | T3: ='Bütçe aylık-TL'!$H$2 | U3: ='gerç aylık-tl'!$H$2 | W3: ='Bütçe aylık-TL'!$I$2 | X3: ='gerç aylık-tl'!$I$2 | Z3: ='Bütçe aylık-TL'!$J$2 | AA3: ='gerç aylık-tl'!$J$2 | AC3: ='Bütçe aylık-TL'!$K$2 | AD3: ='gerç aylık-tl'!$K$2 | AF3: ='Bütçe aylık-TL'!$L$2 | AG3: ='gerç aylık-tl'!$L$2 | AI3: ='Bütçe aylık-TL'!$M$2 | AJ3: ='gerç aylık-tl'!$M$2 | AL3: =AP3-AO3 | AM3: =AP3/AO3-1 | AO3: =IF($A$1=$B$1,B3,IF($A$1=$E$1,E3,IF($A$1=$H$1,H3,IF($A$1=$K$1,K3,IF($A$1=$N$1,N3,IF($A$1=$Q$1,Q3,IF($A$1=$T$1,T3,IF($A$1=$W$1,W3,IF($A$1=$Z$1,Z3,IF($A$1=$AC$1,AC3,IF($A$1=$AF$1,AF3,IF($A$1=$AI$1,AI3)))))))))))) | AP3: =IF($A$1=$B$1,C3,IF($A$1=$E$1,F3,IF($A$1=$H$1,I3,IF($A$1=$K$1,L3,IF($A$1=$N$1,O3,IF($A$1=$Q$1,R3,IF($A$1=$T$1,U3,IF($A$1=$W$1,X3,IF($A$1=$Z$1,AA3,IF($A$1=$AC$1,AD3,IF($A$1=$AF$1,AG3,IF($A$1=$AI$1,AJ3)))))))))))) | AR3: =250000000/L3
A4: Eur Ortalama | B4: ='Bütçe aylık-TL'!$B$3 | C4: ='gerç aylık-tl'!$B$3 | E4: ='Bütçe aylık-TL'!$C$3 | F4: ='gerç aylık-tl'!$C$3 | H4: ='Bütçe aylık-TL'!$D$3 | I4: ='gerç aylık-tl'!$D$3 | K4: ='Bütçe aylık-TL'!$E$3 | L4: ='gerç aylık-tl'!$E$3 | N4: ='Bütçe aylık-TL'!$F$3 | O4: ='gerç aylık-tl'!$F$3 | Q4: ='Bütçe aylık-TL'!$G$3 | R4: ='gerç aylık-tl'!$G$3 | T4: ='Bütçe aylık-TL'!$H$3 | U4: ='gerç aylık-tl'!$H$3 | W4: ='Bütçe aylık-TL'!$I$3 | X4: ='gerç aylık-tl'!$I$3 | Z4: ='Bütçe aylık-TL'!$J$3 | AA4: ='gerç aylık-tl'!$J$3 | AC4: ='Bütçe aylık-TL'!$K$3 | AD4: ='gerç aylık-tl'!$K$3 | AF4: ='Bütçe aylık-TL'!$L$3 | AG4: ='gerç aylık-tl'!$L$3 | AI4: ='Bütçe aylık-TL'!$M$3 | AJ4: ='gerç aylık-tl'!$M$3 | AL4: =AP4-AO4 | AM4: =AP4/AO4-1 | AO4: =IF($A$1=$B$1,B4,IF($A$1=$E$1,E4,IF($A$1=$H$1,H4,IF($A$1=$K$1,K4,IF($A$1=$N$1,N4,IF($A$1=$Q$1,Q4,IF($A$1=$T$1,T4,IF($A$1=$W$1,W4,IF($A$1=$Z$1,Z4,IF($A$1=$AC$1,AC4,IF($A$1=$AF$1,AF4,IF($A$1=$AI$1,AI4)))))))))))) | AP4: =IF($A$1=$B$1,C4,IF($A$1=$E$1,F4,IF($A$1=$H$1,I4,IF($A$1=$K$1,L4,IF($A$1=$N$1,O4,IF($A$1=$Q$1,R4,IF($A$1=$T$1,U4,IF($A$1=$W$1,X4,IF($A$1=$Z$1,AA4,IF($A$1=$AC$1,AD4,IF($A$1=$AF$1,AG4,IF($A$1=$AI$1,AJ4))))))))))))
A6: Net Sales | B6: ='Bütçe aylık-Eur'!$B$4 | C6: ='gerç aylık-eur'!$B$4 | E6: ='Bütçe aylık-Eur'!$C$4 | F6: ='gerç aylık-eur'!$C$4 | H6: ='Bütçe aylık-Eur'!$D$4 | I6: ='gerç aylık-eur'!$D$4 | K6: ='Bütçe aylık-Eur'!$E$4 | L6: ='gerç aylık-eur'!$E$4 | N6: ='Bütçe aylık-Eur'!$F$4 | O6: ='gerç aylık-eur'!$F$4 | Q6: ='Bütçe aylık-Eur'!$G$4 | R6: ='gerç aylık-eur'!$G$4 | T6: ='Bütçe aylık-Eur'!$H$4 | U6: ='gerç aylık-eur'!$H$4 | W6: ='Bütçe aylık-Eur'!$I$4 | X6: ='gerç aylık-eur'!$I$4 | Z6: ='Bütçe aylık-Eur'!$J$4 | AA6: ='gerç aylık-eur'!$J$4 | AC6: ='Bütçe aylık-Eur'!$K$4 | AD6: ='gerç aylık-eur'!$K$4 | AF6: ='Bütçe aylık-Eur'!$L$4 | AG6: ='gerç aylık-eur'!$L$4 | AI6: ='Bütçe aylık-Eur'!$M$4 | AJ6: ='gerç aylık-eur'!$M$4 | AL6: =AP6-AO6 | AM6: =AP6/AO6-1 | AO6: =IF($A$1=$B$1,B6,IF($A$1=$E$1,E6,IF($A$1=$H$1,H6,IF($A$1=$K$1,K6,IF($A$1=$N$1,N6,IF($A$1=$Q$1,Q6,IF($A$1=$T$1,T6,IF($A$1=$W$1,W6,IF($A$1=$Z$1,Z6,IF($A$1=$AC$1,AC6,IF($A$1=$AF$1,AF6,IF($A$1=$AI$1,AI6)))))))))))) | AP6: =IF($A$1=$B$1,C6,IF($A$1=$E$1,F6,IF($A$1=$H$1,I6,IF($A$1=$K$1,L6,IF($A$1=$N$1,O6,IF($A$1=$Q$1,R6,IF($A$1=$T$1,U6,IF($A$1=$W$1,X6,IF($A$1=$Z$1,AA6,IF($A$1=$AC$1,AD6,IF($A$1=$AF$1,AG6,IF($A$1=$AI$1,AJ6))))))))))))
C7: =B6-C6 | F7: =E6-F6 | I7: =H6-I6 | L7: =K6-L6 | O7: =N6-O6
A8: SALES BY CHANNELS(100% Satışlar)
A9: İnci Holding | B9: ='Bütçe aylık-Eur'!$B$5 | C9: ='gerç aylık-eur'!$B$5 | E9: ='Bütçe aylık-Eur'!$C$5 | F9: ='gerç aylık-eur'!$C$5 | H9: ='Bütçe aylık-Eur'!$D$5 | I9: ='gerç aylık-eur'!$D$5 | K9: ='Bütçe aylık-Eur'!$E$5 | L9: ='gerç aylık-eur'!$E$5 | N9: ='Bütçe aylık-Eur'!$F$5 | O9: ='gerç aylık-eur'!$F$5 | P9: =O9/N9 | Q9: ='Bütçe aylık-Eur'!$G$5 | R9: ='gerç aylık-eur'!$G$5 | T9: ='Bütçe aylık-Eur'!$H$5 | U9: ='gerç aylık-eur'!$H$5 | W9: ='Bütçe aylık-Eur'!$I$5 | X9: ='gerç aylık-eur'!$I$5 | Z9: ='Bütçe aylık-Eur'!$J$5 | AA9: ='gerç aylık-eur'!$J$5 | AC9: ='Bütçe aylık-Eur'!$K$5 | AD9: ='gerç aylık-eur'!$K$5 | AF9: ='Bütçe aylık-Eur'!$L$5 | AG9: ='gerç aylık-eur'!$L$5 | AI9: ='Bütçe aylık-Eur'!$M$5 | AJ9: ='gerç aylık-eur'!$M$5 | AL9: =AP9-AO9 | AM9: =AP9/AO9-1 | AO9: =IF($A$1=$B$1,B9,IF($A$1=$E$1,E9,IF($A$1=$H$1,H9,IF($A$1=$K$1,K9,IF($A$1=$N$1,N9,IF($A$1=$Q$1,Q9,IF($A$1=$T$1,T9,IF($A$1=$W$1,W9,IF($A$1=$Z$1,Z9,IF($A$1=$AC$1,AC9,IF($A$1=$AF$1,AF9,IF($A$1=$AI$1,AI9)))))))))))) | AP9: =IF($A$1=$B$1,C9,IF($A$1=$E$1,F9,IF($A$1=$H$1,I9,IF($A$1=$K$1,L9,IF($A$1=$N$1,O9,IF($A$1=$Q$1,R9,IF($A$1=$T$1,U9,IF($A$1=$W$1,X9,IF($A$1=$Z$1,AA9,IF($A$1=$AC$1,AD9,IF($A$1=$AF$1,AG9,IF($A$1=$AI$1,AJ9))))))))))))
A10: ISM | B10: ='Bütçe aylık-Eur'!$B$6 | C10: ='gerç aylık-eur'!$B$6 | E10: ='Bütçe aylık-Eur'!$C$6 | F10: ='gerç aylık-eur'!$C$6 | H10: ='Bütçe aylık-Eur'!$D$6 | I10: ='gerç aylık-eur'!$D$6 | K10: ='Bütçe aylık-Eur'!$E$6 | L10: ='gerç aylık-eur'!$E$6 | N10: ='Bütçe aylık-Eur'!$F$6 | O10: ='gerç aylık-eur'!$F$6 | P10: =O10/N10 | Q10: ='Bütçe aylık-Eur'!$G$6 | R10: ='gerç aylık-eur'!$G$6 | T10: ='Bütçe aylık-Eur'!$H$6 | U10: ='gerç aylık-eur'!$H$6 | W10: ='Bütçe aylık-Eur'!$I$6 | X10: ='gerç aylık-eur'!$I$6 | Z10: ='Bütçe aylık-Eur'!$J$6 | AA10: ='gerç aylık-eur'!$J$6 | AC10: ='Bütçe aylık-Eur'!$K$6 | AD10: ='gerç aylık-eur'!$K$6 | AF10: ='Bütçe aylık-Eur'!$L$6 | AG10: ='gerç aylık-eur'!$L$6 | AI10: ='Bütçe aylık-Eur'!$M$6 | AJ10: ='gerç aylık-eur'!$M$6 | AL10: =AP10-AO10 | AM10: =AP10/AO10-1 | AO10: =IF($A$1=$B$1,B10,IF($A$1=$E$1,E10,IF($A$1=$H$1,H10,IF($A$1=$K$1,K10,IF($A$1=$N$1,N10,IF($A$1=$Q$1,Q10,IF($A$1=$T$1,T10,IF($A$1=$W$1,W10,IF($A$1=$Z$1,Z10,IF($A$1=$AC$1,AC10,IF($A$1=$AF$1,AF10,IF($A$1=$AI$1,AI10)))))))))))) | AP10: =IF($A$1=$B$1,C10,IF($A$1=$E$1,F10,IF($A$1=$H$1,I10,IF($A$1=$K$1,L10,IF($A$1=$N$1,O10,IF($A$1=$Q$1,R10,IF($A$1=$T$1,U10,IF($A$1=$W$1,X10,IF($A$1=$Z$1,AA10,IF($A$1=$AC$1,AD10,IF($A$1=$AF$1,AG10,IF($A$1=$AI$1,AJ10))))))))))))
A11: İncitaş | B11: ='Bütçe aylık-Eur'!$B$7 | C11: ='gerç aylık-eur'!$B$7 | E11: ='Bütçe aylık-Eur'!$C$7 | F11: ='gerç aylık-eur'!$C$7 | H11: ='Bütçe aylık-Eur'!$D$7 | I11: ='gerç aylık-eur'!$D$7 | K11: ='Bütçe aylık-Eur'!$E$7 | L11: ='gerç aylık-eur'!$E$7 | N11: ='Bütçe aylık-Eur'!$F$7 | O11: ='gerç aylık-eur'!$F$7 | P11: =O11/N11 | Q11: ='Bütçe aylık-Eur'!$G$7 | R11: ='gerç aylık-eur'!$G$7 | T11: ='Bütçe aylık-Eur'!$H$7 | U11: ='gerç aylık-eur'!$H$7 | W11: ='Bütçe aylık-Eur'!$I$7 | X11: ='gerç aylık-eur'!$I$7 | Z11: ='Bütçe aylık-Eur'!$J$7 | AA11: ='gerç aylık-eur'!$J$7 | AC11: ='Bütçe aylık-Eur'!$K$7 | AD11: ='gerç aylık-eur'!$K$7 | AF11: ='Bütçe aylık-Eur'!$L$7 | AG11: ='gerç aylık-eur'!$L$7 | AI11: ='Bütçe aylık-Eur'!$M$7 | AJ11: ='gerç aylık-eur'!$M$7 | AL11: =AP11-AO11 | AM11: =AP11/AO11-1 | AO11: =IF($A$1=$B$1,B11,IF($A$1=$E$1,E11,IF($A$1=$H$1,H11,IF($A$1=$K$1,K11,IF($A$1=$N$1,N11,IF($A$1=$Q$1,Q11,IF($A$1=$T$1,T11,IF($A$1=$W$1,W11,IF($A$1=$Z$1,Z11,IF($A$1=$AC$1,AC11,IF($A$1=$AF$1,AF11,IF($A$1=$AI$1,AI11)))))))))))) | AP11: =IF($A$1=$B$1,C11,IF($A$1=$E$1,F11,IF($A$1=$H$1,I11,IF($A$1=$K$1,L11,IF($A$1=$N$1,O11,IF($A$1=$Q$1,R11,IF($A$1=$T$1,U11,IF($A$1=$W$1,X11,IF($A$1=$Z$1,AA11,IF($A$1=$AC$1,AD11,IF($A$1=$AF$1,AG11,IF($A$1=$AI$1,AJ11))))))))))))
A12: İnci GS Yuasa | B12: ='Bütçe aylık-Eur'!$B$8 | C12: ='gerç aylık-eur'!$B$8 | E12: ='Bütçe aylık-Eur'!$C$8 | F12: ='gerç aylık-eur'!$C$8 | H12: ='Bütçe aylık-Eur'!$D$8 | I12: ='gerç aylık-eur'!$D$8 | K12: ='Bütçe aylık-Eur'!$E$8 | L12: ='gerç aylık-eur'!$E$8 | N12: ='Bütçe aylık-Eur'!$F$8 | O12: ='gerç aylık-eur'!$F$8 | P12: =O12/N12 | Q12: ='Bütçe aylık-Eur'!$G$8 | R12: ='gerç aylık-eur'!$G$8 | T12: ='Bütçe aylık-Eur'!$H$8 | U12: ='gerç aylık-eur'!$H$8 | W12: ='Bütçe aylık-Eur'!$I$8 | X12: ='gerç aylık-eur'!$I$8 | Z12: ='Bütçe aylık-Eur'!$J$8 | AA12: ='gerç aylık-eur'!$J$8 | AC12: ='Bütçe aylık-Eur'!$K$8 | AD12: ='gerç aylık-eur'!$K$8 | AF12: ='Bütçe aylık-Eur'!$L$8 | AG12: ='gerç aylık-eur'!$L$8 | AI12: ='Bütçe aylık-Eur'!$M$8 | AJ12: ='gerç aylık-eur'!$M$8 | AL12: =AP12-AO12 | AM12: =AP12/AO12-1 | AN12: =AL12*0.4 | AO12: =IF($A$1=$B$1,B12,IF($A$1=$E$1,E12,IF($A$1=$H$1,H12,IF($A$1=$K$1,K12,IF($A$1=$N$1,N12,IF($A$1=$Q$1,Q12,IF($A$1=$T$1,T12,IF($A$1=$W$1,W12,IF($A$1=$Z$1,Z12,IF($A$1=$AC$1,AC12,IF($A$1=$AF$1,AF12,IF($A$1=$AI$1,AI12)))))))))))) | AP12: =IF($A$1=$B$1,C12,IF($A$1=$E$1,F12,IF($A$1=$H$1,I12,IF($A$1=$K$1,L12,IF($A$1=$N$1,O12,IF($A$1=$Q$1,R12,IF($A$1=$T$1,U12,IF($A$1=$W$1,X12,IF($A$1=$Z$1,AA12,IF($A$1=$AC$1,AD12,IF($A$1=$AF$1,AG12,IF($A$1=$AI$1,AJ12))))))))))))
A13: Yusen İnci Loj. | B13: ='Bütçe aylık-Eur'!$B$9 | C13: ='gerç aylık-eur'!$B$9 | E13: ='Bütçe aylık-Eur'!$C$9 | F13: ='gerç aylık-eur'!$C$9 | H13: ='Bütçe aylık-Eur'!$D$9 | I13: ='gerç aylık-eur'!$D$9 | K13: ='Bütçe aylık-Eur'!$E$9 | L13: ='gerç aylık-eur'!$E$9 | N13: ='Bütçe aylık-Eur'!$F$9 | O13: ='gerç aylık-eur'!$F$9 | P13: =O13/N13 | Q13: ='Bütçe aylık-Eur'!$G$9 | R13: ='gerç aylık-eur'!$G$9 | T13: ='Bütçe aylık-Eur'!$H$9 | U13: ='gerç aylık-eur'!$H$9 | W13: ='Bütçe aylık-Eur'!$I$9 | X13: ='gerç aylık-eur'!$I$9 | Z13: ='Bütçe aylık-Eur'!$J$9 | AA13: ='gerç aylık-eur'!$J$9 | AC13: ='Bütçe aylık-Eur'!$K$9 | AD13: ='gerç aylık-eur'!$K$9 | AF13: ='Bütçe aylık-Eur'!$L$9 | AG13: ='gerç aylık-eur'!$L$9 | AI13: ='Bütçe aylık-Eur'!$M$9 | AJ13: ='gerç aylık-eur'!$M$9 | AL13: =AP13-AO13 | AM13: =AP13/AO13-1 | AN13: =AL13*0.4 | AO13: =IF($A$1=$B$1,B13,IF($A$1=$E$1,E13,IF($A$1=$H$1,H13,IF($A$1=$K$1,K13,IF($A$1=$N$1,N13,IF($A$1=$Q$1,Q13,IF($A$1=$T$1,T13,IF($A$1=$W$1,W13,IF($A$1=$Z$1,Z13,IF($A$1=$AC$1,AC13,IF($A$1=$AF$1,AF13,IF($A$1=$AI$1,AI13)))))))))))) | AP13: =IF($A$1=$B$1,C13,IF($A$1=$E$1,F13,IF($A$1=$H$1,I13,IF($A$1=$K$1,L13,IF($A$1=$N$1,O13,IF($A$1=$Q$1,R13,IF($A$1=$T$1,U13,IF($A$1=$W$1,X13,IF($A$1=$Z$1,AA13,IF($A$1=$AC$1,AD13,IF($A$1=$AF$1,AG13,IF($A$1=$AI$1,AJ13)))))))))))) | AR13: 43.12 | AS13: =B13/AR13
A14: Jantaş | B14: ='Bütçe aylık-Eur'!$B$10 | C14: ='gerç aylık-eur'!$B$10 | E14: ='Bütçe aylık-Eur'!$C$10 | F14: ='gerç aylık-eur'!$C$10 | H14: ='Bütçe aylık-Eur'!$D$10 | I14: ='gerç aylık-eur'!$D$10 | K14: ='Bütçe aylık-Eur'!$E$10 | L14: ='gerç aylık-eur'!$E$10 | N14: ='Bütçe aylık-Eur'!$F$10 | O14: ='gerç aylık-eur'!$F$10 | P14: =O14/N14 | Q14: ='Bütçe aylık-Eur'!$G$10 | R14: ='gerç aylık-eur'!$G$10 | T14: ='Bütçe aylık-Eur'!$H$10 | U14: ='gerç aylık-eur'!$H$10 | W14: ='Bütçe aylık-Eur'!$I$10 | X14: ='gerç aylık-eur'!$I$10 | Z14: ='Bütçe aylık-Eur'!$J$10 | AA14: ='gerç aylık-eur'!$J$10 | AC14: ='Bütçe aylık-Eur'!$K$10 | AD14: ='gerç aylık-eur'!$K$10 | AF14: ='Bütçe aylık-Eur'!$L$10 | AG14: ='gerç aylık-eur'!$L$10 | AI14: ='Bütçe aylık-Eur'!$M$10 | AJ14: ='gerç aylık-eur'!$M$10 | AL14: =AP14-AO14 | AM14: =AP14/AO14-1 | AN14: =AL14*0.4 | AO14: =IF($A$1=$B$1,B14,IF($A$1=$E$1,E14,IF($A$1=$H$1,H14,IF($A$1=$K$1,K14,IF($A$1=$N$1,N14,IF($A$1=$Q$1,Q14,IF($A$1=$T$1,T14,IF($A$1=$W$1,W14,IF($A$1=$Z$1,Z14,IF($A$1=$AC$1,AC14,IF($A$1=$AF$1,AF14,IF($A$1=$AI$1,AI14)))))))))))) | AP14: =IF($A$1=$B$1,C14,IF($A$1=$E$1,F14,IF($A$1=$H$1,I14,IF($A$1=$K$1,L14,IF($A$1=$N$1,O14,IF($A$1=$Q$1,R14,IF($A$1=$T$1,U14,IF($A$1=$W$1,X14,IF($A$1=$Z$1,AA14,IF($A$1=$AC$1,AD14,IF($A$1=$AF$1,AG14,IF($A$1=$AI$1,AJ14))))))))))))
A15: Çelik | B15: ='Bütçe aylık-Eur'!$B$11 | C15: ='gerç aylık-eur'!$B$11 | E15: ='Bütçe aylık-Eur'!$C$11 | F15: ='gerç aylık-eur'!$C$11 | H15: ='Bütçe aylık-Eur'!$D$11 | I15: ='gerç aylık-eur'!$D$11 | K15: ='Bütçe aylık-Eur'!$E$11 | L15: ='gerç aylık-eur'!$E$11 | N15: ='Bütçe aylık-Eur'!$F$11 | O15: ='gerç aylık-eur'!$F$11 | P15: =O15/N15 | Q15: ='Bütçe aylık-Eur'!$G$11 | R15: ='gerç aylık-eur'!$G$11 | T15: ='Bütçe aylık-Eur'!$H$11 | U15: ='gerç aylık-eur'!$H$11 | W15: ='Bütçe aylık-Eur'!$I$11 | X15: ='gerç aylık-eur'!$I$11 | Z15: ='Bütçe aylık-Eur'!$J$11 | AA15: ='gerç aylık-eur'!$J$11 | AC15: ='Bütçe aylık-Eur'!$K$11 | AD15: ='gerç aylık-eur'!$K$11 | AF15: ='Bütçe aylık-Eur'!$L$11 | AG15: ='gerç aylık-eur'!$L$11 | AI15: ='Bütçe aylık-Eur'!$M$11 | AJ15: ='gerç aylık-eur'!$M$11 | AL15: =AP15-AO15 | AM15: =AP15/AO15-1 | AN15: =AL15*0.4 | AO15: =IF($A$1=$B$1,B15,IF($A$1=$E$1,E15,IF($A$1=$H$1,H15,IF($A$1=$K$1,K15,IF($A$1=$N$1,N15,IF($A$1=$Q$1,Q15,IF($A$1=$T$1,T15,IF($A$1=$W$1,W15,IF($A$1=$Z$1,Z15,IF($A$1=$AC$1,AC15,IF($A$1=$AF$1,AF15,IF($A$1=$AI$1,AI15)))))))))))) | AP15: =IF($A$1=$B$1,C15,IF($A$1=$E$1,F15,IF($A$1=$H$1,I15,IF($A$1=$K$1,L15,IF($A$1=$N$1,O15,IF($A$1=$Q$1,R15,IF($A$1=$T$1,U15,IF($A$1=$W$1,X15,IF($A$1=$Z$1,AA15,IF($A$1=$AC$1,AD15,IF($A$1=$AF$1,AG15,IF($A$1=$AI$1,AJ15))))))))))))
A16: Alüminyum | B16: ='Bütçe aylık-Eur'!$B$12 | C16: ='gerç aylık-eur'!$B$12 | E16: ='Bütçe aylık-Eur'!$C$12 | F16: ='gerç aylık-eur'!$C$12 | H16: ='Bütçe aylık-Eur'!$D$12 | I16: ='gerç aylık-eur'!$D$12 | K16: ='Bütçe aylık-Eur'!$E$12 | L16: ='gerç aylık-eur'!$E$12 | N16: ='Bütçe aylık-Eur'!$F$12 | O16: ='gerç aylık-eur'!$F$12 | P16: =O16/N16 | Q16: ='Bütçe aylık-Eur'!$G$12 | R16: ='gerç aylık-eur'!$G$12 | T16: ='Bütçe aylık-Eur'!$H$12 | U16: ='gerç aylık-eur'!$H$12 | W16: ='Bütçe aylık-Eur'!$I$12 | X16: ='gerç aylık-eur'!$I$12 | Z16: ='Bütçe aylık-Eur'!$J$12 | AA16: ='gerç aylık-eur'!$J$12 | AC16: ='Bütçe aylık-Eur'!$K$12 | AD16: ='gerç aylık-eur'!$K$12 | AF16: ='Bütçe aylık-Eur'!$L$12 | AG16: ='gerç aylık-eur'!$L$12 | AI16: ='Bütçe aylık-Eur'!$M$12 | AJ16: ='gerç aylık-eur'!$M$12 | AL16: =AP16-AO16 | AM16: =AP16/AO16-1 | AN16: =AL16*0.4 | AO16: =IF($A$1=$B$1,B16,IF($A$1=$E$1,E16,IF($A$1=$H$1,H16,IF($A$1=$K$1,K16,IF($A$1=$N$1,N16,IF($A$1=$Q$1,Q16,IF($A$1=$T$1,T16,IF($A$1=$W$1,W16,IF($A$1=$Z$1,Z16,IF($A$1=$AC$1,AC16,IF($A$1=$AF$1,AF16,IF($A$1=$AI$1,AI16)))))))))))) | AP16: =IF($A$1=$B$1,C16,IF($A$1=$E$1,F16,IF($A$1=$H$1,I16,IF($A$1=$K$1,L16,IF($A$1=$N$1,O16,IF($A$1=$Q$1,R16,IF($A$1=$T$1,U16,IF($A$1=$W$1,X16,IF($A$1=$Z$1,AA16,IF($A$1=$AC$1,AD16,IF($A$1=$AF$1,AG16,IF($A$1=$AI$1,AJ16))))))))))))
AO17: =IF($A$1=$B$1,B17,IF($A$1=$E$1,E17,IF($A$1=$H$1,H17,IF($A$1=$K$1,K17,IF($A$1=$N$1,N17,IF($A$1=$Q$1,Q17,IF($A$1=$T$1,T17,IF($A$1=$W$1,W17,IF($A$1=$Z$1,Z17,IF($A$1=$AC$1,AC17,IF($A$1=$AF$1,AF17,IF($A$1=$AI$1,AI17)))))))))))) | AP17: =IF($A$1=$B$1,C17,IF($A$1=$E$1,F17,IF($A$1=$H$1,I17,IF($A$1=$K$1,L17,IF($A$1=$N$1,O17,IF($A$1=$Q$1,R17,IF($A$1=$T$1,U17,IF($A$1=$W$1,X17,IF($A$1=$Z$1,AA17,IF($A$1=$AC$1,AD17,IF($A$1=$AF$1,AG17,IF($A$1=$AI$1,AJ17))))))))))))
AO18: =IF($A$1=$B$1,B18,IF($A$1=$E$1,E18,IF($A$1=$H$1,H18,IF($A$1=$K$1,K18,IF($A$1=$N$1,N18,IF($A$1=$Q$1,Q18,IF($A$1=$T$1,T18,IF($A$1=$W$1,W18,IF($A$1=$Z$1,Z18,IF($A$1=$AC$1,AC18,IF($A$1=$AF$1,AF18,IF($A$1=$AI$1,AI18)))))))))))) | AP18: =IF($A$1=$B$1,C18,IF($A$1=$E$1,F18,IF($A$1=$H$1,I18,IF($A$1=$K$1,L18,IF($A$1=$N$1,O18,IF($A$1=$Q$1,R18,IF($A$1=$T$1,U18,IF($A$1=$W$1,X18,IF($A$1=$Z$1,AA18,IF($A$1=$AC$1,AD18,IF($A$1=$AF$1,AG18,IF($A$1=$AI$1,AJ18))))))))))))
A19: SHARE OF SALES (%)
A20: İnci Holding | B20: =B9/B6 | C20: =C9/C6 | E20: =E9/E6 | F20: =F9/F6 | H20: =H9/H6 | I20: =I9/I6 | K20: =K9/K6 | L20: =L9/L6 | N20: =N9/N6 | O20: =O9/O6 | Q20: =Q9/Q6 | R20: =R9/R6 | T20: =T9/T6 | U20: =U9/U6 | W20: =W9/W6 | X20: =X9/X6 | Z20: =Z9/Z6 | AA20: =AA9/AA6 | AC20: =AC9/AC6 | AD20: =AD9/AD6 | AF20: =AF9/AF6 | AG20: =AG9/AG6 | AI20: =AI9/AI6 | AJ20: =AJ9/AJ6 | AL20: =AP20-AO20 | AO20: =IF($A$1=$B$1,B20,IF($A$1=$E$1,E20,IF($A$1=$H$1,H20,IF($A$1=$K$1,K20,IF($A$1=$N$1,N20,IF($A$1=$Q$1,Q20,IF($A$1=$T$1,T20,IF($A$1=$W$1,W20,IF($A$1=$Z$1,Z20,IF($A$1=$AC$1,AC20,IF($A$1=$AF$1,AF20,IF($A$1=$AI$1,AI20)))))))))))) | AP20: =IF($A$1=$B$1,C20,IF($A$1=$E$1,F20,IF($A$1=$H$1,I20,IF($A$1=$K$1,L20,IF($A$1=$N$1,O20,IF($A$1=$Q$1,R20,IF($A$1=$T$1,U20,IF($A$1=$W$1,X20,IF($A$1=$Z$1,AA20,IF($A$1=$AC$1,AD20,IF($A$1=$AF$1,AG20,IF($A$1=$AI$1,AJ20))))))))))))
A21: ISM | B21: =B10/B6 | C21: =C10/C6 | E21: =E10/E6 | F21: =F10/F6 | H21: =H10/H6 | I21: =I10/I6 | K21: =K10/K6 | L21: =L10/L6 | N21: =N10/N6 | O21: =O10/O6 | Q21: =Q10/Q6 | R21: =R10/R6 | T21: =T10/T6 | U21: =U10/U6 | W21: =W10/W6 | X21: =X10/X6 | Z21: =Z10/Z6 | AA21: =AA10/AA6 | AC21: =AC10/AC6 | AD21: =AD10/AD6 | AF21: =AF10/AF6 | AG21: =AG10/AG6 | AI21: =AI10/AI6 | AJ21: =AJ10/AJ6 | AL21: =AP21-AO21 | AO21: =IF($A$1=$B$1,B21,IF($A$1=$E$1,E21,IF($A$1=$H$1,H21,IF($A$1=$K$1,K21,IF($A$1=$N$1,N21,IF($A$1=$Q$1,Q21,IF($A$1=$T$1,T21,IF($A$1=$W$1,W21,IF($A$1=$Z$1,Z21,IF($A$1=$AC$1,AC21,IF($A$1=$AF$1,AF21,IF($A$1=$AI$1,AI21)))))))))))) | AP21: =IF($A$1=$B$1,C21,IF($A$1=$E$1,F21,IF($A$1=$H$1,I21,IF($A$1=$K$1,L21,IF($A$1=$N$1,O21,IF($A$1=$Q$1,R21,IF($A$1=$T$1,U21,IF($A$1=$W$1,X21,IF($A$1=$Z$1,AA21,IF($A$1=$AC$1,AD21,IF($A$1=$AF$1,AG21,IF($A$1=$AI$1,AJ21))))))))))))
A22: İncitaş | B22: =B11/B6 | C22: =C11/C6 | E22: =E11/E6 | F22: =F11/F6 | H22: =H11/H6 | I22: =I11/I6 | K22: =K11/K6 | L22: =L11/L6 | N22: =N11/N6 | O22: =O11/O6 | Q22: =Q11/Q6 | R22: =R11/R6 | T22: =T11/T6 | U22: =U11/U6 | W22: =W11/W6 | X22: =X11/X6 | Z22: =Z11/Z6 | AA22: =AA11/AA6 | AC22: =AC11/AC6 | AD22: =AD11/AD6 | AF22: =AF11/AF6 | AG22: =AG11/AG6 | AI22: =AI11/AI6 | AJ22: =AJ11/AJ6 | AL22: =AP22-AO22 | AO22: =IF($A$1=$B$1,B22,IF($A$1=$E$1,E22,IF($A$1=$H$1,H22,IF($A$1=$K$1,K22,IF($A$1=$N$1,N22,IF($A$1=$Q$1,Q22,IF($A$1=$T$1,T22,IF($A$1=$W$1,W22,IF($A$1=$Z$1,Z22,IF($A$1=$AC$1,AC22,IF($A$1=$AF$1,AF22,IF($A$1=$AI$1,AI22)))))))))))) | AP22: =IF($A$1=$B$1,C22,IF($A$1=$E$1,F22,IF($A$1=$H$1,I22,IF($A$1=$K$1,L22,IF($A$1=$N$1,O22,IF($A$1=$Q$1,R22,IF($A$1=$T$1,U22,IF($A$1=$W$1,X22,IF($A$1=$Z$1,AA22,IF($A$1=$AC$1,AD22,IF($A$1=$AF$1,AG22,IF($A$1=$AI$1,AJ22))))))))))))
A23: İnci GS Yuasa | B23: =B12*0.5/B6 | C23: =C12*0.5/C6 | E23: =E12*0.5/E6 | F23: =F12*0.5/F6 | H23: =H12*0.5/H6 | I23: =I12*0.5/I6 | K23: =K12*0.5/K6 | L23: =L12*0.5/L6 | N23: =N12*0.5/N6 | O23: =O12*0.5/O6 | Q23: =Q12*0.5/Q6 | R23: =R12*0.5/R6 | T23: =T12*0.5/T6 | U23: =U12*0.5/U6 | W23: =W12*0.5/W6 | X23: =X12*0.5/X6 | Z23: =Z12*0.5/Z6 | AA23: =AA12*0.5/AA6 | AC23: =AC12*0.5/AC6 | AD23: =AD12*0.5/AD6 | AF23: =AF12*0.5/AF6 | AG23: =AG12*0.5/AG6 | AI23: =AI12*0.5/AI6 | AJ23: =AJ12*0.5/AJ6 | AL23: =AP23-AO23 | AO23: =IF($A$1=$B$1,B23,IF($A$1=$E$1,E23,IF($A$1=$H$1,H23,IF($A$1=$K$1,K23,IF($A$1=$N$1,N23,IF($A$1=$Q$1,Q23,IF($A$1=$T$1,T23,IF($A$1=$W$1,W23,IF($A$1=$Z$1,Z23,IF($A$1=$AC$1,AC23,IF($A$1=$AF$1,AF23,IF($A$1=$AI$1,AI23)))))))))))) | AP23: =IF($A$1=$B$1,C23,IF($A$1=$E$1,F23,IF($A$1=$H$1,I23,IF($A$1=$K$1,L23,IF($A$1=$N$1,O23,IF($A$1=$Q$1,R23,IF($A$1=$T$1,U23,IF($A$1=$W$1,X23,IF($A$1=$Z$1,AA23,IF($A$1=$AC$1,AD23,IF($A$1=$AF$1,AG23,IF($A$1=$AI$1,AJ23))))))))))))
A24: Yusen İnci Loj. | B24: =B13*0.4/B6 | C24: =C13*0.4/C6 | E24: =E13*0.4/E6 | F24: =F13*0.4/F6 | H24: =H13*0.4/H6 | I24: =I13*0.4/I6 | K24: =K13*0.4/K6 | L24: =L13*0.4/L6 | N24: =N13*0.4/N6 | O24: =O13*0.4/O6 | Q24: =Q13*0.4/Q6 | R24: =R13*0.4/R6 | T24: =T13*0.4/T6 | U24: =U13*0.4/U6 | W24: =W13*0.4/W6 | X24: =X13*0.4/X6 | Z24: =Z13*0.4/Z6 | AA24: =AA13*0.4/AA6 | AC24: =AC13*0.4/AC6 | AD24: =AD13*0.4/AD6 | AF24: =AF13*0.4/AF6 | AG24: =AG13*0.4/AG6 | AI24: =AI13*0.4/AI6 | AJ24: =AJ13*0.4/AJ6 | AL24: =AP24-AO24 | AO24: =IF($A$1=$B$1,B24,IF($A$1=$E$1,E24,IF($A$1=$H$1,H24,IF($A$1=$K$1,K24,IF($A$1=$N$1,N24,IF($A$1=$Q$1,Q24,IF($A$1=$T$1,T24,IF($A$1=$W$1,W24,IF($A$1=$Z$1,Z24,IF($A$1=$AC$1,AC24,IF($A$1=$AF$1,AF24,IF($A$1=$AI$1,AI24)))))))))))) | AP24: =IF($A$1=$B$1,C24,IF($A$1=$E$1,F24,IF($A$1=$H$1,I24,IF($A$1=$K$1,L24,IF($A$1=$N$1,O24,IF($A$1=$Q$1,R24,IF($A$1=$T$1,U24,IF($A$1=$W$1,X24,IF($A$1=$Z$1,AA24,IF($A$1=$AC$1,AD24,IF($A$1=$AF$1,AG24,IF($A$1=$AI$1,AJ24))))))))))))
A25: Jantaş | B25: =B14*0.4/B6 | C25: =C14*0.4/C6 | E25: =E14*0.4/E6 | F25: =F14*0.4/F6 | H25: =H14*0.4/H6 | I25: =I14*0.4/I6 | K25: =K14*0.4/K6 | L25: =L14*0.4/L6 | N25: =N14*0.4/N6 | O25: =O14*0.4/O6 | Q25: =Q14*0.4/Q6 | R25: =R14*0.4/R6 | T25: =T14*0.4/T6 | U25: =U14*0.4/U6 | W25: =W14*0.4/W6 | X25: =X14*0.4/X6 | Z25: =Z14*0.4/Z6 | AA25: =AA14*0.4/AA6 | AC25: =AC14*0.4/AC6 | AD25: =AD14*0.4/AD6 | AF25: =AF14*0.4/AF6 | AG25: =AG14*0.4/AG6 | AI25: =AI14*0.4/AI6 | AJ25: =AJ14*0.4/AJ6 | AL25: =AP25-AO25 | AO25: =IF($A$1=$B$1,B25,IF($A$1=$E$1,E25,IF($A$1=$H$1,H25,IF($A$1=$K$1,K25,IF($A$1=$N$1,N25,IF($A$1=$Q$1,Q25,IF($A$1=$T$1,T25,IF($A$1=$W$1,W25,IF($A$1=$Z$1,Z25,IF($A$1=$AC$1,AC25,IF($A$1=$AF$1,AF25,IF($A$1=$AI$1,AI25)))))))))))) | AP25: =IF($A$1=$B$1,C25,IF($A$1=$E$1,F25,IF($A$1=$H$1,I25,IF($A$1=$K$1,L25,IF($A$1=$N$1,O25,IF($A$1=$Q$1,R25,IF($A$1=$T$1,U25,IF($A$1=$W$1,X25,IF($A$1=$Z$1,AA25,IF($A$1=$AC$1,AD25,IF($A$1=$AF$1,AG25,IF($A$1=$AI$1,AJ25))))))))))))
A26: Çelik | B26: =B15*0.4/B6 | C26: =C15*0.4/C6 | E26: =E15*0.4/E6 | F26: =F15*0.4/F6 | H26: =H15*0.4/H6 | I26: =I15*0.4/I6 | K26: =K15*0.4/K6 | L26: =L15*0.4/L6 | N26: =N15*0.4/N6 | O26: =O15*0.4/O6 | Q26: =Q15*0.4/Q6 | R26: =R15*0.4/R6 | T26: =T15*0.4/T6 | U26: =U15*0.4/U6 | W26: =W15*0.4/W6 | X26: =X15*0.4/X6 | Z26: =Z15*0.4/Z6 | AA26: =AA15*0.4/AA6 | AC26: =AC15*0.4/AC6 | AD26: =AD15*0.4/AD6 | AF26: =AF15*0.4/AF6 | AG26: =AG15*0.4/AG6 | AI26: =AI15*0.4/AI6 | AJ26: =AJ15*0.4/AJ6 | AL26: =AP26-AO26 | AO26: =IF($A$1=$B$1,B26,IF($A$1=$E$1,E26,IF($A$1=$H$1,H26,IF($A$1=$K$1,K26,IF($A$1=$N$1,N26,IF($A$1=$Q$1,Q26,IF($A$1=$T$1,T26,IF($A$1=$W$1,W26,IF($A$1=$Z$1,Z26,IF($A$1=$AC$1,AC26,IF($A$1=$AF$1,AF26,IF($A$1=$AI$1,AI26)))))))))))) | AP26: =IF($A$1=$B$1,C26,IF($A$1=$E$1,F26,IF($A$1=$H$1,I26,IF($A$1=$K$1,L26,IF($A$1=$N$1,O26,IF($A$1=$Q$1,R26,IF($A$1=$T$1,U26,IF($A$1=$W$1,X26,IF($A$1=$Z$1,AA26,IF($A$1=$AC$1,AD26,IF($A$1=$AF$1,AG26,IF($A$1=$AI$1,AJ26))))))))))))
A27: Alüminyum | B27: =B16*0.4/B6 | C27: =C16*0.4/C6 | E27: =E16*0.4/E6 | F27: =F16*0.4/F6 | H27: =H16*0.4/H6 | I27: =I16*0.4/I6 | K27: =K16*0.4/K6 | L27: =L16*0.4/L6 | N27: =N16*0.4/N6 | O27: =O16*0.4/O6 | Q27: =Q16*0.4/Q6 | R27: =R16*0.4/R6 | T27: =T16*0.4/T6 | U27: =U16*0.4/U6 | W27: =W16*0.4/W6 | X27: =X16*0.4/X6 | Z27: =Z16*0.4/Z6 | AA27: =AA16*0.4/AA6 | AC27: =AC16*0.4/AC6 | AD27: =AD16*0.4/AD6 | AF27: =AF16*0.4/AF6 | AG27: =AG16*0.4/AG6 | AI27: =AI16*0.4/AI6 | AJ27: =AJ16*0.4/AJ6 | AL27: =AP27-AO27 | AO27: =IF($A$1=$B$1,B27,IF($A$1=$E$1,E27,IF($A$1=$H$1,H27,IF($A$1=$K$1,K27,IF($A$1=$N$1,N27,IF($A$1=$Q$1,Q27,IF($A$1=$T$1,T27,IF($A$1=$W$1,W27,IF($A$1=$Z$1,Z27,IF($A$1=$AC$1,AC27,IF($A$1=$AF$1,AF27,IF($A$1=$AI$1,AI27)))))))))))) | AP27: =IF($A$1=$B$1,C27,IF($A$1=$E$1,F27,IF($A$1=$H$1,I27,IF($A$1=$K$1,L27,IF($A$1=$N$1,O27,IF($A$1=$Q$1,R27,IF($A$1=$T$1,U27,IF($A$1=$W$1,X27,IF($A$1=$Z$1,AA27,IF($A$1=$AC$1,AD27,IF($A$1=$AF$1,AG27,IF($A$1=$AI$1,AJ27))))))))))))
AL28: =AP28-AO28 | AO28: =IF($A$1=$B$1,B28,IF($A$1=$E$1,E28,IF($A$1=$H$1,H28,IF($A$1=$K$1,K28,IF($A$1=$N$1,N28,IF($A$1=$Q$1,Q28,IF($A$1=$T$1,T28,IF($A$1=$W$1,W28,IF($A$1=$Z$1,Z28,IF($A$1=$AC$1,AC28,IF($A$1=$AF$1,AF28,IF($A$1=$AI$1,AI28)))))))))))) | AP28: =IF($A$1=$B$1,C28,IF($A$1=$E$1,F28,IF($A$1=$H$1,I28,IF($A$1=$K$1,L28,IF($A$1=$N$1,O28,IF($A$1=$Q$1,R28,IF($A$1=$T$1,U28,IF($A$1=$W$1,X28,IF($A$1=$Z$1,AA28,IF($A$1=$AC$1,AD28,IF($A$1=$AF$1,AG28,IF($A$1=$AI$1,AJ28))))))))))))
AL29: =AP29-AO29 | AO29: =IF($A$1=$B$1,B29,IF($A$1=$E$1,E29,IF($A$1=$H$1,H29,IF($A$1=$K$1,K29,IF($A$1=$N$1,N29,IF($A$1=$Q$1,Q29,IF($A$1=$T$1,T29,IF($A$1=$W$1,W29,IF($A$1=$Z$1,Z29,IF($A$1=$AC$1,AC29,IF($A$1=$AF$1,AF29,IF($A$1=$AI$1,AI29)))))))))))) | AP29: =IF($A$1=$B$1,C29,IF($A$1=$E$1,F29,IF($A$1=$H$1,I29,IF($A$1=$K$1,L29,IF($A$1=$N$1,O29,IF($A$1=$Q$1,R29,IF($A$1=$T$1,U29,IF($A$1=$W$1,X29,IF($A$1=$Z$1,AA29,IF($A$1=$AC$1,AD29,IF($A$1=$AF$1,AG29,IF($A$1=$AI$1,AJ29))))))))))))
A30: Net Sales | B30: ='Bütçe aylık-Eur'!$B$4 | C30: ='gerç aylık-eur'!$B$4 | E30: ='Bütçe aylık-Eur'!$C$4 | F30: ='gerç aylık-eur'!$C$4 | H30: ='Bütçe aylık-Eur'!$D$4 | I30: ='gerç aylık-eur'!$D$4 | K30: ='Bütçe aylık-Eur'!$E$4 | L30: ='gerç aylık-eur'!$E$4 | N30: ='Bütçe aylık-Eur'!$F$4 | O30: ='gerç aylık-eur'!$F$4 | Q30: ='Bütçe aylık-Eur'!$G$4 | R30: ='gerç aylık-eur'!$G$4 | T30: ='Bütçe aylık-Eur'!$H$4 | U30: ='gerç aylık-eur'!$H$4 | W30: ='Bütçe aylık-Eur'!$I$4 | X30: ='gerç aylık-eur'!$I$4 | Z30: ='Bütçe aylık-Eur'!$J$4 | AA30: ='gerç aylık-eur'!$J$4 | AC30: ='Bütçe aylık-Eur'!$K$4 | AD30: ='gerç aylık-eur'!$K$4 | AF30: ='Bütçe aylık-Eur'!$L$4 | AG30: ='gerç aylık-eur'!$L$4 | AI30: ='Bütçe aylık-Eur'!$M$4 | AJ30: ='gerç aylık-eur'!$M$4 | AL30: =AP30-AO30 | AM30: =AP30/AO30-1 | AO30: =IF($A$1=$B$1,B30,IF($A$1=$E$1,E30,IF($A$1=$H$1,H30,IF($A$1=$K$1,K30,IF($A$1=$N$1,N30,IF($A$1=$Q$1,Q30,IF($A$1=$T$1,T30,IF($A$1=$W$1,W30,IF($A$1=$Z$1,Z30,IF($A$1=$AC$1,AC30,IF($A$1=$AF$1,AF30,IF($A$1=$AI$1,AI30)))))))))))) | AP30: =IF($A$1=$B$1,C30,IF($A$1=$E$1,F30,IF($A$1=$H$1,I30,IF($A$1=$K$1,L30,IF($A$1=$N$1,O30,IF($A$1=$Q$1,R30,IF($A$1=$T$1,U30,IF($A$1=$W$1,X30,IF($A$1=$Z$1,AA30,IF($A$1=$AC$1,AD30,IF($A$1=$AF$1,AG30,IF($A$1=$AI$1,AJ30))))))))))))
A31: Cost of Sales | B31: ='Bütçe aylık-Eur'!$B$15 | C31: ='gerç aylık-eur'!$B$15 | E31: ='Bütçe aylık-Eur'!$C$15 | F31: ='gerç aylık-eur'!$C$15 | H31: ='Bütçe aylık-Eur'!$D$15 | I31: ='gerç aylık-eur'!$D$15 | K31: ='Bütçe aylık-Eur'!$E$15 | L31: ='gerç aylık-eur'!$E$15 | N31: ='Bütçe aylık-Eur'!$F$15 | O31: ='gerç aylık-eur'!$F$15 | Q31: ='Bütçe aylık-Eur'!$G$15 | R31: ='gerç aylık-eur'!$G$15 | T31: ='Bütçe aylık-Eur'!$H$15 | U31: ='gerç aylık-eur'!$H$15 | W31: ='Bütçe aylık-Eur'!$I$15 | X31: ='gerç aylık-eur'!$I$15 | Z31: ='Bütçe aylık-Eur'!$J$15 | AA31: ='gerç aylık-eur'!$J$15 | AC31: ='Bütçe aylık-Eur'!$K$15 | AD31: ='gerç aylık-eur'!$K$15 | AF31: ='Bütçe aylık-Eur'!$L$15 | AG31: ='gerç aylık-eur'!$L$15 | AI31: ='Bütçe aylık-Eur'!$M$15 | AJ31: ='gerç aylık-eur'!$M$15 | AL31: =AP31-AO31 | AM31: =AP31/AO31-1 | AO31: =IF($A$1=$B$1,B31,IF($A$1=$E$1,E31,IF($A$1=$H$1,H31,IF($A$1=$K$1,K31,IF($A$1=$N$1,N31,IF($A$1=$Q$1,Q31,IF($A$1=$T$1,T31,IF($A$1=$W$1,W31,IF($A$1=$Z$1,Z31,IF($A$1=$AC$1,AC31,IF($A$1=$AF$1,AF31,IF($A$1=$AI$1,AI31)))))))))))) | AP31: =IF($A$1=$B$1,C31,IF($A$1=$E$1,F31,IF($A$1=$H$1,I31,IF($A$1=$K$1,L31,IF($A$1=$N$1,O31,IF($A$1=$Q$1,R31,IF($A$1=$T$1,U31,IF($A$1=$W$1,X31,IF($A$1=$Z$1,AA31,IF($A$1=$AC$1,AD31,IF($A$1=$AF$1,AG31,IF($A$1=$AI$1,AJ31))))))))))))
A32: Gross Profit | B32: ='Bütçe aylık-Eur'!$B$26 | C32: ='gerç aylık-eur'!$B$26 | E32: ='Bütçe aylık-Eur'!$C$26 | F32: ='gerç aylık-eur'!$C$26 | H32: ='Bütçe aylık-Eur'!$D$26 | I32: ='gerç aylık-eur'!$D$26 | K32: ='Bütçe aylık-Eur'!$E$26 | L32: ='gerç aylık-eur'!$E$26 | N32: ='Bütçe aylık-Eur'!$F$26 | O32: ='gerç aylık-eur'!$F$26 | Q32: ='Bütçe aylık-Eur'!$G$26 | R32: ='gerç aylık-eur'!$G$26 | T32: ='Bütçe aylık-Eur'!$H$26 | U32: ='gerç aylık-eur'!$H$26 | W32: ='Bütçe aylık-Eur'!$I$26 | X32: ='gerç aylık-eur'!$I$26 | Z32: ='Bütçe aylık-Eur'!$J$26 | AA32: ='gerç aylık-eur'!$J$26 | AC32: ='Bütçe aylık-Eur'!$K$26 | AD32: ='gerç aylık-eur'!$K$26 | AF32: ='Bütçe aylık-Eur'!$L$26 | AG32: ='gerç aylık-eur'!$L$26 | AI32: ='Bütçe aylık-Eur'!$M$26 | AJ32: ='gerç aylık-eur'!$M$26 | AL32: =AP32-AO32 | AM32: =AP32/AO32-1 | AO32: =IF($A$1=$B$1,B32,IF($A$1=$E$1,E32,IF($A$1=$H$1,H32,IF($A$1=$K$1,K32,IF($A$1=$N$1,N32,IF($A$1=$Q$1,Q32,IF($A$1=$T$1,T32,IF($A$1=$W$1,W32,IF($A$1=$Z$1,Z32,IF($A$1=$AC$1,AC32,IF($A$1=$AF$1,AF32,IF($A$1=$AI$1,AI32)))))))))))) | AP32: =IF($A$1=$B$1,C32,IF($A$1=$E$1,F32,IF($A$1=$H$1,I32,IF($A$1=$K$1,L32,IF($A$1=$N$1,O32,IF($A$1=$Q$1,R32,IF($A$1=$T$1,U32,IF($A$1=$W$1,X32,IF($A$1=$Z$1,AA32,IF($A$1=$AC$1,AD32,IF($A$1=$AF$1,AG32,IF($A$1=$AI$1,AJ32))))))))))))
A33: Gross Profit Margin | B33: =B32/B30 | C33: =C32/C30 | E33: =E32/E30 | F33: =F32/F30 | H33: =H32/H30 | I33: =I32/I30 | K33: =K32/K30 | L33: =L32/L30 | N33: =N32/N30 | O33: =O32/O30 | Q33: =Q32/Q30 | R33: =R32/R30 | T33: =T32/T30 | U33: =U32/U30 | W33: =W32/W30 | X33: =X32/X30 | Z33: =Z32/Z30 | AA33: =AA32/AA30 | AC33: =AC32/AC30 | AD33: =AD32/AD30 | AF33: =AF32/AF30 | AG33: =AG32/AG30 | AI33: =AI32/AI30 | AJ33: =AJ32/AJ30 | AM33: =AP33-AO33 | AO33: =IF($A$1=$B$1,B33,IF($A$1=$E$1,E33,IF($A$1=$H$1,H33,IF($A$1=$K$1,K33,IF($A$1=$N$1,N33,IF($A$1=$Q$1,Q33,IF($A$1=$T$1,T33,IF($A$1=$W$1,W33,IF($A$1=$Z$1,Z33,IF($A$1=$AC$1,AC33,IF($A$1=$AF$1,AF33,IF($A$1=$AI$1,AI33)))))))))))) | AP33: =IF($A$1=$B$1,C33,IF($A$1=$E$1,F33,IF($A$1=$H$1,I33,IF($A$1=$K$1,L33,IF($A$1=$N$1,O33,IF($A$1=$Q$1,R33,IF($A$1=$T$1,U33,IF($A$1=$W$1,X33,IF($A$1=$Z$1,AA33,IF($A$1=$AC$1,AD33,IF($A$1=$AF$1,AG33,IF($A$1=$AI$1,AJ33))))))))))))
A35: GROSS PROFIT BY CHANNELS (100%)
A36: İnci Holding | B36: ='Bütçe aylık-Eur'!$B$27 | C36: ='gerç aylık-eur'!$B$27 | E36: ='Bütçe aylık-Eur'!$C$27 | F36: ='gerç aylık-eur'!$C$27 | H36: ='Bütçe aylık-Eur'!$D$27 | I36: ='gerç aylık-eur'!$D$27 | K36: ='Bütçe aylık-Eur'!$E$27 | L36: ='gerç aylık-eur'!$E$27 | N36: ='Bütçe aylık-Eur'!$F$27 | O36: ='gerç aylık-eur'!$F$27 | Q36: ='Bütçe aylık-Eur'!$G$27 | R36: ='gerç aylık-eur'!$G$27 | T36: ='Bütçe aylık-Eur'!$H$27 | U36: ='gerç aylık-eur'!$H$27 | W36: ='Bütçe aylık-Eur'!$I$27 | X36: ='gerç aylık-eur'!$I$27 | Z36: ='Bütçe aylık-Eur'!$J$27 | AA36: ='gerç aylık-eur'!$J$27 | AC36: ='Bütçe aylık-Eur'!$K$27 | AD36: ='gerç aylık-eur'!$K$27 | AF36: ='Bütçe aylık-Eur'!$L$27 | AG36: ='gerç aylık-eur'!$L$27 | AI36: ='Bütçe aylık-Eur'!$M$27 | AJ36: ='gerç aylık-eur'!$M$27 | AL36: =AP36-AO36 | AM36: =AP36/AO36-1 | AO36: =IF($A$1=$B$1,B36,IF($A$1=$E$1,E36,IF($A$1=$H$1,H36,IF($A$1=$K$1,K36,IF($A$1=$N$1,N36,IF($A$1=$Q$1,Q36,IF($A$1=$T$1,T36,IF($A$1=$W$1,W36,IF($A$1=$Z$1,Z36,IF($A$1=$AC$1,AC36,IF($A$1=$AF$1,AF36,IF($A$1=$AI$1,AI36)))))))))))) | AP36: =IF($A$1=$B$1,C36,IF($A$1=$E$1,F36,IF($A$1=$H$1,I36,IF($A$1=$K$1,L36,IF($A$1=$N$1,O36,IF($A$1=$Q$1,R36,IF($A$1=$T$1,U36,IF($A$1=$W$1,X36,IF($A$1=$Z$1,AA36,IF($A$1=$AC$1,AD36,IF($A$1=$AF$1,AG36,IF($A$1=$AI$1,AJ36))))))))))))
A37: ISM | B37: ='Bütçe aylık-Eur'!$B$28 | C37: ='gerç aylık-eur'!$B$28 | E37: ='Bütçe aylık-Eur'!$C$28 | F37: ='gerç aylık-eur'!$C$28 | H37: ='Bütçe aylık-Eur'!$D$28 | I37: ='gerç aylık-eur'!$D$28 | K37: ='Bütçe aylık-Eur'!$E$28 | L37: ='gerç aylık-eur'!$E$28 | N37: ='Bütçe aylık-Eur'!$F$28 | O37: ='gerç aylık-eur'!$F$28 | Q37: ='Bütçe aylık-Eur'!$G$28 | R37: ='gerç aylık-eur'!$G$28 | T37: ='Bütçe aylık-Eur'!$H$28 | U37: ='gerç aylık-eur'!$H$28 | W37: ='Bütçe aylık-Eur'!$I$28 | X37: ='gerç aylık-eur'!$I$28 | Z37: ='Bütçe aylık-Eur'!$J$28 | AA37: ='gerç aylık-eur'!$J$28 | AC37: ='Bütçe aylık-Eur'!$K$28 | AD37: ='gerç aylık-eur'!$K$28 | AF37: ='Bütçe aylık-Eur'!$L$28 | AG37: ='gerç aylık-eur'!$L$28 | AI37: ='Bütçe aylık-Eur'!$M$28 | AJ37: ='gerç aylık-eur'!$M$28 | AL37: =AP37-AO37 | AM37: =AP37/AO37-1 | AO37: =IF($A$1=$B$1,B37,IF($A$1=$E$1,E37,IF($A$1=$H$1,H37,IF($A$1=$K$1,K37,IF($A$1=$N$1,N37,IF($A$1=$Q$1,Q37,IF($A$1=$T$1,T37,IF($A$1=$W$1,W37,IF($A$1=$Z$1,Z37,IF($A$1=$AC$1,AC37,IF($A$1=$AF$1,AF37,IF($A$1=$AI$1,AI37)))))))))))) | AP37: =IF($A$1=$B$1,C37,IF($A$1=$E$1,F37,IF($A$1=$H$1,I37,IF($A$1=$K$1,L37,IF($A$1=$N$1,O37,IF($A$1=$Q$1,R37,IF($A$1=$T$1,U37,IF($A$1=$W$1,X37,IF($A$1=$Z$1,AA37,IF($A$1=$AC$1,AD37,IF($A$1=$AF$1,AG37,IF($A$1=$AI$1,AJ37))))))))))))
A38: İncitaş | B38: ='Bütçe aylık-Eur'!$B$29 | C38: ='gerç aylık-eur'!$B$29 | E38: ='Bütçe aylık-Eur'!$C$29 | F38: ='gerç aylık-eur'!$C$29 | H38: ='Bütçe aylık-Eur'!$D$29 | I38: ='gerç aylık-eur'!$D$29 | K38: ='Bütçe aylık-Eur'!$E$29 | L38: ='gerç aylık-eur'!$E$29 | N38: ='Bütçe aylık-Eur'!$F$29 | O38: ='gerç aylık-eur'!$F$29 | Q38: ='Bütçe aylık-Eur'!$G$29 | R38: ='gerç aylık-eur'!$G$29 | T38: ='Bütçe aylık-Eur'!$H$29 | U38: ='gerç aylık-eur'!$H$29 | W38: ='Bütçe aylık-Eur'!$I$29 | X38: ='gerç aylık-eur'!$I$29 | Z38: ='Bütçe aylık-Eur'!$J$29 | AA38: ='gerç aylık-eur'!$J$29 | AC38: ='Bütçe aylık-Eur'!$K$29 | AD38: ='gerç aylık-eur'!$K$29 | AF38: ='Bütçe aylık-Eur'!$L$29 | AG38: ='gerç aylık-eur'!$L$29 | AI38: ='Bütçe aylık-Eur'!$M$29 | AJ38: ='gerç aylık-eur'!$M$29 | AL38: =AP38-AO38 | AM38: =AP38/AO38-1 | AO38: =IF($A$1=$B$1,B38,IF($A$1=$E$1,E38,IF($A$1=$H$1,H38,IF($A$1=$K$1,K38,IF($A$1=$N$1,N38,IF($A$1=$Q$1,Q38,IF($A$1=$T$1,T38,IF($A$1=$W$1,W38,IF($A$1=$Z$1,Z38,IF($A$1=$AC$1,AC38,IF($A$1=$AF$1,AF38,IF($A$1=$AI$1,AI38)))))))))))) | AP38: =IF($A$1=$B$1,C38,IF($A$1=$E$1,F38,IF($A$1=$H$1,I38,IF($A$1=$K$1,L38,IF($A$1=$N$1,O38,IF($A$1=$Q$1,R38,IF($A$1=$T$1,U38,IF($A$1=$W$1,X38,IF($A$1=$Z$1,AA38,IF($A$1=$AC$1,AD38,IF($A$1=$AF$1,AG38,IF($A$1=$AI$1,AJ38))))))))))))
A39: İnci GS Yuasa | B39: ='Bütçe aylık-Eur'!$B$30 | C39: ='gerç aylık-eur'!$B$30 | E39: ='Bütçe aylık-Eur'!$C$30 | F39: ='gerç aylık-eur'!$C$30 | H39: ='Bütçe aylık-Eur'!$D$30 | I39: ='gerç aylık-eur'!$D$30 | K39: ='Bütçe aylık-Eur'!$E$30 | L39: ='gerç aylık-eur'!$E$30 | N39: ='Bütçe aylık-Eur'!$F$30 | O39: ='gerç aylık-eur'!$F$30 | Q39: ='Bütçe aylık-Eur'!$G$30 | R39: ='gerç aylık-eur'!$G$30 | T39: ='Bütçe aylık-Eur'!$H$30 | U39: ='gerç aylık-eur'!$H$30 | W39: ='Bütçe aylık-Eur'!$I$30 | X39: ='gerç aylık-eur'!$I$30 | Z39: ='Bütçe aylık-Eur'!$J$30 | AA39: ='gerç aylık-eur'!$J$30 | AC39: ='Bütçe aylık-Eur'!$K$30 | AD39: ='gerç aylık-eur'!$K$30 | AF39: ='Bütçe aylık-Eur'!$L$30 | AG39: ='gerç aylık-eur'!$L$30 | AI39: ='Bütçe aylık-Eur'!$M$30 | AJ39: ='gerç aylık-eur'!$M$30 | AL39: =AP39-AO39 | AM39: =AP39/AO39-1 | AO39: =IF($A$1=$B$1,B39,IF($A$1=$E$1,E39,IF($A$1=$H$1,H39,IF($A$1=$K$1,K39,IF($A$1=$N$1,N39,IF($A$1=$Q$1,Q39,IF($A$1=$T$1,T39,IF($A$1=$W$1,W39,IF($A$1=$Z$1,Z39,IF($A$1=$AC$1,AC39,IF($A$1=$AF$1,AF39,IF($A$1=$AI$1,AI39)))))))))))) | AP39: =IF($A$1=$B$1,C39,IF($A$1=$E$1,F39,IF($A$1=$H$1,I39,IF($A$1=$K$1,L39,IF($A$1=$N$1,O39,IF($A$1=$Q$1,R39,IF($A$1=$T$1,U39,IF($A$1=$W$1,X39,IF($A$1=$Z$1,AA39,IF($A$1=$AC$1,AD39,IF($A$1=$AF$1,AG39,IF($A$1=$AI$1,AJ39))))))))))))
A40: Yusen İnci Loj. | B40: ='Bütçe aylık-Eur'!$B$31 | C40: ='gerç aylık-eur'!$B$31 | E40: ='Bütçe aylık-Eur'!$C$31 | F40: ='gerç aylık-eur'!$C$31 | H40: ='Bütçe aylık-Eur'!$D$31 | I40: ='gerç aylık-eur'!$D$31 | K40: ='Bütçe aylık-Eur'!$E$31 | L40: ='gerç aylık-eur'!$E$31 | N40: ='Bütçe aylık-Eur'!$F$31 | O40: ='gerç aylık-eur'!$F$31 | Q40: ='Bütçe aylık-Eur'!$G$31 | R40: ='gerç aylık-eur'!$G$31 | T40: ='Bütçe aylık-Eur'!$H$31 | U40: ='gerç aylık-eur'!$H$31 | W40: ='Bütçe aylık-Eur'!$I$31 | X40: ='gerç aylık-eur'!$I$31 | Z40: ='Bütçe aylık-Eur'!$J$31 | AA40: ='gerç aylık-eur'!$J$31 | AC40: ='Bütçe aylık-Eur'!$K$31 | AD40: ='gerç aylık-eur'!$K$31 | AF40: ='Bütçe aylık-Eur'!$L$31 | AG40: ='gerç aylık-eur'!$L$31 | AI40: ='Bütçe aylık-Eur'!$M$31 | AJ40: ='gerç aylık-eur'!$M$31 | AL40: =AP40-AO40 | AM40: =AP40/AO40-1 | AO40: =IF($A$1=$B$1,B40,IF($A$1=$E$1,E40,IF($A$1=$H$1,H40,IF($A$1=$K$1,K40,IF($A$1=$N$1,N40,IF($A$1=$Q$1,Q40,IF($A$1=$T$1,T40,IF($A$1=$W$1,W40,IF($A$1=$Z$1,Z40,IF($A$1=$AC$1,AC40,IF($A$1=$AF$1,AF40,IF($A$1=$AI$1,AI40)))))))))))) | AP40: =IF($A$1=$B$1,C40,IF($A$1=$E$1,F40,IF($A$1=$H$1,I40,IF($A$1=$K$1,L40,IF($A$1=$N$1,O40,IF($A$1=$Q$1,R40,IF($A$1=$T$1,U40,IF($A$1=$W$1,X40,IF($A$1=$Z$1,AA40,IF($A$1=$AC$1,AD40,IF($A$1=$AF$1,AG40,IF($A$1=$AI$1,AJ40))))))))))))
A41: Jantaş | B41: ='Bütçe aylık-Eur'!$B$32 | C41: ='gerç aylık-eur'!$B$32 | E41: ='Bütçe aylık-Eur'!$C$32 | F41: ='gerç aylık-eur'!$C$32 | H41: ='Bütçe aylık-Eur'!$D$32 | I41: ='gerç aylık-eur'!$D$32 | K41: ='Bütçe aylık-Eur'!$E$32 | L41: ='gerç aylık-eur'!$E$32 | N41: ='Bütçe aylık-Eur'!$F$32 | O41: ='gerç aylık-eur'!$F$32 | Q41: ='Bütçe aylık-Eur'!$G$32 | R41: ='gerç aylık-eur'!$G$32 | T41: ='Bütçe aylık-Eur'!$H$32 | U41: ='gerç aylık-eur'!$H$32 | W41: ='Bütçe aylık-Eur'!$I$32 | X41: ='gerç aylık-eur'!$I$32 | Z41: ='Bütçe aylık-Eur'!$J$32 | AA41: ='gerç aylık-eur'!$J$32 | AC41: ='Bütçe aylık-Eur'!$K$32 | AD41: ='gerç aylık-eur'!$K$32 | AF41: ='Bütçe aylık-Eur'!$L$32 | AG41: ='gerç aylık-eur'!$L$32 | AI41: ='Bütçe aylık-Eur'!$M$32 | AJ41: ='gerç aylık-eur'!$M$32 | AL41: =AP41-AO41 | AM41: =AP41/AO41-1 | AO41: =IF($A$1=$B$1,B41,IF($A$1=$E$1,E41,IF($A$1=$H$1,H41,IF($A$1=$K$1,K41,IF($A$1=$N$1,N41,IF($A$1=$Q$1,Q41,IF($A$1=$T$1,T41,IF($A$1=$W$1,W41,IF($A$1=$Z$1,Z41,IF($A$1=$AC$1,AC41,IF($A$1=$AF$1,AF41,IF($A$1=$AI$1,AI41)))))))))))) | AP41: =IF($A$1=$B$1,C41,IF($A$1=$E$1,F41,IF($A$1=$H$1,I41,IF($A$1=$K$1,L41,IF($A$1=$N$1,O41,IF($A$1=$Q$1,R41,IF($A$1=$T$1,U41,IF($A$1=$W$1,X41,IF($A$1=$Z$1,AA41,IF($A$1=$AC$1,AD41,IF($A$1=$AF$1,AG41,IF($A$1=$AI$1,AJ41))))))))))))
A42: Çelik | B42: ='Bütçe aylık-Eur'!$B$33 | C42: ='gerç aylık-eur'!$B$33 | E42: ='Bütçe aylık-Eur'!$C$33 | F42: ='gerç aylık-eur'!$C$33 | H42: ='Bütçe aylık-Eur'!$D$33 | I42: ='gerç aylık-eur'!$D$33 | K42: ='Bütçe aylık-Eur'!$E$33 | L42: ='gerç aylık-eur'!$E$33 | N42: ='Bütçe aylık-Eur'!$F$33 | O42: ='gerç aylık-eur'!$F$33 | Q42: ='Bütçe aylık-Eur'!$G$33 | R42: ='gerç aylık-eur'!$G$33 | T42: ='Bütçe aylık-Eur'!$H$33 | U42: ='gerç aylık-eur'!$H$33 | W42: ='Bütçe aylık-Eur'!$I$33 | X42: ='gerç aylık-eur'!$I$33 | Z42: ='Bütçe aylık-Eur'!$J$33 | AA42: ='gerç aylık-eur'!$J$33 | AC42: ='Bütçe aylık-Eur'!$K$33 | AD42: ='gerç aylık-eur'!$K$33 | AF42: ='Bütçe aylık-Eur'!$L$33 | AG42: ='gerç aylık-eur'!$L$33 | AI42: ='Bütçe aylık-Eur'!$M$33 | AJ42: ='gerç aylık-eur'!$M$33 | AL42: =AP42-AO42 | AM42: =AP42/AO42-1 | AO42: =IF($A$1=$B$1,B42,IF($A$1=$E$1,E42,IF($A$1=$H$1,H42,IF($A$1=$K$1,K42,IF($A$1=$N$1,N42,IF($A$1=$Q$1,Q42,IF($A$1=$T$1,T42,IF($A$1=$W$1,W42,IF($A$1=$Z$1,Z42,IF($A$1=$AC$1,AC42,IF($A$1=$AF$1,AF42,IF($A$1=$AI$1,AI42)))))))))))) | AP42: =IF($A$1=$B$1,C42,IF($A$1=$E$1,F42,IF($A$1=$H$1,I42,IF($A$1=$K$1,L42,IF($A$1=$N$1,O42,IF($A$1=$Q$1,R42,IF($A$1=$T$1,U42,IF($A$1=$W$1,X42,IF($A$1=$Z$1,AA42,IF($A$1=$AC$1,AD42,IF($A$1=$AF$1,AG42,IF($A$1=$AI$1,AJ42))))))))))))
A43: Alüminyum | B43: ='Bütçe aylık-Eur'!$B$34 | C43: ='gerç aylık-eur'!$B$34 | E43: ='Bütçe aylık-Eur'!$C$34 | F43: ='gerç aylık-eur'!$C$34 | H43: ='Bütçe aylık-Eur'!$D$34 | I43: ='gerç aylık-eur'!$D$34 | K43: ='Bütçe aylık-Eur'!$E$34 | L43: ='gerç aylık-eur'!$E$34 | N43: ='Bütçe aylık-Eur'!$F$34 | O43: ='gerç aylık-eur'!$F$34 | Q43: ='Bütçe aylık-Eur'!$G$34 | R43: ='gerç aylık-eur'!$G$34 | T43: ='Bütçe aylık-Eur'!$H$34 | U43: ='gerç aylık-eur'!$H$34 | W43: ='Bütçe aylık-Eur'!$I$34 | X43: ='gerç aylık-eur'!$I$34 | Z43: ='Bütçe aylık-Eur'!$J$34 | AA43: ='gerç aylık-eur'!$J$34 | AC43: ='Bütçe aylık-Eur'!$K$34 | AD43: ='gerç aylık-eur'!$K$34 | AF43: ='Bütçe aylık-Eur'!$L$34 | AG43: ='gerç aylık-eur'!$L$34 | AI43: ='Bütçe aylık-Eur'!$M$34 | AJ43: ='gerç aylık-eur'!$M$34 | AL43: =AP43-AO43 | AM43: =AP43/AO43-1 | AO43: =IF($A$1=$B$1,B43,IF($A$1=$E$1,E43,IF($A$1=$H$1,H43,IF($A$1=$K$1,K43,IF($A$1=$N$1,N43,IF($A$1=$Q$1,Q43,IF($A$1=$T$1,T43,IF($A$1=$W$1,W43,IF($A$1=$Z$1,Z43,IF($A$1=$AC$1,AC43,IF($A$1=$AF$1,AF43,IF($A$1=$AI$1,AI43)))))))))))) | AP43: =IF($A$1=$B$1,C43,IF($A$1=$E$1,F43,IF($A$1=$H$1,I43,IF($A$1=$K$1,L43,IF($A$1=$N$1,O43,IF($A$1=$Q$1,R43,IF($A$1=$T$1,U43,IF($A$1=$W$1,X43,IF($A$1=$Z$1,AA43,IF($A$1=$AC$1,AD43,IF($A$1=$AF$1,AG43,IF($A$1=$AI$1,AJ43))))))))))))
AO44: =IF($A$1=$B$1,B44,IF($A$1=$E$1,E44,IF($A$1=$H$1,H44,IF($A$1=$K$1,K44,IF($A$1=$N$1,N44,IF($A$1=$Q$1,Q44,IF($A$1=$T$1,T44,IF($A$1=$W$1,W44,IF($A$1=$Z$1,Z44,IF($A$1=$AC$1,AC44,IF($A$1=$AF$1,AF44,IF($A$1=$AI$1,AI44)))))))))))) | AP44: =IF($A$1=$B$1,C44,IF($A$1=$E$1,F44,IF($A$1=$H$1,I44,IF($A$1=$K$1,L44,IF($A$1=$N$1,O44,IF($A$1=$Q$1,R44,IF($A$1=$T$1,U44,IF($A$1=$W$1,X44,IF($A$1=$Z$1,AA44,IF($A$1=$AC$1,AD44,IF($A$1=$AF$1,AG44,IF($A$1=$AI$1,AJ44))))))))))))
AL45: =AP45-AO45 | AM45: =AP45/AO45-1 | AO45: =IF($A$1=$B$1,B45,IF($A$1=$E$1,E45,IF($A$1=$H$1,H45,IF($A$1=$K$1,K45,IF($A$1=$N$1,N45,IF($A$1=$Q$1,Q45,IF($A$1=$T$1,T45,IF($A$1=$W$1,W45,IF($A$1=$Z$1,Z45,IF($A$1=$AC$1,AC45,IF($A$1=$AF$1,AF45,IF($A$1=$AI$1,AI45)))))))))))) | AP45: =IF($A$1=$B$1,C45,IF($A$1=$E$1,F45,IF($A$1=$H$1,I45,IF($A$1=$K$1,L45,IF($A$1=$N$1,O45,IF($A$1=$Q$1,R45,IF($A$1=$T$1,U45,IF($A$1=$W$1,X45,IF($A$1=$Z$1,AA45,IF($A$1=$AC$1,AD45,IF($A$1=$AF$1,AG45,IF($A$1=$AI$1,AJ45))))))))))))
AL46: =AP46-AO46 | AM46: =AP46/AO46-1 | AO46: =IF($A$1=$B$1,B46,IF($A$1=$E$1,E46,IF($A$1=$H$1,H46,IF($A$1=$K$1,K46,IF($A$1=$N$1,N46,IF($A$1=$Q$1,Q46,IF($A$1=$T$1,T46,IF($A$1=$W$1,W46,IF($A$1=$Z$1,Z46,IF($A$1=$AC$1,AC46,IF($A$1=$AF$1,AF46,IF($A$1=$AI$1,AI46)))))))))))) | AP46: =IF($A$1=$B$1,C46,IF($A$1=$E$1,F46,IF($A$1=$H$1,I46,IF($A$1=$K$1,L46,IF($A$1=$N$1,O46,IF($A$1=$Q$1,R46,IF($A$1=$T$1,U46,IF($A$1=$W$1,X46,IF($A$1=$Z$1,AA46,IF($A$1=$AC$1,AD46,IF($A$1=$AF$1,AG46,IF($A$1=$AI$1,AJ46))))))))))))
AL47: =AP47-AO47 | AM47: =AP47/AO47-1 | AO47: =IF($A$1=$B$1,B47,IF($A$1=$E$1,E47,IF($A$1=$H$1,H47,IF($A$1=$K$1,K47,IF($A$1=$N$1,N47,IF($A$1=$Q$1,Q47,IF($A$1=$T$1,T47,IF($A$1=$W$1,W47,IF($A$1=$Z$1,Z47,IF($A$1=$AC$1,AC47,IF($A$1=$AF$1,AF47,IF($A$1=$AI$1,AI47)))))))))))) | AP47: =IF($A$1=$B$1,C47,IF($A$1=$E$1,F47,IF($A$1=$H$1,I47,IF($A$1=$K$1,L47,IF($A$1=$N$1,O47,IF($A$1=$Q$1,R47,IF($A$1=$T$1,U47,IF($A$1=$W$1,X47,IF($A$1=$Z$1,AA47,IF($A$1=$AC$1,AD47,IF($A$1=$AF$1,AG47,IF($A$1=$AI$1,AJ47))))))))))))
AL48: =AP48-AO48 | AM48: =AP48/AO48-1 | AO48: =IF($A$1=$B$1,B48,IF($A$1=$E$1,E48,IF($A$1=$H$1,H48,IF($A$1=$K$1,K48,IF($A$1=$N$1,N48,IF($A$1=$Q$1,Q48,IF($A$1=$T$1,T48,IF($A$1=$W$1,W48,IF($A$1=$Z$1,Z48,IF($A$1=$AC$1,AC48,IF($A$1=$AF$1,AF48,IF($A$1=$AI$1,AI48)))))))))))) | AP48: =IF($A$1=$B$1,C48,IF($A$1=$E$1,F48,IF($A$1=$H$1,I48,IF($A$1=$K$1,L48,IF($A$1=$N$1,O48,IF($A$1=$Q$1,R48,IF($A$1=$T$1,U48,IF($A$1=$W$1,X48,IF($A$1=$Z$1,AA48,IF($A$1=$AC$1,AD48,IF($A$1=$AF$1,AG48,IF($A$1=$AI$1,AJ48))))))))))))
AO49: =IF($A$1=$B$1,B49,IF($A$1=$E$1,E49,IF($A$1=$H$1,H49,IF($A$1=$K$1,K49,IF($A$1=$N$1,N49,IF($A$1=$Q$1,Q49,IF($A$1=$T$1,T49,IF($A$1=$W$1,W49,IF($A$1=$Z$1,Z49,IF($A$1=$AC$1,AC49,IF($A$1=$AF$1,AF49,IF($A$1=$AI$1,AI49)))))))))))) | AP49: =IF($A$1=$B$1,C49,IF($A$1=$E$1,F49,IF($A$1=$H$1,I49,IF($A$1=$K$1,L49,IF($A$1=$N$1,O49,IF($A$1=$Q$1,R49,IF($A$1=$T$1,U49,IF($A$1=$W$1,X49,IF($A$1=$Z$1,AA49,IF($A$1=$AC$1,AD49,IF($A$1=$AF$1,AG49,IF($A$1=$AI$1,AJ49))))))))))))
AL50: =AP50-AO50 | AM50: =AP50/AO50-1 | AO50: =IF($A$1=$B$1,B50,IF($A$1=$E$1,E50,IF($A$1=$H$1,H50,IF($A$1=$K$1,K50,IF($A$1=$N$1,N50,IF($A$1=$Q$1,Q50,IF($A$1=$T$1,T50,IF($A$1=$W$1,W50,IF($A$1=$Z$1,Z50,IF($A$1=$AC$1,AC50,IF($A$1=$AF$1,AF50,IF($A$1=$AI$1,AI50)))))))))))) | AP50: =IF($A$1=$B$1,C50,IF($A$1=$E$1,F50,IF($A$1=$H$1,I50,IF($A$1=$K$1,L50,IF($A$1=$N$1,O50,IF($A$1=$Q$1,R50,IF($A$1=$T$1,U50,IF($A$1=$W$1,X50,IF($A$1=$Z$1,AA50,IF($A$1=$AC$1,AD50,IF($A$1=$AF$1,AG50,IF($A$1=$AI$1,AJ50))))))))))))
AL51: =AP51-AO51 | AM51: =AP51/AO51-1 | AO51: =IF($A$1=$B$1,B51,IF($A$1=$E$1,E51,IF($A$1=$H$1,H51,IF($A$1=$K$1,K51,IF($A$1=$N$1,N51,IF($A$1=$Q$1,Q51,IF($A$1=$T$1,T51,IF($A$1=$W$1,W51,IF($A$1=$Z$1,Z51,IF($A$1=$AC$1,AC51,IF($A$1=$AF$1,AF51,IF($A$1=$AI$1,AI51)))))))))))) | AP51: =IF($A$1=$B$1,C51,IF($A$1=$E$1,F51,IF($A$1=$H$1,I51,IF($A$1=$K$1,L51,IF($A$1=$N$1,O51,IF($A$1=$Q$1,R51,IF($A$1=$T$1,U51,IF($A$1=$W$1,X51,IF($A$1=$Z$1,AA51,IF($A$1=$AC$1,AD51,IF($A$1=$AF$1,AG51,IF($A$1=$AI$1,AJ51))))))))))))
AL52: =AP52-AO52 | AM52: =AP52/AO52-1 | AO52: =IF($A$1=$B$1,B52,IF($A$1=$E$1,E52,IF($A$1=$H$1,H52,IF($A$1=$K$1,K52,IF($A$1=$N$1,N52,IF($A$1=$Q$1,Q52,IF($A$1=$T$1,T52,IF($A$1=$W$1,W52,IF($A$1=$Z$1,Z52,IF($A$1=$AC$1,AC52,IF($A$1=$AF$1,AF52,IF($A$1=$AI$1,AI52)))))))))))) | AP52: =IF($A$1=$B$1,C52,IF($A$1=$E$1,F52,IF($A$1=$H$1,I52,IF($A$1=$K$1,L52,IF($A$1=$N$1,O52,IF($A$1=$Q$1,R52,IF($A$1=$T$1,U52,IF($A$1=$W$1,X52,IF($A$1=$Z$1,AA52,IF($A$1=$AC$1,AD52,IF($A$1=$AF$1,AG52,IF($A$1=$AI$1,AJ52))))))))))))
AL53: =AP53-AO53 | AM53: =AP53/AO53-1 | AO53: =IF($A$1=$B$1,B53,IF($A$1=$E$1,E53,IF($A$1=$H$1,H53,IF($A$1=$K$1,K53,IF($A$1=$N$1,N53,IF($A$1=$Q$1,Q53,IF($A$1=$T$1,T53,IF($A$1=$W$1,W53,IF($A$1=$Z$1,Z53,IF($A$1=$AC$1,AC53,IF($A$1=$AF$1,AF53,IF($A$1=$AI$1,AI53)))))))))))) | AP53: =IF($A$1=$B$1,C53,IF($A$1=$E$1,F53,IF($A$1=$H$1,I53,IF($A$1=$K$1,L53,IF($A$1=$N$1,O53,IF($A$1=$Q$1,R53,IF($A$1=$T$1,U53,IF($A$1=$W$1,X53,IF($A$1=$Z$1,AA53,IF($A$1=$AC$1,AD53,IF($A$1=$AF$1,AG53,IF($A$1=$AI$1,AJ53))))))))))))
AL54: =AP54-AO54 | AM54: =AP54/AO54-1 | AO54: =IF($A$1=$B$1,B54,IF($A$1=$E$1,E54,IF($A$1=$H$1,H54,IF($A$1=$K$1,K54,IF($A$1=$N$1,N54,IF($A$1=$Q$1,Q54,IF($A$1=$T$1,T54,IF($A$1=$W$1,W54,IF($A$1=$Z$1,Z54,IF($A$1=$AC$1,AC54,IF($A$1=$AF$1,AF54,IF($A$1=$AI$1,AI54)))))))))))) | AP54: =IF($A$1=$B$1,C54,IF($A$1=$E$1,F54,IF($A$1=$H$1,I54,IF($A$1=$K$1,L54,IF($A$1=$N$1,O54,IF($A$1=$Q$1,R54,IF($A$1=$T$1,U54,IF($A$1=$W$1,X54,IF($A$1=$Z$1,AA54,IF($A$1=$AC$1,AD54,IF($A$1=$AF$1,AG54,IF($A$1=$AI$1,AJ54))))))))))))
AL55: =AP55-AO55 | AM55: =AP55/AO55-1 | AO55: =IF($A$1=$B$1,B55,IF($A$1=$E$1,E55,IF($A$1=$H$1,H55,IF($A$1=$K$1,K55,IF($A$1=$N$1,N55,IF($A$1=$Q$1,Q55,IF($A$1=$T$1,T55,IF($A$1=$W$1,W55,IF($A$1=$Z$1,Z55,IF($A$1=$AC$1,AC55,IF($A$1=$AF$1,AF55,IF($A$1=$AI$1,AI55)))))))))))) | AP55: =IF($A$1=$B$1,C55,IF($A$1=$E$1,F55,IF($A$1=$H$1,I55,IF($A$1=$K$1,L55,IF($A$1=$N$1,O55,IF($A$1=$Q$1,R55,IF($A$1=$T$1,U55,IF($A$1=$W$1,X55,IF($A$1=$Z$1,AA55,IF($A$1=$AC$1,AD55,IF($A$1=$AF$1,AG55,IF($A$1=$AI$1,AJ55))))))))))))
AL56: =AP56-AO56 | AM56: =AP56/AO56-1 | AO56: =IF($A$1=$B$1,B56,IF($A$1=$E$1,E56,IF($A$1=$H$1,H56,IF($A$1=$K$1,K56,IF($A$1=$N$1,N56,IF($A$1=$Q$1,Q56,IF($A$1=$T$1,T56,IF($A$1=$W$1,W56,IF($A$1=$Z$1,Z56,IF($A$1=$AC$1,AC56,IF($A$1=$AF$1,AF56,IF($A$1=$AI$1,AI56)))))))))))) | AP56: =IF($A$1=$B$1,C56,IF($A$1=$E$1,F56,IF($A$1=$H$1,I56,IF($A$1=$K$1,L56,IF($A$1=$N$1,O56,IF($A$1=$Q$1,R56,IF($A$1=$T$1,U56,IF($A$1=$W$1,X56,IF($A$1=$Z$1,AA56,IF($A$1=$AC$1,AD56,IF($A$1=$AF$1,AG56,IF($A$1=$AI$1,AJ56))))))))))))
AL57: =AP57-AO57 | AM57: =AP57/AO57-1 | AO57: =IF($A$1=$B$1,B57,IF($A$1=$E$1,E57,IF($A$1=$H$1,H57,IF($A$1=$K$1,K57,IF($A$1=$N$1,N57,IF($A$1=$Q$1,Q57,IF($A$1=$T$1,T57,IF($A$1=$W$1,W57,IF($A$1=$Z$1,Z57,IF($A$1=$AC$1,AC57,IF($A$1=$AF$1,AF57,IF($A$1=$AI$1,AI57)))))))))))) | AP57: =IF($A$1=$B$1,C57,IF($A$1=$E$1,F57,IF($A$1=$H$1,I57,IF($A$1=$K$1,L57,IF($A$1=$N$1,O57,IF($A$1=$Q$1,R57,IF($A$1=$T$1,U57,IF($A$1=$W$1,X57,IF($A$1=$Z$1,AA57,IF($A$1=$AC$1,AD57,IF($A$1=$AF$1,AG57,IF($A$1=$AI$1,AJ57))))))))))))
AL58: =AP58-AO58 | AM58: =AP58/AO58-1 | AO58: =IF($A$1=$B$1,B58,IF($A$1=$E$1,E58,IF($A$1=$H$1,H58,IF($A$1=$K$1,K58,IF($A$1=$N$1,N58,IF($A$1=$Q$1,Q58,IF($A$1=$T$1,T58,IF($A$1=$W$1,W58,IF($A$1=$Z$1,Z58,IF($A$1=$AC$1,AC58,IF($A$1=$AF$1,AF58,IF($A$1=$AI$1,AI58)))))))))))) | AP58: =IF($A$1=$B$1,C58,IF($A$1=$E$1,F58,IF($A$1=$H$1,I58,IF($A$1=$K$1,L58,IF($A$1=$N$1,O58,IF($A$1=$Q$1,R58,IF($A$1=$T$1,U58,IF($A$1=$W$1,X58,IF($A$1=$Z$1,AA58,IF($A$1=$AC$1,AD58,IF($A$1=$AF$1,AG58,IF($A$1=$AI$1,AJ58))))))))))))
AL59: =AP59-AO59 | AM59: =AP59/AO59-1 | AO59: =IF($A$1=$B$1,B59,IF($A$1=$E$1,E59,IF($A$1=$H$1,H59,IF($A$1=$K$1,K59,IF($A$1=$N$1,N59,IF($A$1=$Q$1,Q59,IF($A$1=$T$1,T59,IF($A$1=$W$1,W59,IF($A$1=$Z$1,Z59,IF($A$1=$AC$1,AC59,IF($A$1=$AF$1,AF59,IF($A$1=$AI$1,AI59)))))))))))) | AP59: =IF($A$1=$B$1,C59,IF($A$1=$E$1,F59,IF($A$1=$H$1,I59,IF($A$1=$K$1,L59,IF($A$1=$N$1,O59,IF($A$1=$Q$1,R59,IF($A$1=$T$1,U59,IF($A$1=$W$1,X59,IF($A$1=$Z$1,AA59,IF($A$1=$AC$1,AD59,IF($A$1=$AF$1,AG59,IF($A$1=$AI$1,AJ59))))))))))))
AL60: =AP60-AO60 | AM60: =AP60/AO60-1 | AO60: =IF($A$1=$B$1,B60,IF($A$1=$E$1,E60,IF($A$1=$H$1,H60,IF($A$1=$K$1,K60,IF($A$1=$N$1,N60,IF($A$1=$Q$1,Q60,IF($A$1=$T$1,T60,IF($A$1=$W$1,W60,IF($A$1=$Z$1,Z60,IF($A$1=$AC$1,AC60,IF($A$1=$AF$1,AF60,IF($A$1=$AI$1,AI60)))))))))))) | AP60: =IF($A$1=$B$1,C60,IF($A$1=$E$1,F60,IF($A$1=$H$1,I60,IF($A$1=$K$1,L60,IF($A$1=$N$1,O60,IF($A$1=$Q$1,R60,IF($A$1=$T$1,U60,IF($A$1=$W$1,X60,IF($A$1=$Z$1,AA60,IF($A$1=$AC$1,AD60,IF($A$1=$AF$1,AG60,IF($A$1=$AI$1,AJ60))))))))))))
AL61: =AP61-AO61 | AM61: =AP61/AO61-1 | AO61: =IF($A$1=$B$1,B61,IF($A$1=$E$1,E61,IF($A$1=$H$1,H61,IF($A$1=$K$1,K61,IF($A$1=$N$1,N61,IF($A$1=$Q$1,Q61,IF($A$1=$T$1,T61,IF($A$1=$W$1,W61,IF($A$1=$Z$1,Z61,IF($A$1=$AC$1,AC61,IF($A$1=$AF$1,AF61,IF($A$1=$AI$1,AI61)))))))))))) | AP61: =IF($A$1=$B$1,C61,IF($A$1=$E$1,F61,IF($A$1=$H$1,I61,IF($A$1=$K$1,L61,IF($A$1=$N$1,O61,IF($A$1=$Q$1,R61,IF($A$1=$T$1,U61,IF($A$1=$W$1,X61,IF($A$1=$Z$1,AA61,IF($A$1=$AC$1,AD61,IF($A$1=$AF$1,AG61,IF($A$1=$AI$1,AJ61))))))))))))
... AL75: =AP75-AO75 | AM75: =AP75/AO75-1 | AO75: =IF($A$1=$B$1,B75,IF($A$1=$E$1,E75,IF($A$1=$H$1,H75,IF($A$1=$K$1,K75,IF($A$1=$N$1,N75,IF($A$1=$Q$1,Q75,IF($A$1=$T$1,T75,IF($A$1=$W$1,W75,IF($A$1=$Z$1,Z75,IF($A$1=$AC$1,AC75,IF($A$1=$AF$1,AF75,IF($A$1=$AI$1,AI75)))))))))))) | AP75: =IF($A$1=$B$1,C75,IF($A$1=$E$1,F75,IF($A$1=$H$1,I75,IF($A$1=$K$1,L75,IF($A$1=$N$1,O75,IF($A$1=$Q$1,R75,IF($A$1=$T$1,U75,IF($A$1=$W$1,X75,IF($A$1=$Z$1,AA75,IF($A$1=$AC$1,AD75,IF($A$1=$AF$1,AG75,IF($A$1=$AI$1,AJ75))))))))))))
A78: GROSS PROFIT MARGIN BY CHANNELS
A79: İnci Holding | B79: =B36/B9 | C79: =IFERROR((C36/C9),"") | E79: =E36/E9 | F79: =IFERROR((F36/F9),"") | H79: =H36/H9 | I79: =IFERROR((I36/I9),"") | K79: =K36/K9 | L79: =IFERROR((L36/L9),"") | N79: =N36/N9 | O79: =IFERROR((O36/O9),"") | Q79: =Q36/Q9 | R79: =IFERROR((R36/R9),"") | T79: =T36/T9 | U79: =IFERROR((U36/U9),"") | W79: =W36/W9 | X79: =IFERROR((X36/X9),"") | Z79: =Z36/Z9 | AA79: =IFERROR((AA36/AA9),"") | AC79: =AC36/AC9 | AD79: =IFERROR((AD36/AD9),"") | AF79: =AF36/AF9 | AG79: =IFERROR((AG36/AG9),"") | AI79: =AI36/AI9 | AJ79: =IFERROR((AJ36/AJ9),"") | AM79: =AP79-AO79 | AO79: =IF($A$1=$B$1,B79,IF($A$1=$E$1,E79,IF($A$1=$H$1,H79,IF($A$1=$K$1,K79,IF($A$1=$N$1,N79,IF($A$1=$Q$1,Q79,IF($A$1=$T$1,T79,IF($A$1=$W$1,W79,IF($A$1=$Z$1,Z79,IF($A$1=$AC$1,AC79,IF($A$1=$AF$1,AF79,IF($A$1=$AI$1,AI79)))))))))))) | AP79: =IF($A$1=$B$1,C79,IF($A$1=$E$1,F79,IF($A$1=$H$1,I79,IF($A$1=$K$1,L79,IF($A$1=$N$1,O79,IF($A$1=$Q$1,R79,IF($A$1=$T$1,U79,IF($A$1=$W$1,X79,IF($A$1=$Z$1,AA79,IF($A$1=$AC$1,AD79,IF($A$1=$AF$1,AG79,IF($A$1=$AI$1,AJ79))))))))))))
A80: ISM | B80: =B37/B10 | C80: =IFERROR((C37/C10),"") | E80: =E37/E10 | F80: =IFERROR((F37/F10),"") | H80: =H37/H10 | I80: =IFERROR((I37/I10),"") | K80: =K37/K10 | L80: =IFERROR((L37/L10),"") | N80: =N37/N10 | O80: =IFERROR((O37/O10),"") | Q80: =Q37/Q10 | R80: =IFERROR((R37/R10),"") | T80: =T37/T10 | U80: =IFERROR((U37/U10),"") | W80: =W37/W10 | X80: =IFERROR((X37/X10),"") | Z80: =Z37/Z10 | AA80: =IFERROR((AA37/AA10),"") | AC80: =AC37/AC10 | AD80: =IFERROR((AD37/AD10),"") | AF80: =AF37/AF10 | AG80: =IFERROR((AG37/AG10),"") | AI80: =AI37/AI10 | AJ80: =IFERROR((AJ37/AJ10),"") | AM80: =AP80-AO80 | AO80: =IF($A$1=$B$1,B80,IF($A$1=$E$1,E80,IF($A$1=$H$1,H80,IF($A$1=$K$1,K80,IF($A$1=$N$1,N80,IF($A$1=$Q$1,Q80,IF($A$1=$T$1,T80,IF($A$1=$W$1,W80,IF($A$1=$Z$1,Z80,IF($A$1=$AC$1,AC80,IF($A$1=$AF$1,AF80,IF($A$1=$AI$1,AI80)))))))))))) | AP80: =IF($A$1=$B$1,C80,IF($A$1=$E$1,F80,IF($A$1=$H$1,I80,IF($A$1=$K$1,L80,IF($A$1=$N$1,O80,IF($A$1=$Q$1,R80,IF($A$1=$T$1,U80,IF($A$1=$W$1,X80,IF($A$1=$Z$1,AA80,IF($A$1=$AC$1,AD80,IF($A$1=$AF$1,AG80,IF($A$1=$AI$1,AJ80))))))))))))
A81: İncitaş | B81: =B38/B11 | C81: =IFERROR((C38/C11),"") | E81: =E38/E11 | F81: =IFERROR((F38/F11),"") | H81: =H38/H11 | I81: =IFERROR((I38/I11),"") | K81: =K38/K11 | L81: =IFERROR((L38/L11),"") | N81: =N38/N11 | O81: =IFERROR((O38/O11),"") | Q81: =Q38/Q11 | R81: =IFERROR((R38/R11),"") | T81: =T38/T11 | U81: =IFERROR((U38/U11),"") | W81: =W38/W11 | X81: =IFERROR((X38/X11),"") | Z81: =Z38/Z11 | AA81: =IFERROR((AA38/AA11),"") | AC81: =AC38/AC11 | AD81: =IFERROR((AD38/AD11),"") | AF81: =AF38/AF11 | AG81: =IFERROR((AG38/AG11),"") | AI81: =AI38/AI11 | AJ81: =IFERROR((AJ38/AJ11),"") | AM81: =AP81-AO81 | AO81: =IF($A$1=$B$1,B81,IF($A$1=$E$1,E81,IF($A$1=$H$1,H81,IF($A$1=$K$1,K81,IF($A$1=$N$1,N81,IF($A$1=$Q$1,Q81,IF($A$1=$T$1,T81,IF($A$1=$W$1,W81,IF($A$1=$Z$1,Z81,IF($A$1=$AC$1,AC81,IF($A$1=$AF$1,AF81,IF($A$1=$AI$1,AI81)))))))))))) | AP81: =IF($A$1=$B$1,C81,IF($A$1=$E$1,F81,IF($A$1=$H$1,I81,IF($A$1=$K$1,L81,IF($A$1=$N$1,O81,IF($A$1=$Q$1,R81,IF($A$1=$T$1,U81,IF($A$1=$W$1,X81,IF($A$1=$Z$1,AA81,IF($A$1=$AC$1,AD81,IF($A$1=$AF$1,AG81,IF($A$1=$AI$1,AJ81))))))))))))
A82: İnci GS Yuasa | B82: =B39/B12 | C82: =IFERROR((C39/C12),"") | E82: =E39/E12 | F82: =IFERROR((F39/F12),"") | H82: =H39/H12 | I82: =IFERROR((I39/I12),"") | K82: =K39/K12 | L82: =IFERROR((L39/L12),"") | N82: =N39/N12 | O82: =IFERROR((O39/O12),"") | Q82: =Q39/Q12 | R82: =IFERROR((R39/R12),"") | T82: =T39/T12 | U82: =IFERROR((U39/U12),"") | W82: =W39/W12 | X82: =IFERROR((X39/X12),"") | Z82: =Z39/Z12 | AA82: =IFERROR((AA39/AA12),"") | AC82: =AC39/AC12 | AD82: =IFERROR((AD39/AD12),"") | AF82: =AF39/AF12 | AG82: =IFERROR((AG39/AG12),"") | AI82: =AI39/AI12 | AJ82: =IFERROR((AJ39/AJ12),"") | AM82: =AP82-AO82 | AO82: =IF($A$1=$B$1,B82,IF($A$1=$E$1,E82,IF($A$1=$H$1,H82,IF($A$1=$K$1,K82,IF($A$1=$N$1,N82,IF($A$1=$Q$1,Q82,IF($A$1=$T$1,T82,IF($A$1=$W$1,W82,IF($A$1=$Z$1,Z82,IF($A$1=$AC$1,AC82,IF($A$1=$AF$1,AF82,IF($A$1=$AI$1,AI82)))))))))))) | AP82: =IF($A$1=$B$1,C82,IF($A$1=$E$1,F82,IF($A$1=$H$1,I82,IF($A$1=$K$1,L82,IF($A$1=$N$1,O82,IF($A$1=$Q$1,R82,IF($A$1=$T$1,U82,IF($A$1=$W$1,X82,IF($A$1=$Z$1,AA82,IF($A$1=$AC$1,AD82,IF($A$1=$AF$1,AG82,IF($A$1=$AI$1,AJ82))))))))))))
A83: Yusen İnci Loj. | B83: =B40/B13 | C83: =IFERROR((C40/C13),"") | E83: =E40/E13 | F83: =IFERROR((F40/F13),"") | H83: =H40/H13 | I83: =IFERROR((I40/I13),"") | K83: =K40/K13 | L83: =IFERROR((L40/L13),"") | N83: =N40/N13 | O83: =IFERROR((O40/O13),"") | Q83: =Q40/Q13 | R83: =IFERROR((R40/R13),"") | T83: =T40/T13 | U83: =IFERROR((U40/U13),"") | W83: =W40/W13 | X83: =IFERROR((X40/X13),"") | Z83: =Z40/Z13 | AA83: =IFERROR((AA40/AA13),"") | AC83: =AC40/AC13 | AD83: =IFERROR((AD40/AD13),"") | AF83: =AF40/AF13 | AG83: =IFERROR((AG40/AG13),"") | AI83: =AI40/AI13 | AJ83: =IFERROR((AJ40/AJ13),"") | AM83: =AP83-AO83 | AO83: =IF($A$1=$B$1,B83,IF($A$1=$E$1,E83,IF($A$1=$H$1,H83,IF($A$1=$K$1,K83,IF($A$1=$N$1,N83,IF($A$1=$Q$1,Q83,IF($A$1=$T$1,T83,IF($A$1=$W$1,W83,IF($A$1=$Z$1,Z83,IF($A$1=$AC$1,AC83,IF($A$1=$AF$1,AF83,IF($A$1=$AI$1,AI83)))))))))))) | AP83: =IF($A$1=$B$1,C83,IF($A$1=$E$1,F83,IF($A$1=$H$1,I83,IF($A$1=$K$1,L83,IF($A$1=$N$1,O83,IF($A$1=$Q$1,R83,IF($A$1=$T$1,U83,IF($A$1=$W$1,X83,IF($A$1=$Z$1,AA83,IF($A$1=$AC$1,AD83,IF($A$1=$AF$1,AG83,IF($A$1=$AI$1,AJ83))))))))))))
A84: Jantaş | B84: =B41/B14 | C84: =IFERROR((C41/C14),"") | E84: =E41/E14 | F84: =IFERROR((F41/F14),"") | H84: =H41/H14 | I84: =IFERROR((I41/I14),"") | K84: =K41/K14 | L84: =IFERROR((L41/L14),"") | N84: =N41/N14 | O84: =IFERROR((O41/O14),"") | Q84: =Q41/Q14 | R84: =IFERROR((R41/R14),"") | T84: =T41/T14 | U84: =IFERROR((U41/U14),"") | W84: =W41/W14 | X84: =IFERROR((X41/X14),"") | Z84: =Z41/Z14 | AA84: =IFERROR((AA41/AA14),"") | AC84: =AC41/AC14 | AD84: =IFERROR((AD41/AD14),"") | AF84: =AF41/AF14 | AG84: =IFERROR((AG41/AG14),"") | AI84: =AI41/AI14 | AJ84: =IFERROR((AJ41/AJ14),"") | AM84: =AP84-AO84 | AO84: =IF($A$1=$B$1,B84,IF($A$1=$E$1,E84,IF($A$1=$H$1,H84,IF($A$1=$K$1,K84,IF($A$1=$N$1,N84,IF($A$1=$Q$1,Q84,IF($A$1=$T$1,T84,IF($A$1=$W$1,W84,IF($A$1=$Z$1,Z84,IF($A$1=$AC$1,AC84,IF($A$1=$AF$1,AF84,IF($A$1=$AI$1,AI84)))))))))))) | AP84: =IF($A$1=$B$1,C84,IF($A$1=$E$1,F84,IF($A$1=$H$1,I84,IF($A$1=$K$1,L84,IF($A$1=$N$1,O84,IF($A$1=$Q$1,R84,IF($A$1=$T$1,U84,IF($A$1=$W$1,X84,IF($A$1=$Z$1,AA84,IF($A$1=$AC$1,AD84,IF($A$1=$AF$1,AG84,IF($A$1=$AI$1,AJ84))))))))))))
A85: Çelik | B85: =B42/B15 | C85: =IFERROR((C42/C15),"") | E85: =E42/E15 | F85: =IFERROR((F42/F15),"") | H85: =H42/H15 | I85: =IFERROR((I42/I15),"") | K85: =K42/K15 | L85: =IFERROR((L42/L15),"") | N85: =N42/N15 | O85: =IFERROR((O42/O15),"") | Q85: =Q42/Q15 | R85: =IFERROR((R42/R15),"") | T85: =T42/T15 | U85: =IFERROR((U42/U15),"") | W85: =W42/W15 | X85: =IFERROR((X42/X15),"") | Z85: =Z42/Z15 | AA85: =IFERROR((AA42/AA15),"") | AC85: =AC42/AC15 | AD85: =IFERROR((AD42/AD15),"") | AF85: =AF42/AF15 | AG85: =IFERROR((AG42/AG15),"") | AI85: =AI42/AI15 | AJ85: =IFERROR((AJ42/AJ15),"") | AM85: =AP85-AO85 | AO85: =IF($A$1=$B$1,B85,IF($A$1=$E$1,E85,IF($A$1=$H$1,H85,IF($A$1=$K$1,K85,IF($A$1=$N$1,N85,IF($A$1=$Q$1,Q85,IF($A$1=$T$1,T85,IF($A$1=$W$1,W85,IF($A$1=$Z$1,Z85,IF($A$1=$AC$1,AC85,IF($A$1=$AF$1,AF85,IF($A$1=$AI$1,AI85)))))))))))) | AP85: =IF($A$1=$B$1,C85,IF($A$1=$E$1,F85,IF($A$1=$H$1,I85,IF($A$1=$K$1,L85,IF($A$1=$N$1,O85,IF($A$1=$Q$1,R85,IF($A$1=$T$1,U85,IF($A$1=$W$1,X85,IF($A$1=$Z$1,AA85,IF($A$1=$AC$1,AD85,IF($A$1=$AF$1,AG85,IF($A$1=$AI$1,AJ85))))))))))))
A86: Alüminyum | B86: =B43/B16 | C86: =IFERROR((C43/C16),"") | E86: =E43/E16 | F86: =IFERROR((F43/F16),"") | H86: =H43/H16 | I86: =IFERROR((I43/I16),"") | K86: =K43/K16 | L86: =IFERROR((L43/L16),"") | N86: =N43/N16 | O86: =IFERROR((O43/O16),"") | Q86: =Q43/Q16 | R86: =IFERROR((R43/R16),"") | T86: =T43/T16 | U86: =IFERROR((U43/U16),"") | W86: =W43/W16 | X86: =IFERROR((X43/X16),"") | Z86: =Z43/Z16 | AA86: =IFERROR((AA43/AA16),"") | AC86: =AC43/AC16 | AD86: =IFERROR((AD43/AD16),"") | AF86: =AF43/AF16 | AG86: =IFERROR((AG43/AG16),"") | AI86: =AI43/AI16 | AJ86: =IFERROR((AJ43/AJ16),"") | AM86: =AP86-AO86 | AO86: =IF($A$1=$B$1,B86,IF($A$1=$E$1,E86,IF($A$1=$H$1,H86,IF($A$1=$K$1,K86,IF($A$1=$N$1,N86,IF($A$1=$Q$1,Q86,IF($A$1=$T$1,T86,IF($A$1=$W$1,W86,IF($A$1=$Z$1,Z86,IF($A$1=$AC$1,AC86,IF($A$1=$AF$1,AF86,IF($A$1=$AI$1,AI86)))))))))))) | AP86: =IF($A$1=$B$1,C86,IF($A$1=$E$1,F86,IF($A$1=$H$1,I86,IF($A$1=$K$1,L86,IF($A$1=$N$1,O86,IF($A$1=$Q$1,R86,IF($A$1=$T$1,U86,IF($A$1=$W$1,X86,IF($A$1=$Z$1,AA86,IF($A$1=$AC$1,AD86,IF($A$1=$AF$1,AG86,IF($A$1=$AI$1,AJ86))))))))))))
C87: =IFERROR((C44/C17),"") | F87: =IFERROR((F44/F17),"") | I87: =IFERROR((I44/I17),"") | L87: =IFERROR((L44/L17),"") | O87: =IFERROR((O44/O17),"") | R87: =IFERROR((R44/R17),"") | U87: =IFERROR((U44/U17),"") | X87: =IFERROR((X44/X17),"") | AA87: =IFERROR((AA44/AA17),"") | AD87: =IFERROR((AD44/AD17),"") | AG87: =IFERROR((AG44/AG17),"") | AJ87: =IFERROR((AJ44/AJ17),"") | AO87: =IF($A$1=$B$1,B87,IF($A$1=$E$1,E87,IF($A$1=$H$1,H87,IF($A$1=$K$1,K87,IF($A$1=$N$1,N87,IF($A$1=$Q$1,Q87,IF($A$1=$T$1,T87,IF($A$1=$W$1,W87,IF($A$1=$Z$1,Z87,IF($A$1=$AC$1,AC87,IF($A$1=$AF$1,AF87,IF($A$1=$AI$1,AI87)))))))))))) | AP87: =IF($A$1=$B$1,C87,IF($A$1=$E$1,F87,IF($A$1=$H$1,I87,IF($A$1=$K$1,L87,IF($A$1=$N$1,O87,IF($A$1=$Q$1,R87,IF($A$1=$T$1,U87,IF($A$1=$W$1,X87,IF($A$1=$Z$1,AA87,IF($A$1=$AC$1,AD87,IF($A$1=$AF$1,AG87,IF($A$1=$AI$1,AJ87))))))))))))
A88: Operating Expenses | B88: =-'Bütçe aylık-Eur'!$B$37 | C88: ='gerç aylık-eur'!$B$37 | E88: =-'Bütçe aylık-Eur'!$C$37 | F88: ='gerç aylık-eur'!$C$37 | H88: =-'Bütçe aylık-Eur'!$D$37 | I88: ='gerç aylık-eur'!$D$37 | K88: =-'Bütçe aylık-Eur'!$E$37 | L88: ='gerç aylık-eur'!$E$37 | N88: =-'Bütçe aylık-Eur'!$F$37 | O88: ='gerç aylık-eur'!$F$37 | Q88: =-'Bütçe aylık-Eur'!$G$37 | R88: ='gerç aylık-eur'!$G$37 | T88: =-'Bütçe aylık-Eur'!$H$37 | U88: ='gerç aylık-eur'!$H$37 | W88: =-'Bütçe aylık-Eur'!$I$37 | X88: ='gerç aylık-eur'!$I$37 | Z88: =-'Bütçe aylık-Eur'!$J$37 | AA88: ='gerç aylık-eur'!$J$37 | AC88: =-'Bütçe aylık-Eur'!$K$37 | AD88: ='gerç aylık-eur'!$K$37 | AF88: =-'Bütçe aylık-Eur'!$L$37 | AG88: ='gerç aylık-eur'!$L$37 | AI88: =-'Bütçe aylık-Eur'!$M$37 | AJ88: ='gerç aylık-eur'!$M$37 | AL88: =AP88-AO88 | AM88: =AP88/AO88-1 | AO88: =IF($A$1=$B$1,B88,IF($A$1=$E$1,E88,IF($A$1=$H$1,H88,IF($A$1=$K$1,K88,IF($A$1=$N$1,N88,IF($A$1=$Q$1,Q88,IF($A$1=$T$1,T88,IF($A$1=$W$1,W88,IF($A$1=$Z$1,Z88,IF($A$1=$AC$1,AC88,IF($A$1=$AF$1,AF88,IF($A$1=$AI$1,AI88)))))))))))) | AP88: =IF($A$1=$B$1,C88,IF($A$1=$E$1,F88,IF($A$1=$H$1,I88,IF($A$1=$K$1,L88,IF($A$1=$N$1,O88,IF($A$1=$Q$1,R88,IF($A$1=$T$1,U88,IF($A$1=$W$1,X88,IF($A$1=$Z$1,AA88,IF($A$1=$AC$1,AD88,IF($A$1=$AF$1,AG88,IF($A$1=$AI$1,AJ88))))))))))))
B89: =B88/-B30 | C89: =C88/-C30 | AO89: =IF($A$1=$B$1,B89,IF($A$1=$E$1,E89,IF($A$1=$H$1,H89,IF($A$1=$K$1,K89,IF($A$1=$N$1,N89,IF($A$1=$Q$1,Q89,IF($A$1=$T$1,T89,IF($A$1=$W$1,W89,IF($A$1=$Z$1,Z89,IF($A$1=$AC$1,AC89,IF($A$1=$AF$1,AF89,IF($A$1=$AI$1,AI89)))))))))))) | AP89: =IF($A$1=$B$1,C89,IF($A$1=$E$1,F89,IF($A$1=$H$1,I89,IF($A$1=$K$1,L89,IF($A$1=$N$1,O89,IF($A$1=$Q$1,R89,IF($A$1=$T$1,U89,IF($A$1=$W$1,X89,IF($A$1=$Z$1,AA89,IF($A$1=$AC$1,AD89,IF($A$1=$AF$1,AG89,IF($A$1=$AI$1,AJ89))))))))))))
A90: Operating Expenses by channels (100%)
A91: İnci Holding | B91: =-'Bütçe aylık-Eur'!$B$38 | C91: ='gerç aylık-eur'!$B$38 | E91: =-'Bütçe aylık-Eur'!$C$38 | F91: ='gerç aylık-eur'!$C$38 | H91: =-'Bütçe aylık-Eur'!$D$38 | I91: ='gerç aylık-eur'!$D$38 | K91: =-'Bütçe aylık-Eur'!$E$38 | L91: ='gerç aylık-eur'!$E$38 | N91: =-'Bütçe aylık-Eur'!$F$38 | O91: ='gerç aylık-eur'!$F$38 | Q91: =-'Bütçe aylık-Eur'!$G$38 | R91: ='gerç aylık-eur'!$G$38 | T91: =-'Bütçe aylık-Eur'!$H$38 | U91: ='gerç aylık-eur'!$H$38 | W91: =-'Bütçe aylık-Eur'!$I$38 | X91: ='gerç aylık-eur'!$I$38 | Z91: =-'Bütçe aylık-Eur'!$J$38 | AA91: ='gerç aylık-eur'!$J$38 | AC91: =-'Bütçe aylık-Eur'!$K$38 | AD91: ='gerç aylık-eur'!$K$38 | AF91: =-'Bütçe aylık-Eur'!$L$38 | AG91: ='gerç aylık-eur'!$L$38 | AI91: =-'Bütçe aylık-Eur'!$M$38 | AJ91: ='gerç aylık-eur'!$M$38 | AL91: =AP91-AO91 | AM91: =AP91/AO91-1 | AO91: =IF($A$1=$B$1,B91,IF($A$1=$E$1,E91,IF($A$1=$H$1,H91,IF($A$1=$K$1,K91,IF($A$1=$N$1,N91,IF($A$1=$Q$1,Q91,IF($A$1=$T$1,T91,IF($A$1=$W$1,W91,IF($A$1=$Z$1,Z91,IF($A$1=$AC$1,AC91,IF($A$1=$AF$1,AF91,IF($A$1=$AI$1,AI91)))))))))))) | AP91: =IF($A$1=$B$1,C91,IF($A$1=$E$1,F91,IF($A$1=$H$1,I91,IF($A$1=$K$1,L91,IF($A$1=$N$1,O91,IF($A$1=$Q$1,R91,IF($A$1=$T$1,U91,IF($A$1=$W$1,X91,IF($A$1=$Z$1,AA91,IF($A$1=$AC$1,AD91,IF($A$1=$AF$1,AG91,IF($A$1=$AI$1,AJ91))))))))))))
A92: ISM | B92: =-'Bütçe aylık-Eur'!$B$39 | C92: ='gerç aylık-eur'!$B$39 | E92: =-'Bütçe aylık-Eur'!$C$39 | F92: ='gerç aylık-eur'!$C$39 | H92: =-'Bütçe aylık-Eur'!$D$39 | I92: ='gerç aylık-eur'!$D$39 | K92: =-'Bütçe aylık-Eur'!$E$39 | L92: ='gerç aylık-eur'!$E$39 | N92: =-'Bütçe aylık-Eur'!$F$39 | O92: ='gerç aylık-eur'!$F$39 | Q92: =-'Bütçe aylık-Eur'!$G$39 | R92: ='gerç aylık-eur'!$G$39 | T92: =-'Bütçe aylık-Eur'!$H$39 | U92: ='gerç aylık-eur'!$H$39 | W92: =-'Bütçe aylık-Eur'!$I$39 | X92: ='gerç aylık-eur'!$I$39 | Z92: =-'Bütçe aylık-Eur'!$J$39 | AA92: ='gerç aylık-eur'!$J$39 | AC92: =-'Bütçe aylık-Eur'!$K$39 | AD92: ='gerç aylık-eur'!$K$39 | AF92: =-'Bütçe aylık-Eur'!$L$39 | AG92: ='gerç aylık-eur'!$L$39 | AI92: =-'Bütçe aylık-Eur'!$M$39 | AJ92: ='gerç aylık-eur'!$M$39 | AL92: =AP92-AO92 | AM92: =AP92/AO92-1 | AO92: =IF($A$1=$B$1,B92,IF($A$1=$E$1,E92,IF($A$1=$H$1,H92,IF($A$1=$K$1,K92,IF($A$1=$N$1,N92,IF($A$1=$Q$1,Q92,IF($A$1=$T$1,T92,IF($A$1=$W$1,W92,IF($A$1=$Z$1,Z92,IF($A$1=$AC$1,AC92,IF($A$1=$AF$1,AF92,IF($A$1=$AI$1,AI92)))))))))))) | AP92: =IF($A$1=$B$1,C92,IF($A$1=$E$1,F92,IF($A$1=$H$1,I92,IF($A$1=$K$1,L92,IF($A$1=$N$1,O92,IF($A$1=$Q$1,R92,IF($A$1=$T$1,U92,IF($A$1=$W$1,X92,IF($A$1=$Z$1,AA92,IF($A$1=$AC$1,AD92,IF($A$1=$AF$1,AG92,IF($A$1=$AI$1,AJ92))))))))))))
A93: İncitaş | B93: =-'Bütçe aylık-Eur'!$B$40 | C93: ='gerç aylık-eur'!$B$40 | E93: =-'Bütçe aylık-Eur'!$C$40 | F93: ='gerç aylık-eur'!$C$40 | H93: =-'Bütçe aylık-Eur'!$D$40 | I93: ='gerç aylık-eur'!$D$40 | K93: =-'Bütçe aylık-Eur'!$E$40 | L93: ='gerç aylık-eur'!$E$40 | N93: =-'Bütçe aylık-Eur'!$F$40 | O93: ='gerç aylık-eur'!$F$40 | Q93: =-'Bütçe aylık-Eur'!$G$40 | R93: ='gerç aylık-eur'!$G$40 | T93: =-'Bütçe aylık-Eur'!$H$40 | U93: ='gerç aylık-eur'!$H$40 | W93: =-'Bütçe aylık-Eur'!$I$40 | X93: ='gerç aylık-eur'!$I$40 | Z93: =-'Bütçe aylık-Eur'!$J$40 | AA93: ='gerç aylık-eur'!$J$40 | AC93: =-'Bütçe aylık-Eur'!$K$40 | AD93: ='gerç aylık-eur'!$K$40 | AF93: =-'Bütçe aylık-Eur'!$L$40 | AG93: ='gerç aylık-eur'!$L$40 | AI93: =-'Bütçe aylık-Eur'!$M$40 | AJ93: ='gerç aylık-eur'!$M$40 | AL93: =AP93-AO93 | AM93: =AP93/AO93-1 | AO93: =IF($A$1=$B$1,B93,IF($A$1=$E$1,E93,IF($A$1=$H$1,H93,IF($A$1=$K$1,K93,IF($A$1=$N$1,N93,IF($A$1=$Q$1,Q93,IF($A$1=$T$1,T93,IF($A$1=$W$1,W93,IF($A$1=$Z$1,Z93,IF($A$1=$AC$1,AC93,IF($A$1=$AF$1,AF93,IF($A$1=$AI$1,AI93)))))))))))) | AP93: =IF($A$1=$B$1,C93,IF($A$1=$E$1,F93,IF($A$1=$H$1,I93,IF($A$1=$K$1,L93,IF($A$1=$N$1,O93,IF($A$1=$Q$1,R93,IF($A$1=$T$1,U93,IF($A$1=$W$1,X93,IF($A$1=$Z$1,AA93,IF($A$1=$AC$1,AD93,IF($A$1=$AF$1,AG93,IF($A$1=$AI$1,AJ93))))))))))))
A94: İnci GS Yuasa | B94: =-'Bütçe aylık-Eur'!$B$41 | C94: ='gerç aylık-eur'!$B$41 | E94: =-'Bütçe aylık-Eur'!$C$41 | F94: ='gerç aylık-eur'!$C$41 | H94: =-'Bütçe aylık-Eur'!$D$41 | I94: ='gerç aylık-eur'!$D$41 | K94: =-'Bütçe aylık-Eur'!$E$41 | L94: ='gerç aylık-eur'!$E$41 | N94: =-'Bütçe aylık-Eur'!$F$41 | O94: ='gerç aylık-eur'!$F$41 | Q94: =-'Bütçe aylık-Eur'!$G$41 | R94: ='gerç aylık-eur'!$G$41 | T94: =-'Bütçe aylık-Eur'!$H$41 | U94: ='gerç aylık-eur'!$H$41 | W94: =-'Bütçe aylık-Eur'!$I$41 | X94: ='gerç aylık-eur'!$I$41 | Z94: =-'Bütçe aylık-Eur'!$J$41 | AA94: ='gerç aylık-eur'!$J$41 | AC94: =-'Bütçe aylık-Eur'!$K$41 | AD94: ='gerç aylık-eur'!$K$41 | AF94: =-'Bütçe aylık-Eur'!$L$41 | AG94: ='gerç aylık-eur'!$L$41 | AI94: =-'Bütçe aylık-Eur'!$M$41 | AJ94: ='gerç aylık-eur'!$M$41 | AL94: =AP94-AO94 | AM94: =AP94/AO94-1 | AO94: =IF($A$1=$B$1,B94,IF($A$1=$E$1,E94,IF($A$1=$H$1,H94,IF($A$1=$K$1,K94,IF($A$1=$N$1,N94,IF($A$1=$Q$1,Q94,IF($A$1=$T$1,T94,IF($A$1=$W$1,W94,IF($A$1=$Z$1,Z94,IF($A$1=$AC$1,AC94,IF($A$1=$AF$1,AF94,IF($A$1=$AI$1,AI94)))))))))))) | AP94: =IF($A$1=$B$1,C94,IF($A$1=$E$1,F94,IF($A$1=$H$1,I94,IF($A$1=$K$1,L94,IF($A$1=$N$1,O94,IF($A$1=$Q$1,R94,IF($A$1=$T$1,U94,IF($A$1=$W$1,X94,IF($A$1=$Z$1,AA94,IF($A$1=$AC$1,AD94,IF($A$1=$AF$1,AG94,IF($A$1=$AI$1,AJ94))))))))))))
A95: Yusen İnci Loj. | B95: =-'Bütçe aylık-Eur'!$B$42 | C95: ='gerç aylık-eur'!$B$42 | E95: =-'Bütçe aylık-Eur'!$C$42 | F95: ='gerç aylık-eur'!$C$42 | H95: =-'Bütçe aylık-Eur'!$D$42 | I95: ='gerç aylık-eur'!$D$42 | K95: =-'Bütçe aylık-Eur'!$E$42 | L95: ='gerç aylık-eur'!$E$42 | N95: =-'Bütçe aylık-Eur'!$F$42 | O95: ='gerç aylık-eur'!$F$42 | Q95: =-'Bütçe aylık-Eur'!$G$42 | R95: ='gerç aylık-eur'!$G$42 | T95: =-'Bütçe aylık-Eur'!$H$42 | U95: ='gerç aylık-eur'!$H$42 | W95: =-'Bütçe aylık-Eur'!$I$42 | X95: ='gerç aylık-eur'!$I$42 | Z95: =-'Bütçe aylık-Eur'!$J$42 | AA95: ='gerç aylık-eur'!$J$42 | AC95: =-'Bütçe aylık-Eur'!$K$42 | AD95: ='gerç aylık-eur'!$K$42 | AF95: =-'Bütçe aylık-Eur'!$L$42 | AG95: ='gerç aylık-eur'!$L$42 | AI95: =-'Bütçe aylık-Eur'!$M$42 | AJ95: ='gerç aylık-eur'!$M$42 | AL95: =AP95-AO95 | AM95: =AP95/AO95-1 | AO95: =IF($A$1=$B$1,B95,IF($A$1=$E$1,E95,IF($A$1=$H$1,H95,IF($A$1=$K$1,K95,IF($A$1=$N$1,N95,IF($A$1=$Q$1,Q95,IF($A$1=$T$1,T95,IF($A$1=$W$1,W95,IF($A$1=$Z$1,Z95,IF($A$1=$AC$1,AC95,IF($A$1=$AF$1,AF95,IF($A$1=$AI$1,AI95)))))))))))) | AP95: =IF($A$1=$B$1,C95,IF($A$1=$E$1,F95,IF($A$1=$H$1,I95,IF($A$1=$K$1,L95,IF($A$1=$N$1,O95,IF($A$1=$Q$1,R95,IF($A$1=$T$1,U95,IF($A$1=$W$1,X95,IF($A$1=$Z$1,AA95,IF($A$1=$AC$1,AD95,IF($A$1=$AF$1,AG95,IF($A$1=$AI$1,AJ95))))))))))))
A96: Jantaş | B96: =-'Bütçe aylık-Eur'!$B$43 | C96: ='gerç aylık-eur'!$B$43 | E96: =-'Bütçe aylık-Eur'!$C$43 | F96: ='gerç aylık-eur'!$C$43 | H96: =-'Bütçe aylık-Eur'!$D$43 | I96: ='gerç aylık-eur'!$D$43 | K96: =-'Bütçe aylık-Eur'!$E$43 | L96: ='gerç aylık-eur'!$E$43 | N96: =-'Bütçe aylık-Eur'!$F$43 | O96: ='gerç aylık-eur'!$F$43 | Q96: =-'Bütçe aylık-Eur'!$G$43 | R96: ='gerç aylık-eur'!$G$43 | T96: =-'Bütçe aylık-Eur'!$H$43 | U96: ='gerç aylık-eur'!$H$43 | W96: =-'Bütçe aylık-Eur'!$I$43 | X96: ='gerç aylık-eur'!$I$43 | Z96: =-'Bütçe aylık-Eur'!$J$43 | AA96: ='gerç aylık-eur'!$J$43 | AC96: =-'Bütçe aylık-Eur'!$K$43 | AD96: ='gerç aylık-eur'!$K$43 | AF96: =-'Bütçe aylık-Eur'!$L$43 | AG96: ='gerç aylık-eur'!$L$43 | AI96: =-'Bütçe aylık-Eur'!$M$43 | AJ96: ='gerç aylık-eur'!$M$43 | AL96: =AP96-AO96 | AM96: =AP96/AO96-1 | AO96: =IF($A$1=$B$1,B96,IF($A$1=$E$1,E96,IF($A$1=$H$1,H96,IF($A$1=$K$1,K96,IF($A$1=$N$1,N96,IF($A$1=$Q$1,Q96,IF($A$1=$T$1,T96,IF($A$1=$W$1,W96,IF($A$1=$Z$1,Z96,IF($A$1=$AC$1,AC96,IF($A$1=$AF$1,AF96,IF($A$1=$AI$1,AI96)))))))))))) | AP96: =IF($A$1=$B$1,C96,IF($A$1=$E$1,F96,IF($A$1=$H$1,I96,IF($A$1=$K$1,L96,IF($A$1=$N$1,O96,IF($A$1=$Q$1,R96,IF($A$1=$T$1,U96,IF($A$1=$W$1,X96,IF($A$1=$Z$1,AA96,IF($A$1=$AC$1,AD96,IF($A$1=$AF$1,AG96,IF($A$1=$AI$1,AJ96))))))))))))
A97: Çelik | B97: =-'Bütçe aylık-Eur'!$B$44 | C97: ='gerç aylık-eur'!$B$44 | E97: =-'Bütçe aylık-Eur'!$C$44 | F97: ='gerç aylık-eur'!$C$44 | H97: =-'Bütçe aylık-Eur'!$D$44 | I97: ='gerç aylık-eur'!$D$44 | K97: =-'Bütçe aylık-Eur'!$E$44 | L97: ='gerç aylık-eur'!$E$44 | N97: =-'Bütçe aylık-Eur'!$F$44 | O97: ='gerç aylık-eur'!$F$44 | Q97: =-'Bütçe aylık-Eur'!$G$44 | R97: ='gerç aylık-eur'!$G$44 | T97: =-'Bütçe aylık-Eur'!$H$44 | U97: ='gerç aylık-eur'!$H$44 | W97: =-'Bütçe aylık-Eur'!$I$44 | X97: ='gerç aylık-eur'!$I$44 | Z97: =-'Bütçe aylık-Eur'!$J$44 | AA97: ='gerç aylık-eur'!$J$44 | AC97: =-'Bütçe aylık-Eur'!$K$44 | AD97: ='gerç aylık-eur'!$K$44 | AF97: =-'Bütçe aylık-Eur'!$L$44 | AG97: ='gerç aylık-eur'!$L$44 | AI97: =-'Bütçe aylık-Eur'!$M$44 | AJ97: ='gerç aylık-eur'!$M$44 | AL97: =AP97-AO97 | AM97: =AP97/AO97-1 | AO97: =IF($A$1=$B$1,B97,IF($A$1=$E$1,E97,IF($A$1=$H$1,H97,IF($A$1=$K$1,K97,IF($A$1=$N$1,N97,IF($A$1=$Q$1,Q97,IF($A$1=$T$1,T97,IF($A$1=$W$1,W97,IF($A$1=$Z$1,Z97,IF($A$1=$AC$1,AC97,IF($A$1=$AF$1,AF97,IF($A$1=$AI$1,AI97)))))))))))) | AP97: =IF($A$1=$B$1,C97,IF($A$1=$E$1,F97,IF($A$1=$H$1,I97,IF($A$1=$K$1,L97,IF($A$1=$N$1,O97,IF($A$1=$Q$1,R97,IF($A$1=$T$1,U97,IF($A$1=$W$1,X97,IF($A$1=$Z$1,AA97,IF($A$1=$AC$1,AD97,IF($A$1=$AF$1,AG97,IF($A$1=$AI$1,AJ97))))))))))))
A98: Alüminyum | B98: =-'Bütçe aylık-Eur'!$B$45 | C98: ='gerç aylık-eur'!$B$45 | E98: =-'Bütçe aylık-Eur'!$C$45 | F98: ='gerç aylık-eur'!$C$45 | H98: =-'Bütçe aylık-Eur'!$D$45 | I98: ='gerç aylık-eur'!$D$45 | K98: =-'Bütçe aylık-Eur'!$E$45 | L98: ='gerç aylık-eur'!$E$45 | N98: =-'Bütçe aylık-Eur'!$F$45 | O98: ='gerç aylık-eur'!$F$45 | Q98: =-'Bütçe aylık-Eur'!$G$45 | R98: ='gerç aylık-eur'!$G$45 | T98: =-'Bütçe aylık-Eur'!$H$45 | U98: ='gerç aylık-eur'!$H$45 | W98: =-'Bütçe aylık-Eur'!$I$45 | X98: ='gerç aylık-eur'!$I$45 | Z98: =-'Bütçe aylık-Eur'!$J$45 | AA98: ='gerç aylık-eur'!$J$45 | AC98: =-'Bütçe aylık-Eur'!$K$45 | AD98: ='gerç aylık-eur'!$K$45 | AF98: =-'Bütçe aylık-Eur'!$L$45 | AG98: ='gerç aylık-eur'!$L$45 | AI98: ='Bütçe aylık-Eur'!$M$45 | AJ98: ='gerç aylık-eur'!$M$45 | AL98: =AP98-AO98 | AM98: =AP98/AO98-1 | AO98: =IF($A$1=$B$1,B98,IF($A$1=$E$1,E98,IF($A$1=$H$1,H98,IF($A$1=$K$1,K98,IF($A$1=$N$1,N98,IF($A$1=$Q$1,Q98,IF($A$1=$T$1,T98,IF($A$1=$W$1,W98,IF($A$1=$Z$1,Z98,IF($A$1=$AC$1,AC98,IF($A$1=$AF$1,AF98,IF($A$1=$AI$1,AI98)))))))))))) | AP98: =IF($A$1=$B$1,C98,IF($A$1=$E$1,F98,IF($A$1=$H$1,I98,IF($A$1=$K$1,L98,IF($A$1=$N$1,O98,IF($A$1=$Q$1,R98,IF($A$1=$T$1,U98,IF($A$1=$W$1,X98,IF($A$1=$Z$1,AA98,IF($A$1=$AC$1,AD98,IF($A$1=$AF$1,AG98,IF($A$1=$AI$1,AJ98))))))))))))
AO99: =IF($A$1=$B$1,B99,IF($A$1=$E$1,E99,IF($A$1=$H$1,H99,IF($A$1=$K$1,K99,IF($A$1=$N$1,N99,IF($A$1=$Q$1,Q99,IF($A$1=$T$1,T99,IF($A$1=$W$1,W99,IF($A$1=$Z$1,Z99,IF($A$1=$AC$1,AC99,IF($A$1=$AF$1,AF99,IF($A$1=$AI$1,AI99)))))))))))) | AP99: =IF($A$1=$B$1,C99,IF($A$1=$E$1,F99,IF($A$1=$H$1,I99,IF($A$1=$K$1,L99,IF($A$1=$N$1,O99,IF($A$1=$Q$1,R99,IF($A$1=$T$1,U99,IF($A$1=$W$1,X99,IF($A$1=$Z$1,AA99,IF($A$1=$AC$1,AD99,IF($A$1=$AF$1,AG99,IF($A$1=$AI$1,AJ99))))))))))))
A101: Operating expense/Sales
A102: İnci Holding | B102: =B91*-1/B9 | C102: =C91*-1/C9 | E102: =E91*-1/E9 | F102: =F91*-1/F9 | H102: =H91*-1/H9 | I102: =I91*-1/I9 | K102: =K91*-1/K9 | L102: =L91*-1/L9 | N102: =N91*-1/N9 | O102: =O91*-1/O9 | Q102: =Q91*-1/Q9 | R102: =R91*-1/R9 | T102: =T91*-1/T9 | U102: =U91*-1/U9 | W102: =W91*-1/W9 | X102: =X91*-1/X9 | Z102: =Z91*-1/Z9 | AA102: =AA91*-1/AA9 | AC102: =AC91*-1/AC9 | AD102: =AD91*-1/AD9 | AF102: =AF91*-1/AF9 | AG102: =AG91*-1/AG9 | AI102: =AI91*-1/AI9 | AJ102: =AJ91*-1/AJ9 | AM102: =AP102-AO102 | AO102: =IF($A$1=$B$1,B102,IF($A$1=$E$1,E102,IF($A$1=$H$1,H102,IF($A$1=$K$1,K102,IF($A$1=$N$1,N102,IF($A$1=$Q$1,Q102,IF($A$1=$T$1,T102,IF($A$1=$W$1,W102,IF($A$1=$Z$1,Z102,IF($A$1=$AC$1,AC102,IF($A$1=$AF$1,AF102,IF($A$1=$AI$1,AI102)))))))))))) | AP102: =IF($A$1=$B$1,C102,IF($A$1=$E$1,F102,IF($A$1=$H$1,I102,IF($A$1=$K$1,L102,IF($A$1=$N$1,O102,IF($A$1=$Q$1,R102,IF($A$1=$T$1,U102,IF($A$1=$W$1,X102,IF($A$1=$Z$1,AA102,IF($A$1=$AC$1,AD102,IF($A$1=$AF$1,AG102,IF($A$1=$AI$1,AJ102))))))))))))
A103: ISM | B103: =B92*-1/B10 | C103: =C92*-1/C10 | E103: =E92*-1/E10 | F103: =F92*-1/F10 | H103: =H92*-1/H10 | I103: =I92*-1/I10 | K103: =K92*-1/K10 | L103: =L92*-1/L10 | N103: =N92*-1/N10 | O103: =O92*-1/O10 | Q103: =Q92*-1/Q10 | R103: =R92*-1/R10 | T103: =T92*-1/T10 | U103: =U92*-1/U10 | W103: =W92*-1/W10 | X103: =X92*-1/X10 | Z103: =Z92*-1/Z10 | AA103: =AA92*-1/AA10 | AC103: =AC92*-1/AC10 | AD103: =AD92*-1/AD10 | AF103: =AF92*-1/AF10 | AG103: =AG92*-1/AG10 | AI103: =AI92*-1/AI10 | AJ103: =AJ92*-1/AJ10 | AM103: =AP103-AO103 | AO103: =IF($A$1=$B$1,B103,IF($A$1=$E$1,E103,IF($A$1=$H$1,H103,IF($A$1=$K$1,K103,IF($A$1=$N$1,N103,IF($A$1=$Q$1,Q103,IF($A$1=$T$1,T103,IF($A$1=$W$1,W103,IF($A$1=$Z$1,Z103,IF($A$1=$AC$1,AC103,IF($A$1=$AF$1,AF103,IF($A$1=$AI$1,AI103)))))))))))) | AP103: =IF($A$1=$B$1,C103,IF($A$1=$E$1,F103,IF($A$1=$H$1,I103,IF($A$1=$K$1,L103,IF($A$1=$N$1,O103,IF($A$1=$Q$1,R103,IF($A$1=$T$1,U103,IF($A$1=$W$1,X103,IF($A$1=$Z$1,AA103,IF($A$1=$AC$1,AD103,IF($A$1=$AF$1,AG103,IF($A$1=$AI$1,AJ103))))))))))))
A104: İncitaş | B104: =B93*-1/B11 | C104: =C93*-1/C11 | E104: =E93*-1/E11 | F104: =F93*-1/F11 | H104: =H93*-1/H11 | I104: =I93*-1/I11 | K104: =K93*-1/K11 | L104: =L93*-1/L11 | N104: =N93*-1/N11 | O104: =O93*-1/O11 | Q104: =Q93*-1/Q11 | R104: =R93*-1/R11 | T104: =T93*-1/T11 | U104: =U93*-1/U11 | W104: =W93*-1/W11 | X104: =X93*-1/X11 | Z104: =Z93*-1/Z11 | AA104: =AA93*-1/AA11 | AC104: =AC93*-1/AC11 | AD104: =AD93*-1/AD11 | AF104: =AF93*-1/AF11 | AG104: =AG93*-1/AG11 | AI104: =AI93*-1/AI11 | AJ104: =AJ93*-1/AJ11 | AM104: =AP104-AO104 | AO104: =IF($A$1=$B$1,B104,IF($A$1=$E$1,E104,IF($A$1=$H$1,H104,IF($A$1=$K$1,K104,IF($A$1=$N$1,N104,IF($A$1=$Q$1,Q104,IF($A$1=$T$1,T104,IF($A$1=$W$1,W104,IF($A$1=$Z$1,Z104,IF($A$1=$AC$1,AC104,IF($A$1=$AF$1,AF104,IF($A$1=$AI$1,AI104)))))))))))) | AP104: =IF($A$1=$B$1,C104,IF($A$1=$E$1,F104,IF($A$1=$H$1,I104,IF($A$1=$K$1,L104,IF($A$1=$N$1,O104,IF($A$1=$Q$1,R104,IF($A$1=$T$1,U104,IF($A$1=$W$1,X104,IF($A$1=$Z$1,AA104,IF($A$1=$AC$1,AD104,IF($A$1=$AF$1,AG104,IF($A$1=$AI$1,AJ104))))))))))))
A105: İnci GS Yuasa | B105: =B94*-1/B12 | C105: =C94*-1/C12 | E105: =E94*-1/E12 | F105: =F94*-1/F12 | H105: =H94*-1/H12 | I105: =I94*-1/I12 | K105: =K94*-1/K12 | L105: =L94*-1/L12 | N105: =N94*-1/N12 | O105: =O94*-1/O12 | Q105: =Q94*-1/Q12 | R105: =R94*-1/R12 | T105: =T94*-1/T12 | U105: =U94*-1/U12 | W105: =W94*-1/W12 | X105: =X94*-1/X12 | Z105: =Z94*-1/Z12 | AA105: =AA94*-1/AA12 | AC105: =AC94*-1/AC12 | AD105: =AD94*-1/AD12 | AF105: =AF94*-1/AF12 | AG105: =AG94*-1/AG12 | AI105: =AI94*-1/AI12 | AJ105: =AJ94*-1/AJ12 | AM105: =AP105-AO105 | AO105: =IF($A$1=$B$1,B105,IF($A$1=$E$1,E105,IF($A$1=$H$1,H105,IF($A$1=$K$1,K105,IF($A$1=$N$1,N105,IF($A$1=$Q$1,Q105,IF($A$1=$T$1,T105,IF($A$1=$W$1,W105,IF($A$1=$Z$1,Z105,IF($A$1=$AC$1,AC105,IF($A$1=$AF$1,AF105,IF($A$1=$AI$1,AI105)))))))))))) | AP105: =IF($A$1=$B$1,C105,IF($A$1=$E$1,F105,IF($A$1=$H$1,I105,IF($A$1=$K$1,L105,IF($A$1=$N$1,O105,IF($A$1=$Q$1,R105,IF($A$1=$T$1,U105,IF($A$1=$W$1,X105,IF($A$1=$Z$1,AA105,IF($A$1=$AC$1,AD105,IF($A$1=$AF$1,AG105,IF($A$1=$AI$1,AJ105))))))))))))
A106: Yusen İnci Loj. | B106: =B95*-1/B13 | C106: =C95*-1/C13 | E106: =E95*-1/E13 | F106: =F95*-1/F13 | H106: =H95*-1/H13 | I106: =I95*-1/I13 | K106: =K95*-1/K13 | L106: =L95*-1/L13 | N106: =N95*-1/N13 | O106: =O95*-1/O13 | Q106: =Q95*-1/Q13 | R106: =R95*-1/R13 | T106: =T95*-1/T13 | U106: =U95*-1/U13 | W106: =W95*-1/W13 | X106: =X95*-1/X13 | Z106: =Z95*-1/Z13 | AA106: =AA95*-1/AA13 | AC106: =AC95*-1/AC13 | AD106: =AD95*-1/AD13 | AF106: =AF95*-1/AF13 | AG106: =AG95*-1/AG13 | AI106: =AI95*-1/AI13 | AJ106: =AJ95*-1/AJ13 | AM106: =AP106-AO106 | AO106: =IF($A$1=$B$1,B106,IF($A$1=$E$1,E106,IF($A$1=$H$1,H106,IF($A$1=$K$1,K106,IF($A$1=$N$1,N106,IF($A$1=$Q$1,Q106,IF($A$1=$T$1,T106,IF($A$1=$W$1,W106,IF($A$1=$Z$1,Z106,IF($A$1=$AC$1,AC106,IF($A$1=$AF$1,AF106,IF($A$1=$AI$1,AI106)))))))))))) | AP106: =IF($A$1=$B$1,C106,IF($A$1=$E$1,F106,IF($A$1=$H$1,I106,IF($A$1=$K$1,L106,IF($A$1=$N$1,O106,IF($A$1=$Q$1,R106,IF($A$1=$T$1,U106,IF($A$1=$W$1,X106,IF($A$1=$Z$1,AA106,IF($A$1=$AC$1,AD106,IF($A$1=$AF$1,AG106,IF($A$1=$AI$1,AJ106))))))))))))
A107: Jantaş | B107: =B96*-1/B14 | C107: =C96*-1/C14 | E107: =E96*-1/E14 | F107: =F96*-1/F14 | H107: =H96*-1/H14 | I107: =I96*-1/I14 | K107: =K96*-1/K14 | L107: =L96*-1/L14 | N107: =N96*-1/N14 | O107: =O96*-1/O14 | Q107: =Q96*-1/Q14 | R107: =R96*-1/R14 | T107: =T96*-1/T14 | U107: =U96*-1/U14 | W107: =W96*-1/W14 | X107: =X96*-1/X14 | Z107: =Z96*-1/Z14 | AA107: =AA96*-1/AA14 | AC107: =AC96*-1/AC14 | AD107: =AD96*-1/AD14 | AF107: =AF96*-1/AF14 | AG107: =AG96*-1/AG14 | AI107: =AI96*-1/AI14 | AJ107: =AJ96*-1/AJ14 | AM107: =AP107-AO107 | AO107: =IF($A$1=$B$1,B107,IF($A$1=$E$1,E107,IF($A$1=$H$1,H107,IF($A$1=$K$1,K107,IF($A$1=$N$1,N107,IF($A$1=$Q$1,Q107,IF($A$1=$T$1,T107,IF($A$1=$W$1,W107,IF($A$1=$Z$1,Z107,IF($A$1=$AC$1,AC107,IF($A$1=$AF$1,AF107,IF($A$1=$AI$1,AI107)))))))))))) | AP107: =IF($A$1=$B$1,C107,IF($A$1=$E$1,F107,IF($A$1=$H$1,I107,IF($A$1=$K$1,L107,IF($A$1=$N$1,O107,IF($A$1=$Q$1,R107,IF($A$1=$T$1,U107,IF($A$1=$W$1,X107,IF($A$1=$Z$1,AA107,IF($A$1=$AC$1,AD107,IF($A$1=$AF$1,AG107,IF($A$1=$AI$1,AJ107))))))))))))
A108: Çelik | B108: =B97*-1/B15 | C108: =C97*-1/C15 | E108: =E97*-1/E15 | F108: =F97*-1/F15 | H108: =H97*-1/H15 | I108: =I97*-1/I15 | K108: =K97*-1/K15 | L108: =L97*-1/L15 | N108: =N97*-1/N15 | O108: =O97*-1/O15 | Q108: =Q97*-1/Q15 | R108: =R97*-1/R15 | T108: =T97*-1/T15 | U108: =U97*-1/U15 | W108: =W97*-1/W15 | X108: =X97*-1/X15 | Z108: =Z97*-1/Z15 | AA108: =AA97*-1/AA15 | AC108: =AC97*-1/AC15 | AD108: =AD97*-1/AD15 | AF108: =AF97*-1/AF15 | AG108: =AG97*-1/AG15 | AI108: =AI97*-1/AI15 | AJ108: =AJ97*-1/AJ15 | AM108: =AP108-AO108 | AO108: =IF($A$1=$B$1,B108,IF($A$1=$E$1,E108,IF($A$1=$H$1,H108,IF($A$1=$K$1,K108,IF($A$1=$N$1,N108,IF($A$1=$Q$1,Q108,IF($A$1=$T$1,T108,IF($A$1=$W$1,W108,IF($A$1=$Z$1,Z108,IF($A$1=$AC$1,AC108,IF($A$1=$AF$1,AF108,IF($A$1=$AI$1,AI108)))))))))))) | AP108: =IF($A$1=$B$1,C108,IF($A$1=$E$1,F108,IF($A$1=$H$1,I108,IF($A$1=$K$1,L108,IF($A$1=$N$1,O108,IF($A$1=$Q$1,R108,IF($A$1=$T$1,U108,IF($A$1=$W$1,X108,IF($A$1=$Z$1,AA108,IF($A$1=$AC$1,AD108,IF($A$1=$AF$1,AG108,IF($A$1=$AI$1,AJ108))))))))))))
A109: Alüminyum | B109: =B98*-1/B16 | C109: =C98*-1/C16 | E109: =E98*-1/E16 | F109: =F98*-1/F16 | H109: =H98*-1/H16 | I109: =I98*-1/I16 | K109: =K98*-1/K16 | L109: =L98*-1/L16 | N109: =N98*-1/N16 | O109: =O98*-1/O16 | Q109: =Q98*-1/Q16 | R109: =R98*-1/R16 | T109: =T98*-1/T16 | U109: =U98*-1/U16 | W109: =W98*-1/W16 | X109: =X98*-1/X16 | Z109: =Z98*-1/Z16 | AA109: =AA98*-1/AA16 | AC109: =AC98*-1/AC16 | AD109: =AD98*-1/AD16 | AF109: =AF98*-1/AF16 | AG109: =AG98*-1/AG16 | AI109: =AI98*-1/AI16 | AJ109: =AJ98*-1/AJ16 | AM109: =AP109-AO109 | AO109: =IF($A$1=$B$1,B109,IF($A$1=$E$1,E109,IF($A$1=$H$1,H109,IF($A$1=$K$1,K109,IF($A$1=$N$1,N109,IF($A$1=$Q$1,Q109,IF($A$1=$T$1,T109,IF($A$1=$W$1,W109,IF($A$1=$Z$1,Z109,IF($A$1=$AC$1,AC109,IF($A$1=$AF$1,AF109,IF($A$1=$AI$1,AI109)))))))))))) | AP109: =IF($A$1=$B$1,C109,IF($A$1=$E$1,F109,IF($A$1=$H$1,I109,IF($A$1=$K$1,L109,IF($A$1=$N$1,O109,IF($A$1=$Q$1,R109,IF($A$1=$T$1,U109,IF($A$1=$W$1,X109,IF($A$1=$Z$1,AA109,IF($A$1=$AC$1,AD109,IF($A$1=$AF$1,AG109,IF($A$1=$AI$1,AJ109))))))))))))
A112: EBİT | B112: ='Bütçe aylık-Eur'!$B$59 | C112: ='gerç aylık-eur'!$B$59 | E112: ='Bütçe aylık-Eur'!$C$59 | F112: ='gerç aylık-eur'!$C$59 | H112: ='Bütçe aylık-Eur'!$D$59 | I112: ='gerç aylık-eur'!$D$59 | K112: ='Bütçe aylık-Eur'!$E$59 | L112: ='gerç aylık-eur'!$E$59 | N112: ='Bütçe aylık-Eur'!$F$59 | O112: ='gerç aylık-eur'!$F$59 | Q112: ='Bütçe aylık-Eur'!$G$59 | R112: ='gerç aylık-eur'!$G$59 | T112: ='Bütçe aylık-Eur'!$H$59 | U112: ='gerç aylık-eur'!$H$59 | W112: ='Bütçe aylık-Eur'!$I$59 | X112: ='gerç aylık-eur'!$I$59 | Z112: ='Bütçe aylık-Eur'!$J$59 | AA112: ='gerç aylık-eur'!$J$59 | AC112: ='Bütçe aylık-Eur'!$K$59 | AD112: ='gerç aylık-eur'!$K$59 | AF112: ='Bütçe aylık-Eur'!$L$59 | AG112: ='gerç aylık-eur'!$L$59 | AI112: ='Bütçe aylık-Eur'!$M$59 | AJ112: ='gerç aylık-eur'!$M$59 | AL112: =AP112-AO112 | AM112: =AP112/AO112-1 | AO112: =IF($A$1=$B$1,B112,IF($A$1=$E$1,E112,IF($A$1=$H$1,H112,IF($A$1=$K$1,K112,IF($A$1=$N$1,N112,IF($A$1=$Q$1,Q112,IF($A$1=$T$1,T112,IF($A$1=$W$1,W112,IF($A$1=$Z$1,Z112,IF($A$1=$AC$1,AC112,IF($A$1=$AF$1,AF112,IF($A$1=$AI$1,AI112)))))))))))) | AP112: =IF($A$1=$B$1,C112,IF($A$1=$E$1,F112,IF($A$1=$H$1,I112,IF($A$1=$K$1,L112,IF($A$1=$N$1,O112,IF($A$1=$Q$1,R112,IF($A$1=$T$1,U112,IF($A$1=$W$1,X112,IF($A$1=$Z$1,AA112,IF($A$1=$AC$1,AD112,IF($A$1=$AF$1,AG112,IF($A$1=$AI$1,AJ112))))))))))))
AO113: =IF($A$1=$B$1,B113,IF($A$1=$E$1,E113,IF($A$1=$H$1,H113,IF($A$1=$K$1,K113,IF($A$1=$N$1,N113,IF($A$1=$Q$1,Q113,IF($A$1=$T$1,T113,IF($A$1=$W$1,W113,IF($A$1=$Z$1,Z113,IF($A$1=$AC$1,AC113,IF($A$1=$AF$1,AF113,IF($A$1=$AI$1,AI113)))))))))))) | AP113: =IF($A$1=$B$1,C113,IF($A$1=$E$1,F113,IF($A$1=$H$1,I113,IF($A$1=$K$1,L113,IF($A$1=$N$1,O113,IF($A$1=$Q$1,R113,IF($A$1=$T$1,U113,IF($A$1=$W$1,X113,IF($A$1=$Z$1,AA113,IF($A$1=$AC$1,AD113,IF($A$1=$AF$1,AG113,IF($A$1=$AI$1,AJ113))))))))))))
A114: Ebit by channels (100%)
A115: İnci Holding | B115: ='Bütçe aylık-Eur'!$B$60 | C115: ='gerç aylık-eur'!$B$60 | E115: ='Bütçe aylık-Eur'!$C$60 | F115: ='gerç aylık-eur'!$C$60 | H115: ='Bütçe aylık-Eur'!$D$60 | I115: ='gerç aylık-eur'!$D$60 | K115: ='Bütçe aylık-Eur'!$E$60 | L115: ='gerç aylık-eur'!$E$60 | N115: ='Bütçe aylık-Eur'!$F$60 | O115: ='gerç aylık-eur'!$F$60 | Q115: ='Bütçe aylık-Eur'!$G$60 | R115: ='gerç aylık-eur'!$G$60 | T115: ='Bütçe aylık-Eur'!$H$60 | U115: ='gerç aylık-eur'!$H$60 | W115: ='Bütçe aylık-Eur'!$I$60 | X115: ='gerç aylık-eur'!$I$60 | Z115: ='Bütçe aylık-Eur'!$J$60 | AA115: ='gerç aylık-eur'!$J$60 | AC115: ='Bütçe aylık-Eur'!$K$60 | AD115: ='gerç aylık-eur'!$K$60 | AF115: ='Bütçe aylık-Eur'!$L$60 | AG115: ='gerç aylık-eur'!$L$60 | AI115: ='Bütçe aylık-Eur'!$M$60 | AJ115: ='gerç aylık-eur'!$M$60 | AL115: =AP115-AO115 | AM115: =AP115/AO115-1 | AO115: =IF($A$1=$B$1,B115,IF($A$1=$E$1,E115,IF($A$1=$H$1,H115,IF($A$1=$K$1,K115,IF($A$1=$N$1,N115,IF($A$1=$Q$1,Q115,IF($A$1=$T$1,T115,IF($A$1=$W$1,W115,IF($A$1=$Z$1,Z115,IF($A$1=$AC$1,AC115,IF($A$1=$AF$1,AF115,IF($A$1=$AI$1,AI115)))))))))))) | AP115: =IF($A$1=$B$1,C115,IF($A$1=$E$1,F115,IF($A$1=$H$1,I115,IF($A$1=$K$1,L115,IF($A$1=$N$1,O115,IF($A$1=$Q$1,R115,IF($A$1=$T$1,U115,IF($A$1=$W$1,X115,IF($A$1=$Z$1,AA115,IF($A$1=$AC$1,AD115,IF($A$1=$AF$1,AG115,IF($A$1=$AI$1,AJ115))))))))))))
A116: ISM | B116: ='Bütçe aylık-Eur'!$B$61 | C116: ='gerç aylık-eur'!$B$61 | E116: ='Bütçe aylık-Eur'!$C$61 | F116: ='gerç aylık-eur'!$C$61 | H116: ='Bütçe aylık-Eur'!$D$61 | I116: ='gerç aylık-eur'!$D$61 | K116: ='Bütçe aylık-Eur'!$E$61 | L116: ='gerç aylık-eur'!$E$61 | N116: ='Bütçe aylık-Eur'!$F$61 | O116: ='gerç aylık-eur'!$F$61 | Q116: ='Bütçe aylık-Eur'!$G$61 | R116: ='gerç aylık-eur'!$G$61 | T116: ='Bütçe aylık-Eur'!$H$61 | U116: ='gerç aylık-eur'!$H$61 | W116: ='Bütçe aylık-Eur'!$I$61 | X116: ='gerç aylık-eur'!$I$61 | Z116: ='Bütçe aylık-Eur'!$J$61 | AA116: ='gerç aylık-eur'!$J$61 | AC116: ='Bütçe aylık-Eur'!$K$61 | AD116: ='gerç aylık-eur'!$K$61 | AF116: ='Bütçe aylık-Eur'!$L$61 | AG116: ='gerç aylık-eur'!$L$61 | AI116: ='Bütçe aylık-Eur'!$M$61 | AJ116: ='gerç aylık-eur'!$M$61 | AL116: =AP116-AO116 | AM116: =AP116/AO116-1 | AO116: =IF($A$1=$B$1,B116,IF($A$1=$E$1,E116,IF($A$1=$H$1,H116,IF($A$1=$K$1,K116,IF($A$1=$N$1,N116,IF($A$1=$Q$1,Q116,IF($A$1=$T$1,T116,IF($A$1=$W$1,W116,IF($A$1=$Z$1,Z116,IF($A$1=$AC$1,AC116,IF($A$1=$AF$1,AF116,IF($A$1=$AI$1,AI116)))))))))))) | AP116: =IF($A$1=$B$1,C116,IF($A$1=$E$1,F116,IF($A$1=$H$1,I116,IF($A$1=$K$1,L116,IF($A$1=$N$1,O116,IF($A$1=$Q$1,R116,IF($A$1=$T$1,U116,IF($A$1=$W$1,X116,IF($A$1=$Z$1,AA116,IF($A$1=$AC$1,AD116,IF($A$1=$AF$1,AG116,IF($A$1=$AI$1,AJ116))))))))))))
A117: İncitaş | B117: ='Bütçe aylık-Eur'!$B$62 | C117: ='gerç aylık-eur'!$B$62 | E117: ='Bütçe aylık-Eur'!$C$62 | F117: ='gerç aylık-eur'!$C$62 | H117: ='Bütçe aylık-Eur'!$D$62 | I117: ='gerç aylık-eur'!$D$62 | K117: ='Bütçe aylık-Eur'!$E$62 | L117: ='gerç aylık-eur'!$E$62 | N117: ='Bütçe aylık-Eur'!$F$62 | O117: ='gerç aylık-eur'!$F$62 | Q117: ='Bütçe aylık-Eur'!$G$62 | R117: ='gerç aylık-eur'!$G$62 | T117: ='Bütçe aylık-Eur'!$H$62 | U117: ='gerç aylık-eur'!$H$62 | W117: ='Bütçe aylık-Eur'!$I$62 | X117: ='gerç aylık-eur'!$I$62 | Z117: ='Bütçe aylık-Eur'!$J$62 | AA117: ='gerç aylık-eur'!$J$62 | AC117: ='Bütçe aylık-Eur'!$K$62 | AD117: ='gerç aylık-eur'!$K$62 | AF117: ='Bütçe aylık-Eur'!$L$62 | AG117: ='gerç aylık-eur'!$L$62 | AI117: ='Bütçe aylık-Eur'!$M$62 | AJ117: ='gerç aylık-eur'!$M$62 | AL117: =AP117-AO117 | AM117: =AP117/AO117-1 | AO117: =IF($A$1=$B$1,B117,IF($A$1=$E$1,E117,IF($A$1=$H$1,H117,IF($A$1=$K$1,K117,IF($A$1=$N$1,N117,IF($A$1=$Q$1,Q117,IF($A$1=$T$1,T117,IF($A$1=$W$1,W117,IF($A$1=$Z$1,Z117,IF($A$1=$AC$1,AC117,IF($A$1=$AF$1,AF117,IF($A$1=$AI$1,AI117)))))))))))) | AP117: =IF($A$1=$B$1,C117,IF($A$1=$E$1,F117,IF($A$1=$H$1,I117,IF($A$1=$K$1,L117,IF($A$1=$N$1,O117,IF($A$1=$Q$1,R117,IF($A$1=$T$1,U117,IF($A$1=$W$1,X117,IF($A$1=$Z$1,AA117,IF($A$1=$AC$1,AD117,IF($A$1=$AF$1,AG117,IF($A$1=$AI$1,AJ117))))))))))))
A118: İnci GS Yuasa | B118: ='Bütçe aylık-Eur'!$B$63 | C118: ='gerç aylık-eur'!$B$63 | E118: ='Bütçe aylık-Eur'!$C$63 | F118: ='gerç aylık-eur'!$C$63 | H118: ='Bütçe aylık-Eur'!$D$63 | I118: ='gerç aylık-eur'!$D$63 | K118: ='Bütçe aylık-Eur'!$E$63 | L118: ='gerç aylık-eur'!$E$63 | N118: ='Bütçe aylık-Eur'!$F$63 | O118: ='gerç aylık-eur'!$F$63 | Q118: ='Bütçe aylık-Eur'!$G$63 | R118: ='gerç aylık-eur'!$G$63 | T118: ='Bütçe aylık-Eur'!$H$63 | U118: ='gerç aylık-eur'!$H$63 | W118: ='Bütçe aylık-Eur'!$I$63 | X118: ='gerç aylık-eur'!$I$63 | Z118: ='Bütçe aylık-Eur'!$J$63 | AA118: ='gerç aylık-eur'!$J$63 | AC118: ='Bütçe aylık-Eur'!$K$63 | AD118: ='gerç aylık-eur'!$K$63 | AF118: ='Bütçe aylık-Eur'!$L$63 | AG118: ='gerç aylık-eur'!$L$63 | AI118: ='Bütçe aylık-Eur'!$M$63 | AJ118: ='gerç aylık-eur'!$M$63 | AL118: =AP118-AO118 | AM118: =AP118/AO118-1 | AO118: =IF($A$1=$B$1,B118,IF($A$1=$E$1,E118,IF($A$1=$H$1,H118,IF($A$1=$K$1,K118,IF($A$1=$N$1,N118,IF($A$1=$Q$1,Q118,IF($A$1=$T$1,T118,IF($A$1=$W$1,W118,IF($A$1=$Z$1,Z118,IF($A$1=$AC$1,AC118,IF($A$1=$AF$1,AF118,IF($A$1=$AI$1,AI118)))))))))))) | AP118: =IF($A$1=$B$1,C118,IF($A$1=$E$1,F118,IF($A$1=$H$1,I118,IF($A$1=$K$1,L118,IF($A$1=$N$1,O118,IF($A$1=$Q$1,R118,IF($A$1=$T$1,U118,IF($A$1=$W$1,X118,IF($A$1=$Z$1,AA118,IF($A$1=$AC$1,AD118,IF($A$1=$AF$1,AG118,IF($A$1=$AI$1,AJ118))))))))))))
A119: Yusen İnci Loj. | B119: ='Bütçe aylık-Eur'!$B$64 | C119: ='gerç aylık-eur'!$B$64 | E119: ='Bütçe aylık-Eur'!$C$64 | F119: ='gerç aylık-eur'!$C$64 | H119: ='Bütçe aylık-Eur'!$D$64 | I119: ='gerç aylık-eur'!$D$64 | K119: ='Bütçe aylık-Eur'!$E$64 | L119: ='gerç aylık-eur'!$E$64 | N119: ='Bütçe aylık-Eur'!$F$64 | O119: ='gerç aylık-eur'!$F$64 | Q119: ='Bütçe aylık-Eur'!$G$64 | R119: ='gerç aylık-eur'!$G$64 | T119: ='Bütçe aylık-Eur'!$H$64 | U119: ='gerç aylık-eur'!$H$64 | W119: ='Bütçe aylık-Eur'!$I$64 | X119: ='gerç aylık-eur'!$I$64 | Z119: ='Bütçe aylık-Eur'!$J$64 | AA119: ='gerç aylık-eur'!$J$64 | AC119: ='Bütçe aylık-Eur'!$K$64 | AD119: ='gerç aylık-eur'!$K$64 | AF119: ='Bütçe aylık-Eur'!$L$64 | AG119: ='gerç aylık-eur'!$L$64 | AI119: ='Bütçe aylık-Eur'!$M$64 | AJ119: ='gerç aylık-eur'!$M$64 | AL119: =AP119-AO119 | AM119: =AP119/AO119-1 | AO119: =IF($A$1=$B$1,B119,IF($A$1=$E$1,E119,IF($A$1=$H$1,H119,IF($A$1=$K$1,K119,IF($A$1=$N$1,N119,IF($A$1=$Q$1,Q119,IF($A$1=$T$1,T119,IF($A$1=$W$1,W119,IF($A$1=$Z$1,Z119,IF($A$1=$AC$1,AC119,IF($A$1=$AF$1,AF119,IF($A$1=$AI$1,AI119)))))))))))) | AP119: =IF($A$1=$B$1,C119,IF($A$1=$E$1,F119,IF($A$1=$H$1,I119,IF($A$1=$K$1,L119,IF($A$1=$N$1,O119,IF($A$1=$Q$1,R119,IF($A$1=$T$1,U119,IF($A$1=$W$1,X119,IF($A$1=$Z$1,AA119,IF($A$1=$AC$1,AD119,IF($A$1=$AF$1,AG119,IF($A$1=$AI$1,AJ119))))))))))))
A120: Jantaş | B120: ='Bütçe aylık-Eur'!$B$65 | C120: ='gerç aylık-eur'!$B$65 | E120: ='Bütçe aylık-Eur'!$C$65 | F120: ='gerç aylık-eur'!$C$65 | H120: ='Bütçe aylık-Eur'!$D$65 | I120: ='gerç aylık-eur'!$D$65 | K120: ='Bütçe aylık-Eur'!$E$65 | L120: ='gerç aylık-eur'!$E$65 | N120: ='Bütçe aylık-Eur'!$F$65 | O120: ='gerç aylık-eur'!$F$65 | Q120: ='Bütçe aylık-Eur'!$G$65 | R120: ='gerç aylık-eur'!$G$65 | T120: ='Bütçe aylık-Eur'!$H$65 | U120: ='gerç aylık-eur'!$H$65 | W120: ='Bütçe aylık-Eur'!$I$65 | X120: ='gerç aylık-eur'!$I$65 | Z120: ='Bütçe aylık-Eur'!$J$65 | AA120: ='gerç aylık-eur'!$J$65 | AC120: ='Bütçe aylık-Eur'!$K$65 | AD120: ='gerç aylık-eur'!$K$65 | AF120: ='Bütçe aylık-Eur'!$L$65 | AG120: ='gerç aylık-eur'!$L$65 | AI120: ='Bütçe aylık-Eur'!$M$65 | AJ120: ='gerç aylık-eur'!$M$65 | AL120: =AP120-AO120 | AM120: =AP120/AO120-1 | AO120: =IF($A$1=$B$1,B120,IF($A$1=$E$1,E120,IF($A$1=$H$1,H120,IF($A$1=$K$1,K120,IF($A$1=$N$1,N120,IF($A$1=$Q$1,Q120,IF($A$1=$T$1,T120,IF($A$1=$W$1,W120,IF($A$1=$Z$1,Z120,IF($A$1=$AC$1,AC120,IF($A$1=$AF$1,AF120,IF($A$1=$AI$1,AI120)))))))))))) | AP120: =IF($A$1=$B$1,C120,IF($A$1=$E$1,F120,IF($A$1=$H$1,I120,IF($A$1=$K$1,L120,IF($A$1=$N$1,O120,IF($A$1=$Q$1,R120,IF($A$1=$T$1,U120,IF($A$1=$W$1,X120,IF($A$1=$Z$1,AA120,IF($A$1=$AC$1,AD120,IF($A$1=$AF$1,AG120,IF($A$1=$AI$1,AJ120))))))))))))
...

Sheet C-Döviz
A1: ='C-TRY'!A1 | B1: OCAK | E1: ŞUBAT | H1: MART | K1: NİSAN | N1: MAYIS | Q1: HAZİRAN | T1: TEMMUZ | W1: AĞUSTOS | Z1: EYLÜL | AC1: EKİM | AF1: KASIM | AI1: ARALIK
B2: Budget | C2: Actual | E2: Budget | F2: Actual | H2: Budget | I2: Actual | K2: Budget | L2: Actual | N2: Budget | O2: Actual | Q2: Budget | R2: Actual | T2: Budget | U2: Actual | W2: Budget | X2: Actual | Z2: Budget | AA2: Actual | AC2: Budget | AD2: Actual | AF2: Budget | AG2: Actual | AI2: Budget | AJ2: Actual | AL2: Difference | AM2: Variance % | AO2: Budget | AP2: Actual
A3: Eur Kapanış | B3: ='C-TRY'!B3 | C3: ='C-TRY'!C3 | D3: ='C-TRY'!D3 | E3: ='C-TRY'!E3 | F3: ='C-TRY'!F3 | G3: ='C-TRY'!G3 | H3: ='C-TRY'!H3 | I3: ='C-TRY'!I3 | K3: ='C-TRY'!K3 | L3: ='C-TRY'!L3 | M3: ='C-TRY'!M3 | N3: ='C-TRY'!N3 | O3: ='C-TRY'!O3 | P3: ='C-TRY'!P3 | Q3: ='C-TRY'!Q3 | R3: ='C-TRY'!R3 | T3: ='C-TRY'!T3 | U3: ='C-TRY'!U3 | W3: ='C-TRY'!W3 | X3: ='C-TRY'!X3 | Y3: ='C-TRY'!Y3 | Z3: ='C-TRY'!Z3 | AA3: ='C-TRY'!AA3 | AC3: ='C-TRY'!AC3 | AD3: ='C-TRY'!AD3 | AE3: ='C-TRY'!AE3 | AF3: ='C-TRY'!AF3 | AG3: ='C-TRY'!AG3 | AH3: ='C-TRY'!AH3 | AI3: ='C-TRY'!AI3 | AJ3: ='C-TRY'!AJ3 | AL3: =AP3-AO3 | AM3: =AP3/AO3-1 | AO3: =IF($A$1=$B$1,B3,IF($A$1=$E$1,E3,IF($A$1=$H$1,H3,IF($A$1=$K$1,K3,IF($A$1=$N$1,N3,IF($A$1=$Q$1,Q3,IF($A$1=$T$1,T3,IF($A$1=$W$1,W3,IF($A$1=$Z$1,Z3,IF($A$1=$AC$1,AC3,IF($A$1=$AF$1,AF3,IF($A$1=$AI$1,AI3)))))))))))) | AP3: =IF($A$1=$B$1,C3,IF($A$1=$E$1,F3,IF($A$1=$H$1,I3,IF($A$1=$K$1,L3,IF($A$1=$N$1,O3,IF($A$1=$Q$1,R3,IF($A$1=$T$1,U3,IF($A$1=$W$1,X3,IF($A$1=$Z$1,AA3,IF($A$1=$AC$1,AD3,IF($A$1=$AF$1,AG3,IF($A$1=$AI$1,AJ3))))))))))))
A4: Eur Ortalama | B4: ='C-TRY'!B4 | C4: ='C-TRY'!C4 | D4: ='C-TRY'!D4 | E4: ='C-TRY'!E4 | F4: ='C-TRY'!F4 | G4: ='C-TRY'!G4 | H4: ='C-TRY'!H4 | I4: ='C-TRY'!I4 | K4: ='C-TRY'!K4 | L4: ='C-TRY'!L4 | M4: ='C-TRY'!M4 | N4: ='C-TRY'!N4 | O4: ='C-TRY'!O4 | P4: ='C-TRY'!P4 | Q4: ='C-TRY'!Q4 | R4: ='C-TRY'!R4 | T4: ='C-TRY'!T4 | U4: ='C-TRY'!U4 | W4: ='C-TRY'!W4 | X4: ='C-TRY'!X4 | Y4: ='C-TRY'!Y4 | Z4: ='C-TRY'!Z4 | AA4: ='C-TRY'!AA4 | AC4: ='C-TRY'!AC4 | AD4: ='C-TRY'!AD4 | AE4: ='C-TRY'!AE4 | AF4: ='C-TRY'!AF4 | AG4: ='C-TRY'!AG4 | AH4: ='C-TRY'!AH4 | AI4: ='C-TRY'!AI4 | AJ4: ='C-TRY'!AJ4 | AL4: =AP4-AO4 | AM4: =AP4/AO4-1 | AO4: =IF($A$1=$B$1,B4,IF($A$1=$E$1,E4,IF($A$1=$H$1,H4,IF($A$1=$K$1,K4,IF($A$1=$N$1,N4,IF($A$1=$Q$1,Q4,IF($A$1=$T$1,T4,IF($A$1=$W$1,W4,IF($A$1=$Z$1,Z4,IF($A$1=$AC$1,AC4,IF($A$1=$AF$1,AF4,IF($A$1=$AI$1,AI4)))))))))))) | AP4: =IF($A$1=$B$1,C4,IF($A$1=$E$1,F4,IF($A$1=$H$1,I4,IF($A$1=$K$1,L4,IF($A$1=$N$1,O4,IF($A$1=$Q$1,R4,IF($A$1=$T$1,U4,IF($A$1=$W$1,X4,IF($A$1=$Z$1,AA4,IF($A$1=$AC$1,AD4,IF($A$1=$AF$1,AG4,IF($A$1=$AI$1,AJ4))))))))))))
A6: Net Sales | B6: ='A -Döviz'!B6 | C6: ='A -Döviz'!C6 | E6: =B6+'A -Döviz'!E6 | F6: =C6+'A -Döviz'!F6 | H6: =E6+'A -Döviz'!H6 | I6: =F6+'A -Döviz'!I6 | K6: =H6+'A -Döviz'!K6 | L6: =I6+'A -Döviz'!L6 | N6: =K6+'A -Döviz'!N6 | O6: =L6+'A -Döviz'!O6 | Q6: =N6+'A -Döviz'!Q6 | R6: =O6+'A -Döviz'!R6 | T6: =Q6+'A -Döviz'!T6 | U6: =R6+'A -Döviz'!U6 | W6: =T6+'A -Döviz'!W6 | X6: =U6+'A -Döviz'!X6 | Z6: =W6+'A -Döviz'!Z6 | AA6: =X6+'A -Döviz'!AA6 | AC6: =Z6+'A -Döviz'!AC6 | AD6: =AA6+'A -Döviz'!AD6 | AF6: =AC6+'A -Döviz'!AF6 | AG6: =AD6+'A -Döviz'!AG6 | AI6: =AF6+'A -Döviz'!AI6 | AJ6: =AG6+'A -Döviz'!AJ6 | AL6: =AP6-AO6 | AM6: =AP6/AO6-1 | AO6: =IF($A$1=$B$1,B6,IF($A$1=$E$1,E6,IF($A$1=$H$1,H6,IF($A$1=$K$1,K6,IF($A$1=$N$1,N6,IF($A$1=$Q$1,Q6,IF($A$1=$T$1,T6,IF($A$1=$W$1,W6,IF($A$1=$Z$1,Z6,IF($A$1=$AC$1,AC6,IF($A$1=$AF$1,AF6,IF($A$1=$AI$1,AI6)))))))))))) | AP6: =IF($A$1=$B$1,C6,IF($A$1=$E$1,F6,IF($A$1=$H$1,I6,IF($A$1=$K$1,L6,IF($A$1=$N$1,O6,IF($A$1=$Q$1,R6,IF($A$1=$T$1,U6,IF($A$1=$W$1,X6,IF($A$1=$Z$1,AA6,IF($A$1=$AC$1,AD6,IF($A$1=$AF$1,AG6,IF($A$1=$AI$1,AJ6))))))))))))
A8: SALES BY CHANNELS(100% Satışlar) | AR8: =SUM(AR9:AR16) | AS8: =SUM(AS9:AS16)
A9: İnci Holding | B9: ='A -Döviz'!B9 | C9: ='A -Döviz'!C9 | E9: =B9+'A -Döviz'!E9 | F9: =C9+'A -Döviz'!F9 | G9: =F9/E9-1 | H9: =E9+'A -Döviz'!H9 | I9: =F9+'A -Döviz'!I9 | K9: =H9+'A -Döviz'!K9 | L9: =I9+'A -Döviz'!L9 | N9: =K9+'A -Döviz'!N9 | O9: =L9+'A -Döviz'!O9 | Q9: =N9+'A -Döviz'!Q9 | R9: =O9+'A -Döviz'!R9 | T9: =Q9+'A -Döviz'!T9 | U9: =R9+'A -Döviz'!U9 | W9: =T9+'A -Döviz'!W9 | X9: =U9+'A -Döviz'!X9 | Z9: =W9+'A -Döviz'!Z9 | AA9: =X9+'A -Döviz'!AA9 | AB9: =Z9/AA9-1 | AC9: =Z9+'A -Döviz'!AC9 | AD9: =AA9+'A -Döviz'!AD9 | AF9: =AC9+'A -Döviz'!AF9 | AG9: =AD9+'A -Döviz'!AG9 | AI9: =AF9+'A -Döviz'!AI9 | AJ9: =AG9+'A -Döviz'!AJ9 | AL9: =AP9-AO9 | AM9: =AP9/AO9-1 | AO9: =IF($A$1=$B$1,B9,IF($A$1=$E$1,E9,IF($A$1=$H$1,H9,IF($A$1=$K$1,K9,IF($A$1=$N$1,N9,IF($A$1=$Q$1,Q9,IF($A$1=$T$1,T9,IF($A$1=$W$1,W9,IF($A$1=$Z$1,Z9,IF($A$1=$AC$1,AC9,IF($A$1=$AF$1,AF9,IF($A$1=$AI$1,AI9)))))))))))) | AP9: =IF($A$1=$B$1,C9,IF($A$1=$E$1,F9,IF($A$1=$H$1,I9,IF($A$1=$K$1,L9,IF($A$1=$N$1,O9,IF($A$1=$Q$1,R9,IF($A$1=$T$1,U9,IF($A$1=$W$1,X9,IF($A$1=$Z$1,AA9,IF($A$1=$AC$1,AD9,IF($A$1=$AF$1,AG9,IF($A$1=$AI$1,AJ9)))))))))))) | AR9: =W9 | AS9: =AD9 | AT9: =AS9-AR9 | AV9: 9233250.8 | AW9: =AV9-AI9
A10: ISM | B10: ='A -Döviz'!B10 | C10: ='A -Döviz'!C10 | E10: =B10+'A -Döviz'!E10 | F10: =C10+'A -Döviz'!F10 | G10: =F10/E10-1 | H10: =E10+'A -Döviz'!H10 | I10: =F10+'A -Döviz'!I10 | K10: =H10+'A -Döviz'!K10 | L10: =I10+'A -Döviz'!L10 | N10: =K10+'A -Döviz'!N10 | O10: =L10+'A -Döviz'!O10 | Q10: =N10+'A -Döviz'!Q10 | R10: =O10+'A -Döviz'!R10 | T10: =Q10+'A -Döviz'!T10 | U10: =R10+'A -Döviz'!U10 | W10: =T10+'A -Döviz'!W10 | X10: =U10+'A -Döviz'!X10 | Z10: =W10+'A -Döviz'!Z10 | AA10: =X10+'A -Döviz'!AA10 | AB10: =Z10/AA10-1 | AC10: =Z10+'A -Döviz'!AC10 | AD10: =AA10+'A -Döviz'!AD10 | AF10: =AC10+'A -Döviz'!AF10 | AG10: =AD10+'A -Döviz'!AG10 | AI10: =AF10+'A -Döviz'!AI10 | AJ10: =AG10+'A -Döviz'!AJ10 | AL10: =AP10-AO10 | AM10: =AP10/AO10-1 | AO10: =IF($A$1=$B$1,B10,IF($A$1=$E$1,E10,IF($A$1=$H$1,H10,IF($A$1=$K$1,K10,IF($A$1=$N$1,N10,IF($A$1=$Q$1,Q10,IF($A$1=$T$1,T10,IF($A$1=$W$1,W10,IF($A$1=$Z$1,Z10,IF($A$1=$AC$1,AC10,IF($A$1=$AF$1,AF10,IF($A$1=$AI$1,AI10)))))))))))) | AP10: =IF($A$1=$B$1,C10,IF($A$1=$E$1,F10,IF($A$1=$H$1,I10,IF($A$1=$K$1,L10,IF($A$1=$N$1,O10,IF($A$1=$Q$1,R10,IF($A$1=$T$1,U10,IF($A$1=$W$1,X10,IF($A$1=$Z$1,AA10,IF($A$1=$AC$1,AD10,IF($A$1=$AF$1,AG10,IF($A$1=$AI$1,AJ10)))))))))))) | AR10: =W10 | AS10: =AD10 | AT10: =AS10-AR10 | AV10: 9248212 | AW10: =AV10-AI10
A11: İncitaş | B11: ='A -Döviz'!B11 | C11: ='A -Döviz'!C11 | E11: =B11+'A -Döviz'!E11 | F11: =C11+'A -Döviz'!F11 | G11: =F11/E11-1 | H11: =E11+'A -Döviz'!H11 | I11: =F11+'A -Döviz'!I11 | K11: =H11+'A -Döviz'!K11 | L11: =I11+'A -Döviz'!L11 | N11: =K11+'A -Döviz'!N11 | O11: =L11+'A -Döviz'!O11 | Q11: =N11+'A -Döviz'!Q11 | R11: =O11+'A -Döviz'!R11 | T11: =Q11+'A -Döviz'!T11 | U11: =R11+'A -Döviz'!U11 | W11: =T11+'A -Döviz'!W11 | X11: =U11+'A -Döviz'!X11 | Z11: =W11+'A -Döviz'!Z11 | AA11: =X11+'A -Döviz'!AA11 | AB11: =Z11/AA11-1 | AC11: =Z11+'A -Döviz'!AC11 | AD11: =AA11+'A -Döviz'!AD11 | AF11: =AC11+'A -Döviz'!AF11 | AG11: =AD11+'A -Döviz'!AG11 | AI11: =AF11+'A -Döviz'!AI11 | AJ11: =AG11+'A -Döviz'!AJ11 | AL11: =AP11-AO11 | AM11: =AP11/AO11-1 | AO11: =IF($A$1=$B$1,B11,IF($A$1=$E$1,E11,IF($A$1=$H$1,H11,IF($A$1=$K$1,K11,IF($A$1=$N$1,N11,IF($A$1=$Q$1,Q11,IF($A$1=$T$1,T11,IF($A$1=$W$1,W11,IF($A$1=$Z$1,Z11,IF($A$1=$AC$1,AC11,IF($A$1=$AF$1,AF11,IF($A$1=$AI$1,AI11)))))))))))) | AP11: =IF($A$1=$B$1,C11,IF($A$1=$E$1,F11,IF($A$1=$H$1,I11,IF($A$1=$K$1,L11,IF($A$1=$N$1,O11,IF($A$1=$Q$1,R11,IF($A$1=$T$1,U11,IF($A$1=$W$1,X11,IF($A$1=$Z$1,AA11,IF($A$1=$AC$1,AD11,IF($A$1=$AF$1,AG11,IF($A$1=$AI$1,AJ11)))))))))))) | AR11: =W11 | AS11: =AD11 | AT11: =AS11-AR11 | AV11: 16822043 | AW11: =AV11-AI11
A12: İnci GS Yuasa | B12: ='A -Döviz'!B12 | C12: ='A -Döviz'!C12 | D12: =+(C12/B12)-1 | E12: =B12+'A -Döviz'!E12 | F12: =C12+'A -Döviz'!F12 | G12: =F12/E12-1 | H12: =E12+'A -Döviz'!H12 | I12: =F12+'A -Döviz'!I12 | K12: =H12+'A -Döviz'!K12 | L12: =I12+'A -Döviz'!L12 | N12: =K12+'A -Döviz'!N12 | O12: =L12+'A -Döviz'!O12 | Q12: =N12+'A -Döviz'!Q12 | R12: =O12+'A -Döviz'!R12 | T12: =Q12+'A -Döviz'!T12 | U12: =R12+'A -Döviz'!U12 | W12: =T12+'A -Döviz'!W12 | X12: =U12+'A -Döviz'!X12 | Z12: =W12+'A -Döviz'!Z12 | AA12: =X12+'A -Döviz'!AA12 | AB12: =Z12/AA12-1 | AC12: =Z12+'A -Döviz'!AC12 | AD12: =AA12+'A -Döviz'!AD12 | AF12: =AC12+'A -Döviz'!AF12 | AG12: =AD12+'A -Döviz'!AG12 | AI12: =AF12+'A -Döviz'!AI12 | AJ12: =AG12+'A -Döviz'!AJ12 | AL12: =AP12-AO12 | AM12: =AP12/AO12-1 | AN12: =AL12*0.4 | AO12: =IF($A$1=$B$1,B12,IF($A$1=$E$1,E12,IF($A$1=$H$1,H12,IF($A$1=$K$1,K12,IF($A$1=$N$1,N12,IF($A$1=$Q$1,Q12,IF($A$1=$T$1,T12,IF($A$1=$W$1,W12,IF($A$1=$Z$1,Z12,IF($A$1=$AC$1,AC12,IF($A$1=$AF$1,AF12,IF($A$1=$AI$1,AI12)))))))))))) | AP12: =IF($A$1=$B$1,C12,IF($A$1=$E$1,F12,IF($A$1=$H$1,I12,IF($A$1=$K$1,L12,IF($A$1=$N$1,O12,IF($A$1=$Q$1,R12,IF($A$1=$T$1,U12,IF($A$1=$W$1,X12,IF($A$1=$Z$1,AA12,IF($A$1=$AC$1,AD12,IF($A$1=$AF$1,AG12,IF($A$1=$AI$1,AJ12)))))))))))) | AR12: =W12*0.4 | AS12: =AD12*0.4 | AT12: =AS12-AR12 | AV12: 2.5849199e+08 | AW12: =AV12-AI12
A13: Yusen İnci Loj. | B13: ='A -Döviz'!B13 | C13: ='A -Döviz'!C13 | E13: =B13+'A -Döviz'!E13 | F13: =C13+'A -Döviz'!F13 | G13: =F13/E13-1 | H13: =E13+'A -Döviz'!H13 | I13: =F13+'A -Döviz'!I13 | K13: =H13+'A -Döviz'!K13 | L13: =I13+'A -Döviz'!L13 | N13: =K13+'A -Döviz'!N13 | O13: =L13+'A -Döviz'!O13 | Q13: =N13+'A -Döviz'!Q13 | R13: =O13+'A -Döviz'!R13 | T13: =Q13+'A -Döviz'!T13 | U13: =R13+'A -Döviz'!U13 | W13: =T13+'A -Döviz'!W13 | X13: =U13+'A -Döviz'!X13 | Z13: =W13+'A -Döviz'!Z13 | AA13: =X13+'A -Döviz'!AA13 | AB13: =Z13/AA13-1 | AC13: =Z13+'A -Döviz'!AC13 | AD13: =AA13+'A -Döviz'!AD13 | AF13: =AC13+'A -Döviz'!AF13 | AG13: =AD13+'A -Döviz'!AG13 | AI13: =AF13+'A -Döviz'!AI13 | AJ13: =AG13+'A -Döviz'!AJ13 | AL13: =AP13-AO13 | AM13: =AP13/AO13-1 | AN13: =AL13*0.4 | AO13: =IF($A$1=$B$1,B13,IF($A$1=$E$1,E13,IF($A$1=$H$1,H13,IF($A$1=$K$1,K13,IF($A$1=$N$1,N13,IF($A$1=$Q$1,Q13,IF($A$1=$T$1,T13,IF($A$1=$W$1,W13,IF($A$1=$Z$1,Z13,IF($A$1=$AC$1,AC13,IF($A$1=$AF$1,AF13,IF($A$1=$AI$1,AI13)))))))))))) | AP13: =IF($A$1=$B$1,C13,IF($A$1=$E$1,F13,IF($A$1=$H$1,I13,IF($A$1=$K$1,L13,IF($A$1=$N$1,O13,IF($A$1=$Q$1,R13,IF($A$1=$T$1,U13,IF($A$1=$W$1,X13,IF($A$1=$Z$1,AA13,IF($A$1=$AC$1,AD13,IF($A$1=$AF$1,AG13,IF($A$1=$AI$1,AJ13)))))))))))) | AR13: =W13*0.4 | AS13: =AD13*0.4 | AT13: =AS13-AR13 | AV13: 78339112 | AW13: =AV13-AI13 | AX13: 135771921
A14: Jantaş | B14: ='A -Döviz'!B14 | C14: ='A -Döviz'!C14 | E14: =B14+'A -Döviz'!E14 | F14: =C14+'A -Döviz'!F14 | G14: =F14/E14-1 | H14: =E14+'A -Döviz'!H14 | I14: =F14+'A -Döviz'!I14 | K14: =H14+'A -Döviz'!K14 | L14: =I14+'A -Döviz'!L14 | N14: =K14+'A -Döviz'!N14 | O14: =L14+'A -Döviz'!O14 | Q14: =N14+'A -Döviz'!Q14 | R14: =O14+'A -Döviz'!R14 | T14: =Q14+'A -Döviz'!T14 | U14: =R14+'A -Döviz'!U14 | W14: =T14+'A -Döviz'!W14 | X14: =U14+'A -Döviz'!X14 | Z14: =W14+'A -Döviz'!Z14 | AA14: =X14+'A -Döviz'!AA14 | AB14: =Z14/AA14-1 | AC14: =Z14+'A -Döviz'!AC14 | AD14: =AA14+'A -Döviz'!AD14 | AF14: =AC14+'A -Döviz'!AF14 | AG14: =AD14+'A -Döviz'!AG14 | AI14: =AF14+'A -Döviz'!AI14 | AJ14: =AG14+'A -Döviz'!AJ14 | AL14: =AP14-AO14 | AM14: =AP14/AO14-1 | AN14: =AL14*0.4 | AO14: =IF($A$1=$B$1,B14,IF($A$1=$E$1,E14,IF($A$1=$H$1,H14,IF($A$1=$K$1,K14,IF($A$1=$N$1,N14,IF($A$1=$Q$1,Q14,IF($A$1=$T$1,T14,IF($A$1=$W$1,W14,IF($A$1=$Z$1,Z14,IF($A$1=$AC$1,AC14,IF($A$1=$AF$1,AF14,IF($A$1=$AI$1,AI14)))))))))))) | AP14: =IF($A$1=$B$1,C14,IF($A$1=$E$1,F14,IF($A$1=$H$1,I14,IF($A$1=$K$1,L14,IF($A$1=$N$1,O14,IF($A$1=$Q$1,R14,IF($A$1=$T$1,U14,IF($A$1=$W$1,X14,IF($A$1=$Z$1,AA14,IF($A$1=$AC$1,AD14,IF($A$1=$AF$1,AG14,IF($A$1=$AI$1,AJ14)))))))))))) | AR14: =W14*0.4 | AS14: =AD14*0.4 | AT14: =AS14-AR14 | AV14: 1.3399974e+08 | AW14: =AV14-AI14 | AX14: =AX13/30.77
A15: Çelik | B15: ='A -Döviz'!B15 | C15: ='A -Döviz'!C15 | E15: =B15+'A -Döviz'!E15 | F15: =C15+'A -Döviz'!F15 | G15: =F15/E15-1 | H15: =E15+'A -Döviz'!H15 | I15: =F15+'A -Döviz'!I15 | K15: =H15+'A -Döviz'!K15 | L15: =I15+'A -Döviz'!L15 | N15: =K15+'A -Döviz'!N15 | O15: =L15+'A -Döviz'!O15 | Q15: =N15+'A -Döviz'!Q15 | R15: =O15+'A -Döviz'!R15 | T15: =Q15+'A -Döviz'!T15 | U15: =R15+'A -Döviz'!U15 | W15: =T15+'A -Döviz'!W15 | X15: =U15+'A -Döviz'!X15 | Z15: =W15+'A -Döviz'!Z15 | AA15: =X15+'A -Döviz'!AA15 | AB15: =Z15/AA15-1 | AC15: =Z15+'A -Döviz'!AC15 | AD15: =AA15+'A -Döviz'!AD15 | AF15: =AC15+'A -Döviz'!AF15 | AG15: =AD15+'A -Döviz'!AG15 | AI15: =AF15+'A -Döviz'!AI15 | AJ15: =AG15+'A -Döviz'!AJ15 | AL15: =AP15-AO15 | AM15: =AP15/AO15-1 | AN15: =AL15*0.4 | AO15: =IF($A$1=$B$1,B15,IF($A$1=$E$1,E15,IF($A$1=$H$1,H15,IF($A$1=$K$1,K15,IF($A$1=$N$1,N15,IF($A$1=$Q$1,Q15,IF($A$1=$T$1,T15,IF($A$1=$W$1,W15,IF($A$1=$Z$1,Z15,IF($A$1=$AC$1,AC15,IF($A$1=$AF$1,AF15,IF($A$1=$AI$1,AI15)))))))))))) | AP15: =IF($A$1=$B$1,C15,IF($A$1=$E$1,F15,IF($A$1=$H$1,I15,IF($A$1=$K$1,L15,IF($A$1=$N$1,O15,IF($A$1=$Q$1,R15,IF($A$1=$T$1,U15,IF($A$1=$W$1,X15,IF($A$1=$Z$1,AA15,IF($A$1=$AC$1,AD15,IF($A$1=$AF$1,AG15,IF($A$1=$AI$1,AJ15)))))))))))) | AR15: =W15*0.4 | AS15: =AD15*0.4 | AT15: =AS15-AR15 | AV15: 85847861 | AW15: =AV15-AI15
A16: Alüminyum | B16: ='A -Döviz'!B16 | C16: ='A -Döviz'!C16 | E16: =B16+'A -Döviz'!E16 | F16: =C16+'A -Döviz'!F16 | G16: =F16/E16-1 | H16: =E16+'A -Döviz'!H16 | I16: =F16+'A -Döviz'!I16 | K16: =H16+'A -Döviz'!K16 | L16: =I16+'A -Döviz'!L16 | N16: =K16+'A -Döviz'!N16 | O16: =L16+'A -Döviz'!O16 | Q16: =N16+'A -Döviz'!Q16 | R16: =O16+'A -Döviz'!R16 | T16: =Q16+'A -Döviz'!T16 | U16: =R16+'A -Döviz'!U16 | W16: =T16+'A -Döviz'!W16 | X16: =U16+'A -Döviz'!X16 | Z16: =W16+'A -Döviz'!Z16 | AA16: =X16+'A -Döviz'!AA16 | AB16: =Z16/AA16-1 | AC16: =Z16+'A -Döviz'!AC16 | AD16: =AA16+'A -Döviz'!AD16 | AF16: =AC16+'A -Döviz'!AF16 | AG16: =AD16+'A -Döviz'!AG16 | AI16: =AF16+'A -Döviz'!AI16 | AJ16: =AG16+'A -Döviz'!AJ16 | AL16: =AP16-AO16 | AM16: =AP16/AO16-1 | AN16: =AL16*0.4 | AO16: =IF($A$1=$B$1,B16,IF($A$1=$E$1,E16,IF($A$1=$H$1,H16,IF($A$1=$K$1,K16,IF($A$1=$N$1,N16,IF($A$1=$Q$1,Q16,IF($A$1=$T$1,T16,IF($A$1=$W$1,W16,IF($A$1=$Z$1,Z16,IF($A$1=$AC$1,AC16,IF($A$1=$AF$1,AF16,IF($A$1=$AI$1,AI16)))))))))))) | AP16: =IF($A$1=$B$1,C16,IF($A$1=$E$1,F16,IF($A$1=$H$1,I16,IF($A$1=$K$1,L16,IF($A$1=$N$1,O16,IF($A$1=$Q$1,R16,IF($A$1=$T$1,U16,IF($A$1=$W$1,X16,IF($A$1=$Z$1,AA16,IF($A$1=$AC$1,AD16,IF($A$1=$AF$1,AG16,IF($A$1=$AI$1,AJ16)))))))))))) | AR16: =W16*0.4 | AS16: =AD16*0.4 | AT16: =AS16-AR16 | AV16: 2.4768298e+08 | AW16: =AV16-AI16
L17: =L18-L16 | AO17: =IF($A$1=$B$1,B17,IF($A$1=$E$1,E17,IF($A$1=$H$1,H17,IF($A$1=$K$1,K17,IF($A$1=$N$1,N17,IF($A$1=$Q$1,Q17,IF($A$1=$T$1,T17,IF($A$1=$W$1,W17,IF($A$1=$Z$1,Z17,IF($A$1=$AC$1,AC17,IF($A$1=$AF$1,AF17,IF($A$1=$AI$1,AI17)))))))))))) | AP17: =IF($A$1=$B$1,C17,IF($A$1=$E$1,F17,IF($A$1=$H$1,I17,IF($A$1=$K$1,L17,IF($A$1=$N$1,O17,IF($A$1=$Q$1,R17,IF($A$1=$T$1,U17,IF($A$1=$W$1,X17,IF($A$1=$Z$1,AA17,IF($A$1=$AC$1,AD17,IF($A$1=$AF$1,AG17,IF($A$1=$AI$1,AJ17))))))))))))
L18: 110689000 | AO18: =IF($A$1=$B$1,B18,IF($A$1=$E$1,E18,IF($A$1=$H$1,H18,IF($A$1=$K$1,K18,IF($A$1=$N$1,N18,IF($A$1=$Q$1,Q18,IF($A$1=$T$1,T18,IF($A$1=$W$1,W18,IF($A$1=$Z$1,Z18,IF($A$1=$AC$1,AC18,IF($A$1=$AF$1,AF18,IF($A$1=$AI$1,AI18)))))))))))) | AP18: =IF($A$1=$B$1,C18,IF($A$1=$E$1,F18,IF($A$1=$H$1,I18,IF($A$1=$K$1,L18,IF($A$1=$N$1,O18,IF($A$1=$Q$1,R18,IF($A$1=$T$1,U18,IF($A$1=$W$1,X18,IF($A$1=$Z$1,AA18,IF($A$1=$AC$1,AD18,IF($A$1=$AF$1,AG18,IF($A$1=$AI$1,AJ18))))))))))))
A19: SHARE OF SALES (%)
A20: İnci Holding | B20: =B9/B6 | C20: =C9/C6 | E20: =E9/E6 | F20: =F9/F6 | H20: =H9/H6 | I20: =I9/I6 | K20: =K9/K6 | L20: =L9/L6 | N20: =N9/N6 | O20: =O9/O6 | Q20: =Q9/Q6 | R20: =R9/R6 | T20: =T9/T6 | U20: =U9/U6 | W20: =W9/W6 | X20: =X9/X6 | Z20: =Z9/Z6 | AA20: =AA9/AA6 | AC20: =AC9/AC6 | AD20: =AD9/AD6 | AF20: =AF9/AF6 | AG20: =AG9/AG6 | AI20: =AI9/AI6 | AJ20: =AJ9/AJ6 | AL20: =AP20-AO20 | AO20: =IF($A$1=$B$1,B20,IF($A$1=$E$1,E20,IF($A$1=$H$1,H20,IF($A$1=$K$1,K20,IF($A$1=$N$1,N20,IF($A$1=$Q$1,Q20,IF($A$1=$T$1,T20,IF($A$1=$W$1,W20,IF($A$1=$Z$1,Z20,IF($A$1=$AC$1,AC20,IF($A$1=$AF$1,AF20,IF($A$1=$AI$1,AI20)))))))))))) | AP20: =IF($A$1=$B$1,C20,IF($A$1=$E$1,F20,IF($A$1=$H$1,I20,IF($A$1=$K$1,L20,IF($A$1=$N$1,O20,IF($A$1=$Q$1,R20,IF($A$1=$T$1,U20,IF($A$1=$W$1,X20,IF($A$1=$Z$1,AA20,IF($A$1=$AC$1,AD20,IF($A$1=$AF$1,AG20,IF($A$1=$AI$1,AJ20))))))))))))
A21: ISM | B21: =B10/B6 | C21: =C10/C6 | E21: =E10/E6 | F21: =F10/F6 | H21: =H10/H6 | I21: =I10/I6 | K21: =K10/K6 | L21: =L10/L6 | N21: =N10/N6 | O21: =O10/O6 | Q21: =Q10/Q6 | R21: =R10/R6 | T21: =T10/T6 | U21: =U10/U6 | W21: =W10/W6 | X21: =X10/X6 | Z21: =Z10/Z6 | AA21: =AA10/AA6 | AC21: =AC10/AC6 | AD21: =AD10/AD6 | AF21: =AF10/AF6 | AG21: =AG10/AG6 | AI21: =AI10/AI6 | AJ21: =AJ10/AJ6 | AL21: =AP21-AO21 | AO21: =IF($A$1=$B$1,B21,IF($A$1=$E$1,E21,IF($A$1=$H$1,H21,IF($A$1=$K$1,K21,IF($A$1=$N$1,N21,IF($A$1=$Q$1,Q21,IF($A$1=$T$1,T21,IF($A$1=$W$1,W21,IF($A$1=$Z$1,Z21,IF($A$1=$AC$1,AC21,IF($A$1=$AF$1,AF21,IF($A$1=$AI$1,AI21)))))))))))) | AP21: =IF($A$1=$B$1,C21,IF($A$1=$E$1,F21,IF($A$1=$H$1,I21,IF($A$1=$K$1,L21,IF($A$1=$N$1,O21,IF($A$1=$Q$1,R21,IF($A$1=$T$1,U21,IF($A$1=$W$1,X21,IF($A$1=$Z$1,AA21,IF($A$1=$AC$1,AD21,IF($A$1=$AF$1,AG21,IF($A$1=$AI$1,AJ21))))))))))))
A22: İncitaş | B22: =B11/B6 | C22: =C11/C6 | E22: =E11/E6 | F22: =F11/F6 | H22: =H11/H6 | I22: =I11/I6 | K22: =K11/K6 | L22: =L11/L6 | N22: =N11/N6 | O22: =O11/O6 | Q22: =Q11/Q6 | R22: =R11/R6 | T22: =T11/T6 | U22: =U11/U6 | W22: =W11/W6 | X22: =X11/X6 | Z22: =Z11/Z6 | AA22: =AA11/AA6 | AC22: =AC11/AC6 | AD22: =AD11/AD6 | AF22: =AF11/AF6 | AG22: =AG11/AG6 | AI22: =AI11/AI6 | AJ22: =AJ11/AJ6 | AL22: =AP22-AO22 | AO22: =IF($A$1=$B$1,B22,IF($A$1=$E$1,E22,IF($A$1=$H$1,H22,IF($A$1=$K$1,K22,IF($A$1=$N$1,N22,IF($A$1=$Q$1,Q22,IF($A$1=$T$1,T22,IF($A$1=$W$1,W22,IF($A$1=$Z$1,Z22,IF($A$1=$AC$1,AC22,IF($A$1=$AF$1,AF22,IF($A$1=$AI$1,AI22)))))))))))) | AP22: =IF($A$1=$B$1,C22,IF($A$1=$E$1,F22,IF($A$1=$H$1,I22,IF($A$1=$K$1,L22,IF($A$1=$N$1,O22,IF($A$1=$Q$1,R22,IF($A$1=$T$1,U22,IF($A$1=$W$1,X22,IF($A$1=$Z$1,AA22,IF($A$1=$AC$1,AD22,IF($A$1=$AF$1,AG22,IF($A$1=$AI$1,AJ22))))))))))))
A23: İnci GS Yuasa | B23: =B12*0.5/B6 | C23: =C12*0.5/C6 | E23: =E12*0.5/E6 | F23: =F12*0.5/F6 | H23: =H12*0.5/H6 | I23: =I12*0.5/I6 | K23: =K12*0.5/K6 | L23: =L12*0.5/L6 | N23: =N12*0.5/N6 | O23: =O12*0.5/O6 | Q23: =Q12*0.5/Q6 | R23: =R12*0.5/R6 | T23: =T12*0.5/T6 | U23: =U12*0.5/U6 | W23: =W12*0.5/W6 | X23: =X12*0.5/X6 | Z23: =Z12*0.5/Z6 | AA23: =AA12*0.5/AA6 | AC23: =AC12*0.4/AC6 | AD23: =AD12*0.4/AD6 | AF23: =AF12*0.4/AF6 | AG23: =AG12*0.4/AG6 | AI23: =AI12*0.5/AI6 | AJ23: =AJ12*0.5/AJ6 | AL23: =AP23-AO23 | AO23: =IF($A$1=$B$1,B23,IF($A$1=$E$1,E23,IF($A$1=$H$1,H23,IF($A$1=$K$1,K23,IF($A$1=$N$1,N23,IF($A$1=$Q$1,Q23,IF($A$1=$T$1,T23,IF($A$1=$W$1,W23,IF($A$1=$Z$1,Z23,IF($A$1=$AC$1,AC23,IF($A$1=$AF$1,AF23,IF($A$1=$AI$1,AI23)))))))))))) | AP23: =IF($A$1=$B$1,C23,IF($A$1=$E$1,F23,IF($A$1=$H$1,I23,IF($A$1=$K$1,L23,IF($A$1=$N$1,O23,IF($A$1=$Q$1,R23,IF($A$1=$T$1,U23,IF($A$1=$W$1,X23,IF($A$1=$Z$1,AA23,IF($A$1=$AC$1,AD23,IF($A$1=$AF$1,AG23,IF($A$1=$AI$1,AJ23))))))))))))
A24: Yusen İnci Loj. | B24: =B13*0.4/B6 | C24: =C13*0.4/C6 | E24: =E13*0.4/E6 | F24: =F13*0.4/F6 | H24: =H13*0.4/H6 | I24: =I13*0.4/I6 | K24: =K13*0.4/K6 | L24: =L13*0.4/L6 | N24: =N13*0.4/N6 | O24: =O13*0.4/O6 | Q24: =Q13*0.4/Q6 | R24: =R13*0.4/R6 | T24: =T13*0.4/T6 | U24: =U13*0.4/U6 | W24: =W13*0.4/W6 | X24: =X13*0.4/X6 | Z24: =Z13*0.4/Z6 | AA24: =AA13*0.4/AA6 | AC24: =AC13*0.4/AC6 | AD24: =AD13*0.4/AD6 | AF24: =AF13*0.4/AF6 | AG24: =AG13*0.4/AG6 | AI24: =AI13*0.4/AI6 | AJ24: =AJ13*0.4/AJ6 | AL24: =AP24-AO24 | AO24: =IF($A$1=$B$1,B24,IF($A$1=$E$1,E24,IF($A$1=$H$1,H24,IF($A$1=$K$1,K24,IF($A$1=$N$1,N24,IF($A$1=$Q$1,Q24,IF($A$1=$T$1,T24,IF($A$1=$W$1,W24,IF($A$1=$Z$1,Z24,IF($A$1=$AC$1,AC24,IF($A$1=$AF$1,AF24,IF($A$1=$AI$1,AI24)))))))))))) | AP24: =IF($A$1=$B$1,C24,IF($A$1=$E$1,F24,IF($A$1=$H$1,I24,IF($A$1=$K$1,L24,IF($A$1=$N$1,O24,IF($A$1=$Q$1,R24,IF($A$1=$T$1,U24,IF($A$1=$W$1,X24,IF($A$1=$Z$1,AA24,IF($A$1=$AC$1,AD24,IF($A$1=$AF$1,AG24,IF($A$1=$AI$1,AJ24))))))))))))
A25: Jantaş | B25: =B14*0.4/B6 | C25: =C14*0.4/C6 | E25: =E14*0.4/E6 | F25: =F14*0.4/F6 | H25: =H14*0.4/H6 | I25: =I14*0.4/I6 | K25: =K14*0.4/K6 | L25: =L14*0.4/L6 | N25: =N14*0.4/N6 | O25: =O14*0.4/O6 | Q25: =Q14*0.4/Q6 | R25: =R14*0.4/R6 | T25: =T14*0.4/T6 | U25: =U14*0.4/U6 | W25: =W14*0.4/W6 | X25: =X14*0.4/X6 | Z25: =Z14*0.4/Z6 | AA25: =AA14*0.4/AA6 | AC25: =AC14*0.4/AC6 | AD25: =AD14*0.4/AD6 | AF25: =AF14*0.4/AF6 | AG25: =AG14*0.4/AG6 | AI25: =AI14*0.4/AI6 | AJ25: =AJ14*0.4/AJ6 | AL25: =AP25-AO25 | AO25: =IF($A$1=$B$1,B25,IF($A$1=$E$1,E25,IF($A$1=$H$1,H25,IF($A$1=$K$1,K25,IF($A$1=$N$1,N25,IF($A$1=$Q$1,Q25,IF($A$1=$T$1,T25,IF($A$1=$W$1,W25,IF($A$1=$Z$1,Z25,IF($A$1=$AC$1,AC25,IF($A$1=$AF$1,AF25,IF($A$1=$AI$1,AI25)))))))))))) | AP25: =IF($A$1=$B$1,C25,IF($A$1=$E$1,F25,IF($A$1=$H$1,I25,IF($A$1=$K$1,L25,IF($A$1=$N$1,O25,IF($A$1=$Q$1,R25,IF($A$1=$T$1,U25,IF($A$1=$W$1,X25,IF($A$1=$Z$1,AA25,IF($A$1=$AC$1,AD25,IF($A$1=$AF$1,AG25,IF($A$1=$AI$1,AJ25))))))))))))
A26: Çelik | B26: =B15*0.4/B6 | C26: =C15*0.4/C6 | E26: =E15*0.4/E6 | F26: =F15*0.4/F6 | H26: =H15*0.4/H6 | I26: =I15*0.4/I6 | K26: =K15*0.4/K6 | L26: =L15*0.4/L6 | N26: =N15*0.4/N6 | O26: =O15*0.4/O6 | Q26: =Q15*0.4/Q6 | R26: =R15*0.4/R6 | T26: =T15*0.4/T6 | U26: =U15*0.4/U6 | W26: =W15*0.4/W6 | X26: =X15*0.4/X6 | Z26: =Z15*0.4/Z6 | AA26: =AA15*0.4/AA6 | AC26: =AC15*0.4/AC6 | AD26: =AD15*0.4/AD6 | AF26: =AF15*0.4/AF6 | AG26: =AG15*0.4/AG6 | AI26: =AI15*0.4/AI6 | AJ26: =AJ15*0.4/AJ6 | AL26: =AP26-AO26 | AO26: =IF($A$1=$B$1,B26,IF($A$1=$E$1,E26,IF($A$1=$H$1,H26,IF($A$1=$K$1,K26,IF($A$1=$N$1,N26,IF($A$1=$Q$1,Q26,IF($A$1=$T$1,T26,IF($A$1=$W$1,W26,IF($A$1=$Z$1,Z26,IF($A$1=$AC$1,AC26,IF($A$1=$AF$1,AF26,IF($A$1=$AI$1,AI26)))))))))))) | AP26: =IF($A$1=$B$1,C26,IF($A$1=$E$1,F26,IF($A$1=$H$1,I26,IF($A$1=$K$1,L26,IF($A$1=$N$1,O26,IF($A$1=$Q$1,R26,IF($A$1=$T$1,U26,IF($A$1=$W$1,X26,IF($A$1=$Z$1,AA26,IF($A$1=$AC$1,AD26,IF($A$1=$AF$1,AG26,IF($A$1=$AI$1,AJ26))))))))))))
A27: Alüminyum | B27: =B16*0.4/B6 | C27: =C16*0.4/C6 | E27: =E16*0.4/E6 | F27: =F16*0.4/F6 | H27: =H16*0.4/H6 | I27: =I16*0.4/I6 | K27: =K16*0.4/K6 | L27: =L16*0.4/L6 | N27: =N16*0.4/N6 | O27: =O16*0.4/O6 | Q27: =Q16*0.4/Q6 | R27: =R16*0.4/R6 | T27: =T16*0.4/T6 | U27: =U16*0.4/U6 | W27: =W16*0.4/W6 | X27: =X16*0.4/X6 | Z27: =Z16*0.4/Z6 | AA27: =AA16*0.4/AA6 | AC27: =AC16*0.4/AC6 | AD27: =AD16*0.4/AD6 | AF27: =AF16*0.4/AF6 | AG27: =AG16*0.4/AG6 | AI27: =AI16*0.4/AI6 | AJ27: =AJ16*0.4/AJ6 | AL27: =AP27-AO27 | AO27: =IF($A$1=$B$1,B27,IF($A$1=$E$1,E27,IF($A$1=$H$1,H27,IF($A$1=$K$1,K27,IF($A$1=$N$1,N27,IF($A$1=$Q$1,Q27,IF($A$1=$T$1,T27,IF($A$1=$W$1,W27,IF($A$1=$Z$1,Z27,IF($A$1=$AC$1,AC27,IF($A$1=$AF$1,AF27,IF($A$1=$AI$1,AI27)))))))))))) | AP27: =IF($A$1=$B$1,C27,IF($A$1=$E$1,F27,IF($A$1=$H$1,I27,IF($A$1=$K$1,L27,IF($A$1=$N$1,O27,IF($A$1=$Q$1,R27,IF($A$1=$T$1,U27,IF($A$1=$W$1,X27,IF($A$1=$Z$1,AA27,IF($A$1=$AC$1,AD27,IF($A$1=$AF$1,AG27,IF($A$1=$AI$1,AJ27)))))))))))) | AV27: =135000000*0.0028/31.87
AL28: =AP28-AO28 | AO28: =IF($A$1=$B$1,B28,IF($A$1=$E$1,E28,IF($A$1=$H$1,H28,IF($A$1=$K$1,K28,IF($A$1=$N$1,N28,IF($A$1=$Q$1,Q28,IF($A$1=$T$1,T28,IF($A$1=$W$1,W28,IF($A$1=$Z$1,Z28,IF($A$1=$AC$1,AC28,IF($A$1=$AF$1,AF28,IF($A$1=$AI$1,AI28)))))))))))) | AP28: =IF($A$1=$B$1,C28,IF($A$1=$E$1,F28,IF($A$1=$H$1,I28,IF($A$1=$K$1,L28,IF($A$1=$N$1,O28,IF($A$1=$Q$1,R28,IF($A$1=$T$1,U28,IF($A$1=$W$1,X28,IF($A$1=$Z$1,AA28,IF($A$1=$AC$1,AD28,IF($A$1=$AF$1,AG28,IF($A$1=$AI$1,AJ28))))))))))))
AL29: =AP29-AO29 | AO29: =IF($A$1=$B$1,B29,IF($A$1=$E$1,E29,IF($A$1=$H$1,H29,IF($A$1=$K$1,K29,IF($A$1=$N$1,N29,IF($A$1=$Q$1,Q29,IF($A$1=$T$1,T29,IF($A$1=$W$1,W29,IF($A$1=$Z$1,Z29,IF($A$1=$AC$1,AC29,IF($A$1=$AF$1,AF29,IF($A$1=$AI$1,AI29)))))))))))) | AP29: =IF($A$1=$B$1,C29,IF($A$1=$E$1,F29,IF($A$1=$H$1,I29,IF($A$1=$K$1,L29,IF($A$1=$N$1,O29,IF($A$1=$Q$1,R29,IF($A$1=$T$1,U29,IF($A$1=$W$1,X29,IF($A$1=$Z$1,AA29,IF($A$1=$AC$1,AD29,IF($A$1=$AF$1,AG29,IF($A$1=$AI$1,AJ29))))))))))))
A30: Net Sales | B30: ='A -Döviz'!B30 | C30: ='A -Döviz'!C30 | D30: =+(C30/B30)-1 | E30: =B30+'A -Döviz'!E30 | F30: =C30+'A -Döviz'!F30 | H30: =E30+'A -Döviz'!H30 | I30: =F30+'A -Döviz'!I30 | K30: =H30+'A -Döviz'!K30 | L30: =I30+'A -Döviz'!L30 | N30: =K30+'A -Döviz'!N30 | O30: =L30+'A -Döviz'!O30 | Q30: =N30+'A -Döviz'!Q30 | R30: =O30+'A -Döviz'!R30 | T30: =Q30+'A -Döviz'!T30 | U30: =R30+'A -Döviz'!U30 | W30: =T30+'A -Döviz'!W30 | X30: =U30+'A -Döviz'!X30 | Z30: =W30+'A -Döviz'!Z30 | AA30: =X30+'A -Döviz'!AA30 | AC30: =Z30+'A -Döviz'!AC30 | AD30: =AA30+'A -Döviz'!AD30 | AF30: =AC30+'A -Döviz'!AF30 | AG30: =AD30+'A -Döviz'!AG30 | AI30: =AF30+'A -Döviz'!AI30 | AJ30: =AG30+'A -Döviz'!AJ30 | AL30: =AP30-AO30 | AM30: =AP30/AO30-1 | AO30: =IF($A$1=$B$1,B30,IF($A$1=$E$1,E30,IF($A$1=$H$1,H30,IF($A$1=$K$1,K30,IF($A$1=$N$1,N30,IF($A$1=$Q$1,Q30,IF($A$1=$T$1,T30,IF($A$1=$W$1,W30,IF($A$1=$Z$1,Z30,IF($A$1=$AC$1,AC30,IF($A$1=$AF$1,AF30,IF($A$1=$AI$1,AI30)))))))))))) | AP30: =IF($A$1=$B$1,C30,IF($A$1=$E$1,F30,IF($A$1=$H$1,I30,IF($A$1=$K$1,L30,IF($A$1=$N$1,O30,IF($A$1=$Q$1,R30,IF($A$1=$T$1,U30,IF($A$1=$W$1,X30,IF($A$1=$Z$1,AA30,IF($A$1=$AC$1,AD30,IF($A$1=$AF$1,AG30,IF($A$1=$AI$1,AJ30))))))))))))
A31: Cost of Sales | B31: ='A -Döviz'!B31 | C31: ='A -Döviz'!C31 | D31: =+(C31/B31)-1 | E31: =B31+'A -Döviz'!E31 | F31: =C31+'A -Döviz'!F31 | H31: =E31+'A -Döviz'!H31 | I31: =F31+'A -Döviz'!I31 | K31: =H31+'A -Döviz'!K31 | L31: =I31+'A -Döviz'!L31 | N31: =K31+'A -Döviz'!N31 | O31: =L31+'A -Döviz'!O31 | Q31: =N31+'A -Döviz'!Q31 | R31: =O31+'A -Döviz'!R31 | T31: =Q31+'A -Döviz'!T31 | U31: =R31+'A -Döviz'!U31 | W31: =T31+'A -Döviz'!W31 | X31: =U31+'A -Döviz'!X31 | Z31: =W31+'A -Döviz'!Z31 | AA31: =X31+'A -Döviz'!AA31 | AC31: =Z31+'A -Döviz'!AC31 | AD31: =AA31+'A -Döviz'!AD31 | AF31: =AC31+'A -Döviz'!AF31 | AG31: =AD31+'A -Döviz'!AG31 | AI31: =AF31+'A -Döviz'!AI31 | AJ31: =AG31+'A -Döviz'!AJ31 | AL31: =AP31-AO31 | AM31: =AP31/AO31-1 | AO31: =IF($A$1=$B$1,B31,IF($A$1=$E$1,E31,IF($A$1=$H$1,H31,IF($A$1=$K$1,K31,IF($A$1=$N$1,N31,IF($A$1=$Q$1,Q31,IF($A$1=$T$1,T31,IF($A$1=$W$1,W31,IF($A$1=$Z$1,Z31,IF($A$1=$AC$1,AC31,IF($A$1=$AF$1,AF31,IF($A$1=$AI$1,AI31)))))))))))) | AP31: =IF($A$1=$B$1,C31,IF($A$1=$E$1,F31,IF($A$1=$H$1,I31,IF($A$1=$K$1,L31,IF($A$1=$N$1,O31,IF($A$1=$Q$1,R31,IF($A$1=$T$1,U31,IF($A$1=$W$1,X31,IF($A$1=$Z$1,AA31,IF($A$1=$AC$1,AD31,IF($A$1=$AF$1,AG31,IF($A$1=$AI$1,AJ31))))))))))))
A32: Gross Profit | B32: ='A -Döviz'!B32 | C32: ='A -Döviz'!C32 | D32: =+(C32/B32)-1 | E32: =B32+'A -Döviz'!E32 | F32: =C32+'A -Döviz'!F32 | H32: =E32+'A -Döviz'!H32 | I32: =F32+'A -Döviz'!I32 | K32: =H32+'A -Döviz'!K32 | L32: =I32+'A -Döviz'!L32 | N32: =K32+'A -Döviz'!N32 | O32: =L32+'A -Döviz'!O32 | Q32: =N32+'A -Döviz'!Q32 | R32: =O32+'A -Döviz'!R32 | T32: =Q32+'A -Döviz'!T32 | U32: =R32+'A -Döviz'!U32 | W32: =T32+'A -Döviz'!W32 | X32: =U32+'A -Döviz'!X32 | Z32: =W32+'A -Döviz'!Z32 | AA32: =X32+'A -Döviz'!AA32 | AC32: =Z32+'A -Döviz'!AC32 | AD32: =AA32+'A -Döviz'!AD32 | AF32: =AC32+'A -Döviz'!AF32 | AG32: =AD32+'A -Döviz'!AG32 | AI32: =AF32+'A -Döviz'!AI32 | AJ32: =AG32+'A -Döviz'!AJ32 | AL32: =AP32-AO32 | AM32: =AP32/AO32-1 | AO32: =IF($A$1=$B$1,B32,IF($A$1=$E$1,E32,IF($A$1=$H$1,H32,IF($A$1=$K$1,K32,IF($A$1=$N$1,N32,IF($A$1=$Q$1,Q32,IF($A$1=$T$1,T32,IF($A$1=$W$1,W32,IF($A$1=$Z$1,Z32,IF($A$1=$AC$1,AC32,IF($A$1=$AF$1,AF32,IF($A$1=$AI$1,AI32)))))))))))) | AP32: =IF($A$1=$B$1,C32,IF($A$1=$E$1,F32,IF($A$1=$H$1,I32,IF($A$1=$K$1,L32,IF($A$1=$N$1,O32,IF($A$1=$Q$1,R32,IF($A$1=$T$1,U32,IF($A$1=$W$1,X32,IF($A$1=$Z$1,AA32,IF($A$1=$AC$1,AD32,IF($A$1=$AF$1,AG32,IF($A$1=$AI$1,AJ32))))))))))))
A33: Gross Profit Margin | B33: =B32/B30 | C33: =C32/C30 | E33: =E32/E30 | F33: =F32/F30 | H33: =H32/H30 | I33: =I32/I30 | K33: =K32/K30 | L33: =L32/L30 | N33: =N32/N30 | O33: =O32/O30 | Q33: =Q32/Q30 | R33: =R32/R30 | T33: =T32/T30 | U33: =U32/U30 | W33: =W32/W30 | X33: =X32/X30 | Z33: =Z32/Z30 | AA33: =AA32/AA30 | AC33: =AC32/AC30 | AD33: =AD32/AD30 | AF33: =AF32/AF30 | AG33: =AG32/AG30 | AI33: =AI32/AI30 | AJ33: =AJ32/AJ30 | AM33: =AP33-AO33 | AO33: =IF($A$1=$B$1,B33,IF($A$1=$E$1,E33,IF($A$1=$H$1,H33,IF($A$1=$K$1,K33,IF($A$1=$N$1,N33,IF($A$1=$Q$1,Q33,IF($A$1=$T$1,T33,IF($A$1=$W$1,W33,IF($A$1=$Z$1,Z33,IF($A$1=$AC$1,AC33,IF($A$1=$AF$1,AF33,IF($A$1=$AI$1,AI33)))))))))))) | AP33: =IF($A$1=$B$1,C33,IF($A$1=$E$1,F33,IF($A$1=$H$1,I33,IF($A$1=$K$1,L33,IF($A$1=$N$1,O33,IF($A$1=$Q$1,R33,IF($A$1=$T$1,U33,IF($A$1=$W$1,X33,IF($A$1=$Z$1,AA33,IF($A$1=$AC$1,AD33,IF($A$1=$AF$1,AG33,IF($A$1=$AI$1,AJ33))))))))))))
F34: =F32/E32-1
A35: GROSS PROFIT BY CHANNELS (100%) | AR35: =SUM(AR36:AR43) | AS35: =SUM(AS36:AS43)
A36: İnci Holding | B36: ='A -Döviz'!B36 | C36: ='A -Döviz'!C36 | D36: =+(C36/B36)-1 | E36: =B36+'A -Döviz'!E36 | F36: =C36+'A -Döviz'!F36 | H36: =E36+'A -Döviz'!H36 | I36: =F36+'A -Döviz'!I36 | K36: =H36+'A -Döviz'!K36 | L36: =I36+'A -Döviz'!L36 | N36: =K36+'A -Döviz'!N36 | O36: =L36+'A -Döviz'!O36 | Q36: =N36+'A -Döviz'!Q36 | R36: =O36+'A -Döviz'!R36 | T36: =Q36+'A -Döviz'!T36 | U36: =R36+'A -Döviz'!U36 | W36: =T36+'A -Döviz'!W36 | X36: =U36+'A -Döviz'!X36 | Z36: =W36+'A -Döviz'!Z36 | AA36: =X36+'A -Döviz'!AA36 | AB36: =Z36/AA36-1 | AC36: =Z36+'A -Döviz'!AC36 | AD36: =AA36+'A -Döviz'!AD36 | AF36: =AC36+'A -Döviz'!AF36 | AG36: =AD36+'A -Döviz'!AG36 | AI36: =AF36+'A -Döviz'!AI36 | AJ36: =AG36+'A -Döviz'!AJ36 | AL36: =AP36-AO36 | AM36: =AP36/AO36-1 | AO36: =IF($A$1=$B$1,B36,IF($A$1=$E$1,E36,IF($A$1=$H$1,H36,IF($A$1=$K$1,K36,IF($A$1=$N$1,N36,IF($A$1=$Q$1,Q36,IF($A$1=$T$1,T36,IF($A$1=$W$1,W36,IF($A$1=$Z$1,Z36,IF($A$1=$AC$1,AC36,IF($A$1=$AF$1,AF36,IF($A$1=$AI$1,AI36)))))))))))) | AP36: =IF($A$1=$B$1,C36,IF($A$1=$E$1,F36,IF($A$1=$H$1,I36,IF($A$1=$K$1,L36,IF($A$1=$N$1,O36,IF($A$1=$Q$1,R36,IF($A$1=$T$1,U36,IF($A$1=$W$1,X36,IF($A$1=$Z$1,AA36,IF($A$1=$AC$1,AD36,IF($A$1=$AF$1,AG36,IF($A$1=$AI$1,AJ36)))))))))))) | AR36: =W36 | AS36: =X36 | AT36: =AS36-AR36 | AV36: =F36/SUM($F$36:$F$43)
A37: ISM | B37: ='A -Döviz'!B37 | C37: ='A -Döviz'!C37 | D37: =+(C37/B37)-1 | E37: =B37+'A -Döviz'!E37 | F37: =C37+'A -Döviz'!F37 | H37: =E37+'A -Döviz'!H37 | I37: =F37+'A -Döviz'!I37 | K37: =H37+'A -Döviz'!K37 | L37: =I37+'A -Döviz'!L37 | N37: =K37+'A -Döviz'!N37 | O37: =L37+'A -Döviz'!O37 | Q37: =N37+'A -Döviz'!Q37 | R37: =O37+'A -Döviz'!R37 | T37: =Q37+'A -Döviz'!T37 | U37: =R37+'A -Döviz'!U37 | W37: =T37+'A -Döviz'!W37 | X37: =U37+'A -Döviz'!X37 | Z37: =W37+'A -Döviz'!Z37 | AA37: =X37+'A -Döviz'!AA37 | AB37: =Z37/AA37-1 | AC37: =Z37+'A -Döviz'!AC37 | AD37: =AA37+'A -Döviz'!AD37 | AF37: =AC37+'A -Döviz'!AF37 | AG37: =AD37+'A -Döviz'!AG37 | AI37: =AF37+'A -Döviz'!AI37 | AJ37: =AG37+'A -Döviz'!AJ37 | AL37: =AP37-AO37 | AM37: =AP37/AO37-1 | AO37: =IF($A$1=$B$1,B37,IF($A$1=$E$1,E37,IF($A$1=$H$1,H37,IF($A$1=$K$1,K37,IF($A$1=$N$1,N37,IF($A$1=$Q$1,Q37,IF($A$1=$T$1,T37,IF($A$1=$W$1,W37,IF($A$1=$Z$1,Z37,IF($A$1=$AC$1,AC37,IF($A$1=$AF$1,AF37,IF($A$1=$AI$1,AI37)))))))))))) | AP37: =IF($A$1=$B$1,C37,IF($A$1=$E$1,F37,IF($A$1=$H$1,I37,IF($A$1=$K$1,L37,IF($A$1=$N$1,O37,IF($A$1=$Q$1,R37,IF($A$1=$T$1,U37,IF($A$1=$W$1,X37,IF($A$1=$Z$1,AA37,IF($A$1=$AC$1,AD37,IF($A$1=$AF$1,AG37,IF($A$1=$AI$1,AJ37)))))))))))) | AR37: =W37 | AS37: =X37 | AT37: =AS37-AR37 | AV37: =F37/SUM($F$36:$F$43)
A38: İncitaş | B38: ='A -Döviz'!B38 | C38: ='A -Döviz'!C38 | D38: =+(C38/B38)-1 | E38: =B38+'A -Döviz'!E38 | F38: =C38+'A -Döviz'!F38 | H38: =E38+'A -Döviz'!H38 | I38: =F38+'A -Döviz'!I38 | K38: =H38+'A -Döviz'!K38 | L38: =I38+'A -Döviz'!L38 | N38: =K38+'A -Döviz'!N38 | O38: =L38+'A -Döviz'!O38 | Q38: =N38+'A -Döviz'!Q38 | R38: =O38+'A -Döviz'!R38 | T38: =Q38+'A -Döviz'!T38 | U38: =R38+'A -Döviz'!U38 | W38: =T38+'A -Döviz'!W38 | X38: =U38+'A -Döviz'!X38 | Z38: =W38+'A -Döviz'!Z38 | AA38: =X38+'A -Döviz'!AA38 | AB38: =Z38/AA38-1 | AC38: =Z38+'A -Döviz'!AC38 | AD38: =AA38+'A -Döviz'!AD38 | AF38: =AC38+'A -Döviz'!AF38 | AG38: =AD38+'A -Döviz'!AG38 | AI38: =AF38+'A -Döviz'!AI38 | AJ38: =AG38+'A -Döviz'!AJ38 | AL38: =AP38-AO38 | AM38: =AP38/AO38-1 | AO38: =IF($A$1=$B$1,B38,IF($A$1=$E$1,E38,IF($A$1=$H$1,H38,IF($A$1=$K$1,K38,IF($A$1=$N$1,N38,IF($A$1=$Q$1,Q38,IF($A$1=$T$1,T38,IF($A$1=$W$1,W38,IF($A$1=$Z$1,Z38,IF($A$1=$AC$1,AC38,IF($A$1=$AF$1,AF38,IF($A$1=$AI$1,AI38)))))))))))) | AP38: =IF($A$1=$B$1,C38,IF($A$1=$E$1,F38,IF($A$1=$H$1,I38,IF($A$1=$K$1,L38,IF($A$1=$N$1,O38,IF($A$1=$Q$1,R38,IF($A$1=$T$1,U38,IF($A$1=$W$1,X38,IF($A$1=$Z$1,AA38,IF($A$1=$AC$1,AD38,IF($A$1=$AF$1,AG38,IF($A$1=$AI$1,AJ38)))))))))))) | AR38: =W38 | AS38: =X38 | AT38: =AS38-AR38 | AV38: =F38/SUM($F$36:$F$43)
A39: İnci GS Yuasa | B39: ='A -Döviz'!B39 | C39: ='A -Döviz'!C39 | D39: =+(C39/B39)-1 | E39: =B39+'A -Döviz'!E39 | F39: =C39+'A -Döviz'!F39 | H39: =E39+'A -Döviz'!H39 | I39: =F39+'A -Döviz'!I39 | K39: =H39+'A -Döviz'!K39 | L39: =I39+'A -Döviz'!L39 | N39: =K39+'A -Döviz'!N39 | O39: =L39+'A -Döviz'!O39 | Q39: =N39+'A -Döviz'!Q39 | R39: =O39+'A -Döviz'!R39 | T39: =Q39+'A -Döviz'!T39 | U39: =R39+'A -Döviz'!U39 | W39: =T39+'A -Döviz'!W39 | X39: =U39+'A -Döviz'!X39 | Z39: =W39+'A -Döviz'!Z39 | AA39: =X39+'A -Döviz'!AA39 | AB39: =Z39/AA39-1 | AC39: =Z39+'A -Döviz'!AC39 | AD39: =AA39+'A -Döviz'!AD39 | AF39: =AC39+'A -Döviz'!AF39 | AG39: =AD39+'A -Döviz'!AG39 | AI39: =AF39+'A -Döviz'!AI39 | AJ39: =AG39+'A -Döviz'!AJ39 | AL39: =AP39-AO39 | AM39: =AP39/AO39-1 | AO39: =IF($A$1=$B$1,B39,IF($A$1=$E$1,E39,IF($A$1=$H$1,H39,IF($A$1=$K$1,K39,IF($A$1=$N$1,N39,IF($A$1=$Q$1,Q39,IF($A$1=$T$1,T39,IF($A$1=$W$1,W39,IF($A$1=$Z$1,Z39,IF($A$1=$AC$1,AC39,IF($A$1=$AF$1,AF39,IF($A$1=$AI$1,AI39)))))))))))) | AP39: =IF($A$1=$B$1,C39,IF($A$1=$E$1,F39,IF($A$1=$H$1,I39,IF($A$1=$K$1,L39,IF($A$1=$N$1,O39,IF($A$1=$Q$1,R39,IF($A$1=$T$1,U39,IF($A$1=$W$1,X39,IF($A$1=$Z$1,AA39,IF($A$1=$AC$1,AD39,IF($A$1=$AF$1,AG39,IF($A$1=$AI$1,AJ39)))))))))))) | AR39: =W39*0.4 | AS39: =X39*0.4 | AT39: =AS39-AR39 | AV39: =F39/SUM($F$36:$F$43)
A40: Yusen İnci Loj. | B40: ='A -Döviz'!B40 | C40: ='A -Döviz'!C40 | D40: =+(C40/B40)-1 | E40: =B40+'A -Döviz'!E40 | F40: =C40+'A -Döviz'!F40 | H40: =E40+'A -Döviz'!H40 | I40: =F40+'A -Döviz'!I40 | K40: =H40+'A -Döviz'!K40 | L40: =I40+'A -Döviz'!L40 | N40: =K40+'A -Döviz'!N40 | O40: =L40+'A -Döviz'!O40 | Q40: =N40+'A -Döviz'!Q40 | R40: =O40+'A -Döviz'!R40 | T40: =Q40+'A -Döviz'!T40 | U40: =R40+'A -Döviz'!U40 | W40: =T40+'A -Döviz'!W40 | X40: =U40+'A -Döviz'!X40 | Z40: =W40+'A -Döviz'!Z40 | AA40: =X40+'A -Döviz'!AA40 | AB40: =Z40/AA40-1 | AC40: =Z40+'A -Döviz'!AC40 | AD40: =AA40+'A -Döviz'!AD40 | AF40: =AC40+'A -Döviz'!AF40 | AG40: =AD40+'A -Döviz'!AG40 | AI40: =AF40+'A -Döviz'!AI40 | AJ40: =AG40+'A -Döviz'!AJ40 | AL40: =AP40-AO40 | AM40: =AP40/AO40-1 | AO40: =IF($A$1=$B$1,B40,IF($A$1=$E$1,E40,IF($A$1=$H$1,H40,IF($A$1=$K$1,K40,IF($A$1=$N$1,N40,IF($A$1=$Q$1,Q40,IF($A$1=$T$1,T40,IF($A$1=$W$1,W40,IF($A$1=$Z$1,Z40,IF($A$1=$AC$1,AC40,IF($A$1=$AF$1,AF40,IF($A$1=$AI$1,AI40)))))))))))) | AP40: =IF($A$1=$B$1,C40,IF($A$1=$E$1,F40,IF($A$1=$H$1,I40,IF($A$1=$K$1,L40,IF($A$1=$N$1,O40,IF($A$1=$Q$1,R40,IF($A$1=$T$1,U40,IF($A$1=$W$1,X40,IF($A$1=$Z$1,AA40,IF($A$1=$AC$1,AD40,IF($A$1=$AF$1,AG40,IF($A$1=$AI$1,AJ40)))))))))))) | AR40: =W40*0.4 | AS40: =X40*0.4 | AT40: =AS40-AR40 | AV40: =F40/SUM($F$36:$F$43)
A41: Jantaş | B41: ='A -Döviz'!B41 | C41: ='A -Döviz'!C41 | D41: =+(C41/B41)-1 | E41: =B41+'A -Döviz'!E41 | F41: =C41+'A -Döviz'!F41 | H41: =E41+'A -Döviz'!H41 | I41: =F41+'A -Döviz'!I41 | K41: =H41+'A -Döviz'!K41 | L41: =I41+'A -Döviz'!L41 | N41: =K41+'A -Döviz'!N41 | O41: =L41+'A -Döviz'!O41 | Q41: =N41+'A -Döviz'!Q41 | R41: =O41+'A -Döviz'!R41 | T41: =Q41+'A -Döviz'!T41 | U41: =R41+'A -Döviz'!U41 | W41: =T41+'A -Döviz'!W41 | X41: =U41+'A -Döviz'!X41 | Z41: =W41+'A -Döviz'!Z41 | AA41: =X41+'A -Döviz'!AA41 | AB41: =Z41/AA41-1 | AC41: =Z41+'A -Döviz'!AC41 | AD41: =AA41+'A -Döviz'!AD41 | AF41: =AC41+'A -Döviz'!AF41 | AG41: =AD41+'A -Döviz'!AG41 | AI41: =AF41+'A -Döviz'!AI41 | AJ41: =AG41+'A -Döviz'!AJ41 | AL41: =AP41-AO41 | AM41: =AP41/AO41-1 | AO41: =IF($A$1=$B$1,B41,IF($A$1=$E$1,E41,IF($A$1=$H$1,H41,IF($A$1=$K$1,K41,IF($A$1=$N$1,N41,IF($A$1=$Q$1,Q41,IF($A$1=$T$1,T41,IF($A$1=$W$1,W41,IF($A$1=$Z$1,Z41,IF($A$1=$AC$1,AC41,IF($A$1=$AF$1,AF41,IF($A$1=$AI$1,AI41)))))))))))) | AP41: =IF($A$1=$B$1,C41,IF($A$1=$E$1,F41,IF($A$1=$H$1,I41,IF($A$1=$K$1,L41,IF($A$1=$N$1,O41,IF($A$1=$Q$1,R41,IF($A$1=$T$1,U41,IF($A$1=$W$1,X41,IF($A$1=$Z$1,AA41,IF($A$1=$AC$1,AD41,IF($A$1=$AF$1,AG41,IF($A$1=$AI$1,AJ41)))))))))))) | AR41: =W41*0.4 | AS41: =X41*0.4 | AT41: =AS41-AR41 | AV41: =F41/SUM($F$36:$F$43)
A42: Çelik | B42: ='A -Döviz'!B42 | C42: ='A -Döviz'!C42 | D42: =+(C42/B42)-1 | E42: =B42+'A -Döviz'!E42 | F42: =C42+'A -Döviz'!F42 | H42: =E42+'A -Döviz'!H42 | I42: =F42+'A -Döviz'!I42 | K42: =H42+'A -Döviz'!K42 | L42: =I42+'A -Döviz'!L42 | N42: =K42+'A -Döviz'!N42 | O42: =L42+'A -Döviz'!O42 | Q42: =N42+'A -Döviz'!Q42 | R42: =O42+'A -Döviz'!R42 | T42: =Q42+'A -Döviz'!T42 | U42: =R42+'A -Döviz'!U42 | W42: =T42+'A -Döviz'!W42 | X42: =U42+'A -Döviz'!X42 | Z42: =W42+'A -Döviz'!Z42 | AA42: =X42+'A -Döviz'!AA42 | AB42: =Z42/AA42-1 | AC42: =Z42+'A -Döviz'!AC42 | AD42: =AA42+'A -Döviz'!AD42 | AF42: =AC42+'A -Döviz'!AF42 | AG42: =AD42+'A -Döviz'!AG42 | AI42: =AF42+'A -Döviz'!AI42 | AJ42: =AG42+'A -Döviz'!AJ42 | AL42: =AP42-AO42 | AM42: =AP42/AO42-1 | AO42: =IF($A$1=$B$1,B42,IF($A$1=$E$1,E42,IF($A$1=$H$1,H42,IF($A$1=$K$1,K42,IF($A$1=$N$1,N42,IF($A$1=$Q$1,Q42,IF($A$1=$T$1,T42,IF($A$1=$W$1,W42,IF($A$1=$Z$1,Z42,IF($A$1=$AC$1,AC42,IF($A$1=$AF$1,AF42,IF($A$1=$AI$1,AI42)))))))))))) | AP42: =IF($A$1=$B$1,C42,IF($A$1=$E$1,F42,IF($A$1=$H$1,I42,IF($A$1=$K$1,L42,IF($A$1=$N$1,O42,IF($A$1=$Q$1,R42,IF($A$1=$T$1,U42,IF($A$1=$W$1,X42,IF($A$1=$Z$1,AA42,IF($A$1=$AC$1,AD42,IF($A$1=$AF$1,AG42,IF($A$1=$AI$1,AJ42)))))))))))) | AR42: =W42*0.4 | AS42: =X42*0.4 | AT42: =AS42-AR42 | AV42: =F42/SUM($F$36:$F$43)
A43: Alüminyum | B43: ='A -Döviz'!B43 | C43: ='A -Döviz'!C43 | D43: =+(C43/B43)-1 | E43: =B43+'A -Döviz'!E43 | F43: =C43+'A -Döviz'!F43 | H43: =E43+'A -Döviz'!H43 | I43: =F43+'A -Döviz'!I43 | K43: =H43+'A -Döviz'!K43 | L43: =I43+'A -Döviz'!L43 | N43: =K43+'A -Döviz'!N43 | O43: =L43+'A -Döviz'!O43 | Q43: =N43+'A -Döviz'!Q43 | R43: =O43+'A -Döviz'!R43 | T43: =Q43+'A -Döviz'!T43 | U43: =R43+'A -Döviz'!U43 | W43: =T43+'A -Döviz'!W43 | X43: =U43+'A -Döviz'!X43 | Z43: =W43+'A -Döviz'!Z43 | AA43: =X43+'A -Döviz'!AA43 | AB43: =Z43/AA43-1 | AC43: =Z43+'A -Döviz'!AC43 | AD43: =AA43+'A -Döviz'!AD43 | AF43: =AC43+'A -Döviz'!AF43 | AG43: =AD43+'A -Döviz'!AG43 | AI43: =AF43+'A -Döviz'!AI43 | AJ43: =AG43+'A -Döviz'!AJ43 | AL43: =AP43-AO43 | AM43: =AP43/AO43-1 | AO43: =IF($A$1=$B$1,B43,IF($A$1=$E$1,E43,IF($A$1=$H$1,H43,IF($A$1=$K$1,K43,IF($A$1=$N$1,N43,IF($A$1=$Q$1,Q43,IF($A$1=$T$1,T43,IF($A$1=$W$1,W43,IF($A$1=$Z$1,Z43,IF($A$1=$AC$1,AC43,IF($A$1=$AF$1,AF43,IF($A$1=$AI$1,AI43)))))))))))) | AP43: =IF($A$1=$B$1,C43,IF($A$1=$E$1,F43,IF($A$1=$H$1,I43,IF($A$1=$K$1,L43,IF($A$1=$N$1,O43,IF($A$1=$Q$1,R43,IF($A$1=$T$1,U43,IF($A$1=$W$1,X43,IF($A$1=$Z$1,AA43,IF($A$1=$AC$1,AD43,IF($A$1=$AF$1,AG43,IF($A$1=$AI$1,AJ43)))))))))))) | AR43: =W43*0.4 | AS43: =X43*0.4 | AT43: =AS43-AR43 | AV43: =F43/SUM($F$36:$F$43)
AO44: =IF($A$1=$B$1,B44,IF($A$1=$E$1,E44,IF($A$1=$H$1,H44,IF($A$1=$K$1,K44,IF($A$1=$N$1,N44,IF($A$1=$Q$1,Q44,IF($A$1=$T$1,T44,IF($A$1=$W$1,W44,IF($A$1=$Z$1,Z44,IF($A$1=$AC$1,AC44,IF($A$1=$AF$1,AF44,IF($A$1=$AI$1,AI44)))))))))))) | AP44: =IF($A$1=$B$1,C44,IF($A$1=$E$1,F44,IF($A$1=$H$1,I44,IF($A$1=$K$1,L44,IF($A$1=$N$1,O44,IF($A$1=$Q$1,R44,IF($A$1=$T$1,U44,IF($A$1=$W$1,X44,IF($A$1=$Z$1,AA44,IF($A$1=$AC$1,AD44,IF($A$1=$AF$1,AG44,IF($A$1=$AI$1,AJ44))))))))))))
AL45: =AP45-AO45 | AM45: =AP45/AO45-1 | AO45: =IF($A$1=$B$1,B45,IF($A$1=$E$1,E45,IF($A$1=$H$1,H45,IF($A$1=$K$1,K45,IF($A$1=$N$1,N45,IF($A$1=$Q$1,Q45,IF($A$1=$T$1,T45,IF($A$1=$W$1,W45,IF($A$1=$Z$1,Z45,IF($A$1=$AC$1,AC45,IF($A$1=$AF$1,AF45,IF($A$1=$AI$1,AI45)))))))))))) | AP45: =IF($A$1=$B$1,C45,IF($A$1=$E$1,F45,IF($A$1=$H$1,I45,IF($A$1=$K$1,L45,IF($A$1=$N$1,O45,IF($A$1=$Q$1,R45,IF($A$1=$T$1,U45,IF($A$1=$W$1,X45,IF($A$1=$Z$1,AA45,IF($A$1=$AC$1,AD45,IF($A$1=$AF$1,AG45,IF($A$1=$AI$1,AJ45))))))))))))
AL46: =AP46-AO46 | AM46: =AP46/AO46-1 | AO46: =IF($A$1=$B$1,B46,IF($A$1=$E$1,E46,IF($A$1=$H$1,H46,IF($A$1=$K$1,K46,IF($A$1=$N$1,N46,IF($A$1=$Q$1,Q46,IF($A$1=$T$1,T46,IF($A$1=$W$1,W46,IF($A$1=$Z$1,Z46,IF($A$1=$AC$1,AC46,IF($A$1=$AF$1,AF46,IF($A$1=$AI$1,AI46)))))))))))) | AP46: =IF($A$1=$B$1,C46,IF($A$1=$E$1,F46,IF($A$1=$H$1,I46,IF($A$1=$K$1,L46,IF($A$1=$N$1,O46,IF($A$1=$Q$1,R46,IF($A$1=$T$1,U46,IF($A$1=$W$1,X46,IF($A$1=$Z$1,AA46,IF($A$1=$AC$1,AD46,IF($A$1=$AF$1,AG46,IF($A$1=$AI$1,AJ46))))))))))))
AL47: =AP47-AO47 | AM47: =AP47/AO47-1 | AO47: =IF($A$1=$B$1,B47,IF($A$1=$E$1,E47,IF($A$1=$H$1,H47,IF($A$1=$K$1,K47,IF($A$1=$N$1,N47,IF($A$1=$Q$1,Q47,IF($A$1=$T$1,T47,IF($A$1=$W$1,W47,IF($A$1=$Z$1,Z47,IF($A$1=$AC$1,AC47,IF($A$1=$AF$1,AF47,IF($A$1=$AI$1,AI47)))))))))))) | AP47: =IF($A$1=$B$1,C47,IF($A$1=$E$1,F47,IF($A$1=$H$1,I47,IF($A$1=$K$1,L47,IF($A$1=$N$1,O47,IF($A$1=$Q$1,R47,IF($A$1=$T$1,U47,IF($A$1=$W$1,X47,IF($A$1=$Z$1,AA47,IF($A$1=$AC$1,AD47,IF($A$1=$AF$1,AG47,IF($A$1=$AI$1,AJ47))))))))))))
AL48: =AP48-AO48 | AM48: =AP48/AO48-1 | AO48: =IF($A$1=$B$1,B48,IF($A$1=$E$1,E48,IF($A$1=$H$1,H48,IF($A$1=$K$1,K48,IF($A$1=$N$1,N48,IF($A$1=$Q$1,Q48,IF($A$1=$T$1,T48,IF($A$1=$W$1,W48,IF($A$1=$Z$1,Z48,IF($A$1=$AC$1,AC48,IF($A$1=$AF$1,AF48,IF($A$1=$AI$1,AI48)))))))))))) | AP48: =IF($A$1=$B$1,C48,IF($A$1=$E$1,F48,IF($A$1=$H$1,I48,IF($A$1=$K$1,L48,IF($A$1=$N$1,O48,IF($A$1=$Q$1,R48,IF($A$1=$T$1,U48,IF($A$1=$W$1,X48,IF($A$1=$Z$1,AA48,IF($A$1=$AC$1,AD48,IF($A$1=$AF$1,AG48,IF($A$1=$AI$1,AJ48))))))))))))
AO49: =IF($A$1=$B$1,B49,IF($A$1=$E$1,E49,IF($A$1=$H$1,H49,IF($A$1=$K$1,K49,IF($A$1=$N$1,N49,IF($A$1=$Q$1,Q49,IF($A$1=$T$1,T49,IF($A$1=$W$1,W49,IF($A$1=$Z$1,Z49,IF($A$1=$AC$1,AC49,IF($A$1=$AF$1,AF49,IF($A$1=$AI$1,AI49)))))))))))) | AP49: =IF($A$1=$B$1,C49,IF($A$1=$E$1,F49,IF($A$1=$H$1,I49,IF($A$1=$K$1,L49,IF($A$1=$N$1,O49,IF($A$1=$Q$1,R49,IF($A$1=$T$1,U49,IF($A$1=$W$1,X49,IF($A$1=$Z$1,AA49,IF($A$1=$AC$1,AD49,IF($A$1=$AF$1,AG49,IF($A$1=$AI$1,AJ49))))))))))))
AL50: =AP50-AO50 | AM50: =AP50/AO50-1 | AO50: =IF($A$1=$B$1,B50,IF($A$1=$E$1,E50,IF($A$1=$H$1,H50,IF($A$1=$K$1,K50,IF($A$1=$N$1,N50,IF($A$1=$Q$1,Q50,IF($A$1=$T$1,T50,IF($A$1=$W$1,W50,IF($A$1=$Z$1,Z50,IF($A$1=$AC$1,AC50,IF($A$1=$AF$1,AF50,IF($A$1=$AI$1,AI50)))))))))))) | AP50: =IF($A$1=$B$1,C50,IF($A$1=$E$1,F50,IF($A$1=$H$1,I50,IF($A$1=$K$1,L50,IF($A$1=$N$1,O50,IF($A$1=$Q$1,R50,IF($A$1=$T$1,U50,IF($A$1=$W$1,X50,IF($A$1=$Z$1,AA50,IF($A$1=$AC$1,AD50,IF($A$1=$AF$1,AG50,IF($A$1=$AI$1,AJ50))))))))))))
AL51: =AP51-AO51 | AM51: =AP51/AO51-1 | AO51: =IF($A$1=$B$1,B51,IF($A$1=$E$1,E51,IF($A$1=$H$1,H51,IF($A$1=$K$1,K51,IF($A$1=$N$1,N51,IF($A$1=$Q$1,Q51,IF($A$1=$T$1,T51,IF($A$1=$W$1,W51,IF($A$1=$Z$1,Z51,IF($A$1=$AC$1,AC51,IF($A$1=$AF$1,AF51,IF($A$1=$AI$1,AI51)))))))))))) | AP51: =IF($A$1=$B$1,C51,IF($A$1=$E$1,F51,IF($A$1=$H$1,I51,IF($A$1=$K$1,L51,IF($A$1=$N$1,O51,IF($A$1=$Q$1,R51,IF($A$1=$T$1,U51,IF($A$1=$W$1,X51,IF($A$1=$Z$1,AA51,IF($A$1=$AC$1,AD51,IF($A$1=$AF$1,AG51,IF($A$1=$AI$1,AJ51))))))))))))
AL52: =AP52-AO52 | AM52: =AP52/AO52-1 | AO52: =IF($A$1=$B$1,B52,IF($A$1=$E$1,E52,IF($A$1=$H$1,H52,IF($A$1=$K$1,K52,IF($A$1=$N$1,N52,IF($A$1=$Q$1,Q52,IF($A$1=$T$1,T52,IF($A$1=$W$1,W52,IF($A$1=$Z$1,Z52,IF($A$1=$AC$1,AC52,IF($A$1=$AF$1,AF52,IF($A$1=$AI$1,AI52)))))))))))) | AP52: =IF($A$1=$B$1,C52,IF($A$1=$E$1,F52,IF($A$1=$H$1,I52,IF($A$1=$K$1,L52,IF($A$1=$N$1,O52,IF($A$1=$Q$1,R52,IF($A$1=$T$1,U52,IF($A$1=$W$1,X52,IF($A$1=$Z$1,AA52,IF($A$1=$AC$1,AD52,IF($A$1=$AF$1,AG52,IF($A$1=$AI$1,AJ52))))))))))))
AL53: =AP53-AO53 | AM53: =AP53/AO53-1 | AO53: =IF($A$1=$B$1,B53,IF($A$1=$E$1,E53,IF($A$1=$H$1,H53,IF($A$1=$K$1,K53,IF($A$1=$N$1,N53,IF($A$1=$Q$1,Q53,IF($A$1=$T$1,T53,IF($A$1=$W$1,W53,IF($A$1=$Z$1,Z53,IF($A$1=$AC$1,AC53,IF($A$1=$AF$1,AF53,IF($A$1=$AI$1,AI53)))))))))))) | AP53: =IF($A$1=$B$1,C53,IF($A$1=$E$1,F53,IF($A$1=$H$1,I53,IF($A$1=$K$1,L53,IF($A$1=$N$1,O53,IF($A$1=$Q$1,R53,IF($A$1=$T$1,U53,IF($A$1=$W$1,X53,IF($A$1=$Z$1,AA53,IF($A$1=$AC$1,AD53,IF($A$1=$AF$1,AG53,IF($A$1=$AI$1,AJ53))))))))))))
AL54: =AP54-AO54 | AM54: =AP54/AO54-1 | AO54: =IF($A$1=$B$1,B54,IF($A$1=$E$1,E54,IF($A$1=$H$1,H54,IF($A$1=$K$1,K54,IF($A$1=$N$1,N54,IF($A$1=$Q$1,Q54,IF($A$1=$T$1,T54,IF($A$1=$W$1,W54,IF($A$1=$Z$1,Z54,IF($A$1=$AC$1,AC54,IF($A$1=$AF$1,AF54,IF($A$1=$AI$1,AI54)))))))))))) | AP54: =IF($A$1=$B$1,C54,IF($A$1=$E$1,F54,IF($A$1=$H$1,I54,IF($A$1=$K$1,L54,IF($A$1=$N$1,O54,IF($A$1=$Q$1,R54,IF($A$1=$T$1,U54,IF($A$1=$W$1,X54,IF($A$1=$Z$1,AA54,IF($A$1=$AC$1,AD54,IF($A$1=$AF$1,AG54,IF($A$1=$AI$1,AJ54))))))))))))
AL55: =AP55-AO55 | AM55: =AP55/AO55-1 | AO55: =IF($A$1=$B$1,B55,IF($A$1=$E$1,E55,IF($A$1=$H$1,H55,IF($A$1=$K$1,K55,IF($A$1=$N$1,N55,IF($A$1=$Q$1,Q55,IF($A$1=$T$1,T55,IF($A$1=$W$1,W55,IF($A$1=$Z$1,Z55,IF($A$1=$AC$1,AC55,IF($A$1=$AF$1,AF55,IF($A$1=$AI$1,AI55)))))))))))) | AP55: =IF($A$1=$B$1,C55,IF($A$1=$E$1,F55,IF($A$1=$H$1,I55,IF($A$1=$K$1,L55,IF($A$1=$N$1,O55,IF($A$1=$Q$1,R55,IF($A$1=$T$1,U55,IF($A$1=$W$1,X55,IF($A$1=$Z$1,AA55,IF($A$1=$AC$1,AD55,IF($A$1=$AF$1,AG55,IF($A$1=$AI$1,AJ55))))))))))))
AL56: =AP56-AO56 | AM56: =AP56/AO56-1 | AO56: =IF($A$1=$B$1,B56,IF($A$1=$E$1,E56,IF($A$1=$H$1,H56,IF($A$1=$K$1,K56,IF($A$1=$N$1,N56,IF($A$1=$Q$1,Q56,IF($A$1=$T$1,T56,IF($A$1=$W$1,W56,IF($A$1=$Z$1,Z56,IF($A$1=$AC$1,AC56,IF($A$1=$AF$1,AF56,IF($A$1=$AI$1,AI56)))))))))))) | AP56: =IF($A$1=$B$1,C56,IF($A$1=$E$1,F56,IF($A$1=$H$1,I56,IF($A$1=$K$1,L56,IF($A$1=$N$1,O56,IF($A$1=$Q$1,R56,IF($A$1=$T$1,U56,IF($A$1=$W$1,X56,IF($A$1=$Z$1,AA56,IF($A$1=$AC$1,AD56,IF($A$1=$AF$1,AG56,IF($A$1=$AI$1,AJ56))))))))))))
AL57: =AP57-AO57 | AM57: =AP57/AO57-1 | AO57: =IF($A$1=$B$1,B57,IF($A$1=$E$1,E57,IF($A$1=$H$1,H57,IF($A$1=$K$1,K57,IF($A$1=$N$1,N57,IF($A$1=$Q$1,Q57,IF($A$1=$T$1,T57,IF($A$1=$W$1,W57,IF($A$1=$Z$1,Z57,IF($A$1=$AC$1,AC57,IF($A$1=$AF$1,AF57,IF($A$1=$AI$1,AI57)))))))))))) | AP57: =IF($A$1=$B$1,C57,IF($A$1=$E$1,F57,IF($A$1=$H$1,I57,IF($A$1=$K$1,L57,IF($A$1=$N$1,O57,IF($A$1=$Q$1,R57,IF($A$1=$T$1,U57,IF($A$1=$W$1,X57,IF($A$1=$Z$1,AA57,IF($A$1=$AC$1,AD57,IF($A$1=$AF$1,AG57,IF($A$1=$AI$1,AJ57))))))))))))
AL58: =AP58-AO58 | AM58: =AP58/AO58-1 | AO58: =IF($A$1=$B$1,B58,IF($A$1=$E$1,E58,IF($A$1=$H$1,H58,IF($A$1=$K$1,K58,IF($A$1=$N$1,N58,IF($A$1=$Q$1,Q58,IF($A$1=$T$1,T58,IF($A$1=$W$1,W58,IF($A$1=$Z$1,Z58,IF($A$1=$AC$1,AC58,IF($A$1=$AF$1,AF58,IF($A$1=$AI$1,AI58)))))))))))) | AP58: =IF($A$1=$B$1,C58,IF($A$1=$E$1,F58,IF($A$1=$H$1,I58,IF($A$1=$K$1,L58,IF($A$1=$N$1,O58,IF($A$1=$Q$1,R58,IF($A$1=$T$1,U58,IF($A$1=$W$1,X58,IF($A$1=$Z$1,AA58,IF($A$1=$AC$1,AD58,IF($A$1=$AF$1,AG58,IF($A$1=$AI$1,AJ58))))))))))))
AL59: =AP59-AO59 | AM59: =AP59/AO59-1 | AO59: =IF($A$1=$B$1,B59,IF($A$1=$E$1,E59,IF($A$1=$H$1,H59,IF($A$1=$K$1,K59,IF($A$1=$N$1,N59,IF($A$1=$Q$1,Q59,IF($A$1=$T$1,T59,IF($A$1=$W$1,W59,IF($A$1=$Z$1,Z59,IF($A$1=$AC$1,AC59,IF($A$1=$AF$1,AF59,IF($A$1=$AI$1,AI59)))))))))))) | AP59: =IF($A$1=$B$1,C59,IF($A$1=$E$1,F59,IF($A$1=$H$1,I59,IF($A$1=$K$1,L59,IF($A$1=$N$1,O59,IF($A$1=$Q$1,R59,IF($A$1=$T$1,U59,IF($A$1=$W$1,X59,IF($A$1=$Z$1,AA59,IF($A$1=$AC$1,AD59,IF($A$1=$AF$1,AG59,IF($A$1=$AI$1,AJ59))))))))))))
AL60: =AP60-AO60 | AM60: =AP60/AO60-1 | AO60: =IF($A$1=$B$1,B60,IF($A$1=$E$1,E60,IF($A$1=$H$1,H60,IF($A$1=$K$1,K60,IF($A$1=$N$1,N60,IF($A$1=$Q$1,Q60,IF($A$1=$T$1,T60,IF($A$1=$W$1,W60,IF($A$1=$Z$1,Z60,IF($A$1=$AC$1,AC60,IF($A$1=$AF$1,AF60,IF($A$1=$AI$1,AI60)))))))))))) | AP60: =IF($A$1=$B$1,C60,IF($A$1=$E$1,F60,IF($A$1=$H$1,I60,IF($A$1=$K$1,L60,IF($A$1=$N$1,O60,IF($A$1=$Q$1,R60,IF($A$1=$T$1,U60,IF($A$1=$W$1,X60,IF($A$1=$Z$1,AA60,IF($A$1=$AC$1,AD60,IF($A$1=$AF$1,AG60,IF($A$1=$AI$1,AJ60))))))))))))
AL61: =AP61-AO61 | AM61: =AP61/AO61-1 | AO61: =IF($A$1=$B$1,B61,IF($A$1=$E$1,E61,IF($A$1=$H$1,H61,IF($A$1=$K$1,K61,IF($A$1=$N$1,N61,IF($A$1=$Q$1,Q61,IF($A$1=$T$1,T61,IF($A$1=$W$1,W61,IF($A$1=$Z$1,Z61,IF($A$1=$AC$1,AC61,IF($A$1=$AF$1,AF61,IF($A$1=$AI$1,AI61)))))))))))) | AP61: =IF($A$1=$B$1,C61,IF($A$1=$E$1,F61,IF($A$1=$H$1,I61,IF($A$1=$K$1,L61,IF($A$1=$N$1,O61,IF($A$1=$Q$1,R61,IF($A$1=$T$1,U61,IF($A$1=$W$1,X61,IF($A$1=$Z$1,AA61,IF($A$1=$AC$1,AD61,IF($A$1=$AF$1,AG61,IF($A$1=$AI$1,AJ61))))))))))))
... AL75: =AP75-AO75 | AM75: =AP75/AO75-1 | AO75: =IF($A$1=$B$1,B75,IF($A$1=$E$1,E75,IF($A$1=$H$1,H75,IF($A$1=$K$1,K75,IF($A$1=$N$1,N75,IF($A$1=$Q$1,Q75,IF($A$1=$T$1,T75,IF($A$1=$W$1,W75,IF($A$1=$Z$1,Z75,IF($A$1=$AC$1,AC75,IF($A$1=$AF$1,AF75,IF($A$1=$AI$1,AI75)))))))))))) | AP75: =IF($A$1=$B$1,C75,IF($A$1=$E$1,F75,IF($A$1=$H$1,I75,IF($A$1=$K$1,L75,IF($A$1=$N$1,O75,IF($A$1=$Q$1,R75,IF($A$1=$T$1,U75,IF($A$1=$W$1,X75,IF($A$1=$Z$1,AA75,IF($A$1=$AC$1,AD75,IF($A$1=$AF$1,AG75,IF($A$1=$AI$1,AJ75))))))))))))
A78: GROSS PROFIT MARGIN BY CHANNELS
A79: İnci Holding | B79: =B36/B9 | C79: =IFERROR((C36/C9),"") | E79: =E36/E9 | F79: =IFERROR((F36/F9),"") | H79: =H36/H9 | I79: =IFERROR((I36/I9),"") | K79: =K36/K9 | L79: =IFERROR((L36/L9),"") | N79: =N36/N9 | O79: =IFERROR((O36/O9),"") | Q79: =Q36/Q9 | R79: =IFERROR((R36/R9),"") | T79: =T36/T9 | U79: =IFERROR((U36/U9),"") | W79: =W36/W9 | X79: =IFERROR((X36/X9),"") | Z79: =Z36/Z9 | AA79: =IFERROR((AA36/AA9),"") | AC79: =AC36/AC9 | AD79: =IFERROR((AD36/AD9),"") | AF79: =AF36/AF9 | AG79: =IFERROR((AG36/AG9),"") | AI79: =AI36/AI9 | AJ79: =IFERROR((AJ36/AJ9),"") | AM79: =AP79-AO79 | AO79: =IF($A$1=$B$1,B79,IF($A$1=$E$1,E79,IF($A$1=$H$1,H79,IF($A$1=$K$1,K79,IF($A$1=$N$1,N79,IF($A$1=$Q$1,Q79,IF($A$1=$T$1,T79,IF($A$1=$W$1,W79,IF($A$1=$Z$1,Z79,IF($A$1=$AC$1,AC79,IF($A$1=$AF$1,AF79,IF($A$1=$AI$1,AI79)))))))))))) | AP79: =IF($A$1=$B$1,C79,IF($A$1=$E$1,F79,IF($A$1=$H$1,I79,IF($A$1=$K$1,L79,IF($A$1=$N$1,O79,IF($A$1=$Q$1,R79,IF($A$1=$T$1,U79,IF($A$1=$W$1,X79,IF($A$1=$Z$1,AA79,IF($A$1=$AC$1,AD79,IF($A$1=$AF$1,AG79,IF($A$1=$AI$1,AJ79))))))))))))
A80: ISM | B80: =B37/B10 | C80: =IFERROR((C37/C10),"") | E80: =E37/E10 | F80: =IFERROR((F37/F10),"") | H80: =H37/H10 | I80: =IFERROR((I37/I10),"") | K80: =K37/K10 | L80: =IFERROR((L37/L10),"") | N80: =N37/N10 | O80: =IFERROR((O37/O10),"") | Q80: =Q37/Q10 | R80: =IFERROR((R37/R10),"") | T80: =T37/T10 | U80: =IFERROR((U37/U10),"") | W80: =W37/W10 | X80: =IFERROR((X37/X10),"") | Z80: =Z37/Z10 | AA80: =IFERROR((AA37/AA10),"") | AC80: =AC37/AC10 | AD80: =IFERROR((AD37/AD10),"") | AF80: =AF37/AF10 | AG80: =IFERROR((AG37/AG10),"") | AI80: =AI37/AI10 | AJ80: =IFERROR((AJ37/AJ10),"") | AM80: =AP80-AO80 | AO80: =IF($A$1=$B$1,B80,IF($A$1=$E$1,E80,IF($A$1=$H$1,H80,IF($A$1=$K$1,K80,IF($A$1=$N$1,N80,IF($A$1=$Q$1,Q80,IF($A$1=$T$1,T80,IF($A$1=$W$1,W80,IF($A$1=$Z$1,Z80,IF($A$1=$AC$1,AC80,IF($A$1=$AF$1,AF80,IF($A$1=$AI$1,AI80)))))))))))) | AP80: =IF($A$1=$B$1,C80,IF($A$1=$E$1,F80,IF($A$1=$H$1,I80,IF($A$1=$K$1,L80,IF($A$1=$N$1,O80,IF($A$1=$Q$1,R80,IF($A$1=$T$1,U80,IF($A$1=$W$1,X80,IF($A$1=$Z$1,AA80,IF($A$1=$AC$1,AD80,IF($A$1=$AF$1,AG80,IF($A$1=$AI$1,AJ80))))))))))))
A81: İncitaş | B81: =B38/B11 | C81: =IFERROR((C38/C11),"") | E81: =E38/E11 | F81: =IFERROR((F38/F11),"") | H81: =H38/H11 | I81: =IFERROR((I38/I11),"") | K81: =K38/K11 | L81: =IFERROR((L38/L11),"") | N81: =N38/N11 | O81: =IFERROR((O38/O11),"") | Q81: =Q38/Q11 | R81: =IFERROR((R38/R11),"") | T81: =T38/T11 | U81: =IFERROR((U38/U11),"") | W81: =W38/W11 | X81: =IFERROR((X38/X11),"") | Z81: =Z38/Z11 | AA81: =IFERROR((AA38/AA11),"") | AC81: =AC38/AC11 | AD81: =IFERROR((AD38/AD11),"") | AF81: =AF38/AF11 | AG81: =IFERROR((AG38/AG11),"") | AI81: =AI38/AI11 | AJ81: =IFERROR((AJ38/AJ11),"") | AM81: =AP81-AO81 | AO81: =IF($A$1=$B$1,B81,IF($A$1=$E$1,E81,IF($A$1=$H$1,H81,IF($A$1=$K$1,K81,IF($A$1=$N$1,N81,IF($A$1=$Q$1,Q81,IF($A$1=$T$1,T81,IF($A$1=$W$1,W81,IF($A$1=$Z$1,Z81,IF($A$1=$AC$1,AC81,IF($A$1=$AF$1,AF81,IF($A$1=$AI$1,AI81)))))))))))) | AP81: =IF($A$1=$B$1,C81,IF($A$1=$E$1,F81,IF($A$1=$H$1,I81,IF($A$1=$K$1,L81,IF($A$1=$N$1,O81,IF($A$1=$Q$1,R81,IF($A$1=$T$1,U81,IF($A$1=$W$1,X81,IF($A$1=$Z$1,AA81,IF($A$1=$AC$1,AD81,IF($A$1=$AF$1,AG81,IF($A$1=$AI$1,AJ81))))))))))))
A82: İnci GS Yuasa | B82: =B39/B12 | C82: =IFERROR((C39/C12),"") | E82: =E39/E12 | F82: =IFERROR((F39/F12),"") | H82: =H39/H12 | I82: =IFERROR((I39/I12),"") | K82: =K39/K12 | L82: =IFERROR((L39/L12),"") | N82: =N39/N12 | O82: =IFERROR((O39/O12),"") | Q82: =Q39/Q12 | R82: =IFERROR((R39/R12),"") | T82: =T39/T12 | U82: =IFERROR((U39/U12),"") | W82: =W39/W12 | X82: =IFERROR((X39/X12),"") | Z82: =Z39/Z12 | AA82: =IFERROR((AA39/AA12),"") | AC82: =AC39/AC12 | AD82: =IFERROR((AD39/AD12),"") | AF82: =AF39/AF12 | AG82: =IFERROR((AG39/AG12),"") | AI82: =AI39/AI12 | AJ82: =IFERROR((AJ39/AJ12),"") | AM82: =AP82-AO82 | AO82: =IF($A$1=$B$1,B82,IF($A$1=$E$1,E82,IF($A$1=$H$1,H82,IF($A$1=$K$1,K82,IF($A$1=$N$1,N82,IF($A$1=$Q$1,Q82,IF($A$1=$T$1,T82,IF($A$1=$W$1,W82,IF($A$1=$Z$1,Z82,IF($A$1=$AC$1,AC82,IF($A$1=$AF$1,AF82,IF($A$1=$AI$1,AI82)))))))))))) | AP82: =IF($A$1=$B$1,C82,IF($A$1=$E$1,F82,IF($A$1=$H$1,I82,IF($A$1=$K$1,L82,IF($A$1=$N$1,O82,IF($A$1=$Q$1,R82,IF($A$1=$T$1,U82,IF($A$1=$W$1,X82,IF($A$1=$Z$1,AA82,IF($A$1=$AC$1,AD82,IF($A$1=$AF$1,AG82,IF($A$1=$AI$1,AJ82))))))))))))
A83: Yusen İnci Loj. | B83: =B40/B13 | C83: =IFERROR((C40/C13),"") | E83: =E40/E13 | F83: =IFERROR((F40/F13),"") | H83: =H40/H13 | I83: =IFERROR((I40/I13),"") | K83: =K40/K13 | L83: =IFERROR((L40/L13),"") | N83: =N40/N13 | O83: =IFERROR((O40/O13),"") | Q83: =Q40/Q13 | R83: =IFERROR((R40/R13),"") | T83: =T40/T13 | U83: =IFERROR((U40/U13),"") | W83: =W40/W13 | X83: =IFERROR((X40/X13),"") | Z83: =Z40/Z13 | AA83: =IFERROR((AA40/AA13),"") | AC83: =AC40/AC13 | AD83: =IFERROR((AD40/AD13),"") | AF83: =AF40/AF13 | AG83: =IFERROR((AG40/AG13),"") | AI83: =AI40/AI13 | AJ83: =IFERROR((AJ40/AJ13),"") | AM83: =AP83-AO83 | AO83: =IF($A$1=$B$1,B83,IF($A$1=$E$1,E83,IF($A$1=$H$1,H83,IF($A$1=$K$1,K83,IF($A$1=$N$1,N83,IF($A$1=$Q$1,Q83,IF($A$1=$T$1,T83,IF($A$1=$W$1,W83,IF($A$1=$Z$1,Z83,IF($A$1=$AC$1,AC83,IF($A$1=$AF$1,AF83,IF($A$1=$AI$1,AI83)))))))))))) | AP83: =IF($A$1=$B$1,C83,IF($A$1=$E$1,F83,IF($A$1=$H$1,I83,IF($A$1=$K$1,L83,IF($A$1=$N$1,O83,IF($A$1=$Q$1,R83,IF($A$1=$T$1,U83,IF($A$1=$W$1,X83,IF($A$1=$Z$1,AA83,IF($A$1=$AC$1,AD83,IF($A$1=$AF$1,AG83,IF($A$1=$AI$1,AJ83))))))))))))
A84: Jantaş | B84: =B41/B14 | C84: =IFERROR((C41/C14),"") | E84: =E41/E14 | F84: =IFERROR((F41/F14),"") | H84: =H41/H14 | I84: =IFERROR((I41/I14),"") | K84: =K41/K14 | L84: =IFERROR((L41/L14),"") | N84: =N41/N14 | O84: =IFERROR((O41/O14),"") | Q84: =Q41/Q14 | R84: =IFERROR((R41/R14),"") | T84: =T41/T14 | U84: =IFERROR((U41/U14),"") | W84: =W41/W14 | X84: =IFERROR((X41/X14),"") | Z84: =Z41/Z14 | AA84: =IFERROR((AA41/AA14),"") | AC84: =AC41/AC14 | AD84: =IFERROR((AD41/AD14),"") | AF84: =AF41/AF14 | AG84: =IFERROR((AG41/AG14),"") | AI84: =AI41/AI14 | AJ84: =IFERROR((AJ41/AJ14),"") | AM84: =AP84-AO84 | AO84: =IF($A$1=$B$1,B84,IF($A$1=$E$1,E84,IF($A$1=$H$1,H84,IF($A$1=$K$1,K84,IF($A$1=$N$1,N84,IF($A$1=$Q$1,Q84,IF($A$1=$T$1,T84,IF($A$1=$W$1,W84,IF($A$1=$Z$1,Z84,IF($A$1=$AC$1,AC84,IF($A$1=$AF$1,AF84,IF($A$1=$AI$1,AI84)))))))))))) | AP84: =IF($A$1=$B$1,C84,IF($A$1=$E$1,F84,IF($A$1=$H$1,I84,IF($A$1=$K$1,L84,IF($A$1=$N$1,O84,IF($A$1=$Q$1,R84,IF($A$1=$T$1,U84,IF($A$1=$W$1,X84,IF($A$1=$Z$1,AA84,IF($A$1=$AC$1,AD84,IF($A$1=$AF$1,AG84,IF($A$1=$AI$1,AJ84))))))))))))
A85: Çelik | B85: =B42/B15 | C85: =IFERROR((C42/C15),"") | E85: =E42/E15 | F85: =IFERROR((F42/F15),"") | H85: =H42/H15 | I85: =IFERROR((I42/I15),"") | K85: =K42/K15 | L85: =IFERROR((L42/L15),"") | N85: =N42/N15 | O85: =IFERROR((O42/O15),"") | Q85: =Q42/Q15 | R85: =IFERROR((R42/R15),"") | T85: =T42/T15 | U85: =IFERROR((U42/U15),"") | W85: =W42/W15 | X85: =IFERROR((X42/X15),"") | Z85: =Z42/Z15 | AA85: =IFERROR((AA42/AA15),"") | AC85: =AC42/AC15 | AD85: =IFERROR((AD42/AD15),"") | AF85: =AF42/AF15 | AG85: =IFERROR((AG42/AG15),"") | AI85: =AI42/AI15 | AJ85: =IFERROR((AJ42/AJ15),"") | AM85: =AP85-AO85 | AO85: =IF($A$1=$B$1,B85,IF($A$1=$E$1,E85,IF($A$1=$H$1,H85,IF($A$1=$K$1,K85,IF($A$1=$N$1,N85,IF($A$1=$Q$1,Q85,IF($A$1=$T$1,T85,IF($A$1=$W$1,W85,IF($A$1=$Z$1,Z85,IF($A$1=$AC$1,AC85,IF($A$1=$AF$1,AF85,IF($A$1=$AI$1,AI85)))))))))))) | AP85: =IF($A$1=$B$1,C85,IF($A$1=$E$1,F85,IF($A$1=$H$1,I85,IF($A$1=$K$1,L85,IF($A$1=$N$1,O85,IF($A$1=$Q$1,R85,IF($A$1=$T$1,U85,IF($A$1=$W$1,X85,IF($A$1=$Z$1,AA85,IF($A$1=$AC$1,AD85,IF($A$1=$AF$1,AG85,IF($A$1=$AI$1,AJ85))))))))))))
A86: Alüminyum | B86: =B43/B16 | C86: =IFERROR((C43/C16),"") | E86: =E43/E16 | F86: =IFERROR((F43/F16),"") | H86: =H43/H16 | I86: =IFERROR((I43/I16),"") | K86: =K43/K16 | L86: =IFERROR((L43/L16),"") | N86: =N43/N16 | O86: =IFERROR((O43/O16),"") | Q86: =Q43/Q16 | R86: =IFERROR((R43/R16),"") | T86: =T43/T16 | U86: =IFERROR((U43/U16),"") | W86: =W43/W16 | X86: =IFERROR((X43/X16),"") | Z86: =Z43/Z16 | AA86: =IFERROR((AA43/AA16),"") | AC86: =AC43/AC16 | AD86: =IFERROR((AD43/AD16),"") | AF86: =AF43/AF16 | AG86: =IFERROR((AG43/AG16),"") | AI86: =AI43/AI16 | AJ86: =IFERROR((AJ43/AJ16),"") | AM86: =AP86-AO86 | AO86: =IF($A$1=$B$1,B86,IF($A$1=$E$1,E86,IF($A$1=$H$1,H86,IF($A$1=$K$1,K86,IF($A$1=$N$1,N86,IF($A$1=$Q$1,Q86,IF($A$1=$T$1,T86,IF($A$1=$W$1,W86,IF($A$1=$Z$1,Z86,IF($A$1=$AC$1,AC86,IF($A$1=$AF$1,AF86,IF($A$1=$AI$1,AI86)))))))))))) | AP86: =IF($A$1=$B$1,C86,IF($A$1=$E$1,F86,IF($A$1=$H$1,I86,IF($A$1=$K$1,L86,IF($A$1=$N$1,O86,IF($A$1=$Q$1,R86,IF($A$1=$T$1,U86,IF($A$1=$W$1,X86,IF($A$1=$Z$1,AA86,IF($A$1=$AC$1,AD86,IF($A$1=$AF$1,AG86,IF($A$1=$AI$1,AJ86))))))))))))
C87: =IFERROR((C44/C17),"") | F87: =IFERROR((F44/F17),"") | I87: =IFERROR((I44/I17),"") | L87: =IFERROR((L44/L17),"") | O87: =IFERROR((O44/O17),"") | R87: =IFERROR((R44/R17),"") | U87: =IFERROR((U44/U17),"") | X87: =IFERROR((X44/X17),"") | AA87: =AA88-Z88 | AD87: =AD88-AC88 | AG87: =AG88-AF88 | AJ87: =IFERROR((AJ44/AJ17),"") | AO87: =IF($A$1=$B$1,B87,IF($A$1=$E$1,E87,IF($A$1=$H$1,H87,IF($A$1=$K$1,K87,IF($A$1=$N$1,N87,IF($A$1=$Q$1,Q87,IF($A$1=$T$1,T87,IF($A$1=$W$1,W87,IF($A$1=$Z$1,Z87,IF($A$1=$AC$1,AC87,IF($A$1=$AF$1,AF87,IF($A$1=$AI$1,AI87)))))))))))) | AP87: =IF($A$1=$B$1,C87,IF($A$1=$E$1,F87,IF($A$1=$H$1,I87,IF($A$1=$K$1,L87,IF($A$1=$N$1,O87,IF($A$1=$Q$1,R87,IF($A$1=$T$1,U87,IF($A$1=$W$1,X87,IF($A$1=$Z$1,AA87,IF($A$1=$AC$1,AD87,IF($A$1=$AF$1,AG87,IF($A$1=$AI$1,AJ87))))))))))))
A88: Operating Expenses | B88: ='A -Döviz'!B88 | C88: ='A -Döviz'!C88 | E88: =B88+'A -Döviz'!E88 | F88: =C88+'A -Döviz'!F88 | G88: =F88-E88 | H88: =E88+'A -Döviz'!H88 | I88: =F88+'A -Döviz'!I88 | K88: =H88+'A -Döviz'!K88 | L88: =I88+'A -Döviz'!L88 | N88: =K88+'A -Döviz'!N88 | O88: =L88+'A -Döviz'!O88 | Q88: =N88+'A -Döviz'!Q88 | R88: =O88+'A -Döviz'!R88 | T88: =Q88+'A -Döviz'!T88 | U88: =R88+'A -Döviz'!U88 | W88: =T88+'A -Döviz'!W88 | X88: =U88+'A -Döviz'!X88 | Z88: =W88+'A -Döviz'!Z88 | AA88: =X88+'A -Döviz'!AA88 | AC88: =Z88+'A -Döviz'!AC88 | AD88: =AA88+'A -Döviz'!AD88 | AF88: =AC88+'A -Döviz'!AF88 | AG88: =AD88+'A -Döviz'!AG88 | AI88: =AF88+'A -Döviz'!AI88 | AJ88: =AG88+'A -Döviz'!AJ88 | AL88: =AP88-AO88 | AM88: =AP88/AO88-1 | AO88: =IF($A$1=$B$1,B88,IF($A$1=$E$1,E88,IF($A$1=$H$1,H88,IF($A$1=$K$1,K88,IF($A$1=$N$1,N88,IF($A$1=$Q$1,Q88,IF($A$1=$T$1,T88,IF($A$1=$W$1,W88,IF($A$1=$Z$1,Z88,IF($A$1=$AC$1,AC88,IF($A$1=$AF$1,AF88,IF($A$1=$AI$1,AI88)))))))))))) | AP88: =IF($A$1=$B$1,C88,IF($A$1=$E$1,F88,IF($A$1=$H$1,I88,IF($A$1=$K$1,L88,IF($A$1=$N$1,O88,IF($A$1=$Q$1,R88,IF($A$1=$T$1,U88,IF($A$1=$W$1,X88,IF($A$1=$Z$1,AA88,IF($A$1=$AC$1,AD88,IF($A$1=$AF$1,AG88,IF($A$1=$AI$1,AJ88))))))))))))
B89: =-B88/B6 | C89: =-C88/C6 | E89: =-E88/E6 | F89: =-F88/F6 | H89: =-H88/H6 | I89: =-I88/I6 | K89: =-K88/K30 | L89: =-L88/L30 | N89: =-N88/N30 | O89: =-O88/O30 | Q89: =-Q88/Q30 | R89: =-R88/R30 | T89: =-T88/T30 | U89: =-U88/U30 | W89: =-W88/W30 | X89: =-X88/X30 | Z89: =-Z88/Z30 | AA89: =-AA88/AA30 | AC89: =-AC88/AC30 | AD89: =-AD88/AD30 | AF89: =-AF88/AF30 | AG89: =-AG88/AG30 | AI89: =-AI88/AI30 | AJ89: =-AJ88/AJ30 | AM89: =AP89/AO89-1 | AO89: =IF($A$1=$B$1,B89,IF($A$1=$E$1,E89,IF($A$1=$H$1,H89,IF($A$1=$K$1,K89,IF($A$1=$N$1,N89,IF($A$1=$Q$1,Q89,IF($A$1=$T$1,T89,IF($A$1=$W$1,W89,IF($A$1=$Z$1,Z89,IF($A$1=$AC$1,AC89,IF($A$1=$AF$1,AF89,IF($A$1=$AI$1,AI89)))))))))))) | AP89: =IF($A$1=$B$1,C89,IF($A$1=$E$1,F89,IF($A$1=$H$1,I89,IF($A$1=$K$1,L89,IF($A$1=$N$1,O89,IF($A$1=$Q$1,R89,IF($A$1=$T$1,U89,IF($A$1=$W$1,X89,IF($A$1=$Z$1,AA89,IF($A$1=$AC$1,AD89,IF($A$1=$AF$1,AG89,IF($A$1=$AI$1,AJ89))))))))))))
A90: Operating Expenses by channels (100%) | AR90: =SUM(AR91:AR98) | AS90: =SUM(AS91:AS98) | AT90: =AS90-AR90
A91: İnci Holding | B91: ='A -Döviz'!B91 | C91: ='A -Döviz'!C91 | E91: =B91+'A -Döviz'!E91 | F91: =C91+'A -Döviz'!F91 | G91: =F91-E91 | H91: =E91+'A -Döviz'!H91 | I91: =F91+'A -Döviz'!I91 | K91: =H91+'A -Döviz'!K91 | L91: =I91+'A -Döviz'!L91 | N91: =K91+'A -Döviz'!N91 | O91: =L91+'A -Döviz'!O91 | Q91: =N91+'A -Döviz'!Q91 | R91: =O91+'A -Döviz'!R91 | T91: =Q91+'A -Döviz'!T91 | U91: =R91+'A -Döviz'!U91 | W91: =T91+'A -Döviz'!W91 | X91: =U91+'A -Döviz'!X91 | Z91: =W91+'A -Döviz'!Z91 | AA91: =X91+'A -Döviz'!AA91 | AB91: =Z91/AA91-1 | AC91: =Z91+'A -Döviz'!AC91 | AD91: =AA91+'A -Döviz'!AD91 | AF91: =AC91+'A -Döviz'!AF91 | AG91: =AD91+'A -Döviz'!AG91 | AI91: =AF91+'A -Döviz'!AI91 | AJ91: =AG91+'A -Döviz'!AJ91 | AL91: =AP91-AO91 | AM91: =AP91/AO91-1 | AO91: =IF($A$1=$B$1,B91,IF($A$1=$E$1,E91,IF($A$1=$H$1,H91,IF($A$1=$K$1,K91,IF($A$1=$N$1,N91,IF($A$1=$Q$1,Q91,IF($A$1=$T$1,T91,IF($A$1=$W$1,W91,IF($A$1=$Z$1,Z91,IF($A$1=$AC$1,AC91,IF($A$1=$AF$1,AF91,IF($A$1=$AI$1,AI91)))))))))))) | AP91: =IF($A$1=$B$1,C91,IF($A$1=$E$1,F91,IF($A$1=$H$1,I91,IF($A$1=$K$1,L91,IF($A$1=$N$1,O91,IF($A$1=$Q$1,R91,IF($A$1=$T$1,U91,IF($A$1=$W$1,X91,IF($A$1=$Z$1,AA91,IF($A$1=$AC$1,AD91,IF($A$1=$AF$1,AG91,IF($A$1=$AI$1,AJ91)))))))))))) | AR91: =AF91 | AS91: =AG91 | AT91: =AS91-AR91
A92: ISM | B92: ='A -Döviz'!B92 | C92: ='A -Döviz'!C92 | E92: =B92+'A -Döviz'!E92 | F92: =C92+'A -Döviz'!F92 | G92: =F92-E92 | H92: =E92+'A -Döviz'!H92 | I92: =F92+'A -Döviz'!I92 | K92: =H92+'A -Döviz'!K92 | L92: =I92+'A -Döviz'!L92 | N92: =K92+'A -Döviz'!N92 | O92: =L92+'A -Döviz'!O92 | Q92: =N92+'A -Döviz'!Q92 | R92: =O92+'A -Döviz'!R92 | T92: =Q92+'A -Döviz'!T92 | U92: =R92+'A -Döviz'!U92 | W92: =T92+'A -Döviz'!W92 | X92: =U92+'A -Döviz'!X92 | Z92: =W92+'A -Döviz'!Z92 | AA92: =X92+'A -Döviz'!AA92 | AB92: =Z92/AA92-1 | AC92: =Z92+'A -Döviz'!AC92 | AD92: =AA92+'A -Döviz'!AD92 | AF92: =AC92+'A -Döviz'!AF92 | AG92: =AD92+'A -Döviz'!AG92 | AI92: =AF92+'A -Döviz'!AI92 | AJ92: =AG92+'A -Döviz'!AJ92 | AL92: =AP92-AO92 | AM92: =AP92/AO92-1 | AO92: =IF($A$1=$B$1,B92,IF($A$1=$E$1,E92,IF($A$1=$H$1,H92,IF($A$1=$K$1,K92,IF($A$1=$N$1,N92,IF($A$1=$Q$1,Q92,IF($A$1=$T$1,T92,IF($A$1=$W$1,W92,IF($A$1=$Z$1,Z92,IF($A$1=$AC$1,AC92,IF($A$1=$AF$1,AF92,IF($A$1=$AI$1,AI92)))))))))))) | AP92: =IF($A$1=$B$1,C92,IF($A$1=$E$1,F92,IF($A$1=$H$1,I92,IF($A$1=$K$1,L92,IF($A$1=$N$1,O92,IF($A$1=$Q$1,R92,IF($A$1=$T$1,U92,IF($A$1=$W$1,X92,IF($A$1=$Z$1,AA92,IF($A$1=$AC$1,AD92,IF($A$1=$AF$1,AG92,IF($A$1=$AI$1,AJ92)))))))))))) | AR92: =AF92 | AS92: =AG92 | AT92: =AS92-AR92
A93: İncitaş | B93: ='A -Döviz'!B93 | C93: ='A -Döviz'!C93 | E93: =B93+'A -Döviz'!E93 | F93: =C93+'A -Döviz'!F93 | G93: =F93-E93 | H93: =E93+'A -Döviz'!H93 | I93: =F93+'A -Döviz'!I93 | K93: =H93+'A -Döviz'!K93 | L93: =I93+'A -Döviz'!L93 | N93: =K93+'A -Döviz'!N93 | O93: =L93+'A -Döviz'!O93 | Q93: =N93+'A -Döviz'!Q93 | R93: =O93+'A -Döviz'!R93 | T93: =Q93+'A -Döviz'!T93 | U93: =R93+'A -Döviz'!U93 | W93: =T93+'A -Döviz'!W93 | X93: =U93+'A -Döviz'!X93 | Z93: =W93+'A -Döviz'!Z93 | AA93: =X93+'A -Döviz'!AA93 | AB93: =Z93/AA93-1 | AC93: =Z93+'A -Döviz'!AC93 | AD93: =AA93+'A -Döviz'!AD93 | AF93: =AC93+'A -Döviz'!AF93 | AG93: =AD93+'A -Döviz'!AG93 | AI93: =AF93+'A -Döviz'!AI93 | AJ93: =AG93+'A -Döviz'!AJ93 | AL93: =AP93-AO93 | AM93: =AP93/AO93-1 | AO93: =IF($A$1=$B$1,B93,IF($A$1=$E$1,E93,IF($A$1=$H$1,H93,IF($A$1=$K$1,K93,IF($A$1=$N$1,N93,IF($A$1=$Q$1,Q93,IF($A$1=$T$1,T93,IF($A$1=$W$1,W93,IF($A$1=$Z$1,Z93,IF($A$1=$AC$1,AC93,IF($A$1=$AF$1,AF93,IF($A$1=$AI$1,AI93)))))))))))) | AP93: =IF($A$1=$B$1,C93,IF($A$1=$E$1,F93,IF($A$1=$H$1,I93,IF($A$1=$K$1,L93,IF($A$1=$N$1,O93,IF($A$1=$Q$1,R93,IF($A$1=$T$1,U93,IF($A$1=$W$1,X93,IF($A$1=$Z$1,AA93,IF($A$1=$AC$1,AD93,IF($A$1=$AF$1,AG93,IF($A$1=$AI$1,AJ93)))))))))))) | AR93: =AF93 | AS93: =AG93 | AT93: =AS93-AR93
A94: İnci GS Yuasa | B94: ='A -Döviz'!B94 | C94: ='A -Döviz'!C94 | E94: =B94+'A -Döviz'!E94 | F94: =C94+'A -Döviz'!F94 | G94: =F94-E94 | H94: =E94+'A -Döviz'!H94 | I94: =F94+'A -Döviz'!I94 | K94: =H94+'A -Döviz'!K94 | L94: =I94+'A -Döviz'!L94 | N94: =K94+'A -Döviz'!N94 | O94: =L94+'A -Döviz'!O94 | Q94: =N94+'A -Döviz'!Q94 | R94: =O94+'A -Döviz'!R94 | T94: =Q94+'A -Döviz'!T94 | U94: =R94+'A -Döviz'!U94 | W94: =T94+'A -Döviz'!W94 | X94: =U94+'A -Döviz'!X94 | Z94: =W94+'A -Döviz'!Z94 | AA94: =X94+'A -Döviz'!AA94 | AB94: =Z94/AA94-1 | AC94: =Z94+'A -Döviz'!AC94 | AD94: =AA94+'A -Döviz'!AD94 | AF94: =AC94+'A -Döviz'!AF94 | AG94: =AD94+'A -Döviz'!AG94 | AI94: =AF94+'A -Döviz'!AI94 | AJ94: =AG94+'A -Döviz'!AJ94 | AL94: =AP94-AO94 | AM94: =AP94/AO94-1 | AO94: =IF($A$1=$B$1,B94,IF($A$1=$E$1,E94,IF($A$1=$H$1,H94,IF($A$1=$K$1,K94,IF($A$1=$N$1,N94,IF($A$1=$Q$1,Q94,IF($A$1=$T$1,T94,IF($A$1=$W$1,W94,IF($A$1=$Z$1,Z94,IF($A$1=$AC$1,AC94,IF($A$1=$AF$1,AF94,IF($A$1=$AI$1,AI94)))))))))))) | AP94: =IF($A$1=$B$1,C94,IF($A$1=$E$1,F94,IF($A$1=$H$1,I94,IF($A$1=$K$1,L94,IF($A$1=$N$1,O94,IF($A$1=$Q$1,R94,IF($A$1=$T$1,U94,IF($A$1=$W$1,X94,IF($A$1=$Z$1,AA94,IF($A$1=$AC$1,AD94,IF($A$1=$AF$1,AG94,IF($A$1=$AI$1,AJ94)))))))))))) | AR94: =AF94*0.4 | AS94: =AG94*0.4 | AT94: =AS94-AR94
A95: Yusen İnci Loj. | B95: ='A -Döviz'!B95 | C95: ='A -Döviz'!C95 | E95: =B95+'A -Döviz'!E95 | F95: =C95+'A -Döviz'!F95 | G95: =F95-E95 | H95: =E95+'A -Döviz'!H95 | I95: =F95+'A -Döviz'!I95 | K95: =H95+'A -Döviz'!K95 | L95: =I95+'A -Döviz'!L95 | N95: =K95+'A -Döviz'!N95 | O95: =L95+'A -Döviz'!O95 | Q95: =N95+'A -Döviz'!Q95 | R95: =O95+'A -Döviz'!R95 | T95: =Q95+'A -Döviz'!T95 | U95: =R95+'A -Döviz'!U95 | W95: =T95+'A -Döviz'!W95 | X95: =U95+'A -Döviz'!X95 | Z95: =W95+'A -Döviz'!Z95 | AA95: =X95+'A -Döviz'!AA95 | AB95: =Z95/AA95-1 | AC95: =Z95+'A -Döviz'!AC95 | AD95: =AA95+'A -Döviz'!AD95 | AF95: =AC95+'A -Döviz'!AF95 | AG95: =AD95+'A -Döviz'!AG95 | AI95: =AF95+'A -Döviz'!AI95 | AJ95: =AG95+'A -Döviz'!AJ95 | AL95: =AP95-AO95 | AM95: =AP95/AO95-1 | AO95: =IF($A$1=$B$1,B95,IF($A$1=$E$1,E95,IF($A$1=$H$1,H95,IF($A$1=$K$1,K95,IF($A$1=$N$1,N95,IF($A$1=$Q$1,Q95,IF($A$1=$T$1,T95,IF($A$1=$W$1,W95,IF($A$1=$Z$1,Z95,IF($A$1=$AC$1,AC95,IF($A$1=$AF$1,AF95,IF($A$1=$AI$1,AI95)))))))))))) | AP95: =IF($A$1=$B$1,C95,IF($A$1=$E$1,F95,IF($A$1=$H$1,I95,IF($A$1=$K$1,L95,IF($A$1=$N$1,O95,IF($A$1=$Q$1,R95,IF($A$1=$T$1,U95,IF($A$1=$W$1,X95,IF($A$1=$Z$1,AA95,IF($A$1=$AC$1,AD95,IF($A$1=$AF$1,AG95,IF($A$1=$AI$1,AJ95)))))))))))) | AR95: =AF95*0.4 | AS95: =AG95*0.4 | AT95: =AS95-AR95
A96: Jantaş | B96: ='A -Döviz'!B96 | C96: ='A -Döviz'!C96 | E96: =B96+'A -Döviz'!E96 | F96: =C96+'A -Döviz'!F96 | G96: =F96-E96 | H96: =E96+'A -Döviz'!H96 | I96: =F96+'A -Döviz'!I96 | K96: =H96+'A -Döviz'!K96 | L96: =I96+'A -Döviz'!L96 | N96: =K96+'A -Döviz'!N96 | O96: =L96+'A -Döviz'!O96 | Q96: =N96+'A -Döviz'!Q96 | R96: =O96+'A -Döviz'!R96 | T96: =Q96+'A -Döviz'!T96 | U96: =R96+'A -Döviz'!U96 | W96: =T96+'A -Döviz'!W96 | X96: =U96+'A -Döviz'!X96 | Z96: =W96+'A -Döviz'!Z96 | AA96: =X96+'A -Döviz'!AA96 | AB96: =Z96/AA96-1 | AC96: =Z96+'A -Döviz'!AC96 | AD96: =AA96+'A -Döviz'!AD96 | AF96: =AC96+'A -Döviz'!AF96 | AG96: =AD96+'A -Döviz'!AG96 | AI96: =AF96+'A -Döviz'!AI96 | AJ96: =AG96+'A -Döviz'!AJ96 | AL96: =AP96-AO96 | AM96: =AP96/AO96-1 | AO96: =IF($A$1=$B$1,B96,IF($A$1=$E$1,E96,IF($A$1=$H$1,H96,IF($A$1=$K$1,K96,IF($A$1=$N$1,N96,IF($A$1=$Q$1,Q96,IF($A$1=$T$1,T96,IF($A$1=$W$1,W96,IF($A$1=$Z$1,Z96,IF($A$1=$AC$1,AC96,IF($A$1=$AF$1,AF96,IF($A$1=$AI$1,AI96)))))))))))) | AP96: =IF($A$1=$B$1,C96,IF($A$1=$E$1,F96,IF($A$1=$H$1,I96,IF($A$1=$K$1,L96,IF($A$1=$N$1,O96,IF($A$1=$Q$1,R96,IF($A$1=$T$1,U96,IF($A$1=$W$1,X96,IF($A$1=$Z$1,AA96,IF($A$1=$AC$1,AD96,IF($A$1=$AF$1,AG96,IF($A$1=$AI$1,AJ96)))))))))))) | AR96: =AF96*0.4 | AS96: =AG96*0.4 | AT96: =AS96-AR96
