Workbook
Name \A: #REF!
Name \A: #REF!
Name \A: #REF!
Name \A: #REF!
Name \A: #REF!
Name \B: #REF!
Name \B: #REF!
Name \B: #REF!
Name \B: #REF!
Name \B: #REF!
Name \C: #REF!
Name \D: #REF!
Name \E: #REF!
Name \F: #REF!
Name \G: #REF!
Name \H: #REF!
Name \I: #REF!
Name \J: #REF!
Name \P: #REF!
Name \Q: #REF!
Name \R: #REF!
Name \S: #REF!
Name \X: #REF!
Name \Z: #REF!
Name _1___0Yazdırma_Al: #REF!
Name _1_0Yazdırma_Al: #REF!
Name _108CROMO: #REF!
Name _15___0Yazdırma_Al: #REF!
Name _16___0Yazdırma_Al: #REF!
Name _2____Yazdırma_Al: #REF!
Name _2Yazdırma_Al: #REF!
Name _4_0Yazdırma_Al: #REF!
Name _5_0Yazdırma_Al: #REF!
Name _6Yazdırma_Al: #REF!
Name _9._Analysis_of_net_debt: #REF!
Name _ANG1: #REF!
Name _ANG2: #REF!
Name _ANG3: #REF!
Name _ANG4: #REF!
Name _c: #REF!
Name _DAT1: #REF!
Name _DAT11: #REF!
Name _DAT3: #REF!
Name _DAT4: #REF!
Name _DAT5: #REF!
Name _DAT9: #REF!
Name _pan1: #REF!
Name _par1: #REF!
Name _PY1: #REF!
Name _PY2: #REF!
Name _tab3: #REF!
Name _tab3: #REF!
Name _tab3: #REF!
Name _tab3: #REF!
Name _Typ7: "Cost Centre"
Name _Typ8: "Expense/Income"
Name a: {"Werkdp_excl",#N/A,FALSE,"WERKdp"}
Name a: {"Werkdp_excl",#N/A,FALSE,"WERKdp"}
Name a: {"Werkdp_excl",#N/A,FALSE,"WERKdp"}
Name a: {"Werkdp_excl",#N/A,FALSE,"WERKdp"}

Sheet _com.sap.ip.bi.xl.hiddensheet

Sheet Finansal Raporlama AY
C3: AYLIK
C4: bin Avro | D4: Ciro | G4: Brüt Kar | J4: EBITDA | M4: Net Kar
D5: Gerçekleşme | E5: Bütçe - Gerçekleşme Fark | F5: % Değişim | G5: Gerçekleşme | H5: Bütçe - Gerçekleşme Fark | I5: % Değişim | J5: Gerçekleşme | K5: Bütçe - Gerçekleşme Fark | L5: % Değişim | M5: Gerçekleşme | N5: Bütçe - Gerçekleşme Fark | O5: % Değişim
C6: Toplam | D6: =SUM(D7:D14) -> 62184.729 | E6: =SUM(E7:E14) -> -15618.408 | F6: =(D6/(D6-E6))-1 -> -0.20074265 | G6: =SUM(G7:G14) -> 14284.821 | H6: =SUM(H7:H14) -> -3350.4084 | I6: =(G6/(G6-H6))-1 -> -0.18998383 | J6: =SUM(J7:J14) -> 11032.073 | K6: =SUM(K7:K14) -> -2538.0733 | L6: =(J6/(J6-K6))-1 -> -0.1870336 | M6: =SUM(M7:M14) -> 5977.8703 | N6: =SUM(N7:N14) -> -2551.2414 | O6: =(M6/(M6-N6))-1 -> -0.29912158
C7: İnci Holding | D7: ='A -Döviz'!AA9/1000 -> 789.95617 | E7: =('A -Döviz'!AA9-'A -Döviz'!Z9)/1000 -> -86.002945 | F7: =(D7/(D7-E7))-1 -> -0.09818146 | G7: =('A -Döviz'!AA36)/1000 -> 789.95617 | H7: =('A -Döviz'!AA36-'A -Döviz'!Z36)/1000 -> -86.002945 | I7: =(G7/(G7-H7))-1 -> -0.09818146 | J7: ='A -Döviz'!AA139/1000 -> 482.56644 | K7: =('A -Döviz'!AA139-'A -Döviz'!Z139)/1000 -> -4.00163 | L7: =(J7/(J7-K7))-1 -> -0.0082241935 | M7: ='A -Döviz'!AA215/1000 -> 379.22638 | N7: =('A -Döviz'!AA215-'A -Döviz'!Z215)/1000 -> 48.662371 | O7: =(M7/(M7-N7))-1 -> 0.14721013
C8: ISM | D8: ='A -Döviz'!AA10/1000 -> 453.451 | E8: =('A -Döviz'!AA10-'A -Döviz'!Z10)/1000 -> -177.1531 | F8: =(D8/(D8-E8))-1 -> -0.28092603 | G8: =('A -Döviz'!AA37)/1000 -> 103.70261 | H8: =('A -Döviz'!AA37-'A -Döviz'!Z37)/1000 -> -98.326642 | I8: =(G8/(G8-H8))-1 -> -0.48669507 | J8: ='A -Döviz'!AA140/1000 -> -23.409095 | K8: =('A -Döviz'!AA140-'A -Döviz'!Z140)/1000 -> -106.64183 | L8: =((J8/(J8-K8))-1) -> -1.2812487 | M8: ='A -Döviz'!AA216/1000 -> -204.95991 | N8: =('A -Döviz'!AA216-'A -Döviz'!Z216)/1000 -> -251.23212 | O8: =((M8/(M8-N8))-1) -> -5.429438
C9: İncitaş | D9: ='A -Döviz'!AA11/1000 -> 890.67476 | E9: =('A -Döviz'!AA11-'A -Döviz'!Z11)/1000 -> -524.10649 | F9: =(D9/(D9-E9))-1 -> -0.37045055 | G9: =('A -Döviz'!AA38)/1000 -> 170.33583 | H9: =('A -Döviz'!AA38-'A -Döviz'!Z38)/1000 -> -117.78465 | I9: =(G9/(G9-H9))-1 -> -0.40880347 | J9: ='A -Döviz'!AA141/1000 -> 55.231727 | K9: =('A -Döviz'!AA141-'A -Döviz'!Z141)/1000 -> -20.731473 | L9: =((J9/(J9-K9))-1) -> -0.27291469 | M9: ='A -Döviz'!AA217/1000 -> 27.18271 | N9: =('A -Döviz'!AA217-'A -Döviz'!Z217)/1000 -> 2.6174754 | O9: =((M9/(M9-N9))-1) -> 0.10655202
C10: İnci GS Yuasa | D10: ='A -Döviz'!AA12/1000 -> 10760.31 | E10: =('A -Döviz'!AA12-'A -Döviz'!Z12)/1000 -> -11782.675 | F10: =(D10/(D10-E10))-1 -> -0.5226759 | G10: =('A -Döviz'!AA39)/1000 -> 1647.421 | H10: =('A -Döviz'!AA39-'A -Döviz'!Z39)/1000 -> -3233.7434 | I10: =(G10/(G10-H10))-1 -> -0.66249426 | J10: ='A -Döviz'!AA142/1000 -> 274.34946 | K10: =('A -Döviz'!AA142-'A -Döviz'!Z142)/1000 -> -2626.7896 | L10: =(J10/(J10-K10))-1 -> -0.90543388 | M10: ='A -Döviz'!AA218/1000 -> -2472.8123 | N10: =('A -Döviz'!AA218-'A -Döviz'!Z218)/1000 -> -2878.9134 | O10: =((M10/(M10-N10))-1) -> -7.0891548
C11: Yusen İnci Loj. | D11: ='A -Döviz'!AA13/1000 -> 5403.6456 | E11: =('A -Döviz'!AA13-'A -Döviz'!Z13)/1000 -> -554.58101 | F11: =(D11/(D11-E11))-1 -> -0.0930782 | G11: =('A -Döviz'!AA40)/1000 -> 1183.0214 | H11: =('A -Döviz'!AA40-'A -Döviz'!Z40)/1000 -> -53.767077 | I11: =(G11/(G11-H11))-1 -> -0.04347314 | J11: ='A -Döviz'!AA143/1000 -> 606.40071 | K11: =('A -Döviz'!AA143-'A -Döviz'!Z143)/1000 -> 153.79958 | L11: =(J11/(J11-K11))-1 -> 0.33981263 | M11: ='A -Döviz'!AA219/1000 -> 266.91508 | N11: =('A -Döviz'!AA219-'A -Döviz'!Z219)/1000 -> 187.34422 | O11: =(M11/(M11-N11))-1 -> 2.3544324
C12: Jantaş | D12: ='A -Döviz'!AA14/1000 -> 11814.679 | E12: =('A -Döviz'!AA14-'A -Döviz'!Z14)/1000 -> -2041.1323 | F12: =(D12/(D12-E12))-1 -> -0.14731237 | G12: =('A -Döviz'!AA41)/1000 -> 3027.0706 | H12: =('A -Döviz'!AA41-'A -Döviz'!Z41)/1000 -> -195.4839 | I12: =(G12/(G12-H12))-1 -> -0.060661164 | J12: ='A -Döviz'!AA144/1000 -> 2866.0326 | K12: =('A -Döviz'!AA144-'A -Döviz'!Z144)/1000 -> -556.12204 | L12: =(J12/(J12-K12))-1 -> -0.1625064 | M12: ='A -Döviz'!AA220/1000 -> 2095.4481 | N12: =('A -Döviz'!AA220-'A -Döviz'!Z220)/1000 -> 31.085566 | O12: =(M12/(M12-N12))-1 -> 0.015058192
C13: Çelik | D13: ='A -Döviz'!AA15/1000 -> 9589.3663 | E13: =('A -Döviz'!AA15-'A -Döviz'!Z15)/1000 -> 1295.4971 | F13: =(D13/(D13-E13))-1 -> 0.15619936 | G13: =('A -Döviz'!AA42)/1000 -> 3399.9394 | H13: =('A -Döviz'!AA42-'A -Döviz'!Z42)/1000 -> 988.71206 | I13: =(G13/(G13-H13))-1 -> 0.41004514 | J13: ='A -Döviz'!AA145/1000 -> 3117.0046 | K13: =('A -Döviz'!AA145-'A -Döviz'!Z145)/1000 -> 875.91267 | L13: =(J13/(J13-K13))-1 -> 0.39084193 | M13: ='A -Döviz'!AA221/1000 -> 2585.9406 | N13: =('A -Döviz'!AA221-'A -Döviz'!Z221)/1000 -> 861.26263 | O13: =(M13/(M13-N13))-1 -> 0.49937592
C14: Alüminyum | D14: ='A -Döviz'!AA16/1000 -> 22482.647 | E14: =('A -Döviz'!AA16-'A -Döviz'!Z16)/1000 -> -1748.2533 | F14: =(D14/(D14-E14))-1 -> -0.072149746 | G14: =('A -Döviz'!AA43)/1000 -> 3963.3737 | H14: =('A -Döviz'!AA43-'A -Döviz'!Z43)/1000 -> -554.01183 | I14: =(G14/(G14-H14))-1 -> -0.12263993 | J14: ='A -Döviz'!AA146/1000 -> 3653.8965 | K14: =('A -Döviz'!AA146-'A -Döviz'!Z146)/1000 -> -253.49901 | L14: =(J14/(J14-K14))-1 -> -0.064876722 | M14: ='A -Döviz'!AA222/1000 -> 3300.9298 | N14: =('A -Döviz'!AA222-'A -Döviz'!Z222)/1000 -> -552.06812 | O14: =(M14/(M14-N14))-1 -> -0.14328275
C17: bin Avro | D17: Vergi | G17: Operasyonel Nakit | J17: Serbest Nakit | M17: Net Nakit
D18: Gerçekleşme | E18: Bütçe - Gerçekleşme Fark | F18: % Değişim | G18: Gerçekleşme | H18: Bütçe - Gerçekleşme Fark | I18: % Değişim | J18: Gerçekleşme | K18: Bütçe - Gerçekleşme Fark | L18: % Değişim | M18: Gerçekleşme | N18: Bütçe - Gerçekleşme Fark | O18: % Değişim
C19: Toplam | D19: =SUM(D20:D27) -> -341.55929 | E19: =SUM(E20:E27) -> -43.845778 | F19: =(D19/(D19-E19)) -> 1.1472751 | G19: =SUM(G20:G27) -> 10311.75 | H19: =SUM(H20:H27) -> -5682.1969 | I19: =((G19/(G19-H19))-1) -> -0.35527171 | J19: =SUM(J20:J27) -> 9191.7263 | K19: =SUM(K20:K27) -> -5141.0351 | L19: =((J19/(J19-K19))-1) -> -0.35869118 | M19: =SUM(M20:M27) -> -4534.3694 | N19: =SUM(N20:N27) -> -27509.965 | O19: =(M19/(M19-N19))-1 -> -1.1973559
C20: İnci Holding | D20: ='A -Döviz'!AA202/1000 -> -126.40879 | E20: =('A -Döviz'!AA202-'A -Döviz'!Z202)/1000 -> -16.22079 | F20: =-((D20/(D20-E20))-1) -> -0.14721013 | G20: ='A -Döviz'!AA291/1000 -> -322.34966 | H20: =('A -Döviz'!AA291-'A -Döviz'!Z291)/1000 -> -477.1543 | I20: =((G20/(G20-H20))-1) -> -3.0822998 | J20: ='A -Döviz'!AA304/1000 -> -322.34966 | K20: =('A -Döviz'!AA304-'A -Döviz'!Z304)/1000 -> -475.18934 | L20: =((J20/(J20-K20))-1) -> -3.1090706 | M20: ='A -Döviz'!AA265/1000 -> 17091.704 | N20: =('A -Döviz'!AA265-'A -Döviz'!Z265)/1000 -> 7291.21 | O20: =(M20/(M20-N20))-1 -> 0.74396352
C21: ISM | D21: ='A -Döviz'!AA203/1000 -> -20.740769 | E21: =('A -Döviz'!AA203-'A -Döviz'!Z203)/1000 -> -9.1727155 | F21: =-((D21/(D21-E21))-1) -> -0.79293507 | G21: ='A -Döviz'!AA292/1000 -> 182.56356 | H21: =('A -Döviz'!AA292-'A -Döviz'!Z292)/1000 -> -44.509057 | I21: =((G21/(G21-H21))-1) -> -0.19601243 | J21: ='A -Döviz'!AA305/1000 -> 131.81758 | K21: =('A -Döviz'!AA305-'A -Döviz'!Z305)/1000 -> -40.698409 | L21: =((J21/(J21-K21))-1) -> -0.23591095 | M21: ='A -Döviz'!AA266/1000 -> -6388.4993 | N21: =('A -Döviz'!AA266-'A -Döviz'!Z266)/1000 -> -5562.7719 | O21: =-((M21/(M21-N21))-1) -> -6.736814
C22: İncitaş | D22: ='A -Döviz'!AA204/1000 -> 0 | E22: =('A -Döviz'!AA204-'A -Döviz'!Z204)/1000 -> 8.1884116 | F22: =-IFERROR((D22/(D22-E22))-1,0) -> 1 | G22: ='A -Döviz'!AA293/1000 -> 58.366544 | H22: =('A -Döviz'!AA293-'A -Döviz'!Z293)/1000 -> -117.71158 | I22: =((G22/(G22-H22))-1) -> -0.66851905 | J22: ='A -Döviz'!AA306/1000 -> 58.366544 | K22: =('A -Döviz'!AA306-'A -Döviz'!Z306)/1000 -> -117.71158 | L22: =((J22/(J22-K22))-1) -> -0.66851905 | M22: ='A -Döviz'!AA267/1000 -> -178.30217 | N22: =('A -Döviz'!AA267-'A -Döviz'!Z267)/1000 -> 97.4135 | O22: =-((M22/(M22-N22))-1) -> 0.35331144
C23: İnci GS Yuasa | D23: ='A -Döviz'!AA205/1000 -> 0 | E23: =('A -Döviz'!AA205-'A -Döviz'!Z205)/1000 -> 0 | F23: 0 | G23: ='A -Döviz'!AA294/1000 -> 3176.5112 | H23: =('A -Döviz'!AA294-'A -Döviz'!Z294)/1000 -> 2905.8865 | I23: =((G23/(G23-H23))-1) -> 10.737697 | J23: ='A -Döviz'!AA307/1000 -> 2909.0553 | K23: =('A -Döviz'!AA307-'A -Döviz'!Z307)/1000 -> 3254.8766 | L23: =-((J23/(J23-K23))) -> 8.4120194 | M23: ='A -Döviz'!AA268/1000 -> -51044.529 | N23: =('A -Döviz'!AA268-'A -Döviz'!Z268)/1000 -> -9860.7636 | O23: =-((M23/(M23-N23))-1) -> -0.23943327
C24: Yusen İnci Loj. | D24: ='A -Döviz'!AA206/1000 -> 12.510289 | E24: =('A -Döviz'!AA206-'A -Döviz'!Z206)/1000 -> 48.142949 | F24: =-((D24/(D24-E24))-1) -> 1.3510905 | G24: ='A -Döviz'!AA295/1000 -> -182.64657 | H24: =('A -Döviz'!AA295-'A -Döviz'!Z295)/1000 -> -695.67728 | I24: =(G24/(G24-H24))-1 -> -1.3560149 | J24: ='A -Döviz'!AA308/1000 -> -243.77891 | K24: =('A -Döviz'!AA308-'A -Döviz'!Z308)/1000 -> -687.45797 | L24: =(J24/(J24-K24))-1 -> -1.5494488 | M24: ='A -Döviz'!AA269/1000 -> 1603.0792 | N24: =('A -Döviz'!AA269-'A -Döviz'!Z269)/1000 -> -18.032012 | O24: =(M24/(M24-N24))-1 -> -0.011123242
C25: Jantaş | D25: ='A -Döviz'!AA207/1000 -> -373.98408 | E25: =('A -Döviz'!AA207-'A -Döviz'!Z207)/1000 -> 19.208393 | F25: =-((D25/(D25-E25))-1) -> 0.048852392 | G25: ='A -Döviz'!AA296/1000 -> -970.02151 | H25: =('A -Döviz'!AA296-'A -Döviz'!Z296)/1000 -> -4221.8801 | I25: =((G25/(G25-H25))-1) -> -1.2982976 | J25: ='A -Döviz'!AA309/1000 -> -1265.4283 | K25: =('A -Döviz'!AA309-'A -Döviz'!Z309)/1000 -> -4283.0064 | L25: =((J25/(J25-K25))-1) -> -1.4193523 | M25: ='A -Döviz'!AA270/1000 -> 8134.848 | N25: =('A -Döviz'!AA270-'A -Döviz'!Z270)/1000 -> -5129.6927 | O25: =(M25/(M25-N25))-1 -> -0.38672222
C26: Çelik | D26: ='A -Döviz'!AA208/1000 -> -13.92815 | E26: =('A -Döviz'!AA208-'A -Döviz'!Z208)/1000 -> 218.09443 | F26: =-((D26/(D26-E26))-1) -> 0.93997071 | G26: ='A -Döviz'!AA297/1000 -> 4336.1464 | H26: =('A -Döviz'!AA297-'A -Döviz'!Z297)/1000 -> 782.60169 | I26: =((G26/(G26-H26))-1) -> 0.22023127 | J26: ='A -Döviz'!AA310/1000 -> 4086.1464 | K26: =('A -Döviz'!AA310-'A -Döviz'!Z310)/1000 -> 883.60169 | L26: =((J26/(J26-K26))-1) -> 0.27590612 | M26: ='A -Döviz'!AA271/1000 -> 14279.442 | N26: =('A -Döviz'!AA271-'A -Döviz'!Z271)/1000 -> -12626.154 | O26: =(M26/(M26-N26))-1 -> -0.46927614
C27: Alüminyum | D27: ='A -Döviz'!AA209/1000 -> 180.99221 | E27: =('A -Döviz'!AA209-'A -Döviz'!Z209)/1000 -> -312.08646 | F27: =-((D27/(D27-E27))-1) -> 0.63293441 | G27: ='A -Döviz'!AA298/1000 -> 4033.1801 | H27: =('A -Döviz'!AA298-'A -Döviz'!Z298)/1000 -> -3813.7527 | I27: =((G27/(G27-H27))-1) -> -0.48601827 | J27: ='A -Döviz'!AA311/1000 -> 3837.8974 | K27: =('A -Döviz'!AA311-'A -Döviz'!Z311)/1000 -> -3675.4497 | L27: =((J27/(J27-K27))-1) -> -0.4891894 | M27: ='A -Döviz'!AA272/1000 -> 11967.888 | N27: =('A -Döviz'!AA272-'A -Döviz'!Z272)/1000 -> -1701.1734 | O27: =(M27/(M27-N27))-1 -> -0.1244543
D30: Faaliyet Giderleri Marjı | F30: Brüt Kar Marjı | H30: EBITDA Marjı | J30: Net Kar Marjı | L30: Operasyonel Nakit Marjı | N30: Serbest Nakit Marjı
D31: Gerçekleşme | E31: Bütçe - Gerçekleşme Fark | F31: Gerçekleşme | G31: Bütçe - Gerçekleşme Fark | H31: Gerçekleşme | I31: Bütçe - Gerçekleşme Fark | J31: Gerçekleşme | K31: Bütçe - Gerçekleşme Fark | L31: Gerçekleşme | M31: Bütçe - Gerçekleşme Fark | N31: Gerçekleşme | O31: Bütçe - Gerçekleşme Fark
C33: İnci Holding | D33: ='A -Döviz'!AA102 -> 0.3941863 | E33: =-('A -Döviz'!AA102-'A -Döviz'!Z102) -> 0.055169941 | F33: ='A -Döviz'!AA79 -> 1 | G33: ='A -Döviz'!AA79-'A -Döviz'!Z79 -> 0 | H33: ='A -Döviz'!AA150 -> 0.61087749 | I33: ='A -Döviz'!AA150-'A -Döviz'!Z150 -> 0.05540856 | J33: ='A -Döviz'!AA226 -> 0.48006002 | K33: ='A -Döviz'!AA226-'A -Döviz'!Z226 -> 0.10268624 | L33: ='A -Döviz'!AA291/'A -Döviz'!AA9 -> -0.40806019 | M33: =L33-('A -Döviz'!Z291/'A -Döviz'!Z9) -> -0.58478606 | N33: ='A -Döviz'!AA304/'A -Döviz'!AA9 -> -0.40806019 | O33: =N33-'A -Döviz'!Z304/'A -Döviz'!Z9 -> -0.58254285
C34: ISM | D34: ='A -Döviz'!AA103 -> 0.30586298 | E34: =-('A -Döviz'!AA103-'A -Döviz'!Z103) -> -0.085906702 | F34: ='A -Döviz'!AA80 -> 0.22869641 | G34: ='A -Döviz'!AA80-'A -Döviz'!Z80 -> -0.091677749 | H34: ='A -Döviz'!AA151 -> -0.05162431 | I34: ='A -Döviz'!AA151-'A -Döviz'!Z151 -> -0.1836132 | J34: ='A -Döviz'!AA227 -> -0.45200013 | K34: ='A -Döviz'!AA227-'A -Döviz'!Z227 -> -0.52537773 | L34: ='A -Döviz'!AA292/'A -Döviz'!AA10 -> 0.40260924 | M34: =L34-('A -Döviz'!Z292/'A -Döviz'!Z10) -> 0.042521798 | N34: ='A -Döviz'!AA305/'A -Döviz'!AA10 -> 0.29069861 | O34: =N34-'A -Döviz'!Z305/'A -Döviz'!Z10 -> 0.017126042
C35: İncitaş | D35: ='A -Döviz'!AA104 -> 0.12970398 | E35: =-('A -Döviz'!AA104-'A -Döviz'!Z104) -> 0.021042144 | F35: ='A -Döviz'!AA81 -> 0.19124358 | G35: ='A -Döviz'!AA81-'A -Döviz'!Z81 -> -0.012406619 | H35: ='A -Döviz'!AA152 -> 0.062011106 | I35: ='A -Döviz'!AA152-'A -Döviz'!Z152 -> 0.0083185653 | J35: ='A -Döviz'!AA228 -> 0.030519232 | K35: ='A -Döviz'!AA228-'A -Döviz'!Z228 -> 0.013155958 | L35: ='A -Döviz'!AA293/'A -Döviz'!AA11 -> 0.065530704 | M35: =L35-('A -Döviz'!Z293/'A -Döviz'!Z11) -> -0.058925373 | N35: ='A -Döviz'!AA306/'A -Döviz'!AA11 -> 0.065530704 | O35: =N35-'A -Döviz'!Z306/'A -Döviz'!Z11 -> -0.058925373
C36: İnci GS Yuasa | D36: ='A -Döviz'!AA105 -> 0.14794068 | E36: =-('A -Döviz'!AA105-'A -Döviz'!Z105) -> -0.050734338 | F36: ='A -Döviz'!AA82 -> 0.15310162 | G36: ='A -Döviz'!AA82-'A -Döviz'!Z82 -> -0.063425344 | H36: ='A -Döviz'!AA153 -> 0.025496426 | I36: ='A -Döviz'!AA153-'A -Döviz'!Z153 -> -0.10319722 | J36: ='A -Döviz'!AA229 -> -0.22980865 | K36: ='A -Döviz'!AA229-'A -Döviz'!Z229 -> -0.24782317 | L36: ='A -Döviz'!AA294/'A -Döviz'!AA12 -> 0.29520629 | M36: =L36-('A -Döviz'!Z294/'A -Döviz'!Z12) -> 0.28320146 | N36: ='A -Döviz'!AA307/'A -Döviz'!AA12 -> 0.27035051 | O36: =N36-'A -Döviz'!Z307/'A -Döviz'!Z12 -> 0.28569103
C37: Yusen İnci Loj. | D37: ='A -Döviz'!AA106 -> 0.14551814 | E37: =-('A -Döviz'!AA106-'A -Döviz'!Z106) -> 0.01623303 | F37: ='A -Döviz'!AA83 -> 0.21893023 | G37: ='A -Döviz'!AA83-'A -Döviz'!Z83 -> 0.011353625 | H37: ='A -Döviz'!AA154 -> 0.11222067 | I37: ='A -Döviz'!AA154-'A -Döviz'!Z154 -> 0.036258277 | J37: ='A -Döviz'!AA230 -> 0.049395372 | K37: ='A -Döviz'!AA230-'A -Döviz'!Z230 -> 0.036040582 | L37: ='A -Döviz'!AA295/'A -Döviz'!AA13 -> -0.03380062 | M37: =L37-('A -Döviz'!Z295/'A -Döviz'!Z13) -> -0.11990522 | N37: ='A -Döviz'!AA308/'A -Döviz'!AA13 -> -0.045113787 | O37: =N37-'A -Döviz'!Z308/'A -Döviz'!Z13 -> -0.11957874
C38: Jantaş | D38: ='A -Döviz'!AA107 -> 0.050360267 | E38: =-('A -Döviz'!AA107-'A -Döviz'!Z107) -> 0.0050527569 | F38: ='A -Döviz'!AA84 -> 0.25621269 | G38: ='A -Döviz'!AA84-'A -Döviz'!Z84 -> 0.023634856 | H38: ='A -Döviz'!AA155 -> 0.24258236 | I38: ='A -Döviz'!AA155-'A -Döviz'!Z155 -> -0.0044009941 | J38: ='A -Döviz'!AA231 -> 0.17735972 | K38: ='A -Döviz'!AA231-'A -Döviz'!Z231 -> 0.028370784 | L38: ='A -Döviz'!AA296/'A -Döviz'!AA14 -> -0.082103081 | M38: =L38-('A -Döviz'!Z296/'A -Döviz'!Z14) -> -0.31679585 | N38: ='A -Döviz'!AA309/'A -Döviz'!AA14 -> -0.10710645 | O38: =N38-'A -Döviz'!Z309/'A -Döviz'!Z14 -> -0.32489075
C39: Çelik | D39: ='A -Döviz'!AA108 -> 0.054425459 | E39: =-('A -Döviz'!AA108-'A -Döviz'!Z108) -> -0.0021091709 | F39: ='A -Döviz'!AA85 -> 0.35455308 | G39: ='A -Döviz'!AA85-'A -Döviz'!Z85 -> 0.063829023 | H39: ='A -Döviz'!AA156 -> 0.32504802 | I39: ='A -Döviz'!AA156-'A -Döviz'!Z156 -> 0.054837362 | J39: ='A -Döviz'!AA232 -> 0.26966751 | K39: ='A -Döviz'!AA232-'A -Döviz'!Z232 -> 0.061721393 | L39: ='A -Döviz'!AA297/'A -Döviz'!AA15 -> 0.45218279 | M39: =L39-('A -Döviz'!Z297/'A -Döviz'!Z15) -> 0.023728395 | N39: ='A -Döviz'!AA310/'A -Döviz'!AA15 -> 0.42611225 | O39: =N39-'A -Döviz'!Z310/'A -Döviz'!Z15 -> 0.039978267
C40: Alüminyum | D40: ='A -Döviz'!AA109 -> 0.044010085 | E40: =-('A -Döviz'!AA109-'A -Döviz'!Z109) -> 0.0018922525 | F40: ='A -Döviz'!AA86 -> 0.1762859 | G40: ='A -Döviz'!AA86-'A -Döviz'!Z86 -> -0.010144874 | H40: ='A -Döviz'!AA157 -> 0.16252075 | I40: ='A -Döviz'!AA157-'A -Döviz'!Z157 -> 0.001264023 | J40: ='A -Döviz'!AA233 -> 0.14682123 | K40: ='A -Döviz'!AA233-'A -Döviz'!Z233 -> -0.012190526 | L40: ='A -Döviz'!AA298/'A -Döviz'!AA16 -> 0.17939081 | M40: =L40-('A -Döviz'!Z298/'A -Döviz'!Z16) -> -0.14444912 | N40: ='A -Döviz'!AA311/'A -Döviz'!AA16 -> 0.17070487 | O40: =N40-'A -Döviz'!Z311/'A -Döviz'!Z16 -> -0.1393681
D64: Ciro | G64: EBITDA | K64: Net Kar
D65: Gerçekleşme | E65: % | G65: Gerçekleşme | I65: % | K65: Gerçekleşme | M65: %
C66: Ciro | D66: 55 | G66: 55 | K66: 55
C67: Adet | D67: 12 | E67: =D67/$D$66 -> 0.21818182 | G67: 12 | H67: =G67/$D$66 -> 0.21818182 | K67: 12 | M67: =K67/$K$66 -> 0.21818182
C68: Fiyat | D68: 9 | E68: =D68/$D$66 -> 0.16363636 | G68: 9 | H68: =G68/$D$66 -> 0.16363636 | K68: 9 | M68: =K68/$K$66 -> 0.16363636
C69: Miks | D69: 8 | E69: =D69/$D$66 -> 0.14545455 | G69: 8 | H69: =G69/$D$66 -> 0.14545455 | K69: 8 | M69: =K69/$K$66 -> 0.14545455
C70: Ham Madde | D70: 5 | E70: =D70/$D$66 -> 0.090909091 | G70: 5 | H70: =G70/$D$66 -> 0.090909091 | K70: 5 | M70: =K70/$K$66 -> 0.090909091
C71: Enerji | D71: 4 | E71: =D71/$D$66 -> 0.072727273 | G71: 4 | H71: =G71/$D$66 -> 0.072727273 | K71: 4 | M71: =K71/$K$66 -> 0.072727273
C72: Döviz | D72: 3 | E72: =D72/$D$66 -> 0.054545455 | G72: 3 | H72: =G72/$D$66 -> 0.054545455 | K72: 3 | M72: =K72/$K$66 -> 0.054545455
C73: Enflasyon | D73: 3 | E73: =D73/$D$66 -> 0.054545455 | G73: 3 | H73: =G73/$D$66 -> 0.054545455 | K73: 3 | M73: =K73/$K$66 -> 0.054545455

Sheet Finansal Raporlama KÜM
C3: KÜMÜLATİF
C4: bin Avro | D4: Ciro | G4: Brüt Kar | J4: EBITDA | M4: Net Kar
D5: Gerçekleşme | E5: Bütçe - Gerçekleşme Fark | F5: % Değişim | G5: Gerçekleşme | H5: Bütçe - Gerçekleşme Fark | I5: % Değişim | J5: Gerçekleşme | K5: Bütçe - Gerçekleşme Fark | L5: % Değişim | M5: Gerçekleşme | N5: Bütçe - Gerçekleşme Fark | O5: % Değişim
C6: Toplam | D6: =SUM(D7:D14) -> 565671.74 | E6: =SUM(E7:E14) -> -53626.511 | F6: =(D6/(D6-E6))-1 -> -0.086592383 | G6: =SUM(G7:G14) -> 100550.71 | H6: =SUM(H7:H14) -> -16410.107 | I6: =(G6/(G6-H6))-1 -> -0.14030431 | J6: =SUM(J7:J14) -> 66115.062 | K6: =SUM(K7:K14) -> -12763.622 | L6: =(J6/(J6-K6))-1 -> -0.16181332 | M6: =SUM(M7:M14) -> 10077.388 | N6: =SUM(N7:N14) -> -26302.144 | O6: =(M6/(M6-N6))-1 -> -0.72299292
C7: İnci Holding | D7: ='C-Döviz'!AJ9/1000 -> 6530.3115 | E7: =('C-Döviz'!AJ9-'C-Döviz'!Z9)/1000 -> -307.09639 | F7: =(D7/(D7-E7))-1 -> -0.044914154 | G7: =('C-Döviz'!AJ36)/1000 -> 6530.3115 | H7: =('C-Döviz'!AJ36-'C-Döviz'!Z36)/1000 -> -307.09639 | I7: =(G7/(G7-H7))-1 -> -0.044914154 | J7: ='C-Döviz'!AJ139/1000 -> 3039.0888 | K7: =('C-Döviz'!AJ139-'C-Döviz'!Z139)/1000 -> -280.50444 | L7: =(J7/(J7-K7))-1 -> -0.084499641 | M7: ='C-Döviz'!AJ215/1000 -> 2668.6618 | N7: =('C-Döviz'!AJ215-'C-Döviz'!Z215)/1000 -> 534.82385 | O7: =(M7/(M7-N7))-1 -> 0.2506394
C8: ISM | D8: ='C-Döviz'!AJ10/1000 -> 5967.9349 | E8: =('C-Döviz'!AJ10-'C-Döviz'!Z10)/1000 -> -1976.3017 | F8: =(D8/(D8-E8))-1 -> -0.24877176 | G8: =('C-Döviz'!AJ37)/1000 -> 1401.8845 | H8: =('C-Döviz'!AJ37-'C-Döviz'!Z37)/1000 -> -991.12984 | I8: =(G8/(G8-H8))-1 -> -0.41417631 | J8: ='C-Döviz'!AJ140/1000 -> 221.6865 | K8: =('C-Döviz'!AJ140-'C-Döviz'!Z140)/1000 -> -912.01891 | L8: =(J8/(J8-K8))-1 -> -0.80445846 | M8: ='C-Döviz'!AJ216/1000 -> -1015.0345 | N8: =('C-Döviz'!AJ216-'C-Döviz'!Z216)/1000 -> -1756.8359 | O8: =(M8/(M8-N8))-1 -> -2.3683372
C9: İncitaş | D9: ='C-Döviz'!AJ11/1000 -> 9087.7867 | E9: =('C-Döviz'!AJ11-'C-Döviz'!Z11)/1000 -> -3066.7795 | F9: =(D9/(D9-E9))-1 -> -0.25231501 | G9: =('C-Döviz'!AJ38)/1000 -> 1427.8488 | H9: =('C-Döviz'!AJ38-'C-Döviz'!Z38)/1000 -> -893.61152 | I9: =(G9/(G9-H9))-1 -> -0.38493509 | J9: ='C-Döviz'!AJ141/1000 -> 255.55944 | K9: =('C-Döviz'!AJ141-'C-Döviz'!Z141)/1000 -> -319.03575 | L9: =((J9/(J9-K9))-1) -> -0.55523567 | M9: ='C-Döviz'!AJ217/1000 -> -98.697156 | N9: =('C-Döviz'!AJ217-'C-Döviz'!Z217)/1000 -> -159.90088 | O9: =-((M9/(M9-N9))-1) -> 2.6126006
C10: İnci GS Yuasa | D10: ='C-Döviz'!AJ12/1000 -> 126030.1 | E10: =('C-Döviz'!AJ12-'C-Döviz'!Z12)/1000 -> -55175.93 | F10: =(D10/(D10-E10))-1 -> -0.30449279 | G10: =('C-Döviz'!AJ39)/1000 -> 17075.643 | H10: =('C-Döviz'!AJ39-'C-Döviz'!Z39)/1000 -> -17409.143 | I10: =(G10/(G10-H10))-1 -> -0.50483547 | J10: ='C-Döviz'!AJ142/1000 -> 1489.7818 | K10: =('C-Döviz'!AJ142-'C-Döviz'!Z142)/1000 -> -15242.45 | L10: =(J10/(J10-K10))-1 -> -0.91096335 | M10: ='C-Döviz'!AJ218/1000 -> -26215.785 | N10: =('C-Döviz'!AJ218-'C-Döviz'!Z218)/1000 -> -21897.37 | O10: =-((M10/(M10-N10))-1) -> -5.0706956
C11: Yusen İnci Loj. | D11: ='C-Döviz'!AJ13/1000 -> 48487.948 | E11: =('C-Döviz'!AJ13-'C-Döviz'!Z13)/1000 -> -9889.4305 | F11: =(D11/(D11-E11))-1 -> -0.16940518 | G11: =('C-Döviz'!AJ40)/1000 -> 10273.605 | H11: =('C-Döviz'!AJ40-'C-Döviz'!Z40)/1000 -> -896.69385 | I11: =(G11/(G11-H11))-1 -> -0.080274827 | J11: ='C-Döviz'!AJ143/1000 -> 3826.3729 | K11: =('C-Döviz'!AJ143-'C-Döviz'!Z143)/1000 -> 17.779218 | L11: =(J11/(J11-K11))-1 -> 0.0046681845 | M11: ='C-Döviz'!AJ219/1000 -> 1259.3685 | N11: =('C-Döviz'!AJ219-'C-Döviz'!Z219)/1000 -> 557.4965 | O11: =(M11/(M11-N11))-1 -> 0.79429938
C12: Jantaş | D12: ='C-Döviz'!AJ14/1000 -> 104950.21 | E12: =('C-Döviz'!AJ14-'C-Döviz'!Z14)/1000 -> 4362.6068 | F12: =(D12/(D12-E12))-1 -> 0.043371218 | G12: =('C-Döviz'!AJ41)/1000 -> 19353.674 | H12: =('C-Döviz'!AJ41-'C-Döviz'!Z41)/1000 -> 3068.7376 | I12: =(G12/(G12-H12))-1 -> 0.18844025 | J12: ='C-Döviz'!AJ144/1000 -> 17008.492 | K12: =('C-Döviz'!AJ144-'C-Döviz'!Z144)/1000 -> 1717.3841 | L12: =(J12/(J12-K12))-1 -> 0.1123126 | M12: ='C-Döviz'!AJ220/1000 -> 9649.5204 | N12: =('C-Döviz'!AJ220-'C-Döviz'!Z220)/1000 -> 2143.7248 | O12: =(M12/(M12-N12))-1 -> 0.28560927
C13: Çelik | D13: ='C-Döviz'!AJ15/1000 -> 73735.729 | E13: =('C-Döviz'!AJ15-'C-Döviz'!Z15)/1000 -> 8549.5681 | F13: =(D13/(D13-E13))-1 -> 0.13115618 | G13: =('C-Döviz'!AJ42)/1000 -> 21124.56 | H13: =('C-Döviz'!AJ42-'C-Döviz'!Z42)/1000 -> 4880.7707 | I13: =(G13/(G13-H13))-1 -> 0.30046996 | J13: ='C-Döviz'!AJ145/1000 -> 19272.518 | K13: =('C-Döviz'!AJ145-'C-Döviz'!Z145)/1000 -> 4320.8874 | L13: =(J13/(J13-K13))-1 -> 0.28899106 | M13: ='C-Döviz'!AJ221/1000 -> 11051.709 | N13: =('C-Döviz'!AJ221-'C-Döviz'!Z221)/1000 -> 134.63149 | O13: =(M13/(M13-N13))-1 -> 0.012332191
C14: Alüminyum | D14: ='C-Döviz'!AJ16/1000 -> 190881.72 | E14: =('C-Döviz'!AJ16-'C-Döviz'!Z16)/1000 -> 3876.8525 | F14: =(D14/(D14-E14))-1 -> 0.020731292 | G14: =('C-Döviz'!AJ43)/1000 -> 23363.186 | H14: =('C-Döviz'!AJ43-'C-Döviz'!Z43)/1000 -> -3861.941 | I14: =(G14/(G14-H14))-1 -> -0.14185208 | J14: ='C-Döviz'!AJ146/1000 -> 21001.563 | K14: =('C-Döviz'!AJ146-'C-Döviz'!Z146)/1000 -> -2065.6638 | L14: =(J14/(J14-K14))-1 -> -0.089549723 | M14: ='C-Döviz'!AJ222/1000 -> 12777.644 | N14: =('C-Döviz'!AJ222-'C-Döviz'!Z222)/1000 -> -5858.7137 | O14: =(M14/(M14-N14))-1 -> -0.3143701
C17: bin Avro | D17: Vergi | G17: Operasyonel Nakit | J17: Serbest Nakit | M17: Net Nakit
D18: Gerçekleşme | E18: Bütçe - Gerçekleşme Fark | F18: % Değişim | G18: Gerçekleşme | H18: Bütçe - Gerçekleşme Fark | I18: % Değişim | J18: Gerçekleşme | K18: Bütçe - Gerçekleşme Fark | L18: % Değişim | M18: Gerçekleşme | N18: Bütçe - Gerçekleşme Fark | O18: % Değişim
C19: Toplam | D19: =SUM(D20:D27) -> -5919.2195 | E19: =SUM(E20:E27) -> -1944.4595 | F19: =(D19/(D19-E19))-1 -> 0.48920175 | G19: =SUM(G20:G27) -> 47522.539 | H19: =SUM(H20:H27) -> -14203.586 | I19: =((G19/(G19-H19))-1) -> -0.23010656 | J19: =SUM(J20:J27) -> 29480.781 | K19: =SUM(K20:K27) -> -19942.768 | L19: =((J19/(J19-K19))-1) -> -0.4035074 | M19: =SUM(M20:M27) -> -4534.3694 | N19: =SUM(N20:N27) -> -27509.965 | O19: =(M19/(M19-N19))-1 -> -1.1973559
C20: İnci Holding | D20: ='C-Döviz'!AJ202/1000 -> -889.55392 | E20: =('C-Döviz'!AJ202-'C-Döviz'!Z202)/1000 -> -178.27462 | F20: =-((D20/(D20-E20))-1) -> -0.2506394 | G20: ='C-Döviz'!AJ291/1000 -> 2331.0995 | H20: =('C-Döviz'!AA291-'C-Döviz'!Z291)/1000 -> -832.21314 | I20: =(G20/(G20-H20))-1 -> -0.2630828 | J20: ='C-Döviz'!AJ304/1000 -> 2323.5545 | K20: =('C-Döviz'!AA304-'C-Döviz'!Z304)/1000 -> -827.10136 | L20: =(J20/(J20-K20))-1 -> -0.26251721 | M20: ='C-Döviz'!AA265/1000 -> 17091.704 | N20: =M20-'C-Döviz'!Z265/1000 -> 7291.21 | O20: =(M20/(M20-N20))-1 -> 0.74396352
C21: ISM | D21: ='C-Döviz'!AJ203/1000 -> -34.619311 | E21: =('C-Döviz'!AJ203-'C-Döviz'!Z203)/1000 -> 150.83105 | F21: =-((D21/(D21-E21))-1) -> 0.81332304 | G21: ='C-Döviz'!AJ292/1000 -> 94.449464 | H21: =('C-Döviz'!AA292-'C-Döviz'!Z292)/1000 -> -989.0497 | I21: =((G21/(G21-H21))-1) -> -0.91282922 | J21: ='C-Döviz'!AJ305/1000 -> -435.0404 | K21: =('C-Döviz'!AA305-'C-Döviz'!Z305)/1000 -> -939.99587 | L21: =((J21/(J21-K21))-1) -> -1.8615421 | M21: ='C-Döviz'!AA266/1000 -> -6388.4993 | N21: =M21-'C-Döviz'!Z266/1000 -> -5562.7719 | O21: =-((M21/(M21-N21))-1) -> -6.736814
C22: İncitaş | D22: ='C-Döviz'!AJ204/1000 -> -0.0082083884 | E22: =('C-Döviz'!AJ204-'C-Döviz'!Z204)/1000 -> 70.301711 | F22: =-((D22/(D22-E22))-1) -> 0.99988325 | G22: ='C-Döviz'!AJ293/1000 -> 123.07484 | H22: =('C-Döviz'!AA293-'C-Döviz'!Z293)/1000 -> 342.95738 | I22: =-((G22/(G22-H22))-1) -> 1.5597299 | J22: ='C-Döviz'!AJ306/1000 -> 123.07484 | K22: =('C-Döviz'!AA306-'C-Döviz'!Z306)/1000 -> 342.95738 | L22: =-((J22/(J22-K22))-1) -> 1.5597299 | M22: ='C-Döviz'!AA267/1000 -> -178.30217 | N22: =M22-'C-Döviz'!Z267/1000 -> 97.4135 | O22: =-((M22/(M22-N22))-1) -> 0.35331144
C23: İnci GS Yuasa | D23: ='C-Döviz'!AJ205/1000 -> 0 | E23: =('C-Döviz'!AJ205-'C-Döviz'!Z205)/1000 -> 0 | F23: 0 | G23: ='C-Döviz'!AJ294/1000 -> 2616.4004 | H23: =('C-Döviz'!AA294-'C-Döviz'!Z294)/1000 -> -6284.2839 | I23: =((G23/(G23-H23))-1) -> -0.70604503 | J23: ='C-Döviz'!AJ307/1000 -> 1189.1052 | K23: =('C-Döviz'!AA307-'C-Döviz'!Z307)/1000 -> -3766.2794 | L23: =((J23/(J23-K23))-1) -> -0.76003776 | M23: ='C-Döviz'!AA268/1000 -> -51044.529 | N23: =M23-'C-Döviz'!Z268/1000 -> -9860.7636 | O23: =-(M23/(M23-N23))-1 -> -2.2394333
C24: Yusen İnci Loj. | D24: ='C-Döviz'!AJ206/1000 -> -208.38717 | E24: =('C-Döviz'!AJ206-'C-Döviz'!Z206)/1000 -> 141.40323 | F24: =-((D24/(D24-E24))-1) -> 0.40425132 | G24: ='C-Döviz'!AJ295/1000 -> 5080.0747 | H24: =('C-Döviz'!AA295-'C-Döviz'!Z295)/1000 -> 1055.3634 | I24: =((G24/(G24-H24))-1) -> 0.2622209 | J24: ='C-Döviz'!AJ308/1000 -> 3913.7512 | K24: =('C-Döviz'!AA308-'C-Döviz'!Z308)/1000 -> 580.96511 | L24: =(J24/(J24-K24))-1 -> 0.17431815 | M24: ='C-Döviz'!AA269/1000 -> 1603.0792 | N24: =M24-'C-Döviz'!Z269/1000 -> -18.032012 | O24: =(M24/(M24-N24))-1 -> -0.011123242
C25: Jantaş | D25: ='C-Döviz'!AJ207/1000 -> -3042.0139 | E25: =('C-Döviz'!AJ207-'C-Döviz'!Z207)/1000 -> -940.15931 | F25: =-((D25/(D25-E25))-1) -> -0.44729989 | G25: ='C-Döviz'!AJ296/1000 -> 8127.2592 | H25: =('C-Döviz'!AA296-'C-Döviz'!Z296)/1000 -> 557.90043 | I25: =((G25/(G25-H25))-1) -> 0.073705111 | J25: ='C-Döviz'!AJ309/1000 -> 5514.5208 | K25: =('C-Döviz'!AA309-'C-Döviz'!Z309)/1000 -> 71.783698 | L25: =((J25/(J25-K25))-1) -> 0.013188897 | M25: ='C-Döviz'!AA270/1000 -> 8134.848 | N25: =M25-'C-Döviz'!Z270/1000 -> -5129.6927 | O25: =(M25/(M25-N25))-1 -> -0.38672222
C26: Çelik | D26: ='C-Döviz'!AJ208/1000 -> -682.53347 | E26: =('C-Döviz'!AJ208-'C-Döviz'!Z208)/1000 -> 744.45732 | F26: =-((D26/(D26-E26))-1) -> 0.52169735 | G26: ='C-Döviz'!AJ297/1000 -> 15566.602 | H26: =('C-Döviz'!AA297-'C-Döviz'!Z297)/1000 -> -5315.8855 | I26: =((G26/(G26-H26))-1) -> -0.25456189 | J26: ='C-Döviz'!AJ310/1000 -> 5389.8133 | K26: =('C-Döviz'!AA310-'C-Döviz'!Z310)/1000 -> -12664.674 | L26: =(J26/(J26-K26))-1 -> -0.7014696 | M26: ='C-Döviz'!AA271/1000 -> 14279.442 | N26: =M26-'C-Döviz'!Z271/1000 -> -12626.154 | O26: =(M26/(M26-N26))-1 -> -0.46927614
C27: Alüminyum | D27: ='C-Döviz'!AJ209/1000 -> -1062.1036 | E27: =('C-Döviz'!AJ209-'C-Döviz'!Z209)/1000 -> -1933.0189 | F27: =((D27/(D27-E27))-1) -> -2.2195256 | G27: ='C-Döviz'!AJ298/1000 -> 13583.578 | H27: =('C-Döviz'!AA298-'C-Döviz'!Z298)/1000 -> -2738.3749 | I27: =((G27/(G27-H27))-1) -> -0.1677725 | J27: ='C-Döviz'!AJ311/1000 -> 11462.002 | K27: =('C-Döviz'!AA311-'C-Döviz'!Z311)/1000 -> -2740.423 | L27: =((J27/(J27-K27))-1) -> -0.19295458 | M27: ='C-Döviz'!AA272/1000 -> 11967.888 | N27: =M27-'C-Döviz'!Z272/1000 -> -1701.1734 | O27: =(M27/(M27-N27))-1 -> -0.1244543
D30: Faaliyet Giderleri Marjı | F30: Brüt Kar Marjı | H30: EBITDA Marjı | J30: Net Kar Marjı | L30: Operasyonel Nakit Marjı | N30: Serbest Nakit Marjı
D31: Gerçekleşme | E31: Bütçe - Gerçekleşme Fark | F31: Gerçekleşme | G31: Bütçe - Gerçekleşme Fark | H31: Gerçekleşme | I31: Bütçe - Gerçekleşme Fark | J31: Gerçekleşme | K31: Bütçe - Gerçekleşme Fark | L31: Gerçekleşme | M31: Bütçe - Gerçekleşme Fark | N31: Gerçekleşme | O31: Bütçe - Gerçekleşme Fark
C33: İnci Holding | D33: ='C-Döviz'!AJ102 -> 0.54096706 | E33: =-('C-Döviz'!AA102-'C-Döviz'!Z102) -> -0.020469784 | F33: ='C-Döviz'!AJ79 -> 1 | G33: ='C-Döviz'!AA79-'C-Döviz'!Z79 -> 0 | H33: ='C-Döviz'!AJ150 -> 0.46538191 | I33: ='C-Döviz'!AA150-'C-Döviz'!Z150 -> -0.020122734 | J33: ='C-Döviz'!AJ226 -> 0.40865765 | K33: ='C-Döviz'!AA226-'C-Döviz'!Z226 -> 0.096574776 | L33: ='C-Döviz'!AJ291/'C-Döviz'!AJ9 -> 0.35696605 | M33: =L33-('C-Döviz'!Z291/'C-Döviz'!Z9) -> -0.10568188 | N33: ='C-Döviz'!AJ304/'C-Döviz'!AJ9 -> 0.35581066 | O33: =N33-('C-Döviz'!Z304/'C-Döviz'!Z9) -> -0.10498616
C34: ISM | D34: ='C-Döviz'!AJ103 -> 0.21691081 | E34: =-('C-Döviz'!AA103-'C-Döviz'!Z103) -> -0.03860526 | F34: ='C-Döviz'!AJ80 -> 0.23490277 | G34: ='C-Döviz'!AA80-'C-Döviz'!Z80 -> -0.066323691 | H34: ='C-Döviz'!AJ151 -> 0.037146267 | I34: ='C-Döviz'!AA151-'C-Döviz'!Z151 -> -0.10556164 | J34: ='C-Döviz'!AJ227 -> -0.17008136 | K34: ='C-Döviz'!AA227-'C-Döviz'!Z227 -> -0.26345741 | L34: ='C-Döviz'!AJ292/'C-Döviz'!AJ10 -> 0.015826155 | M34: =L34-('C-Döviz'!Z292/'C-Döviz'!Z10) -> -0.12056192 | N34: ='C-Döviz'!AJ305/'C-Döviz'!AJ10 -> -0.072896305 | O34: =N34-('C-Döviz'!Z305/'C-Döviz'!Z10) -> -0.1364588
C35: İncitaş | D35: ='C-Döviz'!AJ104 -> 0.12959812 | E35: =-('C-Döviz'!AA104-'C-Döviz'!Z104) -> 0.015013858 | F35: ='C-Döviz'!AJ81 -> 0.15711733 | G35: ='C-Döviz'!AA81-'C-Döviz'!Z81 -> -0.033877582 | H35: ='C-Döviz'!AJ152 -> 0.028121197 | I35: ='C-Döviz'!AA152-'C-Döviz'!Z152 -> -0.019152821 | J35: ='C-Döviz'!AJ228 -> -0.010860417 | K35: ='C-Döviz'!AA228-'C-Döviz'!Z228 -> -0.015895868 | L35: ='C-Döviz'!AJ293/'C-Döviz'!AJ11 -> 0.013542884 | M35: =L35-('C-Döviz'!Z293/'C-Döviz'!Z11) -> 0.031633413 | N35: ='C-Döviz'!AJ306/'C-Döviz'!AJ11 -> 0.013542884 | O35: =N35-('C-Döviz'!Z306/'C-Döviz'!Z11) -> 0.031633413
C36: İnci GS Yuasa | D36: ='C-Döviz'!AJ105 -> 0.13792311 | E36: =-('C-Döviz'!AA105-'C-Döviz'!Z105) -> -0.028646533 | F36: ='C-Döviz'!AJ82 -> 0.13548861 | G36: ='C-Döviz'!AA82-'C-Döviz'!Z82 -> -0.054818446 | H36: ='C-Döviz'!AJ153 -> 0.011820841 | I36: ='C-Döviz'!AA153-'C-Döviz'!Z153 -> -0.080517319 | J36: ='C-Döviz'!AJ229 -> -0.20801209 | K36: ='C-Döviz'!AA229-'C-Döviz'!Z229 -> -0.18418057 | L36: ='C-Döviz'!AJ294/'C-Döviz'!AJ12 -> 0.020760123 | M36: =L36-('C-Döviz'!Z294/'C-Döviz'!Z12) -> -0.028359016 | N36: ='C-Döviz'!AJ307/'C-Döviz'!AJ12 -> 0.0094350887 | O36: =N36-('C-Döviz'!Z307/'C-Döviz'!Z12) -> -0.017911598
C37: Yusen İnci Loj. | D37: ='C-Döviz'!AJ106 -> 0.16812818 | E37: =-('C-Döviz'!AA106-'C-Döviz'!Z106) -> -0.018282497 | F37: ='C-Döviz'!AJ83 -> 0.21187957 | G37: ='C-Döviz'!AA83-'C-Döviz'!Z83 -> 0.0205332 | H37: ='C-Döviz'!AJ154 -> 0.078913895 | I37: ='C-Döviz'!AA154-'C-Döviz'!Z154 -> 0.013672979 | J37: ='C-Döviz'!AJ230 -> 0.025972815 | K37: ='C-Döviz'!AA230-'C-Döviz'!Z230 -> 0.013949802 | L37: ='C-Döviz'!AJ295/'C-Döviz'!AJ13 -> 0.10476984 | M37: =L37-('C-Döviz'!Z295/'C-Döviz'!Z13) -> 0.035826848 | N37: ='C-Döviz'!AJ308/'C-Döviz'!AJ13 -> 0.080715957 | O37: =N37-('C-Döviz'!Z308/'C-Döviz'!Z13) -> 0.023625589
C38: Jantaş | D38: ='C-Döviz'!AJ107 -> 0.05982241 | E38: =-('C-Döviz'!AA107-'C-Döviz'!Z107) -> 0.0047564489 | F38: ='C-Döviz'!AJ84 -> 0.18440815 | G38: ='C-Döviz'!AA84-'C-Döviz'!Z84 -> 0.022510104 | H38: ='C-Döviz'!AJ155 -> 0.16206249 | I38: ='C-Döviz'!AA155-'C-Döviz'!Z155 -> 0.01004467 | J38: ='C-Döviz'!AJ231 -> 0.091943795 | K38: ='C-Döviz'!AA231-'C-Döviz'!Z231 -> 0.017324304 | L38: ='C-Döviz'!AJ296/'C-Döviz'!AJ14 -> 0.077439191 | M38: =L38-('C-Döviz'!Z296/'C-Döviz'!Z14) -> 0.0021877815 | N38: ='C-Döviz'!AJ309/'C-Döviz'!AJ14 -> 0.052544162 | O38: =N38-('C-Döviz'!Z309/'C-Döviz'!Z14) -> -0.0015652607
C39: Çelik | D39: ='C-Döviz'!AJ108 -> 0.055100064 | E39: =-('C-Döviz'!AA108-'C-Döviz'!Z108) -> 0.00078124024 | F39: ='C-Döviz'!AJ85 -> 0.28649015 | G39: ='C-Döviz'!AA85-'C-Döviz'!Z85 -> 0.037299385 | H39: ='C-Döviz'!AJ156 -> 0.26137285 | I39: ='C-Döviz'!AA156-'C-Döviz'!Z156 -> 0.032004684 | J39: ='C-Döviz'!AJ232 -> 0.14988269 | K39: ='C-Döviz'!AA232-'C-Döviz'!Z232 -> -0.017592703 | L39: ='C-Döviz'!AJ297/'C-Döviz'!AJ15 -> 0.21111342 | M39: =L39-('C-Döviz'!Z297/'C-Döviz'!Z15) -> -0.10923813 | N39: ='C-Döviz'!AJ310/'C-Döviz'!AJ15 -> 0.073096359 | O39: =N39-('C-Döviz'!Z310/'C-Döviz'!Z15) -> -0.20387175
C40: Alüminyum | D40: ='C-Döviz'!AJ109 -> 0.04641657 | E40: =-('C-Döviz'!AA109-'C-Döviz'!Z109) -> 0.0019927702 | F40: ='C-Döviz'!AJ86 -> 0.12239614 | G40: ='C-Döviz'!AA86-'C-Döviz'!Z86 -> -0.023188984 | H40: ='C-Döviz'!AJ157 -> 0.11002396 | I40: ='C-Döviz'!AA157-'C-Döviz'!Z157 -> -0.013326982 | J40: ='C-Döviz'!AJ233 -> 0.066940115 | K40: ='C-Döviz'!AA233-'C-Döviz'!Z233 -> -0.03271696 | L40: ='C-Döviz'!AJ298/'C-Döviz'!AJ16 -> 0.071162282 | M40: =L40-('C-Döviz'!Z298/'C-Döviz'!Z16) -> -0.016118621 | N40: ='C-Döviz'!AJ311/'C-Döviz'!AJ16 -> 0.060047668 | O40: =N40-('C-Döviz'!Z311/'C-Döviz'!Z16) -> -0.015899153
D64: Ciro | G64: EBITDA | K64: Net Kar
D65: Gerçekleşme | E65: % | G65: Gerçekleşme | I65: % | K65: Gerçekleşme | M65: %
C66: Ciro | D66: 55 | G66: 55 | K66: 55
C67: Adet | D67: 12 | E67: =D67/$D$66 -> 0.21818182 | G67: 12 | H67: =G67/$D$66 -> 0.21818182 | K67: 12 | M67: =K67/$K$66 -> 0.21818182
C68: Fiyat | D68: 9 | E68: =D68/$D$66 -> 0.16363636 | G68: 9 | H68: =G68/$D$66 -> 0.16363636 | K68: 9 | M68: =K68/$K$66 -> 0.16363636
C69: Miks | D69: 8 | E69: =D69/$D$66 -> 0.14545455 | G69: 8 | H69: =G69/$D$66 -> 0.14545455 | K69: 8 | M69: =K69/$K$66 -> 0.14545455
C70: Ham Madde | D70: 5 | E70: =D70/$D$66 -> 0.090909091 | G70: 5 | H70: =G70/$D$66 -> 0.090909091 | K70: 5 | M70: =K70/$K$66 -> 0.090909091
C71: Enerji | D71: 4 | E71: =D71/$D$66 -> 0.072727273 | G71: 4 | H71: =G71/$D$66 -> 0.072727273 | K71: 4 | M71: =K71/$K$66 -> 0.072727273
C72: Döviz | D72: 3 | E72: =D72/$D$66 -> 0.054545455 | G72: 3 | H72: =G72/$D$66 -> 0.054545455 | K72: 3 | M72: =K72/$K$66 -> 0.054545455
C73: Enflasyon | D73: 3 | E73: =D73/$D$66 -> 0.054545455 | G73: 3 | H73: =G73/$D$66 -> 0.054545455 | K73: 3 | M73: =K73/$K$66 -> 0.054545455

Sheet Finansal Raporlama Tahmin
C3: KÜMÜLATİF | D3: Ciro | I3: Brüt Kar | N3: EBITDA | S3: Net Kar
C4: bin Avro
D5: Temmuz Tahmin | E5: Ağustos Tahmin | F5: Eylül Tahmin | G5: Bütçe - Tahmin Fark | H5: % Değişim | I5: Temmuz Tahmin | J5: Ağustos Tahmin | K5: Eylül Tahmin | L5: Bütçe - Tahmin Fark | M5: % Değişim | N5: Temmuz Tahmin | O5: Ağustos Tahmin | P5: Eylül Tahmin | Q5: Bütçe - Tahmin Fark | R5: % Değişim | S5: Temmuz Tahmin | T5: Ağustos Tahmin | U5: Eylül Tahmin | V5: Bütçe - Tahmin Fark | W5: % Değişim
C6: Toplam | D6: =SUM(D7:D14) -> 776064.95 | E6: =SUM(E7:E14) -> 757192.3 | F6: =SUM(F7:F14) -> 754778.04 | G6: =SUM(G7:G14) -> -85366.678 | H6: =(F6/(F6-G6))-1 -> -0.10160949 | I6: =SUM(I7:I14) -> 151507.62 | J6: =SUM(J7:J14) -> 145586.15 | K6: =SUM(K7:K14) -> 142940.28 | L6: =SUM(L7:L14) -> -20993.178 | M6: =(K6/(K6-L6))-1 -> -0.12805914 | N6: =SUM(N7:N14) -> 106038.39 | O6: =SUM(O7:O14) -> 100861.3 | P6: =SUM(P7:P14) -> 98351.624 | Q6: =SUM(Q7:Q14) -> -14514.79 | R6: =(P6/(P6-Q6))-1 -> -0.12860149 | S6: =SUM(S7:S14) -> 30465.031 | T6: =SUM(T7:T14) -> 22244.032 | U6: =SUM(U7:U14) -> 19292.456 | V6: =SUM(V7:V14) -> -33324.727 | W6: =(U6/(U6-V6))-1 -> -0.63334304
C7: İnci Holding | D7: ='Tahmin Data'!O4/1000 -> 8537.105 | E7: ='Tahmin Data'!Q4/1000 -> 8329.6736 | F7: ='Tahmin Data'!S4/1000 -> 8347.1112 | G7: =F7-'C-Döviz'!AI9/1000 -> -886.13971 | H7: =(F7/(F7-G7))-1 -> -0.095972666 | I7: ='Tahmin Data'!O20/1000 -> 8537.105 | J7: ='Tahmin Data'!Q20/1000 -> 8329.6736 | K7: ='Tahmin Data'!S20/1000 -> 8347.1112 | L7: =K7-'C-Döviz'!AI36/1000 -> -886.13971 | M7: =(K7/(K7-L7))-1 -> -0.095972666 | N7: ='Tahmin Data'!M60/1000 -> 3415.0849 | O7: ='Tahmin Data'!Q60/1000 -> 3225.6411 | P7: ='Tahmin Data'!S60/1000 -> 3247.08 | Q7: =P7-'C-Döviz'!AI139/1000 -> -692.67236 | R7: =(P7/(P7-Q7))-1 -> -0.17581622 | S7: ='Tahmin Data'!O100/1000 -> 3519.337 | T7: ='Tahmin Data'!Q100/1000 -> 3099.383 | U7: ='Tahmin Data'!S100/1000 -> 2980.6565 | V7: =U7-'C-Döviz'!AI215/1000 -> 434.52102 | W7: =(U7/(U7-V7))-1 -> 0.17065903
C8: ISM | D8: ='Tahmin Data'!O6/1000 -> 8341.0386 | E8: ='Tahmin Data'!Q6/1000 -> 7796.0768 | F8: ='Tahmin Data'!S6/1000 -> 7507.5363 | G8: =F8-'C-Döviz'!AI10/1000 -> -1892.1519 | H8: =(F8/(F8-G8))-1 -> -0.20129944 | I8: ='Tahmin Data'!O22/1000 -> 2061.7774 | J8: ='Tahmin Data'!Q22/1000 -> 1933.6858 | K8: ='Tahmin Data'!S22/1000 -> 1728.7069 | L8: =K8-'C-Döviz'!AI37/1000 -> -1010.888 | M8: =(K8/(K8-L8))-1 -> -0.36899178 | N8: ='Tahmin Data'!O62/1000 -> 596.76644 | O8: ='Tahmin Data'!Q62/1000 -> 490.55285 | P8: ='Tahmin Data'!S62/1000 -> 263.00679 | Q8: =P8-'C-Döviz'!AI140/1000 -> -888.05446 | R8: =(P8/(P8-Q8))-1 -> -0.7715093 | S8: ='Tahmin Data'!O102/1000 -> -1203.5408 | T8: ='Tahmin Data'!Q102/1000 -> -1440.0033 | U8: ='Tahmin Data'!S102/1000 -> -1708.7459 | V8: =U8-'C-Döviz'!AI216/1000 -> -2413.2673 | W8: =(U8/(U8-V8))-1 -> -3.4253995
C9: İncitaş | D9: ='Tahmin Data'!O5/1000 -> 13327.053 | E9: ='Tahmin Data'!Q5/1000 -> 12990.151 | F9: ='Tahmin Data'!S5/1000 -> 12844.341 | G9: =F9-'C-Döviz'!AI11/1000 -> -3977.701 | H9: =(F9/(F9-G9))-1 -> -0.23645767 | I9: ='Tahmin Data'!O21/1000 -> 2151.0436 | J9: ='Tahmin Data'!Q21/1000 -> 2081.2902 | K9: ='Tahmin Data'!S21/1000 -> 2050.8149 | L9: =K9-'C-Döviz'!AI38/1000 -> -1120.6245 | M9: =(K9/(K9-L9))-1 -> -0.35334886 | N9: ='Tahmin Data'!O61/1000 -> 455.3784 | O9: ='Tahmin Data'!Q61/1000 -> 488.72535 | P9: ='Tahmin Data'!S61/1000 -> 473.82975 | Q9: =P9-'C-Döviz'!AI141/1000 -> -358.03084 | R9: =(P9/(P9-Q9))-1 -> -0.43039764 | S9: ='Tahmin Data'!O101/1000 -> -2.7123575 | T9: ='Tahmin Data'!Q101/1000 -> 10.980641 | U9: ='Tahmin Data'!S101/1000 -> 10.583732 | V9: =U9-'C-Döviz'!AI217/1000 -> -146.65484 | W9: =(U9/(U9-V9))-1 -> -0.93268997
C10: İnci GS Yuasa | D10: ='Tahmin Data'!O3/1000 -> 188623.17 | E10: ='Tahmin Data'!Q3/1000 -> 179530.45 | F10: ='Tahmin Data'!S3/1000 -> 175031.2 | G10: =F10-'C-Döviz'!AI12/1000 -> -83460.79 | H10: =(F10/(F10-G10))-1 -> -0.32287573 | I10: ='Tahmin Data'!O19/1000 -> 30932.748 | J10: ='Tahmin Data'!Q19/1000 -> 29215.74 | K10: ='Tahmin Data'!S19/1000 -> 26026.066 | L10: =K10-'C-Döviz'!AI39/1000 -> -26247.099 | M10: =(K10/(K10-L10))-1 -> -0.50211422 | N10: ='Tahmin Data'!O59/1000 -> 10575.876 | O10: ='Tahmin Data'!Q59/1000 -> 9274.5209 | P10: ='Tahmin Data'!S59/1000 -> 6204.1748 | Q10: =P10-'C-Döviz'!AI142/1000 -> -22169.826 | R10: =(P10/(P10-Q10))-1 -> -0.78134297 | S10: ='Tahmin Data'!O99/1000 -> -26431.22 | T10: ='Tahmin Data'!Q99/1000 -> -26769.172 | U10: ='Tahmin Data'!S99/1000 -> -29355.248 | V10: =U10-'C-Döviz'!AI218/1000 -> -29801.069 | W10: =(U10/(U10-V10))-1 -> -66.845311
C11: Yusen İnci Loj. | D11: ='Tahmin Data'!O10/1000 -> 67920.753 | E11: ='Tahmin Data'!Q10/1000 -> 65560.404 | F11: ='Tahmin Data'!S10/1000 -> 66014.098 | G11: =F11-'C-Döviz'!AI13/1000 -> -12653.07 | H11: =(F11/(F11-G11))-1 -> -0.16084309 | I11: ='Tahmin Data'!O26/1000 -> 13230.517 | J11: ='Tahmin Data'!Q26/1000 -> 13039.542 | K11: ='Tahmin Data'!S26/1000 -> 13326.952 | L11: =K11-'C-Döviz'!AI40/1000 -> -1743.4885 | M11: =(K11/(K11-L11))-1 -> -0.11568929 | N11: ='Tahmin Data'!O66/1000 -> 4252.5572 | O11: ='Tahmin Data'!Q66/1000 -> 4416.1308 | P11: ='Tahmin Data'!S66/1000 -> 4791.8744 | Q11: =P11-'C-Döviz'!AI143/1000 -> -545.24383 | R11: =(P11/(P11-Q11))-1 -> -0.10216072 | S11: ='Tahmin Data'!O106/1000 -> 1452.906 | T11: ='Tahmin Data'!Q106/1000 -> 1414.3521 | U11: ='Tahmin Data'!S106/1000 -> 1612.4862 | V11: =U11-'C-Döviz'!AI219/1000 -> 499.63512 | W11: =(U11/(U11-V11))-1 -> 0.44896852
C12: Jantaş | D12: ='Tahmin Data'!O9/1000 -> 138028.08 | E12: ='Tahmin Data'!Q9/1000 -> 134805.53 | F12: ='Tahmin Data'!S9/1000 -> 135924.73 | G12: =F12-'C-Döviz'!AI14/1000 -> 1924.9902 | H12: =(F12/(F12-G12))-1 -> 0.014365627 | I12: ='Tahmin Data'!O25/1000 -> 28313.429 | J12: ='Tahmin Data'!Q25/1000 -> 26203.409 | K12: ='Tahmin Data'!S25/1000 -> 26856.8 | L12: =K12-'C-Döviz'!AI41/1000 -> 4618.3394 | M12: =(K12/(K12-L12))-1 -> 0.20767352 | N12: ='Tahmin Data'!O65/1000 -> 25617.404 | O12: ='Tahmin Data'!Q65/1000 -> 23465.103 | P12: ='Tahmin Data'!S65/1000 -> 24141.524 | Q12: =P12-'C-Döviz'!AI144/1000 -> 2979.1056 | R12: =(P12/(P12-Q12))-1 -> 0.1407734 | S12: ='Tahmin Data'!O105/1000 -> 15040.335 | T12: ='Tahmin Data'!Q105/1000 -> 13183.786 | U12: ='Tahmin Data'!S105/1000 -> 13840.253 | V12: =U12-'C-Döviz'!AI220/1000 -> 3233.2945 | W12: =(U12/(U12-V12))-1 -> 0.30482767
C13: Çelik | D13: ='Tahmin Data'!O8/1000 -> 94646.153 | E13: ='Tahmin Data'!Q8/1000 -> 94582.019 | F13: ='Tahmin Data'!S8/1000 -> 95763.679 | G13: =F13-'C-Döviz'!AI15/1000 -> 9915.8181 | H13: =(F13/(F13-G13))-1 -> 0.11550454 | I13: ='Tahmin Data'!O24/1000 -> 27497.364 | J13: ='Tahmin Data'!Q24/1000 -> 27357.649 | K13: ='Tahmin Data'!S24/1000 -> 27754.871 | L13: =K13-'C-Döviz'!AI42/1000 -> 5992.4757 | M13: =(K13/(K13-L13))-1 -> 0.2753592 | N13: ='Tahmin Data'!O64/1000 -> 25607.473 | O13: ='Tahmin Data'!Q64/1000 -> 25493.943 | P13: ='Tahmin Data'!S64/1000 -> 25763.872 | Q13: =P13-'C-Döviz'!AI145/1000 -> 5623.6209 | R13: =(P13/(P13-Q13))-1 -> 0.27922297 | S13: ='Tahmin Data'!O104/1000 -> 13178.548 | T13: ='Tahmin Data'!Q104/1000 -> 8851.3945 | U13: ='Tahmin Data'!S104/1000 -> 8923.2265 | V13: =U13-'C-Döviz'!AI221/1000 -> -2412.3442 | W13: =(U13/(U13-V13))-1 -> -0.21281189
C14: Alüminyum | D14: ='Tahmin Data'!O7/1000 -> 256641.59 | E14: ='Tahmin Data'!Q7/1000 -> 253598 | F14: ='Tahmin Data'!S7/1000 -> 253345.34 | G14: =F14-'C-Döviz'!AI16/1000 -> 5662.3673 | H14: =(F14/(F14-G14))-1 -> 0.02286135 | I14: ='Tahmin Data'!O23/1000 -> 38783.637 | J14: ='Tahmin Data'!Q23/1000 -> 37425.16 | K14: ='Tahmin Data'!S23/1000 -> 36848.954 | L14: =K14-'C-Döviz'!AI43/1000 -> -595.75293 | M14: =(K14/(K14-L14))-1 -> -0.015910204 | N14: ='Tahmin Data'!O63/1000 -> 35517.853 | O14: ='Tahmin Data'!Q63/1000 -> 34006.684 | P14: ='Tahmin Data'!S63/1000 -> 33466.263 | Q14: =P14-'C-Döviz'!AI146/1000 -> 1536.3116 | R14: =(P14/(P14-Q14))-1 -> 0.048115061 | S14: ='Tahmin Data'!O103/1000 -> 24911.379 | T14: ='Tahmin Data'!Q103/1000 -> 23893.31 | U14: ='Tahmin Data'!S103/1000 -> 22989.244 | V14: =U14-'C-Döviz'!AI222/1000 -> -2718.8422 | W14: =(U14/(U14-V14))-1 -> -0.10575825
D16: Vergi | I16: Operasyonel Nakit | N16: Serbest Nakit
C17: bin Avro
D18: Temmuz Tahmin | E18: Ağustos Tahmin | F18: Eylül Tahmin | G18: Bütçe - Tahmin Fark | H18: % Değişim | I18: Temmuz Tahmin | J18: Ağustos Tahmin | K18: Eylül Tahmin | L18: Bütçe - Tahmin Fark | M18: % Değişim | N18: Temmuz Tahmin | O18: Ağustos Tahmin | P18: Eylül Tahmin | Q18: Bütçe - Tahmin Fark | R18: % Değişim
C19: Toplam | D19: =SUM(D20:D27) -> 11368.66 | E19: =SUM(E20:E27) -> 14457.745 | F19: =SUM(F20:F27) -> 15244.087 | G19: =SUM(G20:G27) -> 6001.7736 | H19: =(F19/(F19-G19))-1 -> 0.64938001 | I19: =SUM(I20:I27) -> 108461.56 | J19: =SUM(J20:J27) -> 96880.475 | K19: =SUM(K20:K27) -> 88358.719 | L19: =SUM(L20:L27) -> -7782.0648 | M19: =(K19/(K19-L19))-1 -> -0.080944469 | N19: =SUM(N20:N27) -> 90736.944 | O19: =SUM(O20:O27) -> 79885.44 | P19: =SUM(P20:P27) -> 70451.485 | Q19: =SUM(Q20:Q27) -> -9408.9875 | R19: =(P19/(P19-Q19))-1 -> -0.11781783
C20: İnci Holding | D20: ='Tahmin Data'!O92/1000 -> 410.74147 | E20: ='Tahmin Data'!Q92/1000 -> 590.843 | F20: ='Tahmin Data'!S92/1000 -> 827.15497 | G20: =F20-('C-Döviz'!AI202/-1000) -> -21.556876 | H20: =(F20/(F20-G20))-1 -> -0.025399524 | I20: ='Tahmin Data'!O140/1000 -> 3252.9798 | J20: ='Tahmin Data'!Q140/1000 -> 2990.0396 | K20: ='Tahmin Data'!S140/1000 -> 2775.1665 | L20: =K20-('C-Döviz'!AI291/1000) -> -454.21833 | M20: =(K20/(K20-L20))-1 -> -0.14065166 | N20: ='Tahmin Data'!O148/1000 -> 3239.5279 | O20: ='Tahmin Data'!Q148/1000 -> 2976.9009 | P20: ='Tahmin Data'!S148/1000 -> 2762.1044 | Q20: =P20-('C-Döviz'!AI304/1000) -> -452.35212 | R20: =(P20/(P20-Q20))-1 -> -0.14072429
C21: ISM | D21: ='Tahmin Data'!O94/1000 -> 3.3571263 | E21: ='Tahmin Data'!Q94/1000 -> 1.1061965 | F21: ='Tahmin Data'!S94/1000 -> 0.48283212 | G21: =F21-('C-Döviz'!AI203/-1000) -> -175.64752 | H21: =(F21/(F21-G21))-1 -> -0.99725867 | I21: ='Tahmin Data'!O142/1000 -> 771.42032 | J21: ='Tahmin Data'!Q142/1000 -> 634.70742 | K21: ='Tahmin Data'!S142/1000 -> 513.20468 | L21: =K21-('C-Döviz'!AI292/1000) -> -690.11326 | M21: =(K21/(K21-L21))-1 -> -0.57350866 | N21: ='Tahmin Data'!O150/1000 -> 186.51448 | O21: ='Tahmin Data'!Q150/1000 -> 54.325379 | P21: ='Tahmin Data'!S150/1000 -> -69.172497 | Q21: =P21-('C-Döviz'!AI305/1000) -> -645.37776 | R21: =(P21/(P21-Q21))-1 -> -1.1200484
C22: İncitaş | D22: ='Tahmin Data'!O93/1000 -> 0.0019830577 | E22: ='Tahmin Data'!Q93/1000 -> 0.002313139 | F22: ='Tahmin Data'!S93/1000 -> 8.4467769 | G22: =F22-('C-Döviz'!AI204/-1000) -> -93.874758 | H22: =(F22/(F22-G22))-1 -> -0.91744869 | I22: ='Tahmin Data'!O141/1000 -> 855.04792 | J22: ='Tahmin Data'!Q141/1000 -> 843.21919 | K22: ='Tahmin Data'!S141/1000 -> 967.11505 | L22: =K22-('C-Döviz'!AI293/1000) -> 1282.0655 | M22: =-(K22/(K22-L22)) -> 3.0706893 | N22: ='Tahmin Data'!O149/1000 -> 855.04792 | O22: ='Tahmin Data'!Q149/1000 -> 843.21919 | P22: ='Tahmin Data'!S149/1000 -> 967.11505 | Q22: =P22-('C-Döviz'!AI306/1000) -> 1282.0655 | R22: =-(P22/(P22-Q22)) -> 3.0706893
C23: İnci GS Yuasa | D23: ='Tahmin Data'!O91/1000 -> 0 | E23: ='Tahmin Data'!Q91/1000 -> 0 | F23: ='Tahmin Data'!S91/1000 -> 0 | G23: =F23-('C-Döviz'!AI205/-1000) -> 0 | H23: 0 | I23: ='Tahmin Data'!O139/1000 -> 15056.206 | J23: ='Tahmin Data'!Q139/1000 -> 13354.778 | K23: ='Tahmin Data'!S139/1000 -> 8648.9199 | L23: =K23-('C-Döviz'!AI294/1000) -> -12656.813 | M23: =(K23/(K23-L23))-1 -> -0.59405669 | N23: ='Tahmin Data'!O147/1000 -> 9583.6562 | O23: ='Tahmin Data'!Q147/1000 -> 8095.7402 | P23: ='Tahmin Data'!S147/1000 -> 3428.1354 | Q23: =P23-('C-Döviz'!AI307/1000) -> -11707.11 | R23: =-(P23/(P23-Q23)) -> -0.22650015
C24: Yusen İnci Loj. | D24: ='Tahmin Data'!O98/1000 -> 360.08078 | E24: ='Tahmin Data'!Q98/1000 -> 389.20972 | F24: ='Tahmin Data'!S98/1000 -> 349.57753 | G24: =F24-('C-Döviz'!AI206/-1000) -> -164.33969 | H24: =(F24/(F24-G24))-1 -> -0.31977853 | I24: ='Tahmin Data'!O146/1000 -> 5383.0295 | J24: ='Tahmin Data'!Q146/1000 -> 5017.2294 | K24: ='Tahmin Data'!S146/1000 -> 5842.0166 | L24: =K24-('C-Döviz'!AI295/1000) -> 366.90172 | M24: =(K24/(K24-L24))-1 -> 0.067012606 | N24: ='Tahmin Data'!O154/1000 -> 4147.0189 | O24: ='Tahmin Data'!Q154/1000 -> 3768.7039 | P24: ='Tahmin Data'!S154/1000 -> 3840.7679 | Q24: =P24-('C-Döviz'!AI308/1000) -> -741.44074 | R24: =(P24/(P24-Q24))-1 -> -0.1618086
C25: Jantaş | D25: ='Tahmin Data'!O97/1000 -> 4700.8966 | E25: ='Tahmin Data'!Q97/1000 -> 4211.0715 | F25: ='Tahmin Data'!S97/1000 -> 4273.66 | G25: =F25-('C-Döviz'!AI207/-1000) -> 1280.7592 | H25: =(F25/(F25-G25))-1 -> 0.42793238 | I25: ='Tahmin Data'!O145/1000 -> 20934.517 | J25: ='Tahmin Data'!Q145/1000 -> 18760.219 | K25: ='Tahmin Data'!S145/1000 -> 16915.992 | L25: =K25-('C-Döviz'!AI296/1000) -> 1325.0498 | M25: =(K25/(K25-L25))-1 -> 0.084988437 | N25: ='Tahmin Data'!O153/1000 -> 17535.581 | O25: ='Tahmin Data'!Q153/1000 -> 15333.093 | P25: ='Tahmin Data'!S153/1000 -> 13489.001 | Q25: =P25-('C-Döviz'!AI309/1000) -> 768.07446 | R25: =(P25/(P25-Q25))-1 -> 0.060378815
C26: Çelik | D26: ='Tahmin Data'!O96/1000 -> 4677.6054 | E26: ='Tahmin Data'!Q96/1000 -> 8383.4498 | F26: ='Tahmin Data'!S96/1000 -> 8408.4782 | G26: =F26-('C-Döviz'!AI208/-1000) -> 3070.5852 | H26: =(F26/(F26-G26))-1 -> 0.57524292 | I26: ='Tahmin Data'!O144/1000 -> 28253.003 | J26: ='Tahmin Data'!Q144/1000 -> 24170.708 | K26: ='Tahmin Data'!S144/1000 -> 24930.27 | L26: =K26-('C-Döviz'!AI297/1000) -> 3374.7711 | M26: =(K26/(K26-L26))-1 -> 0.15656196 | N26: ='Tahmin Data'!O152/1000 -> 25117.016 | O26: ='Tahmin Data'!Q152/1000 -> 21586.653 | P26: ='Tahmin Data'!S152/1000 -> 21850.27 | Q26: =P26-('C-Döviz'!AI310/1000) -> 3381.7711 | R26: =(P26/(P26-Q26))-1 -> 0.18311023
C27: Alüminyum | D27: ='Tahmin Data'!O95/1000 -> 1215.9765 | E27: ='Tahmin Data'!Q95/1000 -> 882.0623 | F27: ='Tahmin Data'!S95/1000 -> 1376.2866 | G27: =F27-('C-Döviz'!AI209/-1000) -> 2105.8481 | H27: =(F27/(F27-G27))-1 -> -2.8864576 | I27: ='Tahmin Data'!O143/1000 -> 33955.352 | J27: ='Tahmin Data'!Q143/1000 -> 31109.575 | K27: ='Tahmin Data'!S143/1000 -> 27766.035 | L27: =K27-('C-Döviz'!AI298/1000) -> -329.70785 | M27: =(K27/(K27-L27))-1 -> -0.011735154 | N27: ='Tahmin Data'!O151/1000 -> 30072.581 | O27: ='Tahmin Data'!Q151/1000 -> 27226.805 | P27: ='Tahmin Data'!S151/1000 -> 24183.265 | Q27: =P27-('C-Döviz'!AI311/1000) -> -1294.6178 | R27: =(P27/(P27-Q27))-1 -> -0.050813399
D30: Faaliyet Giderleri Marjı | H30: Brüt Kar Marjı | L30: EBITDA Marjı
C31: bin Avro
D32: Temmuz Tahmin | E32: Ağustos Tahmin | F32: Eylül Tahmin | G32: Bütçe - Tahmin Fark | H32: Temmuz Tahmin | I32: Ağustos Tahmin | J32: Eylül Tahmin | K32: Bütçe - Tahmin Fark | L32: Temmuz Tahmin | M32: Ağustos Tahmin | N32: Eylül Tahmin | O32: Bütçe - Tahmin Fark
C34: İnci Holding | D34: ='Tahmin Data'!O28/1000/D7*-1 -> 0.60682418 | E34: ='Tahmin Data'!Q28/1000/E7*-1 -> 0.61866796 | F34: ='Tahmin Data'!S28/1000/F7*-1 -> 0.61690877 | G34: =-(F34-'C-Döviz'!AI102) -> -0.037829428 | H34: =I7/D7 -> 1 | I34: =J7/E7 -> 1 | J34: =K7/F7 -> 1 | K34: =J34-'C-Döviz'!AI79 -> 0 | L34: =N7/D7 -> 0.40002846 | M34: =O7/E7 -> 0.387247 | N34: =P7/F7 -> 0.38900644 | O34: =N34-'C-Döviz'!AI150 -> -0.037685351
C35: ISM | D35: ='Tahmin Data'!O30/1000/D8*-1 -> 0.19565259 | E35: ='Tahmin Data'!Q30/1000/E8*-1 -> 0.20575323 | F35: ='Tahmin Data'!S30/1000/F8*-1 -> 0.21588734 | G35: =-(F35-'C-Döviz'!AI103) -> -0.025050889 | H35: =I8/D8 -> 0.24718473 | I35: =J8/E8 -> 0.24803319 | J35: =K8/F8 -> 0.23026287 | K35: =J35-'C-Döviz'!AI80 -> -0.061193054 | L35: =N8/D8 -> 0.071545819 | M35: =O8/E8 -> 0.06292304 | N35: =P8/F8 -> 0.03503237 | O35: =N35-'C-Döviz'!AI151 -> -0.087425016
C36: İncitaş | D36: ='Tahmin Data'!O29/1000/D9*-1 -> 0.12764512 | E36: ='Tahmin Data'!Q29/1000/E9*-1 -> 0.12310905 | F36: ='Tahmin Data'!S29/1000/F9*-1 -> 0.12329411 | G36: =-(F36-'C-Döviz'!AI104) -> 0.016620069 | H36: =I9/D9 -> 0.1614043 | I36: =J9/E9 -> 0.16022063 | J36: =K9/F9 -> 0.1596668 | K36: =J36-'C-Döviz'!AI81 -> -0.028861993 | L36: =N9/D9 -> 0.034169475 | M36: =O9/E9 -> 0.037622762 | N36: =P9/F9 -> 0.036890156 | O36: =N36-'C-Döviz'!AI152 -> -0.012560474
C37: İnci GS Yuasa | D37: ='Tahmin Data'!O27/1000/D10*-1 -> 0.1217235 | E37: ='Tahmin Data'!Q27/1000/E10*-1 -> 0.12482421 | F37: ='Tahmin Data'!S27/1000/F10*-1 -> 0.12744526 | G37: =-(F37-'C-Döviz'!AI105) -> -0.024454444 | H37: =I10/D10 -> 0.16399231 | I37: =J10/E10 -> 0.16273418 | J37: =K10/F10 -> 0.14869387 | K37: =J37-'C-Döviz'!AI82 -> -0.053529673 | L37: =N10/D10 -> 0.056068805 | M37: =O10/E10 -> 0.051659877 | N37: =P10/F10 -> 0.035446108 | O37: =N37-'C-Döviz'!AI153 -> -0.07432132
C38: Yusen İnci Loj. | D38: ='Tahmin Data'!O34/1000/D11*-1 -> 0.16245588 | E38: ='Tahmin Data'!Q34/1000/E11*-1 -> 0.16333987 | F38: ='Tahmin Data'!S34/1000/F11*-1 -> 0.16193424 | G38: =-(F38-'C-Döviz'!AI106) -> -0.013974318 | H38: =I11/D11 -> 0.19479344 | I38: =J11/E11 -> 0.19889355 | J38: =K11/F11 -> 0.20188039 | K38: =J38-'C-Döviz'!AI83 -> 0.010308217 | L38: =N11/D11 -> 0.062610571 | M38: =O11/E11 -> 0.067359724 | N38: =P11/F11 -> 0.072588652 | O38: =N38-'C-Döviz'!AI154 -> 0.0047443616
C39: Jantaş | D39: ='Tahmin Data'!O33/1000/D12*-1 -> 0.05763275 | E39: ='Tahmin Data'!Q33/1000/E12*-1 -> 0.059032185 | F39: ='Tahmin Data'!S33/1000/F12*-1 -> 0.058640818 | G39: =-(F39-'C-Döviz'!AI107) -> 0.0044809718 | H39: =I12/D12 -> 0.20512803 | I39: =J12/E12 -> 0.19437934 | J39: =K12/F12 -> 0.19758583 | K39: =J39-'C-Döviz'!AI84 -> 0.031626843 | L39: =N12/D12 -> 0.18559559 | M39: =O12/E12 -> 0.17406633 | N39: =P12/F12 -> 0.17760951 | O39: =N39-'C-Döviz'!AI155 -> 0.019680703
C40: Çelik | D40: ='Tahmin Data'!O32/1000/D13*-1 -> 0.052245571 | E40: ='Tahmin Data'!Q32/1000/E13*-1 -> 0.051818682 | F40: ='Tahmin Data'!S32/1000/F13*-1 -> 0.052249482 | G40: =-(F40-'C-Döviz'!AI108) -> 0.0033660611 | H40: =I13/D13 -> 0.29052807 | I40: =J13/E13 -> 0.28924789 | J40: =K13/F13 -> 0.2898267 | K40: =J40-'C-Döviz'!AI85 -> 0.036327135 | L40: =N13/D13 -> 0.27056011 | M40: =O13/E13 -> 0.26954323 | N40: =P13/F13 -> 0.26903595 | O40: =N40-'C-Döviz'!AI156 -> 0.034431951
C41: Alüminyum | D41: ='Tahmin Data'!O31/1000/D14*-1 -> 0.04436207 | E41: ='Tahmin Data'!Q31/1000/E14*-1 -> 0.045930348 | F41: ='Tahmin Data'!S31/1000/F14*-1 -> 0.046085893 | G41: =-(F41-'C-Döviz'!AI109) -> -0.0049364307 | H41: =I14/D14 -> 0.15111984 | I41: =J14/E14 -> 0.14757671 | J41: =K14/F14 -> 0.1454495 | K41: =J41-'C-Döviz'!AI86 -> -0.0057304764 | L41: =N14/D14 -> 0.13839476 | M41: =O14/E14 -> 0.13409682 | N41: =P14/F14 -> 0.13209741 | O41: =N41-'C-Döviz'!AI157 -> 0.0031828087
D43: Net Kar Marjı | H43: Operasyonel Nakit Marjı | L43: Serbest Nakit Marjı
C44: bin Avro
D45: Temmuz Tahmin | E45: Ağustos Tahmin | F45: Eylül Tahmin | G45: Bütçe - Tahmin Fark | H45: Temmuz Tahmin | I45: Ağustos Tahmin | J45: Eylül Tahmin | K45: Bütçe - Tahmin Fark | L45: Temmuz Tahmin | M45: Ağustos Tahmin | N45: Eylül Tahmin | O45: Bütçe - Tahmin Fark
C47: İnci Holding | D47: =S7/D7 -> 0.4122401 | E47: =T7/E7 -> 0.37208938 | F47: =U7/F7 -> 0.3570884 | G47: =F47-'C-Döviz'!AI226 -> 0.081331184 | H47: =I20/D7 -> 0.38104015 | I47: =J20/E7 -> 0.35896239 | J47: =K20/F7 -> 0.3324703 | K47: =J47-('C-Döviz'!AI291/'C-Döviz'!AI9) -> -0.0172857 | L47: =N20/D7 -> 0.37946445 | M47: =O20/E7 -> 0.35738506 | N47: =P20/F7 -> 0.33090543 | O47: =N47-'C-Döviz'!AI304/'C-Döviz'!AI9 -> -0.017233765
C48: ISM | D48: =S8/D8 -> -0.14429149 | E48: =T8/E8 -> -0.18470871 | F48: =U8/F8 -> -0.22760408 | G48: =F48-'C-Döviz'!AI227 -> -0.30255565 | H48: =I21/D8 -> 0.092484924 | I48: =J21/E8 -> 0.081413696 | J48: =K21/F8 -> 0.068358601 | K48: =J48-('C-Döviz'!AI292/'C-Döviz'!AI10) -> -0.059658191 | L48: =N21/D8 -> 0.022361062 | M48: =O21/E8 -> 0.0069682972 | N48: =P21/F8 -> -0.0092137413 | O48: =N48-'C-Döviz'!AI305/'C-Döviz'!AI10 -> -0.070514207
C49: İncitaş | D49: =S9/D9 -> -0.00020352268 | E49: =T9/E9 -> 0.00084530511 | F49: =U9/F9 -> 0.00082399959 | G49: =F49-'C-Döviz'!AI228 -> -0.008523175 | H49: =I22/D9 -> 0.064158815 | I49: =J22/E9 -> 0.064912194 | J49: =K22/F9 -> 0.075295028 | K49: =J49-('C-Döviz'!AI293/'C-Döviz'!AI11) -> 0.094017515 | L49: =N22/D9 -> 0.064158815 | M49: =O22/E9 -> 0.064912194 | N49: =P22/F9 -> 0.075295028 | O49: =N49-'C-Döviz'!AI306/'C-Döviz'!AI11 -> 0.094017515
C50: İnci GS Yuasa | D50: =S10/D10 -> -0.14012712 | E50: =T10/E10 -> -0.14910658 | F50: =U10/F10 -> -0.16771437 | G50: =F50-'C-Döviz'!AI229 -> -0.16943907 | H50: =I23/D10 -> 0.079821617 | I50: =J23/E10 -> 0.074387257 | J50: =K23/F10 -> 0.04941359 | K50: =J50-('C-Döviz'!AI294/'C-Döviz'!AI12) -> -0.033009596 | L50: =N23/D10 -> 0.050808479 | M50: =O23/E10 -> 0.045093968 | N50: =P23/F10 -> 0.019585853 | O50: =N50-'C-Döviz'!AI307/'C-Döviz'!AI12 -> -0.038966234
C51: Yusen İnci Loj. | D51: =S11/D11 -> 0.021391193 | E51: =T11/E11 -> 0.021573267 | F51: =U11/F11 -> 0.024426392 | G51: =F51-'C-Döviz'!AI230 -> 0.01028007 | H51: =I24/D11 -> 0.079254561 | I51: =J24/E11 -> 0.076528348 | J51: =K24/F11 -> 0.0884965 | K51: =J51-('C-Döviz'!AI295/'C-Döviz'!AI13) -> 0.018898026 | L51: =N24/D11 -> 0.061056727 | M51: =O24/E11 -> 0.057484451 | N51: =P24/F11 -> 0.058181024 | O51: =N51-'C-Döviz'!AI308/'C-Döviz'!AI13 -> -6.701838e-05
C52: Jantaş | D52: =S12/D12 -> 0.10896576 | E52: =T12/E12 -> 0.09779856 | F52: =U12/F12 -> 0.10182292 | G52: =F52-'C-Döviz'!AI231 -> 0.02266636 | H52: =I25/D12 -> 0.15166853 | I52: =J25/E12 -> 0.13916506 | J52: =K25/F12 -> 0.12445118 | K52: =J52-('C-Döviz'!AI296/'C-Döviz'!AI14) -> 0.0081006319 | L52: =N25/D12 -> 0.12704357 | M52: =O25/E12 -> 0.11374232 | N52: =P25/F12 -> 0.099238756 | O52: =N52-'C-Döviz'!AI309/'C-Döviz'!AI14 -> 0.0043062833
C53: Çelik | D53: =S13/D13 -> 0.13924018 | E53: =T13/E13 -> 0.093584326 | F53: =U13/F13 -> 0.093179654 | G53: =F53-'C-Döviz'!AI232 -> -0.038862898 | H53: =I26/D13 -> 0.2985119 | I53: =J26/E13 -> 0.25555289 | J53: =K26/F13 -> 0.26033116 | K53: =J53-('C-Döviz'!AI297/'C-Döviz'!AI15) -> 0.0092416356 | L53: =N26/D13 -> 0.2653781 | M53: =O26/E13 -> 0.2282321 | N53: =P26/F13 -> 0.22816865 | O53: =N53-'C-Döviz'!AI310/'C-Döviz'!AI15 -> 0.013038091
C54: Alüminyum | D54: =S14/D14 -> 0.097066803 | E54: =T14/E14 -> 0.094217265 | F54: =U14/F14 -> 0.090742712 | G54: =F54-'C-Döviz'!AI233 -> -0.013051606 | H54: =I27/D14 -> 0.1323065 | I54: =J27/E14 -> 0.12267279 | J54: =K27/F14 -> 0.10959757 | K54: =J54-('C-Döviz'!AI298/'C-Döviz'!AI16) -> -0.0038367173 | L54: =N27/D14 -> 0.11717735 | M54: =O27/E14 -> 0.10736206 | N54: =P27/F14 -> 0.095455729 | O54: =N54-'C-Döviz'!AI311/'C-Döviz'!AI16 -> -0.0074091616
D65: Ciro | H65: EBITDA | M65: Net Kar
D66: Gerçekleşme | E66: % | H66: Gerçekleşme | J66: % | M66: Gerçekleşme | O66: %
C67: Ciro | D67: 55 | H67: 55 | M67: 55
C68: Adet | D68: 12 | E68: =D68/$D$67 -> 0.21818182 | H68: 12 | I68: =H68/$D$67 -> 0.21818182 | M68: 12 | O68: =M68/$M$67 -> 0.21818182
C69: Fiyat | D69: 9 | E69: =D69/$D$67 -> 0.16363636 | H69: 9 | I69: =H69/$D$67 -> 0.16363636 | M69: 9 | O69: =M69/$M$67 -> 0.16363636
C70: Miks | D70: 8 | E70: =D70/$D$67 -> 0.14545455 | H70: 8 | I70: =H70/$D$67 -> 0.14545455 | M70: 8 | O70: =M70/$M$67 -> 0.14545455
C71: Ham Madde | D71: 5 | E71: =D71/$D$67 -> 0.090909091 | H71: 5 | I71: =H71/$D$67 -> 0.090909091 | M71: 5 | O71: =M71/$M$67 -> 0.090909091
C72: Enerji | D72: 4 | E72: =D72/$D$67 -> 0.072727273 | H72: 4 | I72: =H72/$D$67 -> 0.072727273 | M72: 4 | O72: =M72/$M$67 -> 0.072727273
C73: Döviz | D73: 3 | E73: =D73/$D$67 -> 0.054545455 | H73: 3 | I73: =H73/$D$67 -> 0.054545455 | M73: 3 | O73: =M73/$M$67 -> 0.054545455
C74: Enflasyon | D74: 3 | E74: =D74/$D$67 -> 0.054545455 | H74: 3 | I74: =H74/$D$67 -> 0.054545455 | M74: 3 | O74: =M74/$M$67 -> 0.054545455

Sheet A -Döviz
A1: ='A-TRY'!A1 -> EYLÜL | B1: OCAK | E1: ŞUBAT | H1: MART | K1: NİSAN | N1: MAYIS | Q1: HAZİRAN | T1: TEMMUZ | W1: AĞUSTOS | Z1: EYLÜL | AC1: EKİM | AF1: KASIM | AI1: ARALIK
B2: Budget | C2: Actual | E2: Budget | F2: Actual | H2: Budget | I2: Actual | K2: Budget | L2: Actual | N2: Budget | O2: Actual | Q2: Budget | R2: Actual | T2: Budget | U2: Actual | W2: Budget | X2: Actual | Z2: Budget | AA2: Actual | AC2: Budget | AD2: Actual | AF2: Budget | AG2: Actual | AI2: Budget | AJ2: Actual | AL2: Difference | AM2: Variance % | AO2: Budget | AP2: Actual
A3: Eur Kapanış | B3: ='Bütçe aylık-TL'!$B$2 -> 37.515625 | C3: ='gerç aylık-tl'!$B$2 -> 37.1844 | E3: ='Bütçe aylık-TL'!$C$2 -> 38.28125 | F3: ='gerç aylık-tl'!$C$2 -> 38.104 | H3: ='Bütçe aylık-TL'!$D$2 -> 39.046875 | I3: ='gerç aylık-tl'!$D$2 -> 40.7019 | K3: ='Bütçe aylık-TL'!$E$2 -> 39.8125 | L3: ='gerç aylık-tl'!$E$2 -> 43.6858 | N3: ='Bütçe aylık-TL'!$F$2 -> 40.578125 | O3: ='gerç aylık-tl'!$F$2 -> 44.2706 | Q3: ='Bütçe aylık-TL'!$G$2 -> 41.34375 | R3: ='gerç aylık-tl'!$G$2 -> 46.5526 | T3: ='Bütçe aylık-TL'!$H$2 -> 42.109375 | U3: ='gerç aylık-tl'!$H$2 -> 46.7684 | W3: ='Bütçe aylık-TL'!$I$2 -> 42.875 | X3: ='gerç aylık-tl'!$I$2 -> 47.7841 | Z3: ='Bütçe aylık-TL'!$J$2 -> 43.640625 | AA3: ='gerç aylık-tl'!$J$2 -> 48.6479 | AC3: ='Bütçe aylık-TL'!$K$2 -> 44.40625 | AD3: ='gerç aylık-tl'!$K$2 -> #DIV/0! | AF3: ='Bütçe aylık-TL'!$L$2 -> 45.171875 | AG3: ='gerç aylık-tl'!$L$2 -> #DIV/0! | AI3: ='Bütçe aylık-TL'!$M$2 -> 45.9375 | AJ3: ='gerç aylık-tl'!$M$2 -> #DIV/0! | AL3: =AP3-AO3 -> 5.007275 | AM3: =AP3/AO3-1 -> 0.11473885 | AO3: =IF($A$1=$B$1,B3,IF($A$1=$E$1,E3,IF($A$1=$H$1,H3,IF($A$1=$K$1,K3,IF($A$1=$N$1,N3,IF($A$1=$Q$1,Q3,IF($A$1=$T$1,T3,IF($A$1=$W$1,W3,IF($A$1=$Z$1,Z3,IF($A$1=$AC$1,AC3,IF($A$1=$AF$1,AF3,IF($A$1=$AI$1,AI3)))))))))))) -> 43.640625 | AP3: =IF($A$1=$B$1,C3,IF($A$1=$E$1,F3,IF($A$1=$H$1,I3,IF($A$1=$K$1,L3,IF($A$1=$N$1,O3,IF($A$1=$Q$1,R3,IF($A$1=$T$1,U3,IF($A$1=$W$1,X3,IF($A$1=$Z$1,AA3,IF($A$1=$AC$1,AD3,IF($A$1=$AF$1,AG3,IF($A$1=$AI$1,AJ3)))))))))))) -> 48.6479 | AR3: =250000000/L3 -> 5722683.3
A4: Eur Ortalama | B4: ='Bütçe aylık-TL'!$B$3 -> 37.132812 | C4: ='gerç aylık-tl'!$B$3 -> 36.689261 | E4: ='Bütçe aylık-TL'!$C$3 -> 37.898438 | F4: ='gerç aylık-tl'!$C$3 -> 37.577707 | H4: ='Bütçe aylık-TL'!$D$3 -> 38.664062 | I4: ='gerç aylık-tl'!$D$3 -> 39.849871 | K4: ='Bütçe aylık-TL'!$E$3 -> 39.429688 | L4: ='gerç aylık-tl'!$E$3 -> 42.673177 | N4: ='Bütçe aylık-TL'!$F$3 -> 40.195312 | O4: ='gerç aylık-tl'!$F$3 -> 43.629358 | Q4: ='Bütçe aylık-TL'!$G$3 -> 40.960938 | R4: ='gerç aylık-tl'!$G$3 -> 45.22721 | T4: ='Bütçe aylık-TL'!$H$3 -> 41.726562 | U4: ='gerç aylık-tl'!$H$3 -> 46.914206 | W4: ='Bütçe aylık-TL'!$I$3 -> 42.492188 | X4: ='gerç aylık-tl'!$I$3 -> 47.302506 | Z4: ='Bütçe aylık-TL'!$J$3 -> 43.257812 | AA4: ='gerç aylık-tl'!$J$3 -> 48.33795 | AC4: ='Bütçe aylık-TL'!$K$3 -> 44.023438 | AD4: ='gerç aylık-tl'!$K$3 -> #DIV/0! | AF4: ='Bütçe aylık-TL'!$L$3 -> 44.789062 | AG4: ='gerç aylık-tl'!$L$3 -> #DIV/0! | AI4: ='Bütçe aylık-TL'!$M$3 -> 45.554688 | AJ4: ='gerç aylık-tl'!$M$3 -> #DIV/0! | AL4: =AP4-AO4 -> 5.0801375 | AM4: =AP4/AO4-1 -> 0.11743861 | AO4: =IF($A$1=$B$1,B4,IF($A$1=$E$1,E4,IF($A$1=$H$1,H4,IF($A$1=$K$1,K4,IF($A$1=$N$1,N4,IF($A$1=$Q$1,Q4,IF($A$1=$T$1,T4,IF($A$1=$W$1,W4,IF($A$1=$Z$1,Z4,IF($A$1=$AC$1,AC4,IF($A$1=$AF$1,AF4,IF($A$1=$AI$1,AI4)))))))))))) -> 43.257812 | AP4: =IF($A$1=$B$1,C4,IF($A$1=$E$1,F4,IF($A$1=$H$1,I4,IF($A$1=$K$1,L4,IF($A$1=$N$1,O4,IF($A$1=$Q$1,R4,IF($A$1=$T$1,U4,IF($A$1=$W$1,X4,IF($A$1=$Z$1,AA4,IF($A$1=$AC$1,AD4,IF($A$1=$AF$1,AG4,IF($A$1=$AI$1,AJ4)))))))))))) -> 48.33795
A6: Net Sales | B6: ='Bütçe aylık-Eur'!$B$4 -> 27601026 | C6: ='gerç aylık-eur'!$B$4 -> 30208401 | E6: ='Bütçe aylık-Eur'!$C$4 -> 28100063 | F6: ='gerç aylık-eur'!$C$4 -> 27091507 | H6: ='Bütçe aylık-Eur'!$D$4 -> 31103326 | I6: ='gerç aylık-eur'!$D$4 -> 28022189 | K6: ='Bütçe aylık-Eur'!$E$4 -> 28901858 | L6: ='gerç aylık-eur'!$E$4 -> 26602564 | N6: ='Bütçe aylık-Eur'!$F$4 -> 29998377 | O6: ='gerç aylık-eur'!$F$4 -> 28299453 | Q6: ='Bütçe aylık-Eur'!$G$4 -> 29120047 | R6: ='gerç aylık-eur'!$G$4 -> 23718502 | T6: ='Bütçe aylık-Eur'!$H$4 -> 29852729 | U6: ='gerç aylık-eur'!$H$4 -> 27200733 | W6: ='Bütçe aylık-Eur'!$I$4 -> 26329537 | X6: ='gerç aylık-eur'!$I$4 -> 21922624 | Z6: ='Bütçe aylık-Eur'!$J$4 -> 32874061 | AA6: ='gerç aylık-eur'!$J$4 -> 26154341 | AC6: ='Bütçe aylık-Eur'!$K$4 -> 33028263 | AD6: ='gerç aylık-eur'!$K$4 -> 0 | AF6: ='Bütçe aylık-Eur'!$L$4 -> 31691839 | AG6: ='gerç aylık-eur'!$L$4 -> 0 | AI6: ='Bütçe aylık-Eur'!$M$4 -> 28729747 | AJ6: ='gerç aylık-eur'!$M$4 -> 0 | AL6: =AP6-AO6 -> -6719720.5 | AM6: =AP6/AO6-1 -> -0.20440798 | AO6: =IF($A$1=$B$1,B6,IF($A$1=$E$1,E6,IF($A$1=$H$1,H6,IF($A$1=$K$1,K6,IF($A$1=$N$1,N6,IF($A$1=$Q$1,Q6,IF($A$1=$T$1,T6,IF($A$1=$W$1,W6,IF($A$1=$Z$1,Z6,IF($A$1=$AC$1,AC6,IF($A$1=$AF$1,AF6,IF($A$1=$AI$1,AI6)))))))))))) -> 32874061 | AP6: =IF($A$1=$B$1,C6,IF($A$1=$E$1,F6,IF($A$1=$H$1,I6,IF($A$1=$K$1,L6,IF($A$1=$N$1,O6,IF($A$1=$Q$1,R6,IF($A$1=$T$1,U6,IF($A$1=$W$1,X6,IF($A$1=$Z$1,AA6,IF($A$1=$AC$1,AD6,IF($A$1=$AF$1,AG6,IF($A$1=$AI$1,AJ6)))))))))))) -> 26154341
C7: =B6-C6 -> -2607374.2 | F7: =E6-F6 -> 1008556.1 | I7: =H6-I6 -> 3081137.2 | L7: =K6-L6 -> 2299293.3 | O7: =N6-O6 -> 1698924
A8: SALES BY CHANNELS(100% Satışlar)
A9: İnci Holding | B9: ='Bütçe aylık-Eur'!$B$5 -> 714880.86 | C9: ='gerç aylık-eur'!$B$5 -> 754597.33 | E9: ='Bütçe aylık-Eur'!$C$5 -> 723499.01 | F9: ='gerç aylık-eur'!$C$5 -> 724922.82 | H9: ='Bütçe aylık-Eur'!$D$5 -> 810291.92 | I9: ='gerç aylık-eur'!$D$5 -> 791351.52 | K9: ='Bütçe aylık-Eur'!$E$5 -> 742627.95 | L9: ='gerç aylık-eur'!$E$5 -> 689017.21 | N9: ='Bütçe aylık-Eur'!$F$5 -> 779760.2 | O9: ='gerç aylık-eur'!$F$5 -> 778380.85 | P9: =O9/N9 -> 0.99823107 | Q9: ='Bütçe aylık-Eur'!$G$5 -> 762531.48 | R9: ='gerç aylık-eur'!$G$5 -> 668367.49 | T9: ='Bütçe aylık-Eur'!$H$5 -> 756667.04 | U9: ='gerç aylık-eur'!$H$5 -> 729930.38 | W9: ='Bütçe aylık-Eur'!$I$5 -> 671190.31 | X9: ='gerç aylık-eur'!$I$5 -> 603787.73 | Z9: ='Bütçe aylık-Eur'!$J$5 -> 875959.11 | AA9: ='gerç aylık-eur'!$J$5 -> 789956.17 | AC9: ='Bütçe aylık-Eur'!$K$5 -> 851941.11 | AD9: ='gerç aylık-eur'!$K$5 -> 0 | AF9: ='Bütçe aylık-Eur'!$L$5 -> 816659.57 | AG9: ='gerç aylık-eur'!$L$5 -> 0 | AI9: ='Bütçe aylık-Eur'!$M$5 -> 727242.32 | AJ9: ='gerç aylık-eur'!$M$5 -> 0 | AL9: =AP9-AO9 -> -86002.945 | AM9: =AP9/AO9-1 -> -0.09818146 | AO9: =IF($A$1=$B$1,B9,IF($A$1=$E$1,E9,IF($A$1=$H$1,H9,IF($A$1=$K$1,K9,IF($A$1=$N$1,N9,IF($A$1=$Q$1,Q9,IF($A$1=$T$1,T9,IF($A$1=$W$1,W9,IF($A$1=$Z$1,Z9,IF($A$1=$AC$1,AC9,IF($A$1=$AF$1,AF9,IF($A$1=$AI$1,AI9)))))))))))) -> 875959.11 | AP9: =IF($A$1=$B$1,C9,IF($A$1=$E$1,F9,IF($A$1=$H$1,I9,IF($A$1=$K$1,L9,IF($A$1=$N$1,O9,IF($A$1=$Q$1,R9,IF($A$1=$T$1,U9,IF($A$1=$W$1,X9,IF($A$1=$Z$1,AA9,IF($A$1=$AC$1,AD9,IF($A$1=$AF$1,AG9,IF($A$1=$AI$1,AJ9)))))))))))) -> 789956.17
A10: ISM | B10: ='Bütçe aylık-Eur'!$B$6 -> 834190.48 | C10: ='gerç aylık-eur'!$B$6 -> 881940.78 | E10: ='Bütçe aylık-Eur'!$C$6 -> 967501.25 | F10: ='gerç aylık-eur'!$C$6 -> 936556.67 | H10: ='Bütçe aylık-Eur'!$D$6 -> 986615.93 | I10: ='gerç aylık-eur'!$D$6 -> 696132.57 | K10: ='Bütçe aylık-Eur'!$E$6 -> 1060816.1 | L10: ='gerç aylık-eur'!$E$6 -> 467016.2 | N10: ='Bütçe aylık-Eur'!$F$6 -> 996710.58 | O10: ='gerç aylık-eur'!$F$6 -> 705071.85 | P10: =O10/N10 -> 0.70739878 | Q10: ='Bütçe aylık-Eur'!$G$6 -> 1017076 | R10: ='gerç aylık-eur'!$G$6 -> 633638.43 | T10: ='Bütçe aylık-Eur'!$H$6 -> 854222.84 | U10: ='gerç aylık-eur'!$H$6 -> 693656.16 | W10: ='Bütçe aylık-Eur'!$I$6 -> 596499.27 | X10: ='gerç aylık-eur'!$I$6 -> 500471.21 | Z10: ='Bütçe aylık-Eur'!$J$6 -> 630604.1 | AA10: ='gerç aylık-eur'!$J$6 -> 453451 | AC10: ='Bütçe aylık-Eur'!$K$6 -> 538427.93 | AD10: ='gerç aylık-eur'!$K$6 -> 0 | AF10: ='Bütçe aylık-Eur'!$L$6 -> 484665.88 | AG10: ='gerç aylık-eur'!$L$6 -> 0 | AI10: ='Bütçe aylık-Eur'!$M$6 -> 432357.9 | AJ10: ='gerç aylık-eur'!$M$6 -> 0 | AL10: =AP10-AO10 -> -177153.1 | AM10: =AP10/AO10-1 -> -0.28092603 | AO10: =IF($A$1=$B$1,B10,IF($A$1=$E$1,E10,IF($A$1=$H$1,H10,IF($A$1=$K$1,K10,IF($A$1=$N$1,N10,IF($A$1=$Q$1,Q10,IF($A$1=$T$1,T10,IF($A$1=$W$1,W10,IF($A$1=$Z$1,Z10,IF($A$1=$AC$1,AC10,IF($A$1=$AF$1,AF10,IF($A$1=$AI$1,AI10)))))))))))) -> 630604.1 | AP10: =IF($A$1=$B$1,C10,IF($A$1=$E$1,F10,IF($A$1=$H$1,I10,IF($A$1=$K$1,L10,IF($A$1=$N$1,O10,IF($A$1=$Q$1,R10,IF($A$1=$T$1,U10,IF($A$1=$W$1,X10,IF($A$1=$Z$1,AA10,IF($A$1=$AC$1,AD10,IF($A$1=$AF$1,AG10,IF($A$1=$AI$1,AJ10)))))))))))) -> 453451
A11: İncitaş | B11: ='Bütçe aylık-Eur'!$B$7 -> 994090.62 | C11: ='gerç aylık-eur'!$B$7 -> 967950.97 | E11: ='Bütçe aylık-Eur'!$C$7 -> 987408.17 | F11: ='gerç aylık-eur'!$C$7 -> 1038871.4 | H11: ='Bütçe aylık-Eur'!$D$7 -> 1292386.7 | I11: ='gerç aylık-eur'!$D$7 -> 1519045.4 | K11: ='Bütçe aylık-Eur'!$E$7 -> 1340897.5 | L11: ='gerç aylık-eur'!$E$7 -> 1265253.2 | N11: ='Bütçe aylık-Eur'!$F$7 -> 1451102.3 | O11: ='gerç aylık-eur'!$F$7 -> 747521.95 | P11: =O11/N11 -> 0.51514078 | Q11: ='Bütçe aylık-Eur'!$G$7 -> 1453352 | R11: ='gerç aylık-eur'!$G$7 -> 899615.96 | T11: ='Bütçe aylık-Eur'!$H$7 -> 1783426.6 | U11: ='gerç aylık-eur'!$H$7 -> 927197.72 | W11: ='Bütçe aylık-Eur'!$I$7 -> 1437121.1 | X11: ='gerç aylık-eur'!$I$7 -> 831655.35 | Z11: ='Bütçe aylık-Eur'!$J$7 -> 1414781.2 | AA11: ='gerç aylık-eur'!$J$7 -> 890674.76 | AC11: ='Bütçe aylık-Eur'!$K$7 -> 1455398.7 | AD11: ='gerç aylık-eur'!$K$7 -> 0 | AF11: ='Bütçe aylık-Eur'!$L$7 -> 1730074.3 | AG11: ='gerç aylık-eur'!$L$7 -> 0 | AI11: ='Bütçe aylık-Eur'!$M$7 -> 1482003.3 | AJ11: ='gerç aylık-eur'!$M$7 -> 0 | AL11: =AP11-AO11 -> -524106.49 | AM11: =AP11/AO11-1 -> -0.37045055 | AO11: =IF($A$1=$B$1,B11,IF($A$1=$E$1,E11,IF($A$1=$H$1,H11,IF($A$1=$K$1,K11,IF($A$1=$N$1,N11,IF($A$1=$Q$1,Q11,IF($A$1=$T$1,T11,IF($A$1=$W$1,W11,IF($A$1=$Z$1,Z11,IF($A$1=$AC$1,AC11,IF($A$1=$AF$1,AF11,IF($A$1=$AI$1,AI11)))))))))))) -> 1414781.2 | AP11: =IF($A$1=$B$1,C11,IF($A$1=$E$1,F11,IF($A$1=$H$1,I11,IF($A$1=$K$1,L11,IF($A$1=$N$1,O11,IF($A$1=$Q$1,R11,IF($A$1=$T$1,U11,IF($A$1=$W$1,X11,IF($A$1=$Z$1,AA11,IF($A$1=$AC$1,AD11,IF($A$1=$AF$1,AG11,IF($A$1=$AI$1,AJ11)))))))))))) -> 890674.76
A12: İnci GS Yuasa | B12: ='Bütçe aylık-Eur'!$B$8 -> 19103568 | C12: ='gerç aylık-eur'!$B$8 -> 21339706 | E12: ='Bütçe aylık-Eur'!$C$8 -> 19444514 | F12: ='gerç aylık-eur'!$C$8 -> 15129669 | H12: ='Bütçe aylık-Eur'!$D$8 -> 20350915 | I12: ='gerç aylık-eur'!$D$8 -> 12750548 | K12: ='Bütçe aylık-Eur'!$E$8 -> 19394471 | L12: ='gerç aylık-eur'!$E$8 -> 12435017 | N12: ='Bütçe aylık-Eur'!$F$8 -> 18642732 | O12: ='gerç aylık-eur'!$F$8 -> 14259477 | P12: =O12/N12 -> 0.7648813 | Q12: ='Bütçe aylık-Eur'!$G$8 -> 18744067 | R12: ='gerç aylık-eur'!$G$8 -> 8679241.2 | T12: ='Bütçe aylık-Eur'!$H$8 -> 21889007 | U12: ='gerç aylık-eur'!$H$8 -> 16380819 | W12: ='Bütçe aylık-Eur'!$I$8 -> 21093772 | X12: ='gerç aylık-eur'!$I$8 -> 14295312 | Z12: ='Bütçe aylık-Eur'!$J$8 -> 22542986 | AA12: ='gerç aylık-eur'!$J$8 -> 10760310 | AC12: ='Bütçe aylık-Eur'!$K$8 -> 25704925 | AD12: ='gerç aylık-eur'!$K$8 -> 0 | AF12: ='Bütçe aylık-Eur'!$L$8 -> 25549148 | AG12: ='gerç aylık-eur'!$L$8 -> 0 | AI12: ='Bütçe aylık-Eur'!$M$8 -> 26031885 | AJ12: ='gerç aylık-eur'!$M$8 -> 0 | AL12: =AP12-AO12 -> -11782675 | AM12: =AP12/AO12-1 -> -0.5226759 | AN12: =AL12*0.4 -> -4713070.2 | AO12: =IF($A$1=$B$1,B12,IF($A$1=$E$1,E12,IF($A$1=$H$1,H12,IF($A$1=$K$1,K12,IF($A$1=$N$1,N12,IF($A$1=$Q$1,Q12,IF($A$1=$T$1,T12,IF($A$1=$W$1,W12,IF($A$1=$Z$1,Z12,IF($A$1=$AC$1,AC12,IF($A$1=$AF$1,AF12,IF($A$1=$AI$1,AI12)))))))))))) -> 22542986 | AP12: =IF($A$1=$B$1,C12,IF($A$1=$E$1,F12,IF($A$1=$H$1,I12,IF($A$1=$K$1,L12,IF($A$1=$N$1,O12,IF($A$1=$Q$1,R12,IF($A$1=$T$1,U12,IF($A$1=$W$1,X12,IF($A$1=$Z$1,AA12,IF($A$1=$AC$1,AD12,IF($A$1=$AF$1,AG12,IF($A$1=$AI$1,AJ12)))))))))))) -> 10760310
A13: Yusen İnci Loj. | B13: ='Bütçe aylık-Eur'!$B$9 -> 6610337 | C13: ='gerç aylık-eur'!$B$9 -> 6014583.7 | E13: ='Bütçe aylık-Eur'!$C$9 -> 6831152.1 | F13: ='gerç aylık-eur'!$C$9 -> 5689931.3 | H13: ='Bütçe aylık-Eur'!$D$9 -> 6764140.1 | I13: ='gerç aylık-eur'!$D$9 -> 6425103.6 | K13: ='Bütçe aylık-Eur'!$E$9 -> 6725265.8 | L13: ='gerç aylık-eur'!$E$9 -> 5089628.4 | N13: ='Bütçe aylık-Eur'!$F$9 -> 6899932.3 | O13: ='gerç aylık-eur'!$F$9 -> 5622265.9 | P13: =O13/N13 -> 0.81482914 | Q13: ='Bütçe aylık-Eur'!$G$9 -> 5650391 | R13: ='gerç aylık-eur'!$G$9 -> 4374597.4 | T13: ='Bütçe aylık-Eur'!$H$9 -> 6884690 | U13: ='gerç aylık-eur'!$H$9 -> 5296348.1 | W13: ='Bütçe aylık-Eur'!$I$9 -> 6053244.1 | X13: ='gerç aylık-eur'!$I$9 -> 4571844.4 | Z13: ='Bütçe aylık-Eur'!$J$9 -> 5958226.6 | AA13: ='gerç aylık-eur'!$J$9 -> 5403645.6 | AC13: ='Bütçe aylık-Eur'!$K$9 -> 7616376.8 | AD13: ='gerç aylık-eur'!$K$9 -> 0 | AF13: ='Bütçe aylık-Eur'!$L$9 -> 6378504.4 | AG13: ='gerç aylık-eur'!$L$9 -> 0 | AI13: ='Bütçe aylık-Eur'!$M$9 -> 6294908.2 | AJ13: ='gerç aylık-eur'!$M$9 -> 0 | AL13: =AP13-AO13 -> -554581.01 | AM13: =AP13/AO13-1 -> -0.0930782 | AN13: =AL13*0.4 -> -221832.4 | AO13: =IF($A$1=$B$1,B13,IF($A$1=$E$1,E13,IF($A$1=$H$1,H13,IF($A$1=$K$1,K13,IF($A$1=$N$1,N13,IF($A$1=$Q$1,Q13,IF($A$1=$T$1,T13,IF($A$1=$W$1,W13,IF($A$1=$Z$1,Z13,IF($A$1=$AC$1,AC13,IF($A$1=$AF$1,AF13,IF($A$1=$AI$1,AI13)))))))))))) -> 5958226.6 | AP13: =IF($A$1=$B$1,C13,IF($A$1=$E$1,F13,IF($A$1=$H$1,I13,IF($A$1=$K$1,L13,IF($A$1=$N$1,O13,IF($A$1=$Q$1,R13,IF($A$1=$T$1,U13,IF($A$1=$W$1,X13,IF($A$1=$Z$1,AA13,IF($A$1=$AC$1,AD13,IF($A$1=$AF$1,AG13,IF($A$1=$AI$1,AJ13)))))))))))) -> 5403645.6 | AR13: 43.12 | AS13: =B13/AR13 -> 153300.95
A14: Jantaş | B14: ='Bütçe aylık-Eur'!$B$10 -> 10048793 | C14: ='gerç aylık-eur'!$B$10 -> 11605520 | E14: ='Bütçe aylık-Eur'!$C$10 -> 10827280 | F14: ='gerç aylık-eur'!$C$10 -> 11543133 | H14: ='Bütçe aylık-Eur'!$D$10 -> 12591061 | I14: ='gerç aylık-eur'!$D$10 -> 12423119 | K14: ='Bütçe aylık-Eur'!$E$10 -> 10932455 | L14: ='gerç aylık-eur'!$E$10 -> 12093195 | N14: ='Bütçe aylık-Eur'!$F$10 -> 11676965 | O14: ='gerç aylık-eur'!$F$10 -> 12658094 | P14: =O14/N14 -> 1.0840226 | Q14: ='Bütçe aylık-Eur'!$G$10 -> 11838098 | R14: ='gerç aylık-eur'!$G$10 -> 12477093 | T14: ='Bütçe aylık-Eur'!$H$10 -> 9412291.1 | U14: ='gerç aylık-eur'!$H$10 -> 10770778 | W14: ='Bütçe aylık-Eur'!$I$10 -> 9404847.8 | X14: ='gerç aylık-eur'!$I$10 -> 9564597.2 | Z14: ='Bütçe aylık-Eur'!$J$10 -> 13855811 | AA14: ='gerç aylık-eur'!$J$10 -> 11814679 | AC14: ='Bütçe aylık-Eur'!$K$10 -> 11997699 | AD14: ='gerç aylık-eur'!$K$10 -> 0 | AF14: ='Bütçe aylık-Eur'!$L$10 -> 11428205 | AG14: ='gerç aylık-eur'!$L$10 -> 0 | AI14: ='Bütçe aylık-Eur'!$M$10 -> 9986231.4 | AJ14: ='gerç aylık-eur'!$M$10 -> 0 | AL14: =AP14-AO14 -> -2041132.3 | AM14: =AP14/AO14-1 -> -0.14731237 | AN14: =AL14*0.4 -> -816452.92 | AO14: =IF($A$1=$B$1,B14,IF($A$1=$E$1,E14,IF($A$1=$H$1,H14,IF($A$1=$K$1,K14,IF($A$1=$N$1,N14,IF($A$1=$Q$1,Q14,IF($A$1=$T$1,T14,IF($A$1=$W$1,W14,IF($A$1=$Z$1,Z14,IF($A$1=$AC$1,AC14,IF($A$1=$AF$1,AF14,IF($A$1=$AI$1,AI14)))))))))))) -> 13855811 | AP14: =IF($A$1=$B$1,C14,IF($A$1=$E$1,F14,IF($A$1=$H$1,I14,IF($A$1=$K$1,L14,IF($A$1=$N$1,O14,IF($A$1=$Q$1,R14,IF($A$1=$T$1,U14,IF($A$1=$W$1,X14,IF($A$1=$Z$1,AA14,IF($A$1=$AC$1,AD14,IF($A$1=$AF$1,AG14,IF($A$1=$AI$1,AJ14)))))))))))) -> 11814679
A15: Çelik | B15: ='Bütçe aylık-Eur'!$B$11 -> 7577608.3 | C15: ='gerç aylık-eur'!$B$11 -> 7830554.3 | E15: ='Bütçe aylık-Eur'!$C$11 -> 6103066.9 | F15: ='gerç aylık-eur'!$C$11 -> 8732829.1 | H15: ='Bütçe aylık-Eur'!$D$11 -> 7983071.5 | I15: ='gerç aylık-eur'!$D$11 -> 8949431.3 | K15: ='Bütçe aylık-Eur'!$E$11 -> 7994757.5 | L15: ='gerç aylık-eur'!$E$11 -> 8776440.4 | N15: ='Bütçe aylık-Eur'!$F$11 -> 7875525.2 | O15: ='gerç aylık-eur'!$F$11 -> 8093665.3 | P15: =O15/N15 -> 1.0276985 | Q15: ='Bütçe aylık-Eur'!$G$11 -> 6939893.5 | R15: ='gerç aylık-eur'!$G$11 -> 7243188.6 | T15: ='Bütçe aylık-Eur'!$H$11 -> 6547612.1 | U15: ='gerç aylık-eur'!$H$11 -> 8047483.4 | W15: ='Bütçe aylık-Eur'!$I$11 -> 5870756.5 | X15: ='gerç aylık-eur'!$I$11 -> 6472770.1 | Z15: ='Bütçe aylık-Eur'!$J$11 -> 8293869.3 | AA15: ='gerç aylık-eur'!$J$11 -> 9589366.3 | AC15: ='Bütçe aylık-Eur'!$K$11 -> 7857375.1 | AD15: ='gerç aylık-eur'!$K$11 -> 0 | AF15: ='Bütçe aylık-Eur'!$L$11 -> 7288061.4 | AG15: ='gerç aylık-eur'!$L$11 -> 0 | AI15: ='Bütçe aylık-Eur'!$M$11 -> 5516264 | AJ15: ='gerç aylık-eur'!$M$11 -> 0 | AL15: =AP15-AO15 -> 1295497.1 | AM15: =AP15/AO15-1 -> 0.15619936 | AN15: =AL15*0.4 -> 518198.83 | AO15: =IF($A$1=$B$1,B15,IF($A$1=$E$1,E15,IF($A$1=$H$1,H15,IF($A$1=$K$1,K15,IF($A$1=$N$1,N15,IF($A$1=$Q$1,Q15,IF($A$1=$T$1,T15,IF($A$1=$W$1,W15,IF($A$1=$Z$1,Z15,IF($A$1=$AC$1,AC15,IF($A$1=$AF$1,AF15,IF($A$1=$AI$1,AI15)))))))))))) -> 8293869.3 | AP15: =IF($A$1=$B$1,C15,IF($A$1=$E$1,F15,IF($A$1=$H$1,I15,IF($A$1=$K$1,L15,IF($A$1=$N$1,O15,IF($A$1=$Q$1,R15,IF($A$1=$T$1,U15,IF($A$1=$W$1,X15,IF($A$1=$Z$1,AA15,IF($A$1=$AC$1,AD15,IF($A$1=$AF$1,AG15,IF($A$1=$AI$1,AJ15)))))))))))) -> 9589366.3
A16: Alüminyum | B16: ='Bütçe aylık-Eur'!$B$12 -> 19304354 | C16: ='gerç aylık-eur'!$B$12 -> 22219414 | E16: ='Bütçe aylık-Eur'!$C$12 -> 20348124 | F16: ='gerç aylık-eur'!$C$12 -> 19882329 | H16: ='Bütçe aylık-Eur'!$D$12 -> 22345892 | I16: ='gerç aylık-eur'!$D$12 -> 21990947 | K16: ='Bütçe aylık-Eur'!$E$12 -> 19346841 | L16: ='gerç aylık-eur'!$E$12 -> 22058914 | N16: ='Bütçe aylık-Eur'!$F$12 -> 21831856 | O16: ='gerç aylık-eur'!$F$12 -> 24537693 | P16: =O16/N16 -> 1.1239399 | Q16: ='Bütçe aylık-Eur'!$G$12 -> 21545270 | R16: ='gerç aylık-eur'!$G$12 -> 21018078 | T16: ='Bütçe aylık-Eur'!$H$12 -> 21412432 | U16: ='gerç aylık-eur'!$H$12 -> 21629444 | W16: ='Bütçe aylık-Eur'!$I$12 -> 16639195 | X16: ='gerç aylık-eur'!$I$12 -> 15062251 | Z16: ='Bütçe aylık-Eur'!$J$12 -> 24230900 | AA16: ='gerç aylık-eur'!$J$12 -> 22482647 | AC16: ='Bütçe aylık-Eur'!$K$12 -> 22279862 | AD16: ='gerç aylık-eur'!$K$12 -> 0 | AF16: ='Bütçe aylık-Eur'!$L$12 -> 21007179 | AG16: ='gerç aylık-eur'!$L$12 -> 0 | AI16: ='Bütçe aylık-Eur'!$M$12 -> 17391071 | AJ16: ='gerç aylık-eur'!$M$12 -> 0 | AL16: =AP16-AO16 -> -1748253.3 | AM16: =AP16/AO16-1 -> -0.072149746 | AN16: =AL16*0.4 -> -699301.31 | AO16: =IF($A$1=$B$1,B16,IF($A$1=$E$1,E16,IF($A$1=$H$1,H16,IF($A$1=$K$1,K16,IF($A$1=$N$1,N16,IF($A$1=$Q$1,Q16,IF($A$1=$T$1,T16,IF($A$1=$W$1,W16,IF($A$1=$Z$1,Z16,IF($A$1=$AC$1,AC16,IF($A$1=$AF$1,AF16,IF($A$1=$AI$1,AI16)))))))))))) -> 24230900 | AP16: =IF($A$1=$B$1,C16,IF($A$1=$E$1,F16,IF($A$1=$H$1,I16,IF($A$1=$K$1,L16,IF($A$1=$N$1,O16,IF($A$1=$Q$1,R16,IF($A$1=$T$1,U16,IF($A$1=$W$1,X16,IF($A$1=$Z$1,AA16,IF($A$1=$AC$1,AD16,IF($A$1=$AF$1,AG16,IF($A$1=$AI$1,AJ16)))))))))))) -> 22482647
AO17: =IF($A$1=$B$1,B17,IF($A$1=$E$1,E17,IF($A$1=$H$1,H17,IF($A$1=$K$1,K17,IF($A$1=$N$1,N17,IF($A$1=$Q$1,Q17,IF($A$1=$T$1,T17,IF($A$1=$W$1,W17,IF($A$1=$Z$1,Z17,IF($A$1=$AC$1,AC17,IF($A$1=$AF$1,AF17,IF($A$1=$AI$1,AI17)))))))))))) -> 0 | AP17: =IF($A$1=$B$1,C17,IF($A$1=$E$1,F17,IF($A$1=$H$1,I17,IF($A$1=$K$1,L17,IF($A$1=$N$1,O17,IF($A$1=$Q$1,R17,IF($A$1=$T$1,U17,IF($A$1=$W$1,X17,IF($A$1=$Z$1,AA17,IF($A$1=$AC$1,AD17,IF($A$1=$AF$1,AG17,IF($A$1=$AI$1,AJ17)))))))))))) -> 0
AO18: =IF($A$1=$B$1,B18,IF($A$1=$E$1,E18,IF($A$1=$H$1,H18,IF($A$1=$K$1,K18,IF($A$1=$N$1,N18,IF($A$1=$Q$1,Q18,IF($A$1=$T$1,T18,IF($A$1=$W$1,W18,IF($A$1=$Z$1,Z18,IF($A$1=$AC$1,AC18,IF($A$1=$AF$1,AF18,IF($A$1=$AI$1,AI18)))))))))))) -> 0 | AP18: =IF($A$1=$B$1,C18,IF($A$1=$E$1,F18,IF($A$1=$H$1,I18,IF($A$1=$K$1,L18,IF($A$1=$N$1,O18,IF($A$1=$Q$1,R18,IF($A$1=$T$1,U18,IF($A$1=$W$1,X18,IF($A$1=$Z$1,AA18,IF($A$1=$AC$1,AD18,IF($A$1=$AF$1,AG18,IF($A$1=$AI$1,AJ18)))))))))))) -> 0
A19: SHARE OF SALES (%)
A20: İnci Holding | B20: =B9/B6 -> 0.025900517 | C20: =C9/C6 -> 0.024979718 | E20: =E9/E6 -> 0.025747238 | F20: =F9/F6 -> 0.026758305 | H20: =H9/H6 -> 0.026051616 | I20: =I9/I6 -> 0.028240175 | K20: =K9/K6 -> 0.025694817 | L20: =L9/L6 -> 0.025900406 | N20: =N9/N6 -> 0.025993413 | O20: =O9/O6 -> 0.027505155 | Q20: =Q9/Q6 -> 0.026185791 | R20: =R9/R6 -> 0.028179162 | T20: =T9/T6 -> 0.025346662 | U20: =U9/U6 -> 0.026834952 | W20: =W9/W6 -> 0.025491915 | X20: =X9/X6 -> 0.027541763 | Z20: =Z9/Z6 -> 0.026645905 | AA20: =AA9/AA6 -> 0.030203635 | AC20: =AC9/AC6 -> 0.025794306 | AD20: =AD9/AD6 -> #DIV/0! | AF20: =AF9/AF6 -> 0.025768766 | AG20: =AG9/AG6 -> #DIV/0! | AI20: =AI9/AI6 -> 0.025313217 | AJ20: =AJ9/AJ6 -> #DIV/0! | AL20: =AP20-AO20 -> 0.0035577302 | AO20: =IF($A$1=$B$1,B20,IF($A$1=$E$1,E20,IF($A$1=$H$1,H20,IF($A$1=$K$1,K20,IF($A$1=$N$1,N20,IF($A$1=$Q$1,Q20,IF($A$1=$T$1,T20,IF($A$1=$W$1,W20,IF($A$1=$Z$1,Z20,IF($A$1=$AC$1,AC20,IF($A$1=$AF$1,AF20,IF($A$1=$AI$1,AI20)))))))))))) -> 0.026645905 | AP20: =IF($A$1=$B$1,C20,IF($A$1=$E$1,F20,IF($A$1=$H$1,I20,IF($A$1=$K$1,L20,IF($A$1=$N$1,O20,IF($A$1=$Q$1,R20,IF($A$1=$T$1,U20,IF($A$1=$W$1,X20,IF($A$1=$Z$1,AA20,IF($A$1=$AC$1,AD20,IF($A$1=$AF$1,AG20,IF($A$1=$AI$1,AJ20)))))))))))) -> 0.030203635
A21: ISM | B21: =B10/B6 -> 0.030223169 | C21: =C10/C6 -> 0.029195216 | E21: =E10/E6 -> 0.034430572 | F21: =F10/F6 -> 0.034570121 | H21: =H10/H6 -> 0.031720592 | I21: =I10/I6 -> 0.024842191 | K21: =K10/K6 -> 0.036704079 | L21: =L10/L6 -> 0.017555308 | N21: =N10/N6 -> 0.033225483 | O21: =O10/O6 -> 0.024914681 | Q21: =Q10/Q6 -> 0.034927004 | R21: =R10/R6 -> 0.026714943 | T21: =T10/T6 -> 0.028614565 | U21: =U10/U6 -> 0.025501377 | W21: =W10/W6 -> 0.022655137 | X21: =X10/X6 -> 0.022828983 | Z21: =Z10/Z6 -> 0.019182421 | AA21: =AA10/AA6 -> 0.017337504 | AC21: =AC10/AC6 -> 0.016302036 | AD21: =AD10/AD6 -> #DIV/0! | AF21: =AF10/AF6 -> 0.015293082 | AG21: =AG10/AG6 -> #DIV/0! | AI21: =AI10/AI6 -> 0.015049137 | AJ21: =AJ10/AJ6 -> #DIV/0! | AL21: =AP21-AO21 -> -0.0018449172 | AO21: =IF($A$1=$B$1,B21,IF($A$1=$E$1,E21,IF($A$1=$H$1,H21,IF($A$1=$K$1,K21,IF($A$1=$N$1,N21,IF($A$1=$Q$1,Q21,IF($A$1=$T$1,T21,IF($A$1=$W$1,W21,IF($A$1=$Z$1,Z21,IF($A$1=$AC$1,AC21,IF($A$1=$AF$1,AF21,IF($A$1=$AI$1,AI21)))))))))))) -> 0.019182421 | AP21: =IF($A$1=$B$1,C21,IF($A$1=$E$1,F21,IF($A$1=$H$1,I21,IF($A$1=$K$1,L21,IF($A$1=$N$1,O21,IF($A$1=$Q$1,R21,IF($A$1=$T$1,U21,IF($A$1=$W$1,X21,IF($A$1=$Z$1,AA21,IF($A$1=$AC$1,AD21,IF($A$1=$AF$1,AG21,IF($A$1=$AI$1,AJ21)))))))))))) -> 0.017337504
A22: İncitaş | B22: =B11/B6 -> 0.036016437 | C22: =C11/C6 -> 0.032042444 | E22: =E11/E6 -> 0.035139001 | F22: =F11/F6 -> 0.038346756 | H22: =H11/H6 -> 0.041551398 | I22: =I11/I6 -> 0.054208663 | K22: =K11/K6 -> 0.046394855 | L22: =L11/L6 -> 0.047561324 | N22: =N11/N6 -> 0.048372693 | O22: =O11/O6 -> 0.026414714 | Q22: =Q11/Q6 -> 0.049908986 | R22: =R11/R6 -> 0.03792887 | T22: =T11/T6 -> 0.059740823 | U22: =U11/U6 -> 0.034087233 | W22: =W11/W6 -> 0.054582088 | X22: =X11/X6 -> 0.03793594 | Z22: =Z11/Z6 -> 0.0430364 | AA22: =AA11/AA6 -> 0.034054567 | AC22: =AC11/AC6 -> 0.04406525 | AD22: =AD11/AD6 -> #DIV/0! | AF22: =AF11/AF6 -> 0.054590529 | AG22: =AG11/AG6 -> #DIV/0! | AI22: =AI11/AI6 -> 0.05158428 | AJ22: =AJ11/AJ6 -> #DIV/0! | AL22: =AP22-AO22 -> -0.0089818326 | AO22: =IF($A$1=$B$1,B22,IF($A$1=$E$1,E22,IF($A$1=$H$1,H22,IF($A$1=$K$1,K22,IF($A$1=$N$1,N22,IF($A$1=$Q$1,Q22,IF($A$1=$T$1,T22,IF($A$1=$W$1,W22,IF($A$1=$Z$1,Z22,IF($A$1=$AC$1,AC22,IF($A$1=$AF$1,AF22,IF($A$1=$AI$1,AI22)))))))))))) -> 0.0430364 | AP22: =IF($A$1=$B$1,C22,IF($A$1=$E$1,F22,IF($A$1=$H$1,I22,IF($A$1=$K$1,L22,IF($A$1=$N$1,O22,IF($A$1=$Q$1,R22,IF($A$1=$T$1,U22,IF($A$1=$W$1,X22,IF($A$1=$Z$1,AA22,IF($A$1=$AC$1,AD22,IF($A$1=$AF$1,AG22,IF($A$1=$AI$1,AJ22)))))))))))) -> 0.034054567
A23: İnci GS Yuasa | B23: =B12*0.5/B6 -> 0.34606626 | C23: =C12*0.5/C6 -> 0.35320815 | E23: =E12*0.5/E6 -> 0.34598702 | F23: =F12*0.5/F6 -> 0.27923269 | H23: =H12*0.5/H6 -> 0.32715014 | I23: =I12*0.5/I6 -> 0.22750807 | K23: =K12*0.5/K6 -> 0.33552291 | L23: =L12*0.5/L6 -> 0.23371839 | N23: =N12*0.5/N6 -> 0.310729 | O23: =O12*0.5/O6 -> 0.25193909 | Q23: =Q12*0.5/Q6 -> 0.32184129 | R23: =R12*0.5/R6 -> 0.18296352 | T23: =T12*0.5/T6 -> 0.36661651 | U23: =U12*0.5/U6 -> 0.30110988 | W23: =W12*0.5/W6 -> 0.40057241 | X23: =X12*0.5/X6 -> 0.32604017 | Z23: =Z12*0.5/Z6 -> 0.34286889 | AA23: =AA12*0.5/AA6 -> 0.20570792 | AC23: =AC12*0.5/AC6 -> 0.38913528 | AD23: =AD12*0.5/AD6 -> #DIV/0! | AF23: =AF12*0.5/AF6 -> 0.40308718 | AG23: =AG12*0.5/AG6 -> #DIV/0! | AI23: =AI12*0.5/AI6 -> 0.45304758 | AJ23: =AJ12*0.5/AJ6 -> #DIV/0! | AL23: =AP23-AO23 -> -0.13716096 | AO23: =IF($A$1=$B$1,B23,IF($A$1=$E$1,E23,IF($A$1=$H$1,H23,IF($A$1=$K$1,K23,IF($A$1=$N$1,N23,IF($A$1=$Q$1,Q23,IF($A$1=$T$1,T23,IF($A$1=$W$1,W23,IF($A$1=$Z$1,Z23,IF($A$1=$AC$1,AC23,IF($A$1=$AF$1,AF23,IF($A$1=$AI$1,AI23)))))))))))) -> 0.34286889 | AP23: =IF($A$1=$B$1,C23,IF($A$1=$E$1,F23,IF($A$1=$H$1,I23,IF($A$1=$K$1,L23,IF($A$1=$N$1,O23,IF($A$1=$Q$1,R23,IF($A$1=$T$1,U23,IF($A$1=$W$1,X23,IF($A$1=$Z$1,AA23,IF($A$1=$AC$1,AD23,IF($A$1=$AF$1,AG23,IF($A$1=$AI$1,AJ23)))))))))))) -> 0.20570792
A24: Yusen İnci Loj. | B24: =B13*0.4/B6 -> 0.095798424 | C24: =C13*0.4/C6 -> 0.079641207 | E24: =E13*0.4/E6 -> 0.09724038 | F24: =F13*0.4/F6 -> 0.084010554 | H24: =H13*0.4/H6 -> 0.086989283 | I24: =I13*0.4/I6 -> 0.091714513 | K24: =K13*0.4/K6 -> 0.09307728 | L24: =L13*0.4/L6 -> 0.076528388 | N24: =N13*0.4/N6 -> 0.092004075 | O24: =O13*0.4/O6 -> 0.079468192 | Q24: =Q13*0.4/Q6 -> 0.077615135 | R24: =R13*0.4/R6 -> 0.073775275 | T24: =T13*0.4/T6 -> 0.092248718 | U24: =U13*0.4/U6 -> 0.077885373 | W24: =W13*0.4/W6 -> 0.091961269 | X24: =X13*0.4/X6 -> 0.083417831 | Z24: =Z13*0.4/Z6 -> 0.072497603 | AA24: =AA13*0.4/AA6 -> 0.082642428 | AC24: =AC13*0.4/AC6 -> 0.092240719 | AD24: =AD13*0.4/AD6 -> #DIV/0! | AF24: =AF13*0.4/AF6 -> 0.080506586 | AG24: =AG13*0.4/AG6 -> #DIV/0! | AI24: =AI13*0.4/AI6 -> 0.087643071 | AJ24: =AJ13*0.4/AJ6 -> #DIV/0! | AL24: =AP24-AO24 -> 0.010144826 | AO24: =IF($A$1=$B$1,B24,IF($A$1=$E$1,E24,IF($A$1=$H$1,H24,IF($A$1=$K$1,K24,IF($A$1=$N$1,N24,IF($A$1=$Q$1,Q24,IF($A$1=$T$1,T24,IF($A$1=$W$1,W24,IF($A$1=$Z$1,Z24,IF($A$1=$AC$1,AC24,IF($A$1=$AF$1,AF24,IF($A$1=$AI$1,AI24)))))))))))) -> 0.072497603 | AP24: =IF($A$1=$B$1,C24,IF($A$1=$E$1,F24,IF($A$1=$H$1,I24,IF($A$1=$K$1,L24,IF($A$1=$N$1,O24,IF($A$1=$Q$1,R24,IF($A$1=$T$1,U24,IF($A$1=$W$1,X24,IF($A$1=$Z$1,AA24,IF($A$1=$AC$1,AD24,IF($A$1=$AF$1,AG24,IF($A$1=$AI$1,AJ24)))))))))))) -> 0.082642428
A25: Jantaş | B25: =B14*0.4/B6 -> 0.14562927 | C25: =C14*0.4/C6 -> 0.15367275 | E25: =E14*0.4/E6 -> 0.15412463 | F25: =F14*0.4/F6 -> 0.17043175 | H25: =H14*0.4/H6 -> 0.16192558 | I25: =I14*0.4/I6 -> 0.1773326 | K25: =K14*0.4/K6 -> 0.15130453 | L25: =L14*0.4/L6 -> 0.18183502 | N25: =N14*0.4/N6 -> 0.15570129 | O25: =O14*0.4/O6 -> 0.17891645 | Q25: =Q14*0.4/Q6 -> 0.16261097 | R25: =R14*0.4/R6 -> 0.21041959 | T25: =T14*0.4/T6 -> 0.12611632 | U25: =U14*0.4/U6 -> 0.15838952 | W25: =W14*0.4/W6 -> 0.14287905 | X25: =X14*0.4/X6 -> 0.17451555 | Z25: =Z14*0.4/Z6 -> 0.16859263 | AA25: =AA14*0.4/AA6 -> 0.18069167 | AC25: =AC14*0.4/AC6 -> 0.14530221 | AD25: =AD14*0.4/AD6 -> #DIV/0! | AF25: =AF14*0.4/AF6 -> 0.14424161 | AG25: =AG14*0.4/AG6 -> #DIV/0! | AI25: =AI14*0.4/AI6 -> 0.13903681 | AJ25: =AJ14*0.4/AJ6 -> #DIV/0! | AL25: =AP25-AO25 -> 0.01209904 | AO25: =IF($A$1=$B$1,B25,IF($A$1=$E$1,E25,IF($A$1=$H$1,H25,IF($A$1=$K$1,K25,IF($A$1=$N$1,N25,IF($A$1=$Q$1,Q25,IF($A$1=$T$1,T25,IF($A$1=$W$1,W25,IF($A$1=$Z$1,Z25,IF($A$1=$AC$1,AC25,IF($A$1=$AF$1,AF25,IF($A$1=$AI$1,AI25)))))))))))) -> 0.16859263 | AP25: =IF($A$1=$B$1,C25,IF($A$1=$E$1,F25,IF($A$1=$H$1,I25,IF($A$1=$K$1,L25,IF($A$1=$N$1,O25,IF($A$1=$Q$1,R25,IF($A$1=$T$1,U25,IF($A$1=$W$1,X25,IF($A$1=$Z$1,AA25,IF($A$1=$AC$1,AD25,IF($A$1=$AF$1,AG25,IF($A$1=$AI$1,AJ25)))))))))))) -> 0.18069167
A26: Çelik | B26: =B15*0.4/B6 -> 0.10981633 | C26: =C15*0.4/C6 -> 0.10368711 | E26: =E15*0.4/E6 -> 0.086876202 | F26: =F15*0.4/F6 -> 0.12893825 | H26: =H15*0.4/H6 -> 0.10266518 | I26: =I15*0.4/I6 -> 0.12774778 | K26: =K15*0.4/K6 -> 0.11064697 | L26: =L15*0.4/L6 -> 0.13196383 | N26: =N15*0.4/N6 -> 0.10501268 | O26: =O15*0.4/O6 -> 0.11440031 | Q26: =Q15*0.4/Q6 -> 0.095328053 | R26: =R15*0.4/R6 -> 0.12215255 | T26: =T15*0.4/T6 -> 0.087732175 | U26: =U15*0.4/U6 -> 0.11834215 | W26: =W15*0.4/W6 -> 0.089188906 | X26: =X15*0.4/X6 -> 0.1181021 | Z26: =Z15*0.4/Z6 -> 0.10091688 | AA26: =AA15*0.4/AA6 -> 0.14665812 | AC26: =AC15*0.4/AC6 -> 0.095159411 | AD26: =AD15*0.4/AD6 -> #DIV/0! | AF26: =AF15*0.4/AF6 -> 0.091986601 | AG26: =AG15*0.4/AG6 -> #DIV/0! | AI26: =AI15*0.4/AI6 -> 0.076802124 | AJ26: =AJ15*0.4/AJ6 -> #DIV/0! | AL26: =AP26-AO26 -> 0.045741243 | AO26: =IF($A$1=$B$1,B26,IF($A$1=$E$1,E26,IF($A$1=$H$1,H26,IF($A$1=$K$1,K26,IF($A$1=$N$1,N26,IF($A$1=$Q$1,Q26,IF($A$1=$T$1,T26,IF($A$1=$W$1,W26,IF($A$1=$Z$1,Z26,IF($A$1=$AC$1,AC26,IF($A$1=$AF$1,AF26,IF($A$1=$AI$1,AI26)))))))))))) -> 0.10091688 | AP26: =IF($A$1=$B$1,C26,IF($A$1=$E$1,F26,IF($A$1=$H$1,I26,IF($A$1=$K$1,L26,IF($A$1=$N$1,O26,IF($A$1=$Q$1,R26,IF($A$1=$T$1,U26,IF($A$1=$W$1,X26,IF($A$1=$Z$1,AA26,IF($A$1=$AC$1,AD26,IF($A$1=$AF$1,AG26,IF($A$1=$AI$1,AJ26)))))))))))) -> 0.14665812
A27: Alüminyum | B27: =B16*0.4/B6 -> 0.27976285 | C27: =C16*0.4/C6 -> 0.29421504 | E27: =E16*0.4/E6 -> 0.28965236 | F27: =F16*0.4/F6 -> 0.2935581 | H27: =H16*0.4/H6 -> 0.28737624 | I27: =I16*0.4/I6 -> 0.31390762 | K27: =K16*0.4/K6 -> 0.26775914 | L27: =L16*0.4/L6 -> 0.33168101 | N27: =N16*0.4/N6 -> 0.29110716 | O27: =O16*0.4/O6 -> 0.34682922 | Q27: =Q16*0.4/Q6 -> 0.29595103 | R27: =R16*0.4/R6 -> 0.35445879 | T27: =T16*0.4/T6 -> 0.28690753 | U27: =U16*0.4/U6 -> 0.31807148 | W27: =W16*0.4/W6 -> 0.25278371 | X27: =X16*0.4/X6 -> 0.27482569 | Z27: =Z16*0.4/Z6 -> 0.29483306 | AA27: =AA16*0.4/AA6 -> 0.34384574 | AC27: =AC16*0.4/AC6 -> 0.26982784 | AD27: =AD16*0.4/AD6 -> #DIV/0! | AF27: =AF16*0.4/AF6 -> 0.26514308 | AG27: =AG16*0.4/AG6 -> #DIV/0! | AI27: =AI16*0.4/AI6 -> 0.24213329 | AJ27: =AJ16*0.4/AJ6 -> #DIV/0! | AL27: =AP27-AO27 -> 0.049012683 | AO27: =IF($A$1=$B$1,B27,IF($A$1=$E$1,E27,IF($A$1=$H$1,H27,IF($A$1=$K$1,K27,IF($A$1=$N$1,N27,IF($A$1=$Q$1,Q27,IF($A$1=$T$1,T27,IF($A$1=$W$1,W27,IF($A$1=$Z$1,Z27,IF($A$1=$AC$1,AC27,IF($A$1=$AF$1,AF27,IF($A$1=$AI$1,AI27)))))))))))) -> 0.29483306 | AP27: =IF($A$1=$B$1,C27,IF($A$1=$E$1,F27,IF($A$1=$H$1,I27,IF($A$1=$K$1,L27,IF($A$1=$N$1,O27,IF($A$1=$Q$1,R27,IF($A$1=$T$1,U27,IF($A$1=$W$1,X27,IF($A$1=$Z$1,AA27,IF($A$1=$AC$1,AD27,IF($A$1=$AF$1,AG27,IF($A$1=$AI$1,AJ27)))))))))))) -> 0.34384574
AL28: =AP28-AO28 -> 0 | AO28: =IF($A$1=$B$1,B28,IF($A$1=$E$1,E28,IF($A$1=$H$1,H28,IF($A$1=$K$1,K28,IF($A$1=$N$1,N28,IF($A$1=$Q$1,Q28,IF($A$1=$T$1,T28,IF($A$1=$W$1,W28,IF($A$1=$Z$1,Z28,IF($A$1=$AC$1,AC28,IF($A$1=$AF$1,AF28,IF($A$1=$AI$1,AI28)))))))))))) -> 0 | AP28: =IF($A$1=$B$1,C28,IF($A$1=$E$1,F28,IF($A$1=$H$1,I28,IF($A$1=$K$1,L28,IF($A$1=$N$1,O28,IF($A$1=$Q$1,R28,IF($A$1=$T$1,U28,IF($A$1=$W$1,X28,IF($A$1=$Z$1,AA28,IF($A$1=$AC$1,AD28,IF($A$1=$AF$1,AG28,IF($A$1=$AI$1,AJ28)))))))))))) -> 0
AL29: =AP29-AO29 -> 0 | AO29: =IF($A$1=$B$1,B29,IF($A$1=$E$1,E29,IF($A$1=$H$1,H29,IF($A$1=$K$1,K29,IF($A$1=$N$1,N29,IF($A$1=$Q$1,Q29,IF($A$1=$T$1,T29,IF($A$1=$W$1,W29,IF($A$1=$Z$1,Z29,IF($A$1=$AC$1,AC29,IF($A$1=$AF$1,AF29,IF($A$1=$AI$1,AI29)))))))))))) -> 0 | AP29: =IF($A$1=$B$1,C29,IF($A$1=$E$1,F29,IF($A$1=$H$1,I29,IF($A$1=$K$1,L29,IF($A$1=$N$1,O29,IF($A$1=$Q$1,R29,IF($A$1=$T$1,U29,IF($A$1=$W$1,X29,IF($A$1=$Z$1,AA29,IF($A$1=$AC$1,AD29,IF($A$1=$AF$1,AG29,IF($A$1=$AI$1,AJ29)))))))))))) -> 0
A30: Net Sales | B30: ='Bütçe aylık-Eur'!$B$4 -> 27601026 | C30: ='gerç aylık-eur'!$B$4 -> 30208401 | E30: ='Bütçe aylık-Eur'!$C$4 -> 28100063 | F30: ='gerç aylık-eur'!$C$4 -> 27091507 | H30: ='Bütçe aylık-Eur'!$D$4 -> 31103326 | I30: ='gerç aylık-eur'!$D$4 -> 28022189 | K30: ='Bütçe aylık-Eur'!$E$4 -> 28901858 | L30: ='gerç aylık-eur'!$E$4 -> 26602564 | N30: ='Bütçe aylık-Eur'!$F$4 -> 29998377 | O30: ='gerç aylık-eur'!$F$4 -> 28299453 | Q30: ='Bütçe aylık-Eur'!$G$4 -> 29120047 | R30: ='gerç aylık-eur'!$G$4 -> 23718502 | T30: ='Bütçe aylık-Eur'!$H$4 -> 29852729 | U30: ='gerç aylık-eur'!$H$4 -> 27200733 | W30: ='Bütçe aylık-Eur'!$I$4 -> 26329537 | X30: ='gerç aylık-eur'!$I$4 -> 21922624 | Z30: ='Bütçe aylık-Eur'!$J$4 -> 32874061 | AA30: ='gerç aylık-eur'!$J$4 -> 26154341 | AC30: ='Bütçe aylık-Eur'!$K$4 -> 33028263 | AD30: ='gerç aylık-eur'!$K$4 -> 0 | AF30: ='Bütçe aylık-Eur'!$L$4 -> 31691839 | AG30: ='gerç aylık-eur'!$L$4 -> 0 | AI30: ='Bütçe aylık-Eur'!$M$4 -> 28729747 | AJ30: ='gerç aylık-eur'!$M$4 -> 0 | AL30: =AP30-AO30 -> -6719720.5 | AM30: =AP30/AO30-1 -> -0.20440798 | AO30: =IF($A$1=$B$1,B30,IF($A$1=$E$1,E30,IF($A$1=$H$1,H30,IF($A$1=$K$1,K30,IF($A$1=$N$1,N30,IF($A$1=$Q$1,Q30,IF($A$1=$T$1,T30,IF($A$1=$W$1,W30,IF($A$1=$Z$1,Z30,IF($A$1=$AC$1,AC30,IF($A$1=$AF$1,AF30,IF($A$1=$AI$1,AI30)))))))))))) -> 32874061 | AP30: =IF($A$1=$B$1,C30,IF($A$1=$E$1,F30,IF($A$1=$H$1,I30,IF($A$1=$K$1,L30,IF($A$1=$N$1,O30,IF($A$1=$Q$1,R30,IF($A$1=$T$1,U30,IF($A$1=$W$1,X30,IF($A$1=$Z$1,AA30,IF($A$1=$AC$1,AD30,IF($A$1=$AF$1,AG30,IF($A$1=$AI$1,AJ30)))))))))))) -> 26154341
A31: Cost of Sales | B31: ='Bütçe aylık-Eur'!$B$15 -> -22308743 | C31: ='gerç aylık-eur'!$B$15 -> -24977661 | E31: ='Bütçe aylık-Eur'!$C$15 -> -22508720 | F31: ='gerç aylık-eur'!$C$15 -> -21839161 | H31: ='Bütçe aylık-Eur'!$D$15 -> -24694860 | I31: ='gerç aylık-eur'!$D$15 -> -22923129 | K31: ='Bütçe aylık-Eur'!$E$15 -> -23329116 | L31: ='gerç aylık-eur'!$E$15 -> -21871431 | N31: ='Bütçe aylık-Eur'!$F$15 -> -23674369 | O31: ='gerç aylık-eur'!$F$15 -> -22630201 | Q31: ='Bütçe aylık-Eur'!$G$15 -> -23220513 | R31: ='gerç aylık-eur'!$G$15 -> -19359712 | T31: ='Bütçe aylık-Eur'!$H$15 -> -23762767 | U31: ='gerç aylık-eur'!$H$15 -> -22225002 | W31: ='Bütçe aylık-Eur'!$I$15 -> -21666177 | X31: ='gerç aylık-eur'!$I$15 -> -17755689 | Z31: ='Bütçe aylık-Eur'!$J$15 -> -25000304 | AA31: ='gerç aylık-eur'!$J$15 -> -19802016 | AC31: ='Bütçe aylık-Eur'!$K$15 -> -25695835 | AD31: ='gerç aylık-eur'!$K$15 -> 0 | AF31: ='Bütçe aylık-Eur'!$L$15 -> -24520547 | AG31: ='gerç aylık-eur'!$L$15 -> 0 | AI31: ='Bütçe aylık-Eur'!$M$15 -> -22288973 | AJ31: ='gerç aylık-eur'!$M$15 -> 0 | AL31: =AP31-AO31 -> 5198288 | AM31: =AP31/AO31-1 -> -0.20792899 | AO31: =IF($A$1=$B$1,B31,IF($A$1=$E$1,E31,IF($A$1=$H$1,H31,IF($A$1=$K$1,K31,IF($A$1=$N$1,N31,IF($A$1=$Q$1,Q31,IF($A$1=$T$1,T31,IF($A$1=$W$1,W31,IF($A$1=$Z$1,Z31,IF($A$1=$AC$1,AC31,IF($A$1=$AF$1,AF31,IF($A$1=$AI$1,AI31)))))))))))) -> -25000304 | AP31: =IF($A$1=$B$1,C31,IF($A$1=$E$1,F31,IF($A$1=$H$1,I31,IF($A$1=$K$1,L31,IF($A$1=$N$1,O31,IF($A$1=$Q$1,R31,IF($A$1=$T$1,U31,IF($A$1=$W$1,X31,IF($A$1=$Z$1,AA31,IF($A$1=$AC$1,AD31,IF($A$1=$AF$1,AG31,IF($A$1=$AI$1,AJ31)))))))))))) -> -19802016
A32: Gross Profit | B32: ='Bütçe aylık-Eur'!$B$26 -> 5292283.2 | C32: ='gerç aylık-eur'!$B$26 -> 5230739.5 | E32: ='Bütçe aylık-Eur'!$C$26 -> 5591343.6 | F32: ='gerç aylık-eur'!$C$26 -> 5252346.4 | H32: ='Bütçe aylık-Eur'!$D$26 -> 6408466.7 | I32: ='gerç aylık-eur'!$D$26 -> 5099060.2 | K32: ='Bütçe aylık-Eur'!$E$26 -> 5572742.7 | L32: ='gerç aylık-eur'!$E$26 -> 4731133.1 | N32: ='Bütçe aylık-Eur'!$F$26 -> 6324007 | O32: ='gerç aylık-eur'!$F$26 -> 5669251.9 | Q32: ='Bütçe aylık-Eur'!$G$26 -> 5899532.2 | R32: ='gerç aylık-eur'!$G$26 -> 4358789.3 | T32: ='Bütçe aylık-Eur'!$H$26 -> 6089964.3 | U32: ='gerç aylık-eur'!$H$26 -> 4975731.5 | W32: ='Bütçe aylık-Eur'!$I$26 -> 4663360.8 | X32: ='gerç aylık-eur'!$I$26 -> 4166934.9 | Z32: ='Bütçe aylık-Eur'!$J$26 -> 7873756.9 | AA32: ='gerç aylık-eur'!$J$26 -> 6352325 | AC32: ='Bütçe aylık-Eur'!$K$26 -> 7332425.3 | AD32: ='gerç aylık-eur'!$K$26 -> 0 | AF32: ='Bütçe aylık-Eur'!$L$26 -> 7171294.2 | AG32: ='gerç aylık-eur'!$L$26 -> 0 | AI32: ='Bütçe aylık-Eur'!$M$26 -> 6440775.3 | AJ32: ='gerç aylık-eur'!$M$26 -> 0 | AL32: =AP32-AO32 -> -1521431.9 | AM32: =AP32/AO32-1 -> -0.1932282 | AO32: =IF($A$1=$B$1,B32,IF($A$1=$E$1,E32,IF($A$1=$H$1,H32,IF($A$1=$K$1,K32,IF($A$1=$N$1,N32,IF($A$1=$Q$1,Q32,IF($A$1=$T$1,T32,IF($A$1=$W$1,W32,IF($A$1=$Z$1,Z32,IF($A$1=$AC$1,AC32,IF($A$1=$AF$1,AF32,IF($A$1=$AI$1,AI32)))))))))))) -> 7873756.9 | AP32: =IF($A$1=$B$1,C32,IF($A$1=$E$1,F32,IF($A$1=$H$1,I32,IF($A$1=$K$1,L32,IF($A$1=$N$1,O32,IF($A$1=$Q$1,R32,IF($A$1=$T$1,U32,IF($A$1=$W$1,X32,IF($A$1=$Z$1,AA32,IF($A$1=$AC$1,AD32,IF($A$1=$AF$1,AG32,IF($A$1=$AI$1,AJ32)))))))))))) -> 6352325
A33: Gross Profit Margin | B33: =B32/B30 -> 0.19174226 | C33: =C32/C30 -> 0.17315513 | E33: =E32/E30 -> 0.19897975 | F33: =F32/F30 -> 0.19387428 | H33: =H32/H30 -> 0.20603798 | I33: =I32/I30 -> 0.18196509 | K33: =K32/K30 -> 0.19281607 | L33: =L32/L30 -> 0.177845 | N33: =N32/N30 -> 0.21081164 | O33: =O32/O30 -> 0.2003308 | Q33: =Q32/Q30 -> 0.2025935 | R33: =R32/R30 -> 0.1837717 | T33: =T32/T30 -> 0.20400025 | U33: =U32/U30 -> 0.18292637 | W33: =W32/W30 -> 0.17711519 | X33: =X32/X30 -> 0.19007464 | Z33: =Z32/Z30 -> 0.23951275 | AA33: =AA32/AA30 -> 0.24287842 | AC33: =AC32/AC30 -> 0.22200457 | AD33: =AD32/AD30 -> #DIV/0! | AF33: =AF32/AF30 -> 0.22628205 | AG33: =AG32/AG30 -> #DIV/0! | AI33: =AI32/AI30 -> 0.22418489 | AJ33: =AJ32/AJ30 -> #DIV/0! | AM33: =AP33-AO33 -> 0.0033656695 | AO33: =IF($A$1=$B$1,B33,IF($A$1=$E$1,E33,IF($A$1=$H$1,H33,IF($A$1=$K$1,K33,IF($A$1=$N$1,N33,IF($A$1=$Q$1,Q33,IF($A$1=$T$1,T33,IF($A$1=$W$1,W33,IF($A$1=$Z$1,Z33,IF($A$1=$AC$1,AC33,IF($A$1=$AF$1,AF33,IF($A$1=$AI$1,AI33)))))))))))) -> 0.23951275 | AP33: =IF($A$1=$B$1,C33,IF($A$1=$E$1,F33,IF($A$1=$H$1,I33,IF($A$1=$K$1,L33,IF($A$1=$N$1,O33,IF($A$1=$Q$1,R33,IF($A$1=$T$1,U33,IF($A$1=$W$1,X33,IF($A$1=$Z$1,AA33,IF($A$1=$AC$1,AD33,IF($A$1=$AF$1,AG33,IF($A$1=$AI$1,AJ33)))))))))))) -> 0.24287842
A35: GROSS PROFIT BY CHANNELS (100%)
A36: İnci Holding | B36: ='Bütçe aylık-Eur'!$B$27 -> 714880.86 | C36: ='gerç aylık-eur'!$B$27 -> 754597.33 | E36: ='Bütçe aylık-Eur'!$C$27 -> 723499.01 | F36: ='gerç aylık-eur'!$C$27 -> 724922.82 | H36: ='Bütçe aylık-Eur'!$D$27 -> 810291.92 | I36: ='gerç aylık-eur'!$D$27 -> 791351.52 | K36: ='Bütçe aylık-Eur'!$E$27 -> 742627.95 | L36: ='gerç aylık-eur'!$E$27 -> 689017.21 | N36: ='Bütçe aylık-Eur'!$F$27 -> 779760.2 | O36: ='gerç aylık-eur'!$F$27 -> 778380.85 | Q36: ='Bütçe aylık-Eur'!$G$27 -> 762531.48 | R36: ='gerç aylık-eur'!$G$27 -> 668367.49 | T36: ='Bütçe aylık-Eur'!$H$27 -> 756667.04 | U36: ='gerç aylık-eur'!$H$27 -> 729930.38 | W36: ='Bütçe aylık-Eur'!$I$27 -> 671190.31 | X36: ='gerç aylık-eur'!$I$27 -> 603787.73 | Z36: ='Bütçe aylık-Eur'!$J$27 -> 875959.11 | AA36: ='gerç aylık-eur'!$J$27 -> 789956.17 | AC36: ='Bütçe aylık-Eur'!$K$27 -> 851941.11 | AD36: ='gerç aylık-eur'!$K$27 -> 0 | AF36: ='Bütçe aylık-Eur'!$L$27 -> 816659.57 | AG36: ='gerç aylık-eur'!$L$27 -> 0 | AI36: ='Bütçe aylık-Eur'!$M$27 -> 727242.32 | AJ36: ='gerç aylık-eur'!$M$27 -> 0 | AL36: =AP36-AO36 -> -86002.945 | AM36: =AP36/AO36-1 -> -0.09818146 | AO36: =IF($A$1=$B$1,B36,IF($A$1=$E$1,E36,IF($A$1=$H$1,H36,IF($A$1=$K$1,K36,IF($A$1=$N$1,N36,IF($A$1=$Q$1,Q36,IF($A$1=$T$1,T36,IF($A$1=$W$1,W36,IF($A$1=$Z$1,Z36,IF($A$1=$AC$1,AC36,IF($A$1=$AF$1,AF36,IF($A$1=$AI$1,AI36)))))))))))) -> 875959.11 | AP36: =IF($A$1=$B$1,C36,IF($A$1=$E$1,F36,IF($A$1=$H$1,I36,IF($A$1=$K$1,L36,IF($A$1=$N$1,O36,IF($A$1=$Q$1,R36,IF($A$1=$T$1,U36,IF($A$1=$W$1,X36,IF($A$1=$Z$1,AA36,IF($A$1=$AC$1,AD36,IF($A$1=$AF$1,AG36,IF($A$1=$AI$1,AJ36)))))))))))) -> 789956.17
A37: ISM | B37: ='Bütçe aylık-Eur'!$B$28 -> 142793.69 | C37: ='gerç aylık-eur'!$B$28 -> 114810.93 | E37: ='Bütçe aylık-Eur'!$C$28 -> 247956.93 | F37: ='gerç aylık-eur'!$C$28 -> 201075.93 | H37: ='Bütçe aylık-Eur'!$D$28 -> 270995.86 | I37: ='gerç aylık-eur'!$D$28 -> 184064.86 | K37: ='Bütçe aylık-Eur'!$E$28 -> 343271.12 | L37: ='gerç aylık-eur'!$E$28 -> 118802.17 | N37: ='Bütçe aylık-Eur'!$F$28 -> 370588.63 | O37: ='gerç aylık-eur'!$F$28 -> 176786.87 | Q37: ='Bütçe aylık-Eur'!$G$28 -> 354534.56 | R37: ='gerç aylık-eur'!$G$28 -> 181448.19 | T37: ='Bütçe aylık-Eur'!$H$28 -> 294235 | U37: ='gerç aylık-eur'!$H$28 -> 192831 | W37: ='Bütçe aylık-Eur'!$I$28 -> 166609.25 | X37: ='gerç aylık-eur'!$I$28 -> 128361.89 | Z37: ='Bütçe aylık-Eur'!$J$28 -> 202029.26 | AA37: ='gerç aylık-eur'!$J$28 -> 103702.61 | AC37: ='Bütçe aylık-Eur'!$K$28 -> 146230.21 | AD37: ='gerç aylık-eur'!$K$28 -> 0 | AF37: ='Bütçe aylık-Eur'!$L$28 -> 120857.32 | AG37: ='gerç aylık-eur'!$L$28 -> 0 | AI37: ='Bütçe aylık-Eur'!$M$28 -> 79493.015 | AJ37: ='gerç aylık-eur'!$M$28 -> 0 | AL37: =AP37-AO37 -> -98326.642 | AM37: =AP37/AO37-1 -> -0.48669507 | AO37: =IF($A$1=$B$1,B37,IF($A$1=$E$1,E37,IF($A$1=$H$1,H37,IF($A$1=$K$1,K37,IF($A$1=$N$1,N37,IF($A$1=$Q$1,Q37,IF($A$1=$T$1,T37,IF($A$1=$W$1,W37,IF($A$1=$Z$1,Z37,IF($A$1=$AC$1,AC37,IF($A$1=$AF$1,AF37,IF($A$1=$AI$1,AI37)))))))))))) -> 202029.26 | AP37: =IF($A$1=$B$1,C37,IF($A$1=$E$1,F37,IF($A$1=$H$1,I37,IF($A$1=$K$1,L37,IF($A$1=$N$1,O37,IF($A$1=$Q$1,R37,IF($A$1=$T$1,U37,IF($A$1=$W$1,X37,IF($A$1=$Z$1,AA37,IF($A$1=$AC$1,AD37,IF($A$1=$AF$1,AG37,IF($A$1=$AI$1,AJ37)))))))))))) -> 103702.61
A38: İncitaş | B38: ='Bütçe aylık-Eur'!$B$29 -> 166073.62 | C38: ='gerç aylık-eur'!$B$29 -> 155750.78 | E38: ='Bütçe aylık-Eur'!$C$29 -> 167711.01 | F38: ='gerç aylık-eur'!$C$29 -> 151226.36 | H38: ='Bütçe aylık-Eur'!$D$29 -> 244700.52 | I38: ='gerç aylık-eur'!$D$29 -> 185887.15 | K38: ='Bütçe aylık-Eur'!$E$29 -> 260983.75 | L38: ='gerç aylık-eur'!$E$29 -> 163819.86 | N38: ='Bütçe aylık-Eur'!$F$29 -> 286550.91 | O38: ='gerç aylık-eur'!$F$29 -> 155411.71 | Q38: ='Bütçe aylık-Eur'!$G$29 -> 292065.18 | R38: ='gerç aylık-eur'!$G$29 -> 142552.22 | T38: ='Bütçe aylık-Eur'!$H$29 -> 324153.65 | U38: ='gerç aylık-eur'!$H$29 -> 172485.32 | W38: ='Bütçe aylık-Eur'!$I$29 -> 291101.19 | X38: ='gerç aylık-eur'!$I$29 -> 130379.57 | Z38: ='Bütçe aylık-Eur'!$J$29 -> 288120.49 | AA38: ='gerç aylık-eur'!$J$29 -> 170335.83 | AC38: ='Bütçe aylık-Eur'!$K$29 -> 281692.4 | AD38: ='gerç aylık-eur'!$K$29 -> 0 | AF38: ='Bütçe aylık-Eur'!$L$29 -> 295577.61 | AG38: ='gerç aylık-eur'!$L$29 -> 0 | AI38: ='Bütçe aylık-Eur'!$M$29 -> 272709.05 | AJ38: ='gerç aylık-eur'!$M$29 -> 0 | AL38: =AP38-AO38 -> -117784.65 | AM38: =AP38/AO38-1 -> -0.40880347 | AO38: =IF($A$1=$B$1,B38,IF($A$1=$E$1,E38,IF($A$1=$H$1,H38,IF($A$1=$K$1,K38,IF($A$1=$N$1,N38,IF($A$1=$Q$1,Q38,IF($A$1=$T$1,T38,IF($A$1=$W$1,W38,IF($A$1=$Z$1,Z38,IF($A$1=$AC$1,AC38,IF($A$1=$AF$1,AF38,IF($A$1=$AI$1,AI38)))))))))))) -> 288120.49 | AP38: =IF($A$1=$B$1,C38,IF($A$1=$E$1,F38,IF($A$1=$H$1,I38,IF($A$1=$K$1,L38,IF($A$1=$N$1,O38,IF($A$1=$Q$1,R38,IF($A$1=$T$1,U38,IF($A$1=$W$1,X38,IF($A$1=$Z$1,AA38,IF($A$1=$AC$1,AD38,IF($A$1=$AF$1,AG38,IF($A$1=$AI$1,AJ38)))))))))))) -> 170335.83
A39: İnci GS Yuasa | B39: ='Bütçe aylık-Eur'!$B$30 -> 3474138.3 | C39: ='gerç aylık-eur'!$B$30 -> 3182076.8 | E39: ='Bütçe aylık-Eur'!$C$30 -> 3424875.7 | F39: ='gerç aylık-eur'!$C$30 -> 2895865.2 | H39: ='Bütçe aylık-Eur'!$D$30 -> 3680540.1 | I39: ='gerç aylık-eur'!$D$30 -> 1755014.7 | K39: ='Bütçe aylık-Eur'!$E$30 -> 3367439.9 | L39: ='gerç aylık-eur'!$E$30 -> 1361465.3 | N39: ='Bütçe aylık-Eur'!$F$30 -> 3387750.9 | O39: ='gerç aylık-eur'!$F$30 -> 1748452.5 | Q39: ='Bütçe aylık-Eur'!$G$30 -> 3696214.7 | R39: ='gerç aylık-eur'!$G$30 -> 880896.07 | T39: ='Bütçe aylık-Eur'!$H$30 -> 4193852.5 | U39: ='gerç aylık-eur'!$H$30 -> 1233671.6 | W39: ='Bütçe aylık-Eur'!$I$30 -> 4378809 | X39: ='gerç aylık-eur'!$I$30 -> 2370779.4 | Z39: ='Bütçe aylık-Eur'!$J$30 -> 4881164.3 | AA39: ='gerç aylık-eur'!$J$30 -> 1647421 | AC39: ='Bütçe aylık-Eur'!$K$30 -> 5606321.8 | AD39: ='gerç aylık-eur'!$K$30 -> 0 | AF39: ='Bütçe aylık-Eur'!$L$30 -> 5680158.8 | AG39: ='gerç aylık-eur'!$L$30 -> 0 | AI39: ='Bütçe aylık-Eur'!$M$30 -> 6501898.6 | AJ39: ='gerç aylık-eur'!$M$30 -> 0 | AL39: =AP39-AO39 -> -3233743.4 | AM39: =AP39/AO39-1 -> -0.66249426 | AO39: =IF($A$1=$B$1,B39,IF($A$1=$E$1,E39,IF($A$1=$H$1,H39,IF($A$1=$K$1,K39,IF($A$1=$N$1,N39,IF($A$1=$Q$1,Q39,IF($A$1=$T$1,T39,IF($A$1=$W$1,W39,IF($A$1=$Z$1,Z39,IF($A$1=$AC$1,AC39,IF($A$1=$AF$1,AF39,IF($A$1=$AI$1,AI39)))))))))))) -> 4881164.3 | AP39: =IF($A$1=$B$1,C39,IF($A$1=$E$1,F39,IF($A$1=$H$1,I39,IF($A$1=$K$1,L39,IF($A$1=$N$1,O39,IF($A$1=$Q$1,R39,IF($A$1=$T$1,U39,IF($A$1=$W$1,X39,IF($A$1=$Z$1,AA39,IF($A$1=$AC$1,AD39,IF($A$1=$AF$1,AG39,IF($A$1=$AI$1,AJ39)))))))))))) -> 1647421
A40: Yusen İnci Loj. | B40: ='Bütçe aylık-Eur'!$B$31 -> 1305194.3 | C40: ='gerç aylık-eur'!$B$31 -> 1207657 | E40: ='Bütçe aylık-Eur'!$C$31 -> 1333939.6 | F40: ='gerç aylık-eur'!$C$31 -> 1325142.9 | H40: ='Bütçe aylık-Eur'!$D$31 -> 1286656.5 | I40: ='gerç aylık-eur'!$D$31 -> 1186840 | K40: ='Bütçe aylık-Eur'!$E$31 -> 1166357.7 | L40: ='gerç aylık-eur'!$E$31 -> 963568.65 | N40: ='Bütçe aylık-Eur'!$F$31 -> 1233362.5 | O40: ='gerç aylık-eur'!$F$31 -> 1246993.7 | Q40: ='Bütçe aylık-Eur'!$G$31 -> 1103088.9 | R40: ='gerç aylık-eur'!$G$31 -> 954988.75 | T40: ='Bütçe aylık-Eur'!$H$31 -> 1240060.1 | U40: ='gerç aylık-eur'!$H$31 -> 1096536.1 | W40: ='Bütçe aylık-Eur'!$I$31 -> 1264851.2 | X40: ='gerç aylık-eur'!$I$31 -> 1108857 | Z40: ='Bütçe aylık-Eur'!$J$31 -> 1236788.4 | AA40: ='gerç aylık-eur'!$J$31 -> 1183021.4 | AC40: ='Bütçe aylık-Eur'!$K$31 -> 1413059.4 | AD40: ='gerç aylık-eur'!$K$31 -> 0 | AF40: ='Bütçe aylık-Eur'!$L$31 -> 1285663.6 | AG40: ='gerç aylık-eur'!$L$31 -> 0 | AI40: ='Bütçe aylık-Eur'!$M$31 -> 1201417.8 | AJ40: ='gerç aylık-eur'!$M$31 -> 0 | AL40: =AP40-AO40 -> -53767.077 | AM40: =AP40/AO40-1 -> -0.04347314 | AO40: =IF($A$1=$B$1,B40,IF($A$1=$E$1,E40,IF($A$1=$H$1,H40,IF($A$1=$K$1,K40,IF($A$1=$N$1,N40,IF($A$1=$Q$1,Q40,IF($A$1=$T$1,T40,IF($A$1=$W$1,W40,IF($A$1=$Z$1,Z40,IF($A$1=$AC$1,AC40,IF($A$1=$AF$1,AF40,IF($A$1=$AI$1,AI40)))))))))))) -> 1236788.4 | AP40: =IF($A$1=$B$1,C40,IF($A$1=$E$1,F40,IF($A$1=$H$1,I40,IF($A$1=$K$1,L40,IF($A$1=$N$1,O40,IF($A$1=$Q$1,R40,IF($A$1=$T$1,U40,IF($A$1=$W$1,X40,IF($A$1=$Z$1,AA40,IF($A$1=$AC$1,AD40,IF($A$1=$AF$1,AG40,IF($A$1=$AI$1,AJ40)))))))))))) -> 1183021.4
A41: Jantaş | B41: ='Bütçe aylık-Eur'!$B$32 -> 1290276.9 | C41: ='gerç aylık-eur'!$B$32 -> 1395842.7 | E41: ='Bütçe aylık-Eur'!$C$32 -> 1749802.4 | F41: ='gerç aylık-eur'!$C$32 -> 2070795.1 | H41: ='Bütçe aylık-Eur'!$D$32 -> 2786154.1 | I41: ='gerç aylık-eur'!$D$32 -> 2402710.9 | K41: ='Bütçe aylık-Eur'!$E$32 -> 1379505.6 | L41: ='gerç aylık-eur'!$E$32 -> 2262828.2 | N41: ='Bütçe aylık-Eur'!$F$32 -> 1879167.9 | O41: ='gerç aylık-eur'!$F$32 -> 2394840.1 | Q41: ='Bütçe aylık-Eur'!$G$32 -> 2130869 | R41: ='gerç aylık-eur'!$G$32 -> 2237292.4 | T41: ='Bütçe aylık-Eur'!$H$32 -> 1168028.1 | U41: ='gerç aylık-eur'!$H$32 -> 2041117.5 | W41: ='Bütçe aylık-Eur'!$I$32 -> 678577.91 | X41: ='gerç aylık-eur'!$I$32 -> 1521176.5 | Z41: ='Bütçe aylık-Eur'!$J$32 -> 3222554.5 | AA41: ='gerç aylık-eur'!$J$32 -> 3027070.6 | AC41: ='Bütçe aylık-Eur'!$K$32 -> 2145554.2 | AD41: ='gerç aylık-eur'!$K$32 -> 0 | AF41: ='Bütçe aylık-Eur'!$L$32 -> 2136550.3 | AG41: ='gerç aylık-eur'!$L$32 -> 0 | AI41: ='Bütçe aylık-Eur'!$M$32 -> 1671419.7 | AJ41: ='gerç aylık-eur'!$M$32 -> 0 | AL41: =AP41-AO41 -> -195483.9 | AM41: =AP41/AO41-1 -> -0.060661164 | AO41: =IF($A$1=$B$1,B41,IF($A$1=$E$1,E41,IF($A$1=$H$1,H41,IF($A$1=$K$1,K41,IF($A$1=$N$1,N41,IF($A$1=$Q$1,Q41,IF($A$1=$T$1,T41,IF($A$1=$W$1,W41,IF($A$1=$Z$1,Z41,IF($A$1=$AC$1,AC41,IF($A$1=$AF$1,AF41,IF($A$1=$AI$1,AI41)))))))))))) -> 3222554.5 | AP41: =IF($A$1=$B$1,C41,IF($A$1=$E$1,F41,IF($A$1=$H$1,I41,IF($A$1=$K$1,L41,IF($A$1=$N$1,O41,IF($A$1=$Q$1,R41,IF($A$1=$T$1,U41,IF($A$1=$W$1,X41,IF($A$1=$Z$1,AA41,IF($A$1=$AC$1,AD41,IF($A$1=$AF$1,AG41,IF($A$1=$AI$1,AJ41)))))))))))) -> 3027070.6
A42: Çelik | B42: ='Bütçe aylık-Eur'!$B$33 -> 1688820.6 | C42: ='gerç aylık-eur'!$B$33 -> 1769605.4 | E42: ='Bütçe aylık-Eur'!$C$33 -> 1490840.7 | F42: ='gerç aylık-eur'!$C$33 -> 2436094.1 | H42: ='Bütçe aylık-Eur'!$D$33 -> 2112732.2 | I42: ='gerç aylık-eur'!$D$33 -> 2280438 | K42: ='Bütçe aylık-Eur'!$E$33 -> 2087721.6 | L42: ='gerç aylık-eur'!$E$33 -> 2714399.9 | N42: ='Bütçe aylık-Eur'!$F$33 -> 2155001.7 | O42: ='gerç aylık-eur'!$F$33 -> 2140261.7 | Q42: ='Bütçe aylık-Eur'!$G$33 -> 1757396 | R42: ='gerç aylık-eur'!$G$33 -> 1984749.9 | T42: ='Bütçe aylık-Eur'!$H$33 -> 1531936.3 | U42: ='gerç aylık-eur'!$H$33 -> 2597414.9 | W42: ='Bütçe aylık-Eur'!$I$33 -> 1008112.5 | X42: ='gerç aylık-eur'!$I$33 -> 1801656.6 | Z42: ='Bütçe aylık-Eur'!$J$33 -> 2411227.4 | AA42: ='gerç aylık-eur'!$J$33 -> 3399939.4 | AC42: ='Bütçe aylık-Eur'!$K$33 -> 2192106.2 | AD42: ='gerç aylık-eur'!$K$33 -> 0 | AF42: ='Bütçe aylık-Eur'!$L$33 -> 2046882.3 | AG42: ='gerç aylık-eur'!$L$33 -> 0 | AI42: ='Bütçe aylık-Eur'!$M$33 -> 1279617.6 | AJ42: ='gerç aylık-eur'!$M$33 -> 0 | AL42: =AP42-AO42 -> 988712.06 | AM42: =AP42/AO42-1 -> 0.41004514 | AO42: =IF($A$1=$B$1,B42,IF($A$1=$E$1,E42,IF($A$1=$H$1,H42,IF($A$1=$K$1,K42,IF($A$1=$N$1,N42,IF($A$1=$Q$1,Q42,IF($A$1=$T$1,T42,IF($A$1=$W$1,W42,IF($A$1=$Z$1,Z42,IF($A$1=$AC$1,AC42,IF($A$1=$AF$1,AF42,IF($A$1=$AI$1,AI42)))))))))))) -> 2411227.4 | AP42: =IF($A$1=$B$1,C42,IF($A$1=$E$1,F42,IF($A$1=$H$1,I42,IF($A$1=$K$1,L42,IF($A$1=$N$1,O42,IF($A$1=$Q$1,R42,IF($A$1=$T$1,U42,IF($A$1=$W$1,X42,IF($A$1=$Z$1,AA42,IF($A$1=$AC$1,AD42,IF($A$1=$AF$1,AG42,IF($A$1=$AI$1,AJ42)))))))))))) -> 3399939.4
A43: Alüminyum | B43: ='Bütçe aylık-Eur'!$B$34 -> 2912907.6 | C43: ='gerç aylık-eur'!$B$34 -> 2958769.2 | E43: ='Bütçe aylık-Eur'!$C$34 -> 3130983.1 | F43: ='gerç aylık-eur'!$C$34 -> 1709906 | H43: ='Bütçe aylık-Eur'!$D$34 -> 2840113 | I43: ='gerç aylık-eur'!$D$34 -> 2219388.1 | K43: ='Bütçe aylık-Eur'!$E$34 -> 2563624.8 | L43: ='gerç aylık-eur'!$E$34 -> 2096472.6 | N43: ='Bütçe aylık-Eur'!$F$34 -> 3562485.1 | O43: ='gerç aylık-eur'!$F$34 -> 3866133.3 | Q43: ='Bütçe aylık-Eur'!$G$34 -> 2538433.7 | R43: ='gerç aylık-eur'!$G$34 -> 2358126.4 | T43: ='Bütçe aylık-Eur'!$H$34 -> 3653394.4 | U43: ='gerç aylık-eur'!$H$34 -> 2732471.8 | W43: ='Bütçe aylık-Eur'!$I$34 -> 1505799.6 | X43: ='gerç aylık-eur'!$I$34 -> 1458544.9 | Z43: ='Bütçe aylık-Eur'!$J$34 -> 4517385.5 | AA43: ='gerç aylık-eur'!$J$34 -> 3963373.7 | AC43: ='Bütçe aylık-Eur'!$K$34 -> 3774362.5 | AD43: ='gerç aylık-eur'!$K$34 -> 0 | AF43: ='Bütçe aylık-Eur'!$L$34 -> 3696244.3 | AG43: ='gerç aylık-eur'!$L$34 -> 0 | AI43: ='Bütçe aylık-Eur'!$M$34 -> 2748973.6 | AJ43: ='gerç aylık-eur'!$M$34 -> 0 | AL43: =AP43-AO43 -> -554011.83 | AM43: =AP43/AO43-1 -> -0.12263993 | AO43: =IF($A$1=$B$1,B43,IF($A$1=$E$1,E43,IF($A$1=$H$1,H43,IF($A$1=$K$1,K43,IF($A$1=$N$1,N43,IF($A$1=$Q$1,Q43,IF($A$1=$T$1,T43,IF($A$1=$W$1,W43,IF($A$1=$Z$1,Z43,IF($A$1=$AC$1,AC43,IF($A$1=$AF$1,AF43,IF($A$1=$AI$1,AI43)))))))))))) -> 4517385.5 | AP43: =IF($A$1=$B$1,C43,IF($A$1=$E$1,F43,IF($A$1=$H$1,I43,IF($A$1=$K$1,L43,IF($A$1=$N$1,O43,IF($A$1=$Q$1,R43,IF($A$1=$T$1,U43,IF($A$1=$W$1,X43,IF($A$1=$Z$1,AA43,IF($A$1=$AC$1,AD43,IF($A$1=$AF$1,AG43,IF($A$1=$AI$1,AJ43)))))))))))) -> 3963373.7
AO44: =IF($A$1=$B$1,B44,IF($A$1=$E$1,E44,IF($A$1=$H$1,H44,IF($A$1=$K$1,K44,IF($A$1=$N$1,N44,IF($A$1=$Q$1,Q44,IF($A$1=$T$1,T44,IF($A$1=$W$1,W44,IF($A$1=$Z$1,Z44,IF($A$1=$AC$1,AC44,IF($A$1=$AF$1,AF44,IF($A$1=$AI$1,AI44)))))))))))) -> 0 | AP44: =IF($A$1=$B$1,C44,IF($A$1=$E$1,F44,IF($A$1=$H$1,I44,IF($A$1=$K$1,L44,IF($A$1=$N$1,O44,IF($A$1=$Q$1,R44,IF($A$1=$T$1,U44,IF($A$1=$W$1,X44,IF($A$1=$Z$1,AA44,IF($A$1=$AC$1,AD44,IF($A$1=$AF$1,AG44,IF($A$1=$AI$1,AJ44)))))))))))) -> 0
AL45: =AP45-AO45 -> 0 | AM45: =AP45/AO45-1 -> #DIV/0! | AO45: =IF($A$1=$B$1,B45,IF($A$1=$E$1,E45,IF($A$1=$H$1,H45,IF($A$1=$K$1,K45,IF($A$1=$N$1,N45,IF($A$1=$Q$1,Q45,IF($A$1=$T$1,T45,IF($A$1=$W$1,W45,IF($A$1=$Z$1,Z45,IF($A$1=$AC$1,AC45,IF($A$1=$AF$1,AF45,IF($A$1=$AI$1,AI45)))))))))))) -> 0 | AP45: =IF($A$1=$B$1,C45,IF($A$1=$E$1,F45,IF($A$1=$H$1,I45,IF($A$1=$K$1,L45,IF($A$1=$N$1,O45,IF($A$1=$Q$1,R45,IF($A$1=$T$1,U45,IF($A$1=$W$1,X45,IF($A$1=$Z$1,AA45,IF($A$1=$AC$1,AD45,IF($A$1=$AF$1,AG45,IF($A$1=$AI$1,AJ45)))))))))))) -> 0
AL46: =AP46-AO46 -> 0 | AM46: =AP46/AO46-1 -> #DIV/0! | AO46: =IF($A$1=$B$1,B46,IF($A$1=$E$1,E46,IF($A$1=$H$1,H46,IF($A$1=$K$1,K46,IF($A$1=$N$1,N46,IF($A$1=$Q$1,Q46,IF($A$1=$T$1,T46,IF($A$1=$W$1,W46,IF($A$1=$Z$1,Z46,IF($A$1=$AC$1,AC46,IF($A$1=$AF$1,AF46,IF($A$1=$AI$1,AI46)))))))))))) -> 0 | AP46: =IF($A$1=$B$1,C46,IF($A$1=$E$1,F46,IF($A$1=$H$1,I46,IF($A$1=$K$1,L46,IF($A$1=$N$1,O46,IF($A$1=$Q$1,R46,IF($A$1=$T$1,U46,IF($A$1=$W$1,X46,IF($A$1=$Z$1,AA46,IF($A$1=$AC$1,AD46,IF($A$1=$AF$1,AG46,IF($A$1=$AI$1,AJ46)))))))))))) -> 0
AL47: =AP47-AO47 -> 0 | AM47: =AP47/AO47-1 -> #DIV/0! | AO47: =IF($A$1=$B$1,B47,IF($A$1=$E$1,E47,IF($A$1=$H$1,H47,IF($A$1=$K$1,K47,IF($A$1=$N$1,N47,IF($A$1=$Q$1,Q47,IF($A$1=$T$1,T47,IF($A$1=$W$1,W47,IF($A$1=$Z$1,Z47,IF($A$1=$AC$1,AC47,IF($A$1=$AF$1,AF47,IF($A$1=$AI$1,AI47)))))))))))) -> 0 | AP47: =IF($A$1=$B$1,C47,IF($A$1=$E$1,F47,IF($A$1=$H$1,I47,IF($A$1=$K$1,L47,IF($A$1=$N$1,O47,IF($A$1=$Q$1,R47,IF($A$1=$T$1,U47,IF($A$1=$W$1,X47,IF($A$1=$Z$1,AA47,IF($A$1=$AC$1,AD47,IF($A$1=$AF$1,AG47,IF($A$1=$AI$1,AJ47)))))))))))) -> 0
AL48: =AP48-AO48 -> 0 | AM48: =AP48/AO48-1 -> #DIV/0! | AO48: =IF($A$1=$B$1,B48,IF($A$1=$E$1,E48,IF($A$1=$H$1,H48,IF($A$1=$K$1,K48,IF($A$1=$N$1,N48,IF($A$1=$Q$1,Q48,IF($A$1=$T$1,T48,IF($A$1=$W$1,W48,IF($A$1=$Z$1,Z48,IF($A$1=$AC$1,AC48,IF($A$1=$AF$1,AF48,IF($A$1=$AI$1,AI48)))))))))))) -> 0 | AP48: =IF($A$1=$B$1,C48,IF($A$1=$E$1,F48,IF($A$1=$H$1,I48,IF($A$1=$K$1,L48,IF($A$1=$N$1,O48,IF($A$1=$Q$1,R48,IF($A$1=$T$1,U48,IF($A$1=$W$1,X48,IF($A$1=$Z$1,AA48,IF($A$1=$AC$1,AD48,IF($A$1=$AF$1,AG48,IF($A$1=$AI$1,AJ48)))))))))))) -> 0
AO49: =IF($A$1=$B$1,B49,IF($A$1=$E$1,E49,IF($A$1=$H$1,H49,IF($A$1=$K$1,K49,IF($A$1=$N$1,N49,IF($A$1=$Q$1,Q49,IF($A$1=$T$1,T49,IF($A$1=$W$1,W49,IF($A$1=$Z$1,Z49,IF($A$1=$AC$1,AC49,IF($A$1=$AF$1,AF49,IF($A$1=$AI$1,AI49)))))))))))) -> 0 | AP49: =IF($A$1=$B$1,C49,IF($A$1=$E$1,F49,IF($A$1=$H$1,I49,IF($A$1=$K$1,L49,IF($A$1=$N$1,O49,IF($A$1=$Q$1,R49,IF($A$1=$T$1,U49,IF($A$1=$W$1,X49,IF($A$1=$Z$1,AA49,IF($A$1=$AC$1,AD49,IF($A$1=$AF$1,AG49,IF($A$1=$AI$1,AJ49)))))))))))) -> 0
AL50: =AP50-AO50 -> 0 | AM50: =AP50/AO50-1 -> #DIV/0! | AO50: =IF($A$1=$B$1,B50,IF($A$1=$E$1,E50,IF($A$1=$H$1,H50,IF($A$1=$K$1,K50,IF($A$1=$N$1,N50,IF($A$1=$Q$1,Q50,IF($A$1=$T$1,T50,IF($A$1=$W$1,W50,IF($A$1=$Z$1,Z50,IF($A$1=$AC$1,AC50,IF($A$1=$AF$1,AF50,IF($A$1=$AI$1,AI50)))))))))))) -> 0 | AP50: =IF($A$1=$B$1,C50,IF($A$1=$E$1,F50,IF($A$1=$H$1,I50,IF($A$1=$K$1,L50,IF($A$1=$N$1,O50,IF($A$1=$Q$1,R50,IF($A$1=$T$1,U50,IF($A$1=$W$1,X50,IF($A$1=$Z$1,AA50,IF($A$1=$AC$1,AD50,IF($A$1=$AF$1,AG50,IF($A$1=$AI$1,AJ50)))))))))))) -> 0
AL51: =AP51-AO51 -> 0 | AM51: =AP51/AO51-1 -> #DIV/0! | AO51: =IF($A$1=$B$1,B51,IF($A$1=$E$1,E51,IF($A$1=$H$1,H51,IF($A$1=$K$1,K51,IF($A$1=$N$1,N51,IF($A$1=$Q$1,Q51,IF($A$1=$T$1,T51,IF($A$1=$W$1,W51,IF($A$1=$Z$1,Z51,IF($A$1=$AC$1,AC51,IF($A$1=$AF$1,AF51,IF($A$1=$AI$1,AI51)))))))))))) -> 0 | AP51: =IF($A$1=$B$1,C51,IF($A$1=$E$1,F51,IF($A$1=$H$1,I51,IF($A$1=$K$1,L51,IF($A$1=$N$1,O51,IF($A$1=$Q$1,R51,IF($A$1=$T$1,U51,IF($A$1=$W$1,X51,IF($A$1=$Z$1,AA51,IF($A$1=$AC$1,AD51,IF($A$1=$AF$1,AG51,IF($A$1=$AI$1,AJ51)))))))))))) -> 0
AL52: =AP52-AO52 -> 0 | AM52: =AP52/AO52-1 -> #DIV/0! | AO52: =IF($A$1=$B$1,B52,IF($A$1=$E$1,E52,IF($A$1=$H$1,H52,IF($A$1=$K$1,K52,IF($A$1=$N$1,N52,IF($A$1=$Q$1,Q52,IF($A$1=$T$1,T52,IF($A$1=$W$1,W52,IF($A$1=$Z$1,Z52,IF($A$1=$AC$1,AC52,IF($A$1=$AF$1,AF52,IF($A$1=$AI$1,AI52)))))))))))) -> 0 | AP52: =IF($A$1=$B$1,C52,IF($A$1=$E$1,F52,IF($A$1=$H$1,I52,IF($A$1=$K$1,L52,IF($A$1=$N$1,O52,IF($A$1=$Q$1,R52,IF($A$1=$T$1,U52,IF($A$1=$W$1,X52,IF($A$1=$Z$1,AA52,IF($A$1=$AC$1,AD52,IF($A$1=$AF$1,AG52,IF($A$1=$AI$1,AJ52)))))))))))) -> 0
AL53: =AP53-AO53 -> 0 | AM53: =AP53/AO53-1 -> #DIV/0! | AO53: =IF($A$1=$B$1,B53,IF($A$1=$E$1,E53,IF($A$1=$H$1,H53,IF($A$1=$K$1,K53,IF($A$1=$N$1,N53,IF($A$1=$Q$1,Q53,IF($A$1=$T$1,T53,IF($A$1=$W$1,W53,IF($A$1=$Z$1,Z53,IF($A$1=$AC$1,AC53,IF($A$1=$AF$1,AF53,IF($A$1=$AI$1,AI53)))))))))))) -> 0 | AP53: =IF($A$1=$B$1,C53,IF($A$1=$E$1,F53,IF($A$1=$H$1,I53,IF($A$1=$K$1,L53,IF($A$1=$N$1,O53,IF($A$1=$Q$1,R53,IF($A$1=$T$1,U53,IF($A$1=$W$1,X53,IF($A$1=$Z$1,AA53,IF($A$1=$AC$1,AD53,IF($A$1=$AF$1,AG53,IF($A$1=$AI$1,AJ53)))))))))))) -> 0
AL54: =AP54-AO54 -> 0 | AM54: =AP54/AO54-1 -> #DIV/0! | AO54: =IF($A$1=$B$1,B54,IF($A$1=$E$1,E54,IF($A$1=$H$1,H54,IF($A$1=$K$1,K54,IF($A$1=$N$1,N54,IF($A$1=$Q$1,Q54,IF($A$1=$T$1,T54,IF($A$1=$W$1,W54,IF($A$1=$Z$1,Z54,IF($A$1=$AC$1,AC54,IF($A$1=$AF$1,AF54,IF($A$1=$AI$1,AI54)))))))))))) -> 0 | AP54: =IF($A$1=$B$1,C54,IF($A$1=$E$1,F54,IF($A$1=$H$1,I54,IF($A$1=$K$1,L54,IF($A$1=$N$1,O54,IF($A$1=$Q$1,R54,IF($A$1=$T$1,U54,IF($A$1=$W$1,X54,IF($A$1=$Z$1,AA54,IF($A$1=$AC$1,AD54,IF($A$1=$AF$1,AG54,IF($A$1=$AI$1,AJ54)))))))))))) -> 0
AL55: =AP55-AO55 -> 0 | AM55: =AP55/AO55-1 -> #DIV/0! | AO55: =IF($A$1=$B$1,B55,IF($A$1=$E$1,E55,IF($A$1=$H$1,H55,IF($A$1=$K$1,K55,IF($A$1=$N$1,N55,IF($A$1=$Q$1,Q55,IF($A$1=$T$1,T55,IF($A$1=$W$1,W55,IF($A$1=$Z$1,Z55,IF($A$1=$AC$1,AC55,IF($A$1=$AF$1,AF55,IF($A$1=$AI$1,AI55)))))))))))) -> 0 | AP55: =IF($A$1=$B$1,C55,IF($A$1=$E$1,F55,IF($A$1=$H$1,I55,IF($A$1=$K$1,L55,IF($A$1=$N$1,O55,IF($A$1=$Q$1,R55,IF($A$1=$T$1,U55,IF($A$1=$W$1,X55,IF($A$1=$Z$1,AA55,IF($A$1=$AC$1,AD55,IF($A$1=$AF$1,AG55,IF($A$1=$AI$1,AJ55)))))))))))) -> 0
AL56: =AP56-AO56 -> 0 | AM56: =AP56/AO56-1 -> #DIV/0! | AO56: =IF($A$1=$B$1,B56,IF($A$1=$E$1,E56,IF($A$1=$H$1,H56,IF($A$1=$K$1,K56,IF($A$1=$N$1,N56,IF($A$1=$Q$1,Q56,IF($A$1=$T$1,T56,IF($A$1=$W$1,W56,IF($A$1=$Z$1,Z56,IF($A$1=$AC$1,AC56,IF($A$1=$AF$1,AF56,IF($A$1=$AI$1,AI56)))))))))))) -> 0 | AP56: =IF($A$1=$B$1,C56,IF($A$1=$E$1,F56,IF($A$1=$H$1,I56,IF($A$1=$K$1,L56,IF($A$1=$N$1,O56,IF($A$1=$Q$1,R56,IF($A$1=$T$1,U56,IF($A$1=$W$1,X56,IF($A$1=$Z$1,AA56,IF($A$1=$AC$1,AD56,IF($A$1=$AF$1,AG56,IF($A$1=$AI$1,AJ56)))))))))))) -> 0
AL57: =AP57-AO57 -> 0 | AM57: =AP57/AO57-1 -> #DIV/0! | AO57: =IF($A$1=$B$1,B57,IF($A$1=$E$1,E57,IF($A$1=$H$1,H57,IF($A$1=$K$1,K57,IF($A$1=$N$1,N57,IF($A$1=$Q$1,Q57,IF($A$1=$T$1,T57,IF($A$1=$W$1,W57,IF($A$1=$Z$1,Z57,IF($A$1=$AC$1,AC57,IF($A$1=$AF$1,AF57,IF($A$1=$AI$1,AI57)))))))))))) -> 0 | AP57: =IF($A$1=$B$1,C57,IF($A$1=$E$1,F57,IF($A$1=$H$1,I57,IF($A$1=$K$1,L57,IF($A$1=$N$1,O57,IF($A$1=$Q$1,R57,IF($A$1=$T$1,U57,IF($A$1=$W$1,X57,IF($A$1=$Z$1,AA57,IF($A$1=$AC$1,AD57,IF($A$1=$AF$1,AG57,IF($A$1=$AI$1,AJ57)))))))))))) -> 0
AL58: =AP58-AO58 -> 0 | AM58: =AP58/AO58-1 -> #DIV/0! | AO58: =IF($A$1=$B$1,B58,IF($A$1=$E$1,E58,IF($A$1=$H$1,H58,IF($A$1=$K$1,K58,IF($A$1=$N$1,N58,IF($A$1=$Q$1,Q58,IF($A$1=$T$1,T58,IF($A$1=$W$1,W58,IF($A$1=$Z$1,Z58,IF($A$1=$AC$1,AC58,IF($A$1=$AF$1,AF58,IF($A$1=$AI$1,AI58)))))))))))) -> 0 | AP58: =IF($A$1=$B$1,C58,IF($A$1=$E$1,F58,IF($A$1=$H$1,I58,IF($A$1=$K$1,L58,IF($A$1=$N$1,O58,IF($A$1=$Q$1,R58,IF($A$1=$T$1,U58,IF($A$1=$W$1,X58,IF($A$1=$Z$1,AA58,IF($A$1=$AC$1,AD58,IF($A$1=$AF$1,AG58,IF($A$1=$AI$1,AJ58)))))))))))) -> 0
AL59: =AP59-AO59 -> 0 | AM59: =AP59/AO59-1 -> #DIV/0! | AO59: =IF($A$1=$B$1,B59,IF($A$1=$E$1,E59,IF($A$1=$H$1,H59,IF($A$1=$K$1,K59,IF($A$1=$N$1,N59,IF($A$1=$Q$1,Q59,IF($A$1=$T$1,T59,IF($A$1=$W$1,W59,IF($A$1=$Z$1,Z59,IF($A$1=$AC$1,AC59,IF($A$1=$AF$1,AF59,IF($A$1=$AI$1,AI59)))))))))))) -> 0 | AP59: =IF($A$1=$B$1,C59,IF($A$1=$E$1,F59,IF($A$1=$H$1,I59,IF($A$1=$K$1,L59,IF($A$1=$N$1,O59,IF($A$1=$Q$1,R59,IF($A$1=$T$1,U59,IF($A$1=$W$1,X59,IF($A$1=$Z$1,AA59,IF($A$1=$AC$1,AD59,IF($A$1=$AF$1,AG59,IF($A$1=$AI$1,AJ59)))))))))))) -> 0
AL60: =AP60-AO60 -> 0 | AM60: =AP60/AO60-1 -> #DIV/0! | AO60: =IF($A$1=$B$1,B60,IF($A$1=$E$1,E60,IF($A$1=$H$1,H60,IF($A$1=$K$1,K60,IF($A$1=$N$1,N60,IF($A$1=$Q$1,Q60,IF($A$1=$T$1,T60,IF($A$1=$W$1,W60,IF($A$1=$Z$1,Z60,IF($A$1=$AC$1,AC60,IF($A$1=$AF$1,AF60,IF($A$1=$AI$1,AI60)))))))))))) -> 0 | AP60: =IF($A$1=$B$1,C60,IF($A$1=$E$1,F60,IF($A$1=$H$1,I60,IF($A$1=$K$1,L60,IF($A$1=$N$1,O60,IF($A$1=$Q$1,R60,IF($A$1=$T$1,U60,IF($A$1=$W$1,X60,IF($A$1=$Z$1,AA60,IF($A$1=$AC$1,AD60,IF($A$1=$AF$1,AG60,IF($A$1=$AI$1,AJ60)))))))))))) -> 0
AL61: =AP61-AO61 -> 0 | AM61: =AP61/AO61-1 -> #DIV/0! | AO61: =IF($A$1=$B$1,B61,IF($A$1=$E$1,E61,IF($A$1=$H$1,H61,IF($A$1=$K$1,K61,IF($A$1=$N$1,N61,IF($A$1=$Q$1,Q61,IF($A$1=$T$1,T61,IF($A$1=$W$1,W61,IF($A$1=$Z$1,Z61,IF($A$1=$AC$1,AC61,IF($A$1=$AF$1,AF61,IF($A$1=$AI$1,AI61)))))))))))) -> 0 | AP61: =IF($A$1=$B$1,C61,IF($A$1=$E$1,F61,IF($A$1=$H$1,I61,IF($A$1=$K$1,L61,IF($A$1=$N$1,O61,IF($A$1=$Q$1,R61,IF($A$1=$T$1,U61,IF($A$1=$W$1,X61,IF($A$1=$Z$1,AA61,IF($A$1=$AC$1,AD61,IF($A$1=$AF$1,AG61,IF($A$1=$AI$1,AJ61)))))))))))) -> 0
... AL75: =AP75-AO75 -> 0 | AM75: =AP75/AO75-1 -> #DIV/0! | AO75: =IF($A$1=$B$1,B75,IF($A$1=$E$1,E75,IF($A$1=$H$1,H75,IF($A$1=$K$1,K75,IF($A$1=$N$1,N75,IF($A$1=$Q$1,Q75,IF($A$1=$T$1,T75,IF($A$1=$W$1,W75,IF($A$1=$Z$1,Z75,IF($A$1=$AC$1,AC75,IF($A$1=$AF$1,AF75,IF($A$1=$AI$1,AI75)))))))))))) -> 0 | AP75: =IF($A$1=$B$1,C75,IF($A$1=$E$1,F75,IF($A$1=$H$1,I75,IF($A$1=$K$1,L75,IF($A$1=$N$1,O75,IF($A$1=$Q$1,R75,IF($A$1=$T$1,U75,IF($A$1=$W$1,X75,IF($A$1=$Z$1,AA75,IF($A$1=$AC$1,AD75,IF($A$1=$AF$1,AG75,IF($A$1=$AI$1,AJ75)))))))))))) -> 0
A78: GROSS PROFIT MARGIN BY CHANNELS
A79: İnci Holding | B79: =B36/B9 -> 1 | C79: =IFERROR((C36/C9),"") -> 1 | E79: =E36/E9 -> 1 | F79: =IFERROR((F36/F9),"") -> 1 | H79: =H36/H9 -> 1 | I79: =IFERROR((I36/I9),"") -> 1 | K79: =K36/K9 -> 1 | L79: =IFERROR((L36/L9),"") -> 1 | N79: =N36/N9 -> 1 | O79: =IFERROR((O36/O9),"") -> 1 | Q79: =Q36/Q9 -> 1 | R79: =IFERROR((R36/R9),"") -> 1 | T79: =T36/T9 -> 1 | U79: =IFERROR((U36/U9),"") -> 1 | W79: =W36/W9 -> 1 | X79: =IFERROR((X36/X9),"") -> 1 | Z79: =Z36/Z9 -> 1 | AA79: =IFERROR((AA36/AA9),"") -> 1 | AC79: =AC36/AC9 -> 1 | AD79: =IFERROR((AD36/AD9),"") | AF79: =AF36/AF9 -> 1 | AG79: =IFERROR((AG36/AG9),"") | AI79: =AI36/AI9 -> 1 | AJ79: =IFERROR((AJ36/AJ9),"") | AM79: =AP79-AO79 -> 0 | AO79: =IF($A$1=$B$1,B79,IF($A$1=$E$1,E79,IF($A$1=$H$1,H79,IF($A$1=$K$1,K79,IF($A$1=$N$1,N79,IF($A$1=$Q$1,Q79,IF($A$1=$T$1,T79,IF($A$1=$W$1,W79,IF($A$1=$Z$1,Z79,IF($A$1=$AC$1,AC79,IF($A$1=$AF$1,AF79,IF($A$1=$AI$1,AI79)))))))))))) -> 1 | AP79: =IF($A$1=$B$1,C79,IF($A$1=$E$1,F79,IF($A$1=$H$1,I79,IF($A$1=$K$1,L79,IF($A$1=$N$1,O79,IF($A$1=$Q$1,R79,IF($A$1=$T$1,U79,IF($A$1=$W$1,X79,IF($A$1=$Z$1,AA79,IF($A$1=$AC$1,AD79,IF($A$1=$AF$1,AG79,IF($A$1=$AI$1,AJ79)))))))))))) -> 1
A80: ISM | B80: =B37/B10 -> 0.17117636 | C80: =IFERROR((C37/C10),"") -> 0.13017986 | E80: =E37/E10 -> 0.25628591 | F80: =IFERROR((F37/F10),"") -> 0.21469702 | H80: =H37/H10 -> 0.27467209 | I80: =IFERROR((I37/I10),"") -> 0.26441064 | K80: =K37/K10 -> 0.32359155 | L80: =IFERROR((L37/L10),"") -> 0.25438556 | N80: =N37/N10 -> 0.37181167 | O80: =IFERROR((O37/O10),"") -> 0.25073597 | Q80: =Q37/Q10 -> 0.34858218 | R80: =IFERROR((R37/R10),"") -> 0.2863592 | T80: =T37/T10 -> 0.34444759 | U80: =IFERROR((U37/U10),"") -> 0.27799219 | W80: =W37/W10 -> 0.27931174 | X80: =IFERROR((X37/X10),"") -> 0.25648207 | Z80: =Z37/Z10 -> 0.32037415 | AA80: =IFERROR((AA37/AA10),"") -> 0.22869641 | AC80: =AC37/AC10 -> 0.27158734 | AD80: =IFERROR((AD37/AD10),"") | AF80: =AF37/AF10 -> 0.24936214 | AG80: =IFERROR((AG37/AG10),"") | AI80: =AI37/AI10 -> 0.18385929 | AJ80: =IFERROR((AJ37/AJ10),"") | AM80: =AP80-AO80 -> -0.091677749 | AO80: =IF($A$1=$B$1,B80,IF($A$1=$E$1,E80,IF($A$1=$H$1,H80,IF($A$1=$K$1,K80,IF($A$1=$N$1,N80,IF($A$1=$Q$1,Q80,IF($A$1=$T$1,T80,IF($A$1=$W$1,W80,IF($A$1=$Z$1,Z80,IF($A$1=$AC$1,AC80,IF($A$1=$AF$1,AF80,IF($A$1=$AI$1,AI80)))))))))))) -> 0.32037415 | AP80: =IF($A$1=$B$1,C80,IF($A$1=$E$1,F80,IF($A$1=$H$1,I80,IF($A$1=$K$1,L80,IF($A$1=$N$1,O80,IF($A$1=$Q$1,R80,IF($A$1=$T$1,U80,IF($A$1=$W$1,X80,IF($A$1=$Z$1,AA80,IF($A$1=$AC$1,AD80,IF($A$1=$AF$1,AG80,IF($A$1=$AI$1,AJ80)))))))))))) -> 0.22869641
A81: İncitaş | B81: =B38/B11 -> 0.16706084 | C81: =IFERROR((C38/C11),"") -> 0.16090771 | E81: =E38/E11 -> 0.16984973 | F81: =IFERROR((F38/F11),"") -> 0.14556793 | H81: =H38/H11 -> 0.18934002 | I81: =IFERROR((I38/I11),"") -> 0.12237103 | K81: =K38/K11 -> 0.19463363 | L81: =IFERROR((L38/L11),"") -> 0.12947595 | N81: =N38/N11 -> 0.1974712 | O81: =IFERROR((O38/O11),"") -> 0.20790254 | Q81: =Q38/Q11 -> 0.2009597 | R81: =IFERROR((R38/R11),"") -> 0.15845897 | T81: =T38/T11 -> 0.1817589 | U81: =IFERROR((U38/U11),"") -> 0.18602863 | W81: =W38/W11 -> 0.20255856 | X81: =IFERROR((X38/X11),"") -> 0.15677115 | Z81: =Z38/Z11 -> 0.2036502 | AA81: =IFERROR((AA38/AA11),"") -> 0.19124358 | AC81: =AC38/AC11 -> 0.19354999 | AD81: =IFERROR((AD38/AD11),"") | AF81: =AF38/AF11 -> 0.17084678 | AG81: =IFERROR((AG38/AG11),"") | AI81: =AI38/AI11 -> 0.18401379 | AJ81: =IFERROR((AJ38/AJ11),"") | AM81: =AP81-AO81 -> -0.012406619 | AO81: =IF($A$1=$B$1,B81,IF($A$1=$E$1,E81,IF($A$1=$H$1,H81,IF($A$1=$K$1,K81,IF($A$1=$N$1,N81,IF($A$1=$Q$1,Q81,IF($A$1=$T$1,T81,IF($A$1=$W$1,W81,IF($A$1=$Z$1,Z81,IF($A$1=$AC$1,AC81,IF($A$1=$AF$1,AF81,IF($A$1=$AI$1,AI81)))))))))))) -> 0.2036502 | AP81: =IF($A$1=$B$1,C81,IF($A$1=$E$1,F81,IF($A$1=$H$1,I81,IF($A$1=$K$1,L81,IF($A$1=$N$1,O81,IF($A$1=$Q$1,R81,IF($A$1=$T$1,U81,IF($A$1=$W$1,X81,IF($A$1=$Z$1,AA81,IF($A$1=$AC$1,AD81,IF($A$1=$AF$1,AG81,IF($A$1=$AI$1,AJ81)))))))))))) -> 0.19124358
A82: İnci GS Yuasa | B82: =B39/B12 -> 0.18185809 | C82: =IFERROR((C39/C12),"") -> 0.14911531 | E82: =E39/E12 -> 0.17613583 | F82: =IFERROR((F39/F12),"") -> 0.19140307 | H82: =H39/H12 -> 0.18085379 | I82: =IFERROR((I39/I12),"") -> 0.13764229 | K82: =K39/K12 -> 0.17362886 | L82: =IFERROR((L39/L12),"") -> 0.1094864 | N82: =N39/N12 -> 0.18171966 | O82: =IFERROR((O39/O12),"") -> 0.12261688 | Q82: =Q39/Q12 -> 0.19719385 | R82: =IFERROR((R39/R12),"") -> 0.10149459 | T82: =T39/T12 -> 0.19159629 | U82: =IFERROR((U39/U12),"") -> 0.075311961 | W82: =W39/W12 -> 0.20758777 | X82: =IFERROR((X39/X12),"") -> 0.16584313 | Z82: =Z39/Z12 -> 0.21652697 | AA82: =IFERROR((AA39/AA12),"") -> 0.15310162 | AC82: =AC39/AC12 -> 0.21810302 | AD82: =IFERROR((AD39/AD12),"") | AF82: =AF39/AF12 -> 0.22232282 | AG82: =IFERROR((AG39/AG12),"") | AI82: =AI39/AI12 -> 0.24976672 | AJ82: =IFERROR((AJ39/AJ12),"") | AM82: =AP82-AO82 -> -0.063425344 | AO82: =IF($A$1=$B$1,B82,IF($A$1=$E$1,E82,IF($A$1=$H$1,H82,IF($A$1=$K$1,K82,IF($A$1=$N$1,N82,IF($A$1=$Q$1,Q82,IF($A$1=$T$1,T82,IF($A$1=$W$1,W82,IF($A$1=$Z$1,Z82,IF($A$1=$AC$1,AC82,IF($A$1=$AF$1,AF82,IF($A$1=$AI$1,AI82)))))))))))) -> 0.21652697 | AP82: =IF($A$1=$B$1,C82,IF($A$1=$E$1,F82,IF($A$1=$H$1,I82,IF($A$1=$K$1,L82,IF($A$1=$N$1,O82,IF($A$1=$Q$1,R82,IF($A$1=$T$1,U82,IF($A$1=$W$1,X82,IF($A$1=$Z$1,AA82,IF($A$1=$AC$1,AD82,IF($A$1=$AF$1,AG82,IF($A$1=$AI$1,AJ82)))))))))))) -> 0.15310162
A83: Yusen İnci Loj. | B83: =B40/B13 -> 0.19744746 | C83: =IFERROR((C40/C13),"") -> 0.20078813 | E83: =E40/E13 -> 0.19527301 | F83: =IFERROR((F40/F13),"") -> 0.2328926 | H83: =H40/H13 -> 0.1902173 | I83: =IFERROR((I40/I13),"") -> 0.1847192 | K83: =K40/K13 -> 0.17342924 | L83: =IFERROR((L40/L13),"") -> 0.18932004 | N83: =N40/N13 -> 0.17874995 | O83: =IFERROR((O40/O13),"") -> 0.22179557 | Q83: =Q40/Q13 -> 0.19522346 | R83: =IFERROR((R40/R13),"") -> 0.21830323 | T83: =T40/T13 -> 0.18011851 | U83: =IFERROR((U40/U13),"") -> 0.20703626 | W83: =W40/W13 -> 0.20895428 | X83: =IFERROR((X40/X13),"") -> 0.24254041 | Z83: =Z40/Z13 -> 0.2075766 | AA83: =IFERROR((AA40/AA13),"") -> 0.21893023 | AC83: =AC40/AC13 -> 0.18552909 | AD83: =IFERROR((AD40/AD13),"") | AF83: =AF40/AF13 -> 0.20156192 | AG83: =IFERROR((AG40/AG13),"") | AI83: =AI40/AI13 -> 0.19085549 | AJ83: =IFERROR((AJ40/AJ13),"") | AM83: =AP83-AO83 -> 0.011353625 | AO83: =IF($A$1=$B$1,B83,IF($A$1=$E$1,E83,IF($A$1=$H$1,H83,IF($A$1=$K$1,K83,IF($A$1=$N$1,N83,IF($A$1=$Q$1,Q83,IF($A$1=$T$1,T83,IF($A$1=$W$1,W83,IF($A$1=$Z$1,Z83,IF($A$1=$AC$1,AC83,IF($A$1=$AF$1,AF83,IF($A$1=$AI$1,AI83)))))))))))) -> 0.2075766 | AP83: =IF($A$1=$B$1,C83,IF($A$1=$E$1,F83,IF($A$1=$H$1,I83,IF($A$1=$K$1,L83,IF($A$1=$N$1,O83,IF($A$1=$Q$1,R83,IF($A$1=$T$1,U83,IF($A$1=$W$1,X83,IF($A$1=$Z$1,AA83,IF($A$1=$AC$1,AD83,IF($A$1=$AF$1,AG83,IF($A$1=$AI$1,AJ83)))))))))))) -> 0.21893023
A84: Jantaş | B84: =B41/B14 -> 0.12840118 | C84: =IFERROR((C41/C14),"") -> 0.12027403 | E84: =E41/E14 -> 0.16161053 | F84: =IFERROR((F41/F14),"") -> 0.17939629 | H84: =H41/H14 -> 0.22128034 | I84: =IFERROR((I41/I14),"") -> 0.19340641 | K84: =K41/K14 -> 0.12618442 | L84: =IFERROR((L41/L14),"") -> 0.18711583 | N84: =N41/N14 -> 0.16092948 | O84: =IFERROR((O41/O14),"") -> 0.18919437 | Q84: =Q41/Q14 -> 0.18000097 | R84: =IFERROR((R41/R14),"") -> 0.17931199 | T84: =T41/T14 -> 0.12409605 | U84: =IFERROR((U41/U14),"") -> 0.18950512 | W84: =W41/W14 -> 0.072151929 | X84: =IFERROR((X41/X14),"") -> 0.1590424 | Z84: =Z41/Z14 -> 0.23257783 | AA84: =IFERROR((AA41/AA14),"") -> 0.25621269 | AC84: =AC41/AC14 -> 0.17883047 | AD84: =IFERROR((AD41/AD14),"") | AF84: =AF41/AF14 -> 0.18695415 | AG84: =IFERROR((AG41/AG14),"") | AI84: =AI41/AI14 -> 0.16737242 | AJ84: =IFERROR((AJ41/AJ14),"") | AM84: =AP84-AO84 -> 0.023634856 | AO84: =IF($A$1=$B$1,B84,IF($A$1=$E$1,E84,IF($A$1=$H$1,H84,IF($A$1=$K$1,K84,IF($A$1=$N$1,N84,IF($A$1=$Q$1,Q84,IF($A$1=$T$1,T84,IF($A$1=$W$1,W84,IF($A$1=$Z$1,Z84,IF($A$1=$AC$1,AC84,IF($A$1=$AF$1,AF84,IF($A$1=$AI$1,AI84)))))))))))) -> 0.23257783 | AP84: =IF($A$1=$B$1,C84,IF($A$1=$E$1,F84,IF($A$1=$H$1,I84,IF($A$1=$K$1,L84,IF($A$1=$N$1,O84,IF($A$1=$Q$1,R84,IF($A$1=$T$1,U84,IF($A$1=$W$1,X84,IF($A$1=$Z$1,AA84,IF($A$1=$AC$1,AD84,IF($A$1=$AF$1,AG84,IF($A$1=$AI$1,AJ84)))))))))))) -> 0.25621269
A85: Çelik | B85: =B42/B15 -> 0.22286987 | C85: =IFERROR((C42/C15),"") -> 0.22598725 | E85: =E42/E15 -> 0.2442773 | F85: =IFERROR((F42/F15),"") -> 0.27895818 | H85: =H42/H15 -> 0.26465154 | I85: =IFERROR((I42/I15),"") -> 0.25481374 | K85: =K42/K15 -> 0.26113633 | L85: =IFERROR((L42/L15),"") -> 0.30928255 | N85: =N42/N15 -> 0.27363277 | O85: =IFERROR((O42/O15),"") -> 0.26443664 | Q85: =Q42/Q15 -> 0.25323098 | R85: =IFERROR((R42/R15),"") -> 0.27401604 | T85: =T42/T15 -> 0.23396871 | U85: =IFERROR((U42/U15),"") -> 0.32276114 | W85: =W42/W15 -> 0.17171764 | X85: =IFERROR((X42/X15),"") -> 0.27834398 | Z85: =Z42/Z15 -> 0.29072406 | AA85: =IFERROR((AA42/AA15),"") -> 0.35455308 | AC85: =AC42/AC15 -> 0.27898708 | AD85: =IFERROR((AD42/AD15),"") | AF85: =AF42/AF15 -> 0.28085415 | AG85: =IFERROR((AG42/AG15),"") | AI85: =AI42/AI15 -> 0.23197178 | AJ85: =IFERROR((AJ42/AJ15),"") | AM85: =AP85-AO85 -> 0.063829023 | AO85: =IF($A$1=$B$1,B85,IF($A$1=$E$1,E85,IF($A$1=$H$1,H85,IF($A$1=$K$1,K85,IF($A$1=$N$1,N85,IF($A$1=$Q$1,Q85,IF($A$1=$T$1,T85,IF($A$1=$W$1,W85,IF($A$1=$Z$1,Z85,IF($A$1=$AC$1,AC85,IF($A$1=$AF$1,AF85,IF($A$1=$AI$1,AI85)))))))))))) -> 0.29072406 | AP85: =IF($A$1=$B$1,C85,IF($A$1=$E$1,F85,IF($A$1=$H$1,I85,IF($A$1=$K$1,L85,IF($A$1=$N$1,O85,IF($A$1=$Q$1,R85,IF($A$1=$T$1,U85,IF($A$1=$W$1,X85,IF($A$1=$Z$1,AA85,IF($A$1=$AC$1,AD85,IF($A$1=$AF$1,AG85,IF($A$1=$AI$1,AJ85)))))))))))) -> 0.35455308
A86: Alüminyum | B86: =B43/B16 -> 0.15089381 | C86: =IFERROR((C43/C16),"") -> 0.13316144 | E86: =E43/E16 -> 0.15387085 | F86: =IFERROR((F43/F16),"") -> 0.086001294 | H86: =H43/H16 -> 0.12709777 | I86: =IFERROR((I43/I16),"") -> 0.10092281 | K86: =K43/K16 -> 0.1325087 | L86: =IFERROR((L43/L16),"") -> 0.095039701 | N86: =N43/N16 -> 0.1631783 | O86: =IFERROR((O43/O16),"") -> 0.15755895 | Q86: =Q43/Q16 -> 0.11781861 | R86: =IFERROR((R43/R16),"") -> 0.11219515 | T86: =T43/T16 -> 0.17062025 | U86: =IFERROR((U43/U16),"") -> 0.12633112 | W86: =W43/W16 -> 0.090497145 | X86: =IFERROR((X43/X16),"") -> 0.096834457 | Z86: =Z43/Z16 -> 0.18643078 | AA86: =IFERROR((AA43/AA16),"") -> 0.1762859 | AC86: =AC43/AC16 -> 0.16940691 | AD86: =IFERROR((AD43/AD16),"") | AF86: =AF43/AF16 -> 0.17595148 | AG86: =IFERROR((AG43/AG16),"") | AI86: =AI43/AI16 -> 0.1580681 | AJ86: =IFERROR((AJ43/AJ16),"") | AM86: =AP86-AO86 -> -0.010144874 | AO86: =IF($A$1=$B$1,B86,IF($A$1=$E$1,E86,IF($A$1=$H$1,H86,IF($A$1=$K$1,K86,IF($A$1=$N$1,N86,IF($A$1=$Q$1,Q86,IF($A$1=$T$1,T86,IF($A$1=$W$1,W86,IF($A$1=$Z$1,Z86,IF($A$1=$AC$1,AC86,IF($A$1=$AF$1,AF86,IF($A$1=$AI$1,AI86)))))))))))) -> 0.18643078 | AP86: =IF($A$1=$B$1,C86,IF($A$1=$E$1,F86,IF($A$1=$H$1,I86,IF($A$1=$K$1,L86,IF($A$1=$N$1,O86,IF($A$1=$Q$1,R86,IF($A$1=$T$1,U86,IF($A$1=$W$1,X86,IF($A$1=$Z$1,AA86,IF($A$1=$AC$1,AD86,IF($A$1=$AF$1,AG86,IF($A$1=$AI$1,AJ86)))))))))))) -> 0.1762859
C87: =IFERROR((C44/C17),"") | F87: =IFERROR((F44/F17),"") | I87: =IFERROR((I44/I17),"") | L87: =IFERROR((L44/L17),"") | O87: =IFERROR((O44/O17),"") | R87: =IFERROR((R44/R17),"") | U87: =IFERROR((U44/U17),"") | X87: =IFERROR((X44/X17),"") | AA87: =IFERROR((AA44/AA17),"") | AD87: =IFERROR((AD44/AD17),"") | AG87: =IFERROR((AG44/AG17),"") | AJ87: =IFERROR((AJ44/AJ17),"") | AO87: =IF($A$1=$B$1,B87,IF($A$1=$E$1,E87,IF($A$1=$H$1,H87,IF($A$1=$K$1,K87,IF($A$1=$N$1,N87,IF($A$1=$Q$1,Q87,IF($A$1=$T$1,T87,IF($A$1=$W$1,W87,IF($A$1=$Z$1,Z87,IF($A$1=$AC$1,AC87,IF($A$1=$AF$1,AF87,IF($A$1=$AI$1,AI87)))))))))))) -> 0 | AP87: =IF($A$1=$B$1,C87,IF($A$1=$E$1,F87,IF($A$1=$H$1,I87,IF($A$1=$K$1,L87,IF($A$1=$N$1,O87,IF($A$1=$Q$1,R87,IF($A$1=$T$1,U87,IF($A$1=$W$1,X87,IF($A$1=$Z$1,AA87,IF($A$1=$AC$1,AD87,IF($A$1=$AF$1,AG87,IF($A$1=$AI$1,AJ87))))))))))))
A88: Operating Expenses | B88: =-'Bütçe aylık-Eur'!$B$37 -> -2743942 | C88: ='gerç aylık-eur'!$B$37 -> -2658838.1 | E88: =-'Bütçe aylık-Eur'!$C$37 -> -2777685.2 | F88: ='gerç aylık-eur'!$C$37 -> -2885711.6 | H88: =-'Bütçe aylık-Eur'!$D$37 -> -3010675 | I88: ='gerç aylık-eur'!$D$37 -> -2803282 | K88: =-'Bütçe aylık-Eur'!$E$37 -> -3109450.3 | L88: ='gerç aylık-eur'!$E$37 -> -3149506.9 | N88: =-'Bütçe aylık-Eur'!$F$37 -> -2917139.4 | O88: ='gerç aylık-eur'!$F$37 -> -2853856.9 | Q88: =-'Bütçe aylık-Eur'!$G$37 -> -2870837.4 | R88: ='gerç aylık-eur'!$G$37 -> -2483556.9 | T88: =-'Bütçe aylık-Eur'!$H$37 -> -2814207 | U88: ='gerç aylık-eur'!$H$37 -> -2479988.8 | W88: =-'Bütçe aylık-Eur'!$I$37 -> -2652098.3 | X88: ='gerç aylık-eur'!$I$37 -> -2225152.4 | Z88: =-'Bütçe aylık-Eur'!$J$37 -> -2933205 | AA88: ='gerç aylık-eur'!$J$37 -> -2359437.9 | AC88: =-'Bütçe aylık-Eur'!$K$37 -> -2879324.6 | AD88: ='gerç aylık-eur'!$K$37 -> 0 | AF88: =-'Bütçe aylık-Eur'!$L$37 -> -2820513.9 | AG88: ='gerç aylık-eur'!$L$37 -> 0 | AI88: =-'Bütçe aylık-Eur'!$M$37 -> -3332477.8 | AJ88: ='gerç aylık-eur'!$M$37 -> 0 | AL88: =AP88-AO88 -> 573767.1 | AM88: =AP88/AO88-1 -> -0.19561098 | AO88: =IF($A$1=$B$1,B88,IF($A$1=$E$1,E88,IF($A$1=$H$1,H88,IF($A$1=$K$1,K88,IF($A$1=$N$1,N88,IF($A$1=$Q$1,Q88,IF($A$1=$T$1,T88,IF($A$1=$W$1,W88,IF($A$1=$Z$1,Z88,IF($A$1=$AC$1,AC88,IF($A$1=$AF$1,AF88,IF($A$1=$AI$1,AI88)))))))))))) -> -2933205 | AP88: =IF($A$1=$B$1,C88,IF($A$1=$E$1,F88,IF($A$1=$H$1,I88,IF($A$1=$K$1,L88,IF($A$1=$N$1,O88,IF($A$1=$Q$1,R88,IF($A$1=$T$1,U88,IF($A$1=$W$1,X88,IF($A$1=$Z$1,AA88,IF($A$1=$AC$1,AD88,IF($A$1=$AF$1,AG88,IF($A$1=$AI$1,AJ88)))))))))))) -> -2359437.9
B89: =B88/-B30 -> 0.09941449 | C89: =C88/-C30 -> 0.088016514 | AO89: =IF($A$1=$B$1,B89,IF($A$1=$E$1,E89,IF($A$1=$H$1,H89,IF($A$1=$K$1,K89,IF($A$1=$N$1,N89,IF($A$1=$Q$1,Q89,IF($A$1=$T$1,T89,IF($A$1=$W$1,W89,IF($A$1=$Z$1,Z89,IF($A$1=$AC$1,AC89,IF($A$1=$AF$1,AF89,IF($A$1=$AI$1,AI89)))))))))))) -> 0 | AP89: =IF($A$1=$B$1,C89,IF($A$1=$E$1,F89,IF($A$1=$H$1,I89,IF($A$1=$K$1,L89,IF($A$1=$N$1,O89,IF($A$1=$Q$1,R89,IF($A$1=$T$1,U89,IF($A$1=$W$1,X89,IF($A$1=$Z$1,AA89,IF($A$1=$AC$1,AD89,IF($A$1=$AF$1,AG89,IF($A$1=$AI$1,AJ89)))))))))))) -> 0
A90: Operating Expenses by channels (100%)
A91: İnci Holding | B91: =-'Bütçe aylık-Eur'!$B$38 -> -378639.33 | C91: ='gerç aylık-eur'!$B$38 -> -379095.49 | E91: =-'Bütçe aylık-Eur'!$C$38 -> -359570.58 | F91: ='gerç aylık-eur'!$C$38 -> -414616.15 | H91: =-'Bütçe aylık-Eur'!$D$38 -> -474077.04 | I91: ='gerç aylık-eur'!$D$38 -> -452066.61 | K91: =-'Bütçe aylık-Eur'!$E$38 -> -405575.78 | L91: ='gerç aylık-eur'!$E$38 -> -555022.3 | N91: =-'Bütçe aylık-Eur'!$F$38 -> -428934.42 | O91: ='gerç aylık-eur'!$F$38 -> -354817.39 | Q91: =-'Bütçe aylık-Eur'!$G$38 -> -404623.81 | R91: ='gerç aylık-eur'!$G$38 -> -370767.34 | T91: =-'Bütçe aylık-Eur'!$H$38 -> -366093.52 | U91: ='gerç aylık-eur'!$H$38 -> -381941.33 | W91: =-'Bütçe aylık-Eur'!$I$38 -> -347719.99 | X91: ='gerç aylık-eur'!$I$38 -> -312966.88 | Z91: =-'Bütçe aylık-Eur'!$J$38 -> -393617.69 | AA91: ='gerç aylık-eur'!$J$38 -> -311389.9 | AC91: =-'Bütçe aylık-Eur'!$K$38 -> -415050.07 | AD91: ='gerç aylık-eur'!$K$38 -> 0 | AF91: =-'Bütçe aylık-Eur'!$L$38 -> -430356.47 | AG91: ='gerç aylık-eur'!$L$38 -> 0 | AI91: =-'Bütçe aylık-Eur'!$M$38 -> -942526.18 | AJ91: ='gerç aylık-eur'!$M$38 -> 0 | AL91: =AP91-AO91 -> 82227.795 | AM91: =AP91/AO91-1 -> -0.20890269 | AO91: =IF($A$1=$B$1,B91,IF($A$1=$E$1,E91,IF($A$1=$H$1,H91,IF($A$1=$K$1,K91,IF($A$1=$N$1,N91,IF($A$1=$Q$1,Q91,IF($A$1=$T$1,T91,IF($A$1=$W$1,W91,IF($A$1=$Z$1,Z91,IF($A$1=$AC$1,AC91,IF($A$1=$AF$1,AF91,IF($A$1=$AI$1,AI91)))))))))))) -> -393617.69 | AP91: =IF($A$1=$B$1,C91,IF($A$1=$E$1,F91,IF($A$1=$H$1,I91,IF($A$1=$K$1,L91,IF($A$1=$N$1,O91,IF($A$1=$Q$1,R91,IF($A$1=$T$1,U91,IF($A$1=$W$1,X91,IF($A$1=$Z$1,AA91,IF($A$1=$AC$1,AD91,IF($A$1=$AF$1,AG91,IF($A$1=$AI$1,AJ91)))))))))))) -> -311389.9
A92: ISM | B92: =-'Bütçe aylık-Eur'!$B$39 -> -172335.84 | C92: ='gerç aylık-eur'!$B$39 -> -126365.65 | E92: =-'Bütçe aylık-Eur'!$C$39 -> -164499.22 | F92: ='gerç aylık-eur'!$C$39 -> -162672.99 | H92: =-'Bütçe aylık-Eur'!$D$39 -> -167922.4 | I92: ='gerç aylık-eur'!$D$39 -> -163546.89 | K92: =-'Bütçe aylık-Eur'!$E$39 -> -172489.17 | L92: ='gerç aylık-eur'!$E$39 -> -138314.24 | N92: =-'Bütçe aylık-Eur'!$F$39 -> -158009.63 | O92: ='gerç aylık-eur'!$F$39 -> -148496.54 | Q92: =-'Bütçe aylık-Eur'!$G$39 -> -161726.86 | R92: ='gerç aylık-eur'!$G$39 -> -160173.08 | T92: =-'Bütçe aylık-Eur'!$H$39 -> -148516.65 | U92: ='gerç aylık-eur'!$H$39 -> -142821.57 | W92: =-'Bütçe aylık-Eur'!$I$39 -> -132296.34 | X92: ='gerç aylık-eur'!$I$39 -> -113424.73 | Z92: =-'Bütçe aylık-Eur'!$J$39 -> -138705.33 | AA92: ='gerç aylık-eur'!$J$39 -> -138693.87 | AC92: =-'Bütçe aylık-Eur'!$K$39 -> -125051.45 | AD92: ='gerç aylık-eur'!$K$39 -> 0 | AF92: =-'Bütçe aylık-Eur'!$L$39 -> -127136.03 | AG92: ='gerç aylık-eur'!$L$39 -> 0 | AI92: =-'Bütçe aylık-Eur'!$M$39 -> -125114.23 | AJ92: ='gerç aylık-eur'!$M$39 -> 0 | AL92: =AP92-AO92 -> 11.457343 | AM92: =AP92/AO92-1 -> -8.2602036e-05 | AO92: =IF($A$1=$B$1,B92,IF($A$1=$E$1,E92,IF($A$1=$H$1,H92,IF($A$1=$K$1,K92,IF($A$1=$N$1,N92,IF($A$1=$Q$1,Q92,IF($A$1=$T$1,T92,IF($A$1=$W$1,W92,IF($A$1=$Z$1,Z92,IF($A$1=$AC$1,AC92,IF($A$1=$AF$1,AF92,IF($A$1=$AI$1,AI92)))))))))))) -> -138705.33 | AP92: =IF($A$1=$B$1,C92,IF($A$1=$E$1,F92,IF($A$1=$H$1,I92,IF($A$1=$K$1,L92,IF($A$1=$N$1,O92,IF($A$1=$Q$1,R92,IF($A$1=$T$1,U92,IF($A$1=$W$1,X92,IF($A$1=$Z$1,AA92,IF($A$1=$AC$1,AD92,IF($A$1=$AF$1,AG92,IF($A$1=$AI$1,AJ92)))))))))))) -> -138693.87
A93: İncitaş | B93: =-'Bütçe aylık-Eur'!$B$40 -> -210929.61 | C93: ='gerç aylık-eur'!$B$40 -> -121903.78 | E93: =-'Bütçe aylık-Eur'!$C$40 -> -165953.17 | F93: ='gerç aylık-eur'!$C$40 -> -119725.07 | H93: =-'Bütçe aylık-Eur'!$D$40 -> -192322.08 | I93: ='gerç aylık-eur'!$D$40 -> -177243.88 | K93: =-'Bütçe aylık-Eur'!$E$40 -> -212051.98 | L93: ='gerç aylık-eur'!$E$40 -> -141699.64 | N93: =-'Bütçe aylık-Eur'!$F$40 -> -182815.62 | O93: ='gerç aylık-eur'!$F$40 -> -122616.72 | Q93: =-'Bütçe aylık-Eur'!$G$40 -> -188693.79 | R93: ='gerç aylık-eur'!$G$40 -> -126790.71 | T93: =-'Bütçe aylık-Eur'!$H$40 -> -198353.25 | U93: ='gerç aylık-eur'!$H$40 -> -143950.89 | W93: =-'Bütçe aylık-Eur'!$I$40 -> -193303.52 | X93: ='gerç aylık-eur'!$I$40 -> -108305.3 | Z93: =-'Bütçe aylık-Eur'!$J$40 -> -213272.79 | AA93: ='gerç aylık-eur'!$J$40 -> -115524.06 | AC93: =-'Bütçe aylık-Eur'!$K$40 -> -187449.81 | AD93: ='gerç aylık-eur'!$K$40 -> 0 | AF93: =-'Bütçe aylık-Eur'!$L$40 -> -182925.49 | AG93: ='gerç aylık-eur'!$L$40 -> 0 | AI93: =-'Bütçe aylık-Eur'!$M$40 -> -225571.09 | AJ93: ='gerç aylık-eur'!$M$40 -> 0 | AL93: =AP93-AO93 -> 97748.727 | AM93: =AP93/AO93-1 -> -0.45832724 | AO93: =IF($A$1=$B$1,B93,IF($A$1=$E$1,E93,IF($A$1=$H$1,H93,IF($A$1=$K$1,K93,IF($A$1=$N$1,N93,IF($A$1=$Q$1,Q93,IF($A$1=$T$1,T93,IF($A$1=$W$1,W93,IF($A$1=$Z$1,Z93,IF($A$1=$AC$1,AC93,IF($A$1=$AF$1,AF93,IF($A$1=$AI$1,AI93)))))))))))) -> -213272.79 | AP93: =IF($A$1=$B$1,C93,IF($A$1=$E$1,F93,IF($A$1=$H$1,I93,IF($A$1=$K$1,L93,IF($A$1=$N$1,O93,IF($A$1=$Q$1,R93,IF($A$1=$T$1,U93,IF($A$1=$W$1,X93,IF($A$1=$Z$1,AA93,IF($A$1=$AC$1,AD93,IF($A$1=$AF$1,AG93,IF($A$1=$AI$1,AJ93)))))))))))) -> -115524.06
A94: İnci GS Yuasa | B94: =-'Bütçe aylık-Eur'!$B$41 -> -2063199.3 | C94: ='gerç aylık-eur'!$B$41 -> -2081641.8 | E94: =-'Bütçe aylık-Eur'!$C$41 -> -2274407.8 | F94: ='gerç aylık-eur'!$C$41 -> -2272721 | H94: =-'Bütçe aylık-Eur'!$D$41 -> -2391404.9 | I94: ='gerç aylık-eur'!$D$41 -> -2300144.4 | K94: =-'Bütçe aylık-Eur'!$E$41 -> -2255190.9 | L94: ='gerç aylık-eur'!$E$41 -> -2068806.5 | N94: =-'Bütçe aylık-Eur'!$F$41 -> -2096565.6 | O94: ='gerç aylık-eur'!$F$41 -> -1942443.4 | Q94: =-'Bütçe aylık-Eur'!$G$41 -> -2141279.6 | R94: ='gerç aylık-eur'!$G$41 -> -1761143.5 | T94: =-'Bütçe aylık-Eur'!$H$41 -> -2192367.9 | U94: ='gerç aylık-eur'!$H$41 -> -1677881.1 | W94: =-'Bütçe aylık-Eur'!$I$41 -> -2195837.7 | X94: ='gerç aylık-eur'!$I$41 -> -1685794.1 | Z94: =-'Bütçe aylık-Eur'!$J$41 -> -2191321.2 | AA94: ='gerç aylık-eur'!$J$41 -> -1591887.6 | AC94: =-'Bütçe aylık-Eur'!$K$41 -> -2273083 | AD94: ='gerç aylık-eur'!$K$41 -> 0 | AF94: =-'Bütçe aylık-Eur'!$L$41 -> -2210193.8 | AG94: ='gerç aylık-eur'!$L$41 -> 0 | AI94: =-'Bütçe aylık-Eur'!$M$41 -> -2337449.6 | AJ94: ='gerç aylık-eur'!$M$41 -> 0 | AL94: =AP94-AO94 -> 599433.59 | AM94: =AP94/AO94-1 -> -0.27354893 | AO94: =IF($A$1=$B$1,B94,IF($A$1=$E$1,E94,IF($A$1=$H$1,H94,IF($A$1=$K$1,K94,IF($A$1=$N$1,N94,IF($A$1=$Q$1,Q94,IF($A$1=$T$1,T94,IF($A$1=$W$1,W94,IF($A$1=$Z$1,Z94,IF($A$1=$AC$1,AC94,IF($A$1=$AF$1,AF94,IF($A$1=$AI$1,AI94)))))))))))) -> -2191321.2 | AP94: =IF($A$1=$B$1,C94,IF($A$1=$E$1,F94,IF($A$1=$H$1,I94,IF($A$1=$K$1,L94,IF($A$1=$N$1,O94,IF($A$1=$Q$1,R94,IF($A$1=$T$1,U94,IF($A$1=$W$1,X94,IF($A$1=$Z$1,AA94,IF($A$1=$AC$1,AD94,IF($A$1=$AF$1,AG94,IF($A$1=$AI$1,AJ94)))))))))))) -> -1591887.6
A95: Yusen İnci Loj. | B95: =-'Bütçe aylık-Eur'!$B$42 -> -871043.93 | C95: ='gerç aylık-eur'!$B$42 -> -958807.09 | E95: =-'Bütçe aylık-Eur'!$C$42 -> -858268.9 | F95: ='gerç aylık-eur'!$C$42 -> -880426.69 | H95: =-'Bütçe aylık-Eur'!$D$42 -> -844035.06 | I95: ='gerç aylık-eur'!$D$42 -> -742575.85 | K95: =-'Bütçe aylık-Eur'!$E$42 -> -1166019.9 | L95: ='gerç aylık-eur'!$E$42 -> -1078954 | N95: =-'Bütçe aylık-Eur'!$F$42 -> -1054675.1 | O95: ='gerç aylık-eur'!$F$42 -> -1220908.3 | Q95: =-'Bütçe aylık-Eur'!$G$42 -> -1010623.5 | R95: ='gerç aylık-eur'!$G$42 -> -889329.38 | T95: =-'Bütçe aylık-Eur'!$H$42 -> -997842.39 | U95: ='gerç aylık-eur'!$H$42 -> -798607.82 | W95: =-'Bütçe aylık-Eur'!$I$42 -> -981339.41 | X95: ='gerç aylık-eur'!$I$42 -> -796253.16 | Z95: =-'Bütçe aylık-Eur'!$J$42 -> -963750.11 | AA95: ='gerç aylık-eur'!$J$42 -> -786328.44 | AC95: =-'Bütçe aylık-Eur'!$K$42 -> -967838.18 | AD95: ='gerç aylık-eur'!$K$42 -> 0 | AF95: =-'Bütçe aylık-Eur'!$L$42 -> -950497.67 | AG95: ='gerç aylık-eur'!$L$42 -> 0 | AI95: =-'Bütçe aylık-Eur'!$M$42 -> -973653.49 | AJ95: ='gerç aylık-eur'!$M$42 -> 0 | AL95: =AP95-AO95 -> 177421.66 | AM95: =AP95/AO95-1 -> -0.18409509 | AO95: =IF($A$1=$B$1,B95,IF($A$1=$E$1,E95,IF($A$1=$H$1,H95,IF($A$1=$K$1,K95,IF($A$1=$N$1,N95,IF($A$1=$Q$1,Q95,IF($A$1=$T$1,T95,IF($A$1=$W$1,W95,IF($A$1=$Z$1,Z95,IF($A$1=$AC$1,AC95,IF($A$1=$AF$1,AF95,IF($A$1=$AI$1,AI95)))))))))))) -> -963750.11 | AP95: =IF($A$1=$B$1,C95,IF($A$1=$E$1,F95,IF($A$1=$H$1,I95,IF($A$1=$K$1,L95,IF($A$1=$N$1,O95,IF($A$1=$Q$1,R95,IF($A$1=$T$1,U95,IF($A$1=$W$1,X95,IF($A$1=$Z$1,AA95,IF($A$1=$AC$1,AD95,IF($A$1=$AF$1,AG95,IF($A$1=$AI$1,AJ95)))))))))))) -> -786328.44
A96: Jantaş | B96: =-'Bütçe aylık-Eur'!$B$43 -> -706181.54 | C96: ='gerç aylık-eur'!$B$43 -> -671544.15 | E96: =-'Bütçe aylık-Eur'!$C$43 -> -676130.13 | F96: ='gerç aylık-eur'!$C$43 -> -817810.99 | H96: =-'Bütçe aylık-Eur'!$D$43 -> -721036.06 | I96: ='gerç aylık-eur'!$D$43 -> -707904.8 | K96: =-'Bütçe aylık-Eur'!$E$43 -> -933968.82 | L96: ='gerç aylık-eur'!$E$43 -> -952352.63 | N96: =-'Bütçe aylık-Eur'!$F$43 -> -739044.16 | O96: ='gerç aylık-eur'!$F$43 -> -828014.35 | Q96: =-'Bütçe aylık-Eur'!$G$43 -> -706378.92 | R96: ='gerç aylık-eur'!$G$43 -> -648135.8 | T96: =-'Bütçe aylık-Eur'!$H$43 -> -673702.83 | U96: ='gerç aylık-eur'!$H$43 -> -607325.29 | W96: =-'Bütçe aylık-Eur'!$I$43 -> -571597.64 | X96: ='gerç aylık-eur'!$I$43 -> -450295.96 | Z96: =-'Bütçe aylık-Eur'!$J$43 -> -767792.37 | AA96: ='gerç aylık-eur'!$J$43 -> -594990.36 | AC96: =-'Bütçe aylık-Eur'!$K$43 -> -700722.59 | AD96: ='gerç aylık-eur'!$K$43 -> 0 | AF96: =-'Bütçe aylık-Eur'!$L$43 -> -675360.4 | AG96: ='gerç aylık-eur'!$L$43 -> 0 | AI96: =-'Bütçe aylık-Eur'!$M$43 -> -586387.74 | AJ96: ='gerç aylık-eur'!$M$43 -> 0 | AL96: =AP96-AO96 -> 172802.01 | AM96: =AP96/AO96-1 -> -0.22506346 | AO96: =IF($A$1=$B$1,B96,IF($A$1=$E$1,E96,IF($A$1=$H$1,H96,IF($A$1=$K$1,K96,IF($A$1=$N$1,N96,IF($A$1=$Q$1,Q96,IF($A$1=$T$1,T96,IF($A$1=$W$1,W96,IF($A$1=$Z$1,Z96,IF($A$1=$AC$1,AC96,IF($A$1=$AF$1,AF96,IF($A$1=$AI$1,AI96)))))))))))) -> -767792.37 | AP96: =IF($A$1=$B$1,C96,IF($A$1=$E$1,F96,IF($A$1=$H$1,I96,IF($A$1=$K$1,L96,IF($A$1=$N$1,O96,IF($A$1=$Q$1,R96,IF($A$1=$T$1,U96,IF($A$1=$W$1,X96,IF($A$1=$Z$1,AA96,IF($A$1=$AC$1,AD96,IF($A$1=$AF$1,AG96,IF($A$1=$AI$1,AJ96)))))))))))) -> -594990.36
A97: Çelik | B97: =-'Bütçe aylık-Eur'!$B$44 -> -400769.22 | C97: ='gerç aylık-eur'!$B$44 -> -411416.13 | E97: =-'Bütçe aylık-Eur'!$C$44 -> -366134.16 | F97: ='gerç aylık-eur'!$C$44 -> -487724.54 | H97: =-'Bütçe aylık-Eur'!$D$44 -> -438537.89 | I97: ='gerç aylık-eur'!$D$44 -> -279388.9 | K97: =-'Bütçe aylık-Eur'!$E$44 -> -457953.46 | L97: ='gerç aylık-eur'!$E$44 -> -687637.28 | N97: =-'Bütçe aylık-Eur'!$F$44 -> -430483.74 | O97: ='gerç aylık-eur'!$F$44 -> -491309.33 | Q97: =-'Bütçe aylık-Eur'!$G$44 -> -393969.2 | R97: ='gerç aylık-eur'!$G$44 -> -384841.35 | T97: =-'Bütçe aylık-Eur'!$H$44 -> -369606.68 | U97: ='gerç aylık-eur'!$H$44 -> -453411.52 | W97: =-'Bütçe aylık-Eur'!$I$44 -> -351328.89 | X97: ='gerç aylık-eur'!$I$44 -> -345208.7 | Z97: =-'Bütçe aylık-Eur'!$J$44 -> -433904.45 | AA97: ='gerç aylık-eur'!$J$44 -> -521905.66 | AC97: =-'Bütçe aylık-Eur'!$K$44 -> -411866.14 | AD97: ='gerç aylık-eur'!$K$44 -> 0 | AF97: =-'Bütçe aylık-Eur'!$L$44 -> -385059.25 | AG97: ='gerç aylık-eur'!$L$44 -> 0 | AI97: =-'Bütçe aylık-Eur'!$M$44 -> -334862.37 | AJ97: ='gerç aylık-eur'!$M$44 -> 0 | AL97: =AP97-AO97 -> -88001.21 | AM97: =AP97/AO97-1 -> 0.20281242 | AO97: =IF($A$1=$B$1,B97,IF($A$1=$E$1,E97,IF($A$1=$H$1,H97,IF($A$1=$K$1,K97,IF($A$1=$N$1,N97,IF($A$1=$Q$1,Q97,IF($A$1=$T$1,T97,IF($A$1=$W$1,W97,IF($A$1=$Z$1,Z97,IF($A$1=$AC$1,AC97,IF($A$1=$AF$1,AF97,IF($A$1=$AI$1,AI97)))))))))))) -> -433904.45 | AP97: =IF($A$1=$B$1,C97,IF($A$1=$E$1,F97,IF($A$1=$H$1,I97,IF($A$1=$K$1,L97,IF($A$1=$N$1,O97,IF($A$1=$Q$1,R97,IF($A$1=$T$1,U97,IF($A$1=$W$1,X97,IF($A$1=$Z$1,AA97,IF($A$1=$AC$1,AD97,IF($A$1=$AF$1,AG97,IF($A$1=$AI$1,AJ97)))))))))))) -> -521905.66
A98: Alüminyum | B98: =-'Bütçe aylık-Eur'!$B$45 -> -913898.94 | C98: ='gerç aylık-eur'!$B$45 -> -955273.81 | E98: =-'Bütçe aylık-Eur'!$C$45 -> -1044214.6 | F98: ='gerç aylık-eur'!$C$45 -> -1013060.2 | H98: =-'Bütçe aylık-Eur'!$D$45 -> -1045869.8 | I98: ='gerç aylık-eur'!$D$45 -> -996047.52 | K98: =-'Bütçe aylık-Eur'!$E$45 -> -985200.21 | L98: ='gerç aylık-eur'!$E$45 -> -998426.49 | N98: =-'Bütçe aylık-Eur'!$F$45 -> -1047680.8 | O98: ='gerç aylık-eur'!$F$45 -> -1087140.3 | Q98: =-'Bütçe aylık-Eur'!$G$45 -> -1037231.2 | R98: ='gerç aylık-eur'!$G$45 -> -881114.42 | T98: =-'Bütçe aylık-Eur'!$H$45 -> -1019589.1 | U98: ='gerç aylık-eur'!$H$45 -> -990961.82 | W98: =-'Bütçe aylık-Eur'!$I$45 -> -846842.58 | X98: ='gerç aylık-eur'!$I$45 -> -948586.86 | Z98: =-'Bütçe aylık-Eur'!$J$45 -> -1112255 | AA98: ='gerç aylık-eur'!$J$45 -> -989463.2 | AC98: =-'Bütçe aylık-Eur'!$K$45 -> -1025923.3 | AD98: ='gerç aylık-eur'!$K$45 -> 0 | AF98: =-'Bütçe aylık-Eur'!$L$45 -> -979128.56 | AG98: ='gerç aylık-eur'!$L$45 -> 0 | AI98: ='Bütçe aylık-Eur'!$M$45 -> 865812.69 | AJ98: ='gerç aylık-eur'!$M$45 -> 0 | AL98: =AP98-AO98 -> 122791.76 | AM98: =AP98/AO98-1 -> -0.11039893 | AO98: =IF($A$1=$B$1,B98,IF($A$1=$E$1,E98,IF($A$1=$H$1,H98,IF($A$1=$K$1,K98,IF($A$1=$N$1,N98,IF($A$1=$Q$1,Q98,IF($A$1=$T$1,T98,IF($A$1=$W$1,W98,IF($A$1=$Z$1,Z98,IF($A$1=$AC$1,AC98,IF($A$1=$AF$1,AF98,IF($A$1=$AI$1,AI98)))))))))))) -> -1112255 | AP98: =IF($A$1=$B$1,C98,IF($A$1=$E$1,F98,IF($A$1=$H$1,I98,IF($A$1=$K$1,L98,IF($A$1=$N$1,O98,IF($A$1=$Q$1,R98,IF($A$1=$T$1,U98,IF($A$1=$W$1,X98,IF($A$1=$Z$1,AA98,IF($A$1=$AC$1,AD98,IF($A$1=$AF$1,AG98,IF($A$1=$AI$1,AJ98)))))))))))) -> -989463.2
AO99: =IF($A$1=$B$1,B99,IF($A$1=$E$1,E99,IF($A$1=$H$1,H99,IF($A$1=$K$1,K99,IF($A$1=$N$1,N99,IF($A$1=$Q$1,Q99,IF($A$1=$T$1,T99,IF($A$1=$W$1,W99,IF($A$1=$Z$1,Z99,IF($A$1=$AC$1,AC99,IF($A$1=$AF$1,AF99,IF($A$1=$AI$1,AI99)))))))))))) -> 0 | AP99: =IF($A$1=$B$1,C99,IF($A$1=$E$1,F99,IF($A$1=$H$1,I99,IF($A$1=$K$1,L99,IF($A$1=$N$1,O99,IF($A$1=$Q$1,R99,IF($A$1=$T$1,U99,IF($A$1=$W$1,X99,IF($A$1=$Z$1,AA99,IF($A$1=$AC$1,AD99,IF($A$1=$AF$1,AG99,IF($A$1=$AI$1,AJ99)))))))))))) -> 0
A101: Operating expense/Sales
A102: İnci Holding | B102: =B91*-1/B9 -> 0.52965375 | C102: =C91*-1/C9 -> 0.50238117 | E102: =E91*-1/E9 -> 0.49698835 | F102: =F91*-1/F9 -> 0.57194523 | H102: =H91*-1/H9 -> 0.58506944 | I102: =I91*-1/I9 -> 0.57125891 | K102: =K91*-1/K9 -> 0.5461359 | L102: =L91*-1/L9 -> 0.80552748 | N102: =N91*-1/N9 -> 0.55008504 | O102: =O91*-1/O9 -> 0.45584034 | Q102: =Q91*-1/Q9 -> 0.53063227 | R102: =R91*-1/R9 -> 0.55473576 | T102: =T91*-1/T9 -> 0.4838238 | U102: =U91*-1/U9 -> 0.52325721 | W102: =W91*-1/W9 -> 0.51806469 | X102: =X91*-1/X9 -> 0.51833925 | Z102: =Z91*-1/Z9 -> 0.44935624 | AA102: =AA91*-1/AA9 -> 0.3941863 | AC102: =AC91*-1/AC9 -> 0.48718165 | AD102: =AD91*-1/AD9 -> #DIV/0! | AF102: =AF91*-1/AF9 -> 0.52697168 | AG102: =AG91*-1/AG9 -> #DIV/0! | AI102: =AI91*-1/AI9 -> 1.2960277 | AJ102: =AJ91*-1/AJ9 -> #DIV/0! | AM102: =AP102-AO102 -> -0.055169941 | AO102: =IF($A$1=$B$1,B102,IF($A$1=$E$1,E102,IF($A$1=$H$1,H102,IF($A$1=$K$1,K102,IF($A$1=$N$1,N102,IF($A$1=$Q$1,Q102,IF($A$1=$T$1,T102,IF($A$1=$W$1,W102,IF($A$1=$Z$1,Z102,IF($A$1=$AC$1,AC102,IF($A$1=$AF$1,AF102,IF($A$1=$AI$1,AI102)))))))))))) -> 0.44935624 | AP102: =IF($A$1=$B$1,C102,IF($A$1=$E$1,F102,IF($A$1=$H$1,I102,IF($A$1=$K$1,L102,IF($A$1=$N$1,O102,IF($A$1=$Q$1,R102,IF($A$1=$T$1,U102,IF($A$1=$W$1,X102,IF($A$1=$Z$1,AA102,IF($A$1=$AC$1,AD102,IF($A$1=$AF$1,AG102,IF($A$1=$AI$1,AJ102)))))))))))) -> 0.3941863
A103: ISM | B103: =B92*-1/B10 -> 0.20659051 | C103: =C92*-1/C10 -> 0.14328133 | E103: =E92*-1/E10 -> 0.17002482 | F103: =F92*-1/F10 -> 0.17369263 | H103: =H92*-1/H10 -> 0.17020038 | I103: =I92*-1/I10 -> 0.23493641 | K103: =K92*-1/K10 -> 0.16260045 | L103: =L92*-1/L10 -> 0.29616583 | N103: =N92*-1/N10 -> 0.15853111 | O103: =O92*-1/O10 -> 0.21061193 | Q103: =Q92*-1/Q10 -> 0.15901158 | R103: =R92*-1/R10 -> 0.2527831 | T103: =T92*-1/T10 -> 0.17386172 | U103: =U92*-1/U10 -> 0.20589679 | W103: =W92*-1/W10 -> 0.22178793 | X103: =X92*-1/X10 -> 0.22663587 | Z103: =Z92*-1/Z10 -> 0.21995627 | AA103: =AA92*-1/AA10 -> 0.30586298 | AC103: =AC92*-1/AC10 -> 0.2322529 | AD103: =AD92*-1/AD10 -> #DIV/0! | AF103: =AF92*-1/AF10 -> 0.26231685 | AG103: =AG92*-1/AG10 -> #DIV/0! | AI103: =AI92*-1/AI10 -> 0.28937654 | AJ103: =AJ92*-1/AJ10 -> #DIV/0! | AM103: =AP103-AO103 -> 0.085906702 | AO103: =IF($A$1=$B$1,B103,IF($A$1=$E$1,E103,IF($A$1=$H$1,H103,IF($A$1=$K$1,K103,IF($A$1=$N$1,N103,IF($A$1=$Q$1,Q103,IF($A$1=$T$1,T103,IF($A$1=$W$1,W103,IF($A$1=$Z$1,Z103,IF($A$1=$AC$1,AC103,IF($A$1=$AF$1,AF103,IF($A$1=$AI$1,AI103)))))))))))) -> 0.21995627 | AP103: =IF($A$1=$B$1,C103,IF($A$1=$E$1,F103,IF($A$1=$H$1,I103,IF($A$1=$K$1,L103,IF($A$1=$N$1,O103,IF($A$1=$Q$1,R103,IF($A$1=$T$1,U103,IF($A$1=$W$1,X103,IF($A$1=$Z$1,AA103,IF($A$1=$AC$1,AD103,IF($A$1=$AF$1,AG103,IF($A$1=$AI$1,AJ103)))))))))))) -> 0.30586298
A104: İncitaş | B104: =B93*-1/B11 -> 0.21218349 | C104: =C93*-1/C11 -> 0.12594004 | E104: =E93*-1/E11 -> 0.16806947 | F104: =F93*-1/F11 -> 0.11524532 | H104: =H93*-1/H11 -> 0.14881156 | I104: =I93*-1/I11 -> 0.11668109 | K104: =K93*-1/K11 -> 0.15814183 | L104: =L93*-1/L11 -> 0.11199311 | N104: =N93*-1/N11 -> 0.12598397 | O104: =O93*-1/O11 -> 0.16403093 | Q104: =Q93*-1/Q11 -> 0.12983351 | R104: =R93*-1/R11 -> 0.1409387 | T104: =T93*-1/T11 -> 0.1112203 | U104: =U93*-1/U11 -> 0.15525371 | W104: =W93*-1/W11 -> 0.13450747 | X104: =X93*-1/X11 -> 0.13022858 | Z104: =Z93*-1/Z11 -> 0.15074612 | AA104: =AA93*-1/AA11 -> 0.12970398 | AC104: =AC93*-1/AC11 -> 0.12879619 | AD104: =AD93*-1/AD11 -> #DIV/0! | AF104: =AF93*-1/AF11 -> 0.10573274 | AG104: =AG93*-1/AG11 -> #DIV/0! | AI104: =AI93*-1/AI11 -> 0.15220687 | AJ104: =AJ93*-1/AJ11 -> #DIV/0! | AM104: =AP104-AO104 -> -0.021042144 | AO104: =IF($A$1=$B$1,B104,IF($A$1=$E$1,E104,IF($A$1=$H$1,H104,IF($A$1=$K$1,K104,IF($A$1=$N$1,N104,IF($A$1=$Q$1,Q104,IF($A$1=$T$1,T104,IF($A$1=$W$1,W104,IF($A$1=$Z$1,Z104,IF($A$1=$AC$1,AC104,IF($A$1=$AF$1,AF104,IF($A$1=$AI$1,AI104)))))))))))) -> 0.15074612 | AP104: =IF($A$1=$B$1,C104,IF($A$1=$E$1,F104,IF($A$1=$H$1,I104,IF($A$1=$K$1,L104,IF($A$1=$N$1,O104,IF($A$1=$Q$1,R104,IF($A$1=$T$1,U104,IF($A$1=$W$1,X104,IF($A$1=$Z$1,AA104,IF($A$1=$AC$1,AD104,IF($A$1=$AF$1,AG104,IF($A$1=$AI$1,AJ104)))))))))))) -> 0.12970398
A105: İnci GS Yuasa | B105: =B94*-1/B12 -> 0.10800073 | C105: =C94*-1/C12 -> 0.097547817 | E105: =E94*-1/E12 -> 0.11696912 | F105: =F94*-1/F12 -> 0.15021618 | H105: =H94*-1/H12 -> 0.11750847 | I105: =I94*-1/I12 -> 0.18039572 | K105: =K94*-1/K12 -> 0.1162801 | L105: =L94*-1/L12 -> 0.16636942 | N105: =N94*-1/N12 -> 0.11246021 | O105: =O94*-1/O12 -> 0.13622122 | Q105: =Q94*-1/Q12 -> 0.11423772 | R105: =R94*-1/R12 -> 0.20291445 | T105: =T94*-1/T12 -> 0.1001584 | U105: =U94*-1/U12 -> 0.10242962 | W105: =W94*-1/W12 -> 0.10409886 | X105: =X94*-1/X12 -> 0.11792636 | Z105: =Z94*-1/Z12 -> 0.097206344 | AA105: =AA94*-1/AA12 -> 0.14794068 | AC105: =AC94*-1/AC12 -> 0.088429862 | AD105: =AD94*-1/AD12 -> #DIV/0! | AF105: =AF94*-1/AF12 -> 0.086507533 | AG105: =AG94*-1/AG12 -> #DIV/0! | AI105: =AI94*-1/AI12 -> 0.08979179 | AJ105: =AJ94*-1/AJ12 -> #DIV/0! | AM105: =AP105-AO105 -> 0.050734338 | AO105: =IF($A$1=$B$1,B105,IF($A$1=$E$1,E105,IF($A$1=$H$1,H105,IF($A$1=$K$1,K105,IF($A$1=$N$1,N105,IF($A$1=$Q$1,Q105,IF($A$1=$T$1,T105,IF($A$1=$W$1,W105,IF($A$1=$Z$1,Z105,IF($A$1=$AC$1,AC105,IF($A$1=$AF$1,AF105,IF($A$1=$AI$1,AI105)))))))))))) -> 0.097206344 | AP105: =IF($A$1=$B$1,C105,IF($A$1=$E$1,F105,IF($A$1=$H$1,I105,IF($A$1=$K$1,L105,IF($A$1=$N$1,O105,IF($A$1=$Q$1,R105,IF($A$1=$T$1,U105,IF($A$1=$W$1,X105,IF($A$1=$Z$1,AA105,IF($A$1=$AC$1,AD105,IF($A$1=$AF$1,AG105,IF($A$1=$AI$1,AJ105)))))))))))) -> 0.14794068
A106: Yusen İnci Loj. | B106: =B95*-1/B13 -> 0.13176997 | C106: =C95*-1/C13 -> 0.15941371 | E106: =E95*-1/E13 -> 0.12564043 | F106: =F95*-1/F13 -> 0.15473415 | H106: =H95*-1/H13 -> 0.12478084 | I106: =I95*-1/I13 -> 0.11557414 | K106: =K95*-1/K13 -> 0.17337901 | L106: =L95*-1/L13 -> 0.21199073 | N106: =N95*-1/N13 -> 0.15285297 | O106: =O95*-1/O13 -> 0.21715591 | Q106: =Q95*-1/Q13 -> 0.17885905 | R106: =R95*-1/R13 -> 0.20329399 | T106: =T95*-1/T13 -> 0.14493643 | U106: =U95*-1/U13 -> 0.15078462 | W106: =W95*-1/W13 -> 0.16211793 | X106: =X95*-1/X13 -> 0.17416454 | Z106: =Z95*-1/Z13 -> 0.16175117 | AA106: =AA95*-1/AA13 -> 0.14551814 | AC106: =AC95*-1/AC13 -> 0.12707331 | AD106: =AD95*-1/AD13 -> #DIV/0! | AF106: =AF95*-1/AF13 -> 0.14901576 | AG106: =AG95*-1/AG13 -> #DIV/0! | AI106: =AI95*-1/AI13 -> 0.15467318 | AJ106: =AJ95*-1/AJ13 -> #DIV/0! | AM106: =AP106-AO106 -> -0.01623303 | AO106: =IF($A$1=$B$1,B106,IF($A$1=$E$1,E106,IF($A$1=$H$1,H106,IF($A$1=$K$1,K106,IF($A$1=$N$1,N106,IF($A$1=$Q$1,Q106,IF($A$1=$T$1,T106,IF($A$1=$W$1,W106,IF($A$1=$Z$1,Z106,IF($A$1=$AC$1,AC106,IF($A$1=$AF$1,AF106,IF($A$1=$AI$1,AI106)))))))))))) -> 0.16175117 | AP106: =IF($A$1=$B$1,C106,IF($A$1=$E$1,F106,IF($A$1=$H$1,I106,IF($A$1=$K$1,L106,IF($A$1=$N$1,O106,IF($A$1=$Q$1,R106,IF($A$1=$T$1,U106,IF($A$1=$W$1,X106,IF($A$1=$Z$1,AA106,IF($A$1=$AC$1,AD106,IF($A$1=$AF$1,AG106,IF($A$1=$AI$1,AJ106)))))))))))) -> 0.14551814
A107: Jantaş | B107: =B96*-1/B14 -> 0.070275258 | C107: =C96*-1/C14 -> 0.057864201 | E107: =E96*-1/E14 -> 0.062446908 | F107: =F96*-1/F14 -> 0.07084827 | H107: =H96*-1/H14 -> 0.057265713 | I107: =I96*-1/I14 -> 0.056982856 | K107: =K96*-1/K14 -> 0.085430839 | L107: =L96*-1/L14 -> 0.07875112 | N107: =N96*-1/N14 -> 0.063290776 | O107: =O96*-1/O14 -> 0.065413824 | Q107: =Q96*-1/Q14 -> 0.059669968 | R107: =R96*-1/R14 -> 0.051946056 | T107: =T96*-1/T14 -> 0.071576922 | U107: =U96*-1/U14 -> 0.056386391 | W107: =W96*-1/W14 -> 0.060776916 | X107: =X96*-1/X14 -> 0.047079448 | Z107: =Z96*-1/Z14 -> 0.055413023 | AA107: =AA96*-1/AA14 -> 0.050360267 | AC107: =AC96*-1/AC14 -> 0.058404749 | AD107: =AD96*-1/AD14 -> #DIV/0! | AF107: =AF96*-1/AF14 -> 0.05909593 | AG107: =AG96*-1/AG14 -> #DIV/0! | AI107: =AI96*-1/AI14 -> 0.058719623 | AJ107: =AJ96*-1/AJ14 -> #DIV/0! | AM107: =AP107-AO107 -> -0.0050527569 | AO107: =IF($A$1=$B$1,B107,IF($A$1=$E$1,E107,IF($A$1=$H$1,H107,IF($A$1=$K$1,K107,IF($A$1=$N$1,N107,IF($A$1=$Q$1,Q107,IF($A$1=$T$1,T107,IF($A$1=$W$1,W107,IF($A$1=$Z$1,Z107,IF($A$1=$AC$1,AC107,IF($A$1=$AF$1,AF107,IF($A$1=$AI$1,AI107)))))))))))) -> 0.055413023 | AP107: =IF($A$1=$B$1,C107,IF($A$1=$E$1,F107,IF($A$1=$H$1,I107,IF($A$1=$K$1,L107,IF($A$1=$N$1,O107,IF($A$1=$Q$1,R107,IF($A$1=$T$1,U107,IF($A$1=$W$1,X107,IF($A$1=$Z$1,AA107,IF($A$1=$AC$1,AD107,IF($A$1=$AF$1,AG107,IF($A$1=$AI$1,AJ107)))))))))))) -> 0.050360267
A108: Çelik | B108: =B97*-1/B15 -> 0.052888617 | C108: =C97*-1/C15 -> 0.052539847 | E108: =E97*-1/E15 -> 0.05999183 | F108: =F97*-1/F15 -> 0.055849546 | H108: =H97*-1/H15 -> 0.054933479 | I108: =I97*-1/I15 -> 0.031218621 | K108: =K97*-1/K15 -> 0.057281721 | L108: =L97*-1/L15 -> 0.078350362 | N108: =N97*-1/N15 -> 0.054660957 | O108: =O97*-1/O15 -> 0.060702946 | Q108: =Q97*-1/Q15 -> 0.056768767 | R108: =R97*-1/R15 -> 0.053131482 | T108: =T97*-1/T15 -> 0.05644908 | U108: =U97*-1/U15 -> 0.056342026 | W108: =W97*-1/W15 -> 0.059843888 | X108: =X97*-1/X15 -> 0.053332452 | Z108: =Z97*-1/Z15 -> 0.052316288 | AA108: =AA97*-1/AA15 -> 0.054425459 | AC108: =AC97*-1/AC15 -> 0.052417777 | AD108: =AD97*-1/AD15 -> #DIV/0! | AF108: =AF97*-1/AF15 -> 0.052834249 | AG108: =AG97*-1/AG15 -> #DIV/0! | AI108: =AI97*-1/AI15 -> 0.060704558 | AJ108: =AJ97*-1/AJ15 -> #DIV/0! | AM108: =AP108-AO108 -> 0.0021091709 | AO108: =IF($A$1=$B$1,B108,IF($A$1=$E$1,E108,IF($A$1=$H$1,H108,IF($A$1=$K$1,K108,IF($A$1=$N$1,N108,IF($A$1=$Q$1,Q108,IF($A$1=$T$1,T108,IF($A$1=$W$1,W108,IF($A$1=$Z$1,Z108,IF($A$1=$AC$1,AC108,IF($A$1=$AF$1,AF108,IF($A$1=$AI$1,AI108)))))))))))) -> 0.052316288 | AP108: =IF($A$1=$B$1,C108,IF($A$1=$E$1,F108,IF($A$1=$H$1,I108,IF($A$1=$K$1,L108,IF($A$1=$N$1,O108,IF($A$1=$Q$1,R108,IF($A$1=$T$1,U108,IF($A$1=$W$1,X108,IF($A$1=$Z$1,AA108,IF($A$1=$AC$1,AD108,IF($A$1=$AF$1,AG108,IF($A$1=$AI$1,AJ108)))))))))))) -> 0.054425459
A109: Alüminyum | B109: =B98*-1/B16 -> 0.047341596 | C109: =C98*-1/C16 -> 0.042992754 | E109: =E98*-1/E16 -> 0.051317486 | F109: =F98*-1/F16 -> 0.050952793 | H109: =H98*-1/H16 -> 0.04680367 | I109: =I98*-1/I16 -> 0.045293526 | K109: =K98*-1/K16 -> 0.050923053 | L109: =L98*-1/L16 -> 0.045261816 | N109: =N98*-1/N16 -> 0.047988626 | O109: =O98*-1/O16 -> 0.04430491 | Q109: =Q98*-1/Q16 -> 0.048141944 | R109: =R98*-1/R16 -> 0.04192174 | T109: =T98*-1/T16 -> 0.047616691 | U109: =U98*-1/U16 -> 0.045815409 | W109: =W98*-1/W16 -> 0.050894444 | X109: =X98*-1/X16 -> 0.062977762 | Z109: =Z98*-1/Z16 -> 0.045902338 | AA109: =AA98*-1/AA16 -> 0.044010085 | AC109: =AC98*-1/AC16 -> 0.046047111 | AD109: =AD98*-1/AD16 -> #DIV/0! | AF109: =AF98*-1/AF16 -> 0.046609235 | AG109: =AG98*-1/AG16 -> #DIV/0! | AI109: =AI98*-1/AI16 -> -0.049784898 | AJ109: =AJ98*-1/AJ16 -> #DIV/0! | AM109: =AP109-AO109 -> -0.0018922525 | AO109: =IF($A$1=$B$1,B109,IF($A$1=$E$1,E109,IF($A$1=$H$1,H109,IF($A$1=$K$1,K109,IF($A$1=$N$1,N109,IF($A$1=$Q$1,Q109,IF($A$1=$T$1,T109,IF($A$1=$W$1,W109,IF($A$1=$Z$1,Z109,IF($A$1=$AC$1,AC109,IF($A$1=$AF$1,AF109,IF($A$1=$AI$1,AI109)))))))))))) -> 0.045902338 | AP109: =IF($A$1=$B$1,C109,IF($A$1=$E$1,F109,IF($A$1=$H$1,I109,IF($A$1=$K$1,L109,IF($A$1=$N$1,O109,IF($A$1=$Q$1,R109,IF($A$1=$T$1,U109,IF($A$1=$W$1,X109,IF($A$1=$Z$1,AA109,IF($A$1=$AC$1,AD109,IF($A$1=$AF$1,AG109,IF($A$1=$AI$1,AJ109)))))))))))) -> 0.044010085
A112: EBİT | B112: ='Bütçe aylık-Eur'!$B$59 -> 2548341.3 | C112: ='gerç aylık-eur'!$B$59 -> 2571901.4 | E112: ='Bütçe aylık-Eur'!$C$59 -> 2813658.4 | F112: ='gerç aylık-eur'!$C$59 -> 2366634.8 | H112: ='Bütçe aylık-Eur'!$D$59 -> 3397791.7 | I112: ='gerç aylık-eur'!$D$59 -> 2295778.2 | K112: ='Bütçe aylık-Eur'!$E$59 -> 2463292.4 | L112: ='gerç aylık-eur'!$E$59 -> 1581626.1 | N112: ='Bütçe aylık-Eur'!$F$59 -> 3406867.6 | O112: ='gerç aylık-eur'!$F$59 -> 2815395 | Q112: ='Bütçe aylık-Eur'!$G$59 -> 3028694.7 | R112: ='gerç aylık-eur'!$G$59 -> 1875232.4 | T112: ='Bütçe aylık-Eur'!$H$59 -> 3275757.3 | U112: ='gerç aylık-eur'!$H$59 -> 2495742.7 | W112: ='Bütçe aylık-Eur'!$I$59 -> 2011262.5 | X112: ='gerç aylık-eur'!$I$59 -> 1941782.5 | Z112: ='Bütçe aylık-Eur'!$J$59 -> 4940551.9 | AA112: ='gerç aylık-eur'!$J$59 -> 3992887.1 | AC112: ='Bütçe aylık-Eur'!$K$59 -> 4453100.8 | AD112: ='gerç aylık-eur'!$K$59 -> 0 | AF112: ='Bütçe aylık-Eur'!$L$59 -> 4350780.4 | AG112: ='gerç aylık-eur'!$L$59 -> 0 | AI112: ='Bütçe aylık-Eur'!$M$59 -> 3108297.5 | AJ112: ='gerç aylık-eur'!$M$59 -> 0 | AL112: =AP112-AO112 -> -947664.78 | AM112: =AP112/AO112-1 -> -0.19181355 | AO112: =IF($A$1=$B$1,B112,IF($A$1=$E$1,E112,IF($A$1=$H$1,H112,IF($A$1=$K$1,K112,IF($A$1=$N$1,N112,IF($A$1=$Q$1,Q112,IF($A$1=$T$1,T112,IF($A$1=$W$1,W112,IF($A$1=$Z$1,Z112,IF($A$1=$AC$1,AC112,IF($A$1=$AF$1,AF112,IF($A$1=$AI$1,AI112)))))))))))) -> 4940551.9 | AP112: =IF($A$1=$B$1,C112,IF($A$1=$E$1,F112,IF($A$1=$H$1,I112,IF($A$1=$K$1,L112,IF($A$1=$N$1,O112,IF($A$1=$Q$1,R112,IF($A$1=$T$1,U112,IF($A$1=$W$1,X112,IF($A$1=$Z$1,AA112,IF($A$1=$AC$1,AD112,IF($A$1=$AF$1,AG112,IF($A$1=$AI$1,AJ112)))))))))))) -> 3992887.1
AO113: =IF($A$1=$B$1,B113,IF($A$1=$E$1,E113,IF($A$1=$H$1,H113,IF($A$1=$K$1,K113,IF($A$1=$N$1,N113,IF($A$1=$Q$1,Q113,IF($A$1=$T$1,T113,IF($A$1=$W$1,W113,IF($A$1=$Z$1,Z113,IF($A$1=$AC$1,AC113,IF($A$1=$AF$1,AF113,IF($A$1=$AI$1,AI113)))))))))))) -> 0 | AP113: =IF($A$1=$B$1,C113,IF($A$1=$E$1,F113,IF($A$1=$H$1,I113,IF($A$1=$K$1,L113,IF($A$1=$N$1,O113,IF($A$1=$Q$1,R113,IF($A$1=$T$1,U113,IF($A$1=$W$1,X113,IF($A$1=$Z$1,AA113,IF($A$1=$AC$1,AD113,IF($A$1=$AF$1,AG113,IF($A$1=$AI$1,AJ113)))))))))))) -> 0
A114: Ebit by channels (100%)
A115: İnci Holding | B115: ='Bütçe aylık-Eur'!$B$60 -> 336241.53 | C115: ='gerç aylık-eur'!$B$60 -> 375501.84 | E115: ='Bütçe aylık-Eur'!$C$60 -> 363928.43 | F115: ='gerç aylık-eur'!$C$60 -> 310306.67 | H115: ='Bütçe aylık-Eur'!$D$60 -> 336214.88 | I115: ='gerç aylık-eur'!$D$60 -> 339284.91 | K115: ='Bütçe aylık-Eur'!$E$60 -> 337052.17 | L115: ='gerç aylık-eur'!$E$60 -> 133994.91 | N115: ='Bütçe aylık-Eur'!$F$60 -> 350825.78 | O115: ='gerç aylık-eur'!$F$60 -> 423563.46 | Q115: ='Bütçe aylık-Eur'!$G$60 -> 357907.67 | R115: ='gerç aylık-eur'!$G$60 -> 297600.14 | T115: ='Bütçe aylık-Eur'!$H$60 -> 390573.52 | U115: ='gerç aylık-eur'!$H$60 -> 347989.04 | W115: ='Bütçe aylık-Eur'!$I$60 -> 323470.31 | X115: ='gerç aylık-eur'!$I$60 -> 290820.85 | Z115: ='Bütçe aylık-Eur'!$J$60 -> 482341.42 | AA115: ='gerç aylık-eur'!$J$60 -> 478566.27 | AC115: ='Bütçe aylık-Eur'!$K$60 -> 436891.03 | AD115: ='gerç aylık-eur'!$K$60 -> 0 | AF115: ='Bütçe aylık-Eur'!$L$60 -> 386303.1 | AG115: ='gerç aylık-eur'!$L$60 -> 0 | AI115: ='Bütçe aylık-Eur'!$M$60 -> -215283.85 | AJ115: ='gerç aylık-eur'!$M$60 -> 0 | AL115: =AP115-AO115 -> -3775.1501 | AM115: =AP115/AO115-1 -> -0.0078267176 | AO115: =IF($A$1=$B$1,B115,IF($A$1=$E$1,E115,IF($A$1=$H$1,H115,IF($A$1=$K$1,K115,IF($A$1=$N$1,N115,IF($A$1=$Q$1,Q115,IF($A$1=$T$1,T115,IF($A$1=$W$1,W115,IF($A$1=$Z$1,Z115,IF($A$1=$AC$1,AC115,IF($A$1=$AF$1,AF115,IF($A$1=$AI$1,AI115)))))))))))) -> 482341.42 | AP115: =IF($A$1=$B$1,C115,IF($A$1=$E$1,F115,IF($A$1=$H$1,I115,IF($A$1=$K$1,L115,IF($A$1=$N$1,O115,IF($A$1=$Q$1,R115,IF($A$1=$T$1,U115,IF($A$1=$W$1,X115,IF($A$1=$Z$1,AA115,IF($A$1=$AC$1,AD115,IF($A$1=$AF$1,AG115,IF($A$1=$AI$1,AJ115)))))))))))) -> 478566.27
A116: ISM | B116: ='Bütçe aylık-Eur'!$B$61 -> -29542.151 | C116: ='gerç aylık-eur'!$B$61 -> -11554.724 | E116: ='Bütçe aylık-Eur'!$C$61 -> 83457.711 | F116: ='gerç aylık-eur'!$C$61 -> 38402.939 | H116: ='Bütçe aylık-Eur'!$D$61 -> 103073.46 | I116: ='gerç aylık-eur'!$D$61 -> 20517.967 | K116: ='Bütçe aylık-Eur'!$E$61 -> 170781.95 | L116: ='gerç aylık-eur'!$E$61 -> -19512.065 | N116: ='Bütçe aylık-Eur'!$F$61 -> 212579 | O116: ='gerç aylık-eur'!$F$61 -> 28290.327 | Q116: ='Bütçe aylık-Eur'!$G$61 -> 192807.7 | R116: ='gerç aylık-eur'!$G$61 -> 21275.11 | T116: ='Bütçe aylık-Eur'!$H$61 -> 145718.35 | U116: ='gerç aylık-eur'!$H$61 -> 50009.422 | W116: ='Bütçe aylık-Eur'!$I$61 -> 34312.91 | X116: ='gerç aylık-eur'!$I$61 -> 14937.167 | Z116: ='Bütçe aylık-Eur'!$J$61 -> 63323.927 | AA116: ='gerç aylık-eur'!$J$61 -> -34991.258 | AC116: ='Bütçe aylık-Eur'!$K$61 -> 21178.759 | AD116: ='gerç aylık-eur'!$K$61 -> 0 | AF116: ='Bütçe aylık-Eur'!$L$61 -> -6278.7083 | AG116: ='gerç aylık-eur'!$L$61 -> 0 | AI116: ='Bütçe aylık-Eur'!$M$61 -> -45621.219 | AJ116: ='gerç aylık-eur'!$M$61 -> 0 | AL116: =AP116-AO116 -> -98315.185 | AM116: =AP116/AO116-1 -> -1.5525756 | AO116: =IF($A$1=$B$1,B116,IF($A$1=$E$1,E116,IF($A$1=$H$1,H116,IF($A$1=$K$1,K116,IF($A$1=$N$1,N116,IF($A$1=$Q$1,Q116,IF($A$1=$T$1,T116,IF($A$1=$W$1,W116,IF($A$1=$Z$1,Z116,IF($A$1=$AC$1,AC116,IF($A$1=$AF$1,AF116,IF($A$1=$AI$1,AI116)))))))))))) -> 63323.927 | AP116: =IF($A$1=$B$1,C116,IF($A$1=$E$1,F116,IF($A$1=$H$1,I116,IF($A$1=$K$1,L116,IF($A$1=$N$1,O116,IF($A$1=$Q$1,R116,IF($A$1=$T$1,U116,IF($A$1=$W$1,X116,IF($A$1=$Z$1,AA116,IF($A$1=$AC$1,AD116,IF($A$1=$AF$1,AG116,IF($A$1=$AI$1,AJ116)))))))))))) -> -34991.258
A117: İncitaş | B117: ='Bütçe aylık-Eur'!$B$62 -> -44855.996 | C117: ='gerç aylık-eur'!$B$62 -> 33846.995 | E117: ='Bütçe aylık-Eur'!$C$62 -> 1757.8422 | F117: ='gerç aylık-eur'!$C$62 -> 31501.291 | H117: ='Bütçe aylık-Eur'!$D$62 -> 52378.441 | I117: ='gerç aylık-eur'!$D$62 -> 8643.2747 | K117: ='Bütçe aylık-Eur'!$E$62 -> 48931.767 | L117: ='gerç aylık-eur'!$E$62 -> 22120.22 | N117: ='Bütçe aylık-Eur'!$F$62 -> 103735.29 | O117: ='gerç aylık-eur'!$F$62 -> 32794.993 | Q117: ='Bütçe aylık-Eur'!$G$62 -> 103371.39 | R117: ='gerç aylık-eur'!$G$62 -> 15761.507 | T117: ='Bütçe aylık-Eur'!$H$62 -> 125800.4 | U117: ='gerç aylık-eur'!$H$62 -> 28534.431 | W117: ='Bütçe aylık-Eur'!$I$62 -> 97797.671 | X117: ='gerç aylık-eur'!$I$62 -> 22074.267 | Z117: ='Bütçe aylık-Eur'!$J$62 -> 74847.697 | AA117: ='gerç aylık-eur'!$J$62 -> 54811.77 | AC117: ='Bütçe aylık-Eur'!$K$62 -> 94242.594 | AD117: ='gerç aylık-eur'!$K$62 -> 0 | AF117: ='Bütçe aylık-Eur'!$L$62 -> 112652.13 | AG117: ='gerç aylık-eur'!$L$62 -> 0 | AI117: ='Bütçe aylık-Eur'!$M$62 -> 47137.958 | AJ117: ='gerç aylık-eur'!$M$62 -> 0 | AL117: =AP117-AO117 -> -20035.927 | AM117: =AP117/AO117-1 -> -0.26768929 | AO117: =IF($A$1=$B$1,B117,IF($A$1=$E$1,E117,IF($A$1=$H$1,H117,IF($A$1=$K$1,K117,IF($A$1=$N$1,N117,IF($A$1=$Q$1,Q117,IF($A$1=$T$1,T117,IF($A$1=$W$1,W117,IF($A$1=$Z$1,Z117,IF($A$1=$AC$1,AC117,IF($A$1=$AF$1,AF117,IF($A$1=$AI$1,AI117)))))))))))) -> 74847.697 | AP117: =IF($A$1=$B$1,C117,IF($A$1=$E$1,F117,IF($A$1=$H$1,I117,IF($A$1=$K$1,L117,IF($A$1=$N$1,O117,IF($A$1=$Q$1,R117,IF($A$1=$T$1,U117,IF($A$1=$W$1,X117,IF($A$1=$Z$1,AA117,IF($A$1=$AC$1,AD117,IF($A$1=$AF$1,AG117,IF($A$1=$AI$1,AJ117)))))))))))) -> 54811.77
A118: İnci GS Yuasa | B118: ='Bütçe aylık-Eur'!$B$63 -> 1410939 | C118: ='gerç aylık-eur'!$B$63 -> 1100435.1 | E118: ='Bütçe aylık-Eur'!$C$63 -> 1150468 | F118: ='gerç aylık-eur'!$C$63 -> 623144.13 | H118: ='Bütçe aylık-Eur'!$D$63 -> 1289135.3 | I118: ='gerç aylık-eur'!$D$63 -> -545129.68 | K118: ='Bütçe aylık-Eur'!$E$63 -> 1112249 | L118: ='gerç aylık-eur'!$E$63 -> -707341.21 | N118: ='Bütçe aylık-Eur'!$F$63 -> 1291185.3 | O118: ='gerç aylık-eur'!$F$63 -> -193990.88 | Q118: ='Bütçe aylık-Eur'!$G$63 -> 1554935.1 | R118: ='gerç aylık-eur'!$G$63 -> -880247.43 | T118: ='Bütçe aylık-Eur'!$H$63 -> 2001484.6 | U118: ='gerç aylık-eur'!$H$63 -> -444209.46 | W118: ='Bütçe aylık-Eur'!$I$63 -> 2182971.3 | X118: ='gerç aylık-eur'!$I$63 -> 684985.28 | Z118: ='Bütçe aylık-Eur'!$J$63 -> 2689843.1 | AA118: ='gerç aylık-eur'!$J$63 -> 55533.327 | AC118: ='Bütçe aylık-Eur'!$K$63 -> 3333238.9 | AD118: ='gerç aylık-eur'!$K$63 -> 0 | AF118: ='Bütçe aylık-Eur'!$L$63 -> 3469965 | AG118: ='gerç aylık-eur'!$L$63 -> 0 | AI118: ='Bütçe aylık-Eur'!$M$63 -> 4164449 | AJ118: ='gerç aylık-eur'!$M$63 -> 0 | AL118: =AP118-AO118 -> -2634309.8 | AM118: =AP118/AO118-1 -> -0.97935444 | AO118: =IF($A$1=$B$1,B118,IF($A$1=$E$1,E118,IF($A$1=$H$1,H118,IF($A$1=$K$1,K118,IF($A$1=$N$1,N118,IF($A$1=$Q$1,Q118,IF($A$1=$T$1,T118,IF($A$1=$W$1,W118,IF($A$1=$Z$1,Z118,IF($A$1=$AC$1,AC118,IF($A$1=$AF$1,AF118,IF($A$1=$AI$1,AI118)))))))))))) -> 2689843.1 | AP118: =IF($A$1=$B$1,C118,IF($A$1=$E$1,F118,IF($A$1=$H$1,I118,IF($A$1=$K$1,L118,IF($A$1=$N$1,O118,IF($A$1=$Q$1,R118,IF($A$1=$T$1,U118,IF($A$1=$W$1,X118,IF($A$1=$Z$1,AA118,IF($A$1=$AC$1,AD118,IF($A$1=$AF$1,AG118,IF($A$1=$AI$1,AJ118)))))))))))) -> 55533.327
A119: Yusen İnci Loj. | B119: ='Bütçe aylık-Eur'!$B$64 -> 434150.35 | C119: ='gerç aylık-eur'!$B$64 -> 248849.95 | E119: ='Bütçe aylık-Eur'!$C$64 -> 475670.74 | F119: ='gerç aylık-eur'!$C$64 -> 444716.21 | H119: ='Bütçe aylık-Eur'!$D$64 -> 442621.4 | I119: ='gerç aylık-eur'!$D$64 -> 444264.14 | K119: ='Bütçe aylık-Eur'!$E$64 -> 337.80857 | L119: ='gerç aylık-eur'!$E$64 -> -115385.37 | N119: ='Bütçe aylık-Eur'!$F$64 -> 178687.39 | O119: ='gerç aylık-eur'!$F$64 -> 26085.403 | Q119: ='Bütçe aylık-Eur'!$G$64 -> 92465.329 | R119: ='gerç aylık-eur'!$G$64 -> 65659.366 | T119: ='Bütçe aylık-Eur'!$H$64 -> 242217.72 | U119: ='gerç aylık-eur'!$H$64 -> 297928.29 | W119: ='Bütçe aylık-Eur'!$I$64 -> 283511.84 | X119: ='gerç aylık-eur'!$I$64 -> 312603.85 | Z119: ='Bütçe aylık-Eur'!$J$64 -> 273038.34 | AA119: ='gerç aylık-eur'!$J$64 -> 396692.93 | AC119: ='Bütçe aylık-Eur'!$K$64 -> 445221.25 | AD119: ='gerç aylık-eur'!$K$64 -> 0 | AF119: ='Bütçe aylık-Eur'!$L$64 -> 335165.94 | AG119: ='gerç aylık-eur'!$L$64 -> 0 | AI119: ='Bütçe aylık-Eur'!$M$64 -> 227764.31 | AJ119: ='gerç aylık-eur'!$M$64 -> 0 | AL119: =AP119-AO119 -> 123654.59 | AM119: =AP119/AO119-1 -> 0.4528836 | AO119: =IF($A$1=$B$1,B119,IF($A$1=$E$1,E119,IF($A$1=$H$1,H119,IF($A$1=$K$1,K119,IF($A$1=$N$1,N119,IF($A$1=$Q$1,Q119,IF($A$1=$T$1,T119,IF($A$1=$W$1,W119,IF($A$1=$Z$1,Z119,IF($A$1=$AC$1,AC119,IF($A$1=$AF$1,AF119,IF($A$1=$AI$1,AI119)))))))))))) -> 273038.34 | AP119: =IF($A$1=$B$1,C119,IF($A$1=$E$1,F119,IF($A$1=$H$1,I119,IF($A$1=$K$1,L119,IF($A$1=$N$1,O119,IF($A$1=$Q$1,R119,IF($A$1=$T$1,U119,IF($A$1=$W$1,X119,IF($A$1=$Z$1,AA119,IF($A$1=$AC$1,AD119,IF($A$1=$AF$1,AG119,IF($A$1=$AI$1,AJ119)))))))))))) -> 396692.93
A120: Jantaş | B120: ='Bütçe aylık-Eur'!$B$65 -> 584095.37 | C120: ='gerç aylık-eur'!$B$65 -> 724298.53 | E120: ='Bütçe aylık-Eur'!$C$65 -> 1073672.3 | F120: ='gerç aylık-eur'!$C$65 -> 1252984.1 | H120: ='Bütçe aylık-Eur'!$D$65 -> 2065118.1 | I120: ='gerç aylık-eur'!$D$65 -> 1694806.1 | K120: ='Bütçe aylık-Eur'!$E$65 -> 445536.75 | L120: ='gerç aylık-eur'!$E$65 -> 1310475.6 | N120: ='Bütçe aylık-Eur'!$F$65 -> 1140123.7 | O120: ='gerç aylık-eur'!$F$65 -> 1566825.8 | Q120: ='Bütçe aylık-Eur'!$G$65 -> 1424490.1 | R120: ='gerç aylık-eur'!$G$65 -> 1589156.6 | T120: ='Bütçe aylık-Eur'!$H$65 -> 494325.3 | U120: ='gerç aylık-eur'!$H$65 -> 1433792.2 | W120: ='Bütçe aylık-Eur'!$I$65 -> 106980.27 | X120: ='gerç aylık-eur'!$I$65 -> 1070880.5 | Z120: ='Bütçe aylık-Eur'!$J$65 -> 2454762.1 | AA120: ='gerç aylık-eur'!$J$65 -> 2432080.2 | AC120: ='Bütçe aylık-Eur'!$K$65 -> 1444831.6 | AD120: ='gerç aylık-eur'!$K$65 -> 0 | AF120: ='Bütçe aylık-Eur'!$L$65 -> 1461189.9 | AG120: ='gerç aylık-eur'!$L$65 -> 0 | AI120: ='Bütçe aylık-Eur'!$M$65 -> 1085032 | AJ120: ='gerç aylık-eur'!$M$65 -> 0 | AL120: =AP120-AO120 -> -22681.895 | AM120: =AP120/AO120-1 -> -0.0092399564 | AO120: =IF($A$1=$B$1,B120,IF($A$1=$E$1,E120,IF($A$1=$H$1,H120,IF($A$1=$K$1,K120,IF($A$1=$N$1,N120,IF($A$1=$Q$1,Q120,IF($A$1=$T$1,T120,IF($A$1=$W$1,W120,IF($A$1=$Z$1,Z120,IF($A$1=$AC$1,AC120,IF($A$1=$AF$1,AF120,IF($A$1=$AI$1,AI120)))))))))))) -> 2454762.1 | AP120: =IF($A$1=$B$1,C120,IF($A$1=$E$1,F120,IF($A$1=$H$1,I120,IF($A$1=$K$1,L120,IF($A$1=$N$1,O120,IF($A$1=$Q$1,R120,IF($A$1=$T$1,U120,IF($A$1=$W$1,X120,IF($A$1=$Z$1,AA120,IF($A$1=$AC$1,AD120,IF($A$1=$AF$1,AG120,IF($A$1=$AI$1,AJ120)))))))))))) -> 2432080.2
...

Sheet C-Döviz
A1: ='C-TRY'!A1 -> EYLÜL | B1: OCAK | E1: ŞUBAT | H1: MART | K1: NİSAN | N1: MAYIS | Q1: HAZİRAN | T1: TEMMUZ | W1: AĞUSTOS | Z1: EYLÜL | AC1: EKİM | AF1: KASIM | AI1: ARALIK
B2: Budget | C2: Actual | E2: Budget | F2: Actual | H2: Budget | I2: Actual | K2: Budget | L2: Actual | N2: Budget | O2: Actual | Q2: Budget | R2: Actual | T2: Budget | U2: Actual | W2: Budget | X2: Actual | Z2: Budget | AA2: Actual | AC2: Budget | AD2: Actual | AF2: Budget | AG2: Actual | AI2: Budget | AJ2: Actual | AL2: Difference | AM2: Variance % | AO2: Budget | AP2: Actual
A3: Eur Kapanış | B3: ='C-TRY'!B3 -> 37.515625 | C3: ='C-TRY'!C3 -> 37.1844 | D3: ='C-TRY'!D3 -> 0 | E3: ='C-TRY'!E3 -> 37.898438 | F3: ='C-TRY'!F3 -> 37.6442 | G3: ='C-TRY'!G3 -> 0 | H3: ='C-TRY'!H3 -> 38.28125 | I3: ='C-TRY'!I3 -> 38.663433 | K3: ='C-TRY'!K3 -> 38.664062 | L3: ='C-TRY'!L3 -> 39.919025 | M3: ='C-TRY'!M3 -> 0 | N3: ='C-TRY'!N3 -> 39.046875 | O3: ='C-TRY'!O3 -> 40.78934 | P3: ='C-TRY'!P3 -> 0 | Q3: ='C-TRY'!Q3 -> 39.429688 | R3: ='C-TRY'!R3 -> 41.749883 | T3: ='C-TRY'!T3 -> 39.8125 | U3: ='C-TRY'!U3 -> 42.466814 | W3: ='C-TRY'!W3 -> 40.195312 | X3: ='C-TRY'!X3 -> 43.131475 | Y3: ='C-TRY'!Y3 -> 0 | Z3: ='C-TRY'!Z3 -> 40.578125 | AA3: ='C-TRY'!AA3 -> 43.744411 | AC3: ='C-TRY'!AC3 -> 40.960938 | AD3: ='C-TRY'!AD3 -> #DIV/0! | AE3: ='C-TRY'!AE3 -> 0 | AF3: ='C-TRY'!AF3 -> 41.34375 | AG3: ='C-TRY'!AG3 -> #DIV/0! | AH3: ='C-TRY'!AH3 -> 0 | AI3: ='C-TRY'!AI3 -> 41.726562 | AJ3: ='C-TRY'!AJ3 -> #DIV/0! | AL3: =AP3-AO3 -> 3.1662861 | AM3: =AP3/AO3-1 -> 0.078029384 | AO3: =IF($A$1=$B$1,B3,IF($A$1=$E$1,E3,IF($A$1=$H$1,H3,IF($A$1=$K$1,K3,IF($A$1=$N$1,N3,IF($A$1=$Q$1,Q3,IF($A$1=$T$1,T3,IF($A$1=$W$1,W3,IF($A$1=$Z$1,Z3,IF($A$1=$AC$1,AC3,IF($A$1=$AF$1,AF3,IF($A$1=$AI$1,AI3)))))))))))) -> 40.578125 | AP3: =IF($A$1=$B$1,C3,IF($A$1=$E$1,F3,IF($A$1=$H$1,I3,IF($A$1=$K$1,L3,IF($A$1=$N$1,O3,IF($A$1=$Q$1,R3,IF($A$1=$T$1,U3,IF($A$1=$W$1,X3,IF($A$1=$Z$1,AA3,IF($A$1=$AC$1,AD3,IF($A$1=$AF$1,AG3,IF($A$1=$AI$1,AJ3)))))))))))) -> 43.744411
A4: Eur Ortalama | B4: ='C-TRY'!B4 -> 37.132812 | C4: ='C-TRY'!C4 -> 36.689261 | D4: ='C-TRY'!D4 -> 0 | E4: ='C-TRY'!E4 -> 37.515625 | F4: ='C-TRY'!F4 -> 37.133484 | G4: ='C-TRY'!G4 -> 0 | H4: ='C-TRY'!H4 -> 37.898438 | I4: ='C-TRY'!I4 -> 38.038946 | K4: ='C-TRY'!K4 -> 38.28125 | L4: ='C-TRY'!L4 -> 39.197504 | M4: ='C-TRY'!M4 -> 0 | N4: ='C-TRY'!N4 -> 38.664062 | O4: ='C-TRY'!O4 -> 40.083875 | P4: ='C-TRY'!P4 -> 0 | Q4: ='C-TRY'!Q4 -> 39.046875 | R4: ='C-TRY'!R4 -> 40.941097 | T4: ='C-TRY'!T4 -> 39.429688 | U4: ='C-TRY'!U4 -> 41.794399 | W4: ='C-TRY'!W4 -> 39.8125 | X4: ='C-TRY'!X4 -> 42.482912 | Y4: ='C-TRY'!Y4 -> 0 | Z4: ='C-TRY'!Z4 -> 40.195312 | AA4: ='C-TRY'!AA4 -> 43.133472 | AC4: ='C-TRY'!AC4 -> 40.578125 | AD4: ='C-TRY'!AD4 -> #DIV/0! | AE4: ='C-TRY'!AE4 -> 0 | AF4: ='C-TRY'!AF4 -> 40.960938 | AG4: ='C-TRY'!AG4 -> #DIV/0! | AH4: ='C-TRY'!AH4 -> 0 | AI4: ='C-TRY'!AI4 -> 41.34375 | AJ4: ='C-TRY'!AJ4 -> #DIV/0! | AL4: =AP4-AO4 -> 2.9381594 | AM4: =AP4/AO4-1 -> 0.073097066 | AO4: =IF($A$1=$B$1,B4,IF($A$1=$E$1,E4,IF($A$1=$H$1,H4,IF($A$1=$K$1,K4,IF($A$1=$N$1,N4,IF($A$1=$Q$1,Q4,IF($A$1=$T$1,T4,IF($A$1=$W$1,W4,IF($A$1=$Z$1,Z4,IF($A$1=$AC$1,AC4,IF($A$1=$AF$1,AF4,IF($A$1=$AI$1,AI4)))))))))))) -> 40.195312 | AP4: =IF($A$1=$B$1,C4,IF($A$1=$E$1,F4,IF($A$1=$H$1,I4,IF($A$1=$K$1,L4,IF($A$1=$N$1,O4,IF($A$1=$Q$1,R4,IF($A$1=$T$1,U4,IF($A$1=$W$1,X4,IF($A$1=$Z$1,AA4,IF($A$1=$AC$1,AD4,IF($A$1=$AF$1,AG4,IF($A$1=$AI$1,AJ4)))))))))))) -> 43.133472
A6: Net Sales | B6: ='A -Döviz'!B6 -> 27601026 | C6: ='A -Döviz'!C6 -> 30208401 | E6: =B6+'A -Döviz'!E6 -> 55701090 | F6: =C6+'A -Döviz'!F6 -> 57299908 | H6: =E6+'A -Döviz'!H6 -> 86804416 | I6: =F6+'A -Döviz'!I6 -> 85322097 | K6: =H6+'A -Döviz'!K6 -> 1.1570627e+08 | L6: =I6+'A -Döviz'!L6 -> 1.1192466e+08 | N6: =K6+'A -Döviz'!N6 -> 1.4570465e+08 | O6: =L6+'A -Döviz'!O6 -> 1.4022411e+08 | Q6: =N6+'A -Döviz'!Q6 -> 1.748247e+08 | R6: =O6+'A -Döviz'!R6 -> 1.6394262e+08 | T6: =Q6+'A -Döviz'!T6 -> 2.0467743e+08 | U6: =R6+'A -Döviz'!U6 -> 1.9114335e+08 | W6: =T6+'A -Döviz'!W6 -> 2.3100696e+08 | X6: =U6+'A -Döviz'!X6 -> 2.1306597e+08 | Z6: =W6+'A -Döviz'!Z6 -> 2.6388103e+08 | AA6: =X6+'A -Döviz'!AA6 -> 2.3922031e+08 | AC6: =Z6+'A -Döviz'!AC6 -> 2.9690929e+08 | AD6: =AA6+'A -Döviz'!AD6 -> 2.3922031e+08 | AF6: =AC6+'A -Döviz'!AF6 -> 3.2860113e+08 | AG6: =AD6+'A -Döviz'!AG6 -> 2.3922031e+08 | AI6: =AF6+'A -Döviz'!AI6 -> 3.5733087e+08 | AJ6: =AG6+'A -Döviz'!AJ6 -> 2.3922031e+08 | AL6: =AP6-AO6 -> -24660711 | AM6: =AP6/AO6-1 -> -0.0934539 | AO6: =IF($A$1=$B$1,B6,IF($A$1=$E$1,E6,IF($A$1=$H$1,H6,IF($A$1=$K$1,K6,IF($A$1=$N$1,N6,IF($A$1=$Q$1,Q6,IF($A$1=$T$1,T6,IF($A$1=$W$1,W6,IF($A$1=$Z$1,Z6,IF($A$1=$AC$1,AC6,IF($A$1=$AF$1,AF6,IF($A$1=$AI$1,AI6)))))))))))) -> 2.6388103e+08 | AP6: =IF($A$1=$B$1,C6,IF($A$1=$E$1,F6,IF($A$1=$H$1,I6,IF($A$1=$K$1,L6,IF($A$1=$N$1,O6,IF($A$1=$Q$1,R6,IF($A$1=$T$1,U6,IF($A$1=$W$1,X6,IF($A$1=$Z$1,AA6,IF($A$1=$AC$1,AD6,IF($A$1=$AF$1,AG6,IF($A$1=$AI$1,AJ6)))))))))))) -> 2.3922031e+08
A8: SALES BY CHANNELS(100% Satışlar) | AR8: =SUM(AR9:AR16) -> 2.3100696e+08 | AS8: =SUM(AS9:AS16) -> 2.3922031e+08
A9: İnci Holding | B9: ='A -Döviz'!B9 -> 714880.86 | C9: ='A -Döviz'!C9 -> 754597.33 | E9: =B9+'A -Döviz'!E9 -> 1438379.9 | F9: =C9+'A -Döviz'!F9 -> 1479520.2 | G9: =F9/E9-1 -> 0.028601819 | H9: =E9+'A -Döviz'!H9 -> 2248671.8 | I9: =F9+'A -Döviz'!I9 -> 2270871.7 | K9: =H9+'A -Döviz'!K9 -> 2991299.7 | L9: =I9+'A -Döviz'!L9 -> 2959888.9 | N9: =K9+'A -Döviz'!N9 -> 3771059.9 | O9: =L9+'A -Döviz'!O9 -> 3738269.7 | Q9: =N9+'A -Döviz'!Q9 -> 4533591.4 | R9: =O9+'A -Döviz'!R9 -> 4406637.2 | T9: =Q9+'A -Döviz'!T9 -> 5290258.5 | U9: =R9+'A -Döviz'!U9 -> 5136567.6 | W9: =T9+'A -Döviz'!W9 -> 5961448.8 | X9: =U9+'A -Döviz'!X9 -> 5740355.3 | Z9: =W9+'A -Döviz'!Z9 -> 6837407.9 | AA9: =X9+'A -Döviz'!AA9 -> 6530311.5 | AB9: =Z9/AA9-1 -> 0.0470263 | AC9: =Z9+'A -Döviz'!AC9 -> 7689349 | AD9: =AA9+'A -Döviz'!AD9 -> 6530311.5 | AF9: =AC9+'A -Döviz'!AF9 -> 8506008.6 | AG9: =AD9+'A -Döviz'!AG9 -> 6530311.5 | AI9: =AF9+'A -Döviz'!AI9 -> 9233250.9 | AJ9: =AG9+'A -Döviz'!AJ9 -> 6530311.5 | AL9: =AP9-AO9 -> -307096.39 | AM9: =AP9/AO9-1 -> -0.044914154 | AO9: =IF($A$1=$B$1,B9,IF($A$1=$E$1,E9,IF($A$1=$H$1,H9,IF($A$1=$K$1,K9,IF($A$1=$N$1,N9,IF($A$1=$Q$1,Q9,IF($A$1=$T$1,T9,IF($A$1=$W$1,W9,IF($A$1=$Z$1,Z9,IF($A$1=$AC$1,AC9,IF($A$1=$AF$1,AF9,IF($A$1=$AI$1,AI9)))))))))))) -> 6837407.9 | AP9: =IF($A$1=$B$1,C9,IF($A$1=$E$1,F9,IF($A$1=$H$1,I9,IF($A$1=$K$1,L9,IF($A$1=$N$1,O9,IF($A$1=$Q$1,R9,IF($A$1=$T$1,U9,IF($A$1=$W$1,X9,IF($A$1=$Z$1,AA9,IF($A$1=$AC$1,AD9,IF($A$1=$AF$1,AG9,IF($A$1=$AI$1,AJ9)))))))))))) -> 6530311.5 | AR9: =W9 -> 5961448.8 | AS9: =AD9 -> 6530311.5 | AT9: =AS9-AR9 -> 568862.73 | AV9: 9233250.8 | AW9: =AV9-AI9 -> -0.093858343
A10: ISM | B10: ='A -Döviz'!B10 -> 834190.48 | C10: ='A -Döviz'!C10 -> 881940.78 | E10: =B10+'A -Döviz'!E10 -> 1801691.7 | F10: =C10+'A -Döviz'!F10 -> 1818497.5 | G10: =F10/E10-1 -> 0.009327745 | H10: =E10+'A -Döviz'!H10 -> 2788307.7 | I10: =F10+'A -Döviz'!I10 -> 2514630 | K10: =H10+'A -Döviz'!K10 -> 3849123.7 | L10: =I10+'A -Döviz'!L10 -> 2981646.2 | N10: =K10+'A -Döviz'!N10 -> 4845834.3 | O10: =L10+'A -Döviz'!O10 -> 3686718.1 | Q10: =N10+'A -Döviz'!Q10 -> 5862910.3 | R10: =O10+'A -Döviz'!R10 -> 4320356.5 | T10: =Q10+'A -Döviz'!T10 -> 6717133.2 | U10: =R10+'A -Döviz'!U10 -> 5014012.6 | W10: =T10+'A -Döviz'!W10 -> 7313632.4 | X10: =U10+'A -Döviz'!X10 -> 5514483.9 | Z10: =W10+'A -Döviz'!Z10 -> 7944236.5 | AA10: =X10+'A -Döviz'!AA10 -> 5967934.9 | AB10: =Z10/AA10-1 -> 0.33115336 | AC10: =Z10+'A -Döviz'!AC10 -> 8482664.5 | AD10: =AA10+'A -Döviz'!AD10 -> 5967934.9 | AF10: =AC10+'A -Döviz'!AF10 -> 8967330.3 | AG10: =AD10+'A -Döviz'!AG10 -> 5967934.9 | AI10: =AF10+'A -Döviz'!AI10 -> 9399688.2 | AJ10: =AG10+'A -Döviz'!AJ10 -> 5967934.9 | AL10: =AP10-AO10 -> -1976301.7 | AM10: =AP10/AO10-1 -> -0.24877176 | AO10: =IF($A$1=$B$1,B10,IF($A$1=$E$1,E10,IF($A$1=$H$1,H10,IF($A$1=$K$1,K10,IF($A$1=$N$1,N10,IF($A$1=$Q$1,Q10,IF($A$1=$T$1,T10,IF($A$1=$W$1,W10,IF($A$1=$Z$1,Z10,IF($A$1=$AC$1,AC10,IF($A$1=$AF$1,AF10,IF($A$1=$AI$1,AI10)))))))))))) -> 7944236.5 | AP10: =IF($A$1=$B$1,C10,IF($A$1=$E$1,F10,IF($A$1=$H$1,I10,IF($A$1=$K$1,L10,IF($A$1=$N$1,O10,IF($A$1=$Q$1,R10,IF($A$1=$T$1,U10,IF($A$1=$W$1,X10,IF($A$1=$Z$1,AA10,IF($A$1=$AC$1,AD10,IF($A$1=$AF$1,AG10,IF($A$1=$AI$1,AJ10)))))))))))) -> 5967934.9 | AR10: =W10 -> 7313632.4 | AS10: =AD10 -> 5967934.9 | AT10: =AS10-AR10 -> -1345697.6 | AV10: 9248212 | AW10: =AV10-AI10 -> -151476.26
A11: İncitaş | B11: ='A -Döviz'!B11 -> 994090.62 | C11: ='A -Döviz'!C11 -> 967950.97 | E11: =B11+'A -Döviz'!E11 -> 1981498.8 | F11: =C11+'A -Döviz'!F11 -> 2006822.4 | G11: =F11/E11-1 -> 0.012780018 | H11: =E11+'A -Döviz'!H11 -> 3273885.5 | I11: =F11+'A -Döviz'!I11 -> 3525867.8 | K11: =H11+'A -Döviz'!K11 -> 4614783 | L11: =I11+'A -Döviz'!L11 -> 4791121 | N11: =K11+'A -Döviz'!N11 -> 6065885.2 | O11: =L11+'A -Döviz'!O11 -> 5538642.9 | Q11: =N11+'A -Döviz'!Q11 -> 7519237.3 | R11: =O11+'A -Döviz'!R11 -> 6438258.9 | T11: =Q11+'A -Döviz'!T11 -> 9302663.9 | U11: =R11+'A -Döviz'!U11 -> 7365456.6 | W11: =T11+'A -Döviz'!W11 -> 10739785 | X11: =U11+'A -Döviz'!X11 -> 8197111.9 | Z11: =W11+'A -Döviz'!Z11 -> 12154566 | AA11: =X11+'A -Döviz'!AA11 -> 9087786.7 | AB11: =Z11/AA11-1 -> 0.33746165 | AC11: =Z11+'A -Döviz'!AC11 -> 13609965 | AD11: =AA11+'A -Döviz'!AD11 -> 9087786.7 | AF11: =AC11+'A -Döviz'!AF11 -> 15340039 | AG11: =AD11+'A -Döviz'!AG11 -> 9087786.7 | AI11: =AF11+'A -Döviz'!AI11 -> 16822042 | AJ11: =AG11+'A -Döviz'!AJ11 -> 9087786.7 | AL11: =AP11-AO11 -> -3066779.5 | AM11: =AP11/AO11-1 -> -0.25231501 | AO11: =IF($A$1=$B$1,B11,IF($A$1=$E$1,E11,IF($A$1=$H$1,H11,IF($A$1=$K$1,K11,IF($A$1=$N$1,N11,IF($A$1=$Q$1,Q11,IF($A$1=$T$1,T11,IF($A$1=$W$1,W11,IF($A$1=$Z$1,Z11,IF($A$1=$AC$1,AC11,IF($A$1=$AF$1,AF11,IF($A$1=$AI$1,AI11)))))))))))) -> 12154566 | AP11: =IF($A$1=$B$1,C11,IF($A$1=$E$1,F11,IF($A$1=$H$1,I11,IF($A$1=$K$1,L11,IF($A$1=$N$1,O11,IF($A$1=$Q$1,R11,IF($A$1=$T$1,U11,IF($A$1=$W$1,X11,IF($A$1=$Z$1,AA11,IF($A$1=$AC$1,AD11,IF($A$1=$AF$1,AG11,IF($A$1=$AI$1,AJ11)))))))))))) -> 9087786.7 | AR11: =W11 -> 10739785 | AS11: =AD11 -> 9087786.7 | AT11: =AS11-AR11 -> -1651998.3 | AV11: 16822043 | AW11: =AV11-AI11 -> 0.8172366
A12: İnci GS Yuasa | B12: ='A -Döviz'!B12 -> 19103568 | C12: ='A -Döviz'!C12 -> 21339706 | D12: =+(C12/B12)-1 -> 0.11705345 | E12: =B12+'A -Döviz'!E12 -> 38548082 | F12: =C12+'A -Döviz'!F12 -> 36469375 | G12: =F12/E12-1 -> -0.053925041 | H12: =E12+'A -Döviz'!H12 -> 58898997 | I12: =F12+'A -Döviz'!I12 -> 49219924 | K12: =H12+'A -Döviz'!K12 -> 78293468 | L12: =I12+'A -Döviz'!L12 -> 61654941 | N12: =K12+'A -Döviz'!N12 -> 96936200 | O12: =L12+'A -Döviz'!O12 -> 75914418 | Q12: =N12+'A -Döviz'!Q12 -> 1.1568027e+08 | R12: =O12+'A -Döviz'!R12 -> 84593659 | T12: =Q12+'A -Döviz'!T12 -> 1.3756927e+08 | U12: =R12+'A -Döviz'!U12 -> 1.0097448e+08 | W12: =T12+'A -Döviz'!W12 -> 1.5866305e+08 | X12: =U12+'A -Döviz'!X12 -> 1.1526979e+08 | Z12: =W12+'A -Döviz'!Z12 -> 1.8120603e+08 | AA12: =X12+'A -Döviz'!AA12 -> 1.260301e+08 | AB12: =Z12/AA12-1 -> 0.43779962 | AC12: =Z12+'A -Döviz'!AC12 -> 2.0691096e+08 | AD12: =AA12+'A -Döviz'!AD12 -> 1.260301e+08 | AF12: =AC12+'A -Döviz'!AF12 -> 2.324601e+08 | AG12: =AD12+'A -Döviz'!AG12 -> 1.260301e+08 | AI12: =AF12+'A -Döviz'!AI12 -> 2.5849199e+08 | AJ12: =AG12+'A -Döviz'!AJ12 -> 1.260301e+08 | AL12: =AP12-AO12 -> -55175930 | AM12: =AP12/AO12-1 -> -0.30449279 | AN12: =AL12*0.4 -> -22070372 | AO12: =IF($A$1=$B$1,B12,IF($A$1=$E$1,E12,IF($A$1=$H$1,H12,IF($A$1=$K$1,K12,IF($A$1=$N$1,N12,IF($A$1=$Q$1,Q12,IF($A$1=$T$1,T12,IF($A$1=$W$1,W12,IF($A$1=$Z$1,Z12,IF($A$1=$AC$1,AC12,IF($A$1=$AF$1,AF12,IF($A$1=$AI$1,AI12)))))))))))) -> 1.8120603e+08 | AP12: =IF($A$1=$B$1,C12,IF($A$1=$E$1,F12,IF($A$1=$H$1,I12,IF($A$1=$K$1,L12,IF($A$1=$N$1,O12,IF($A$1=$Q$1,R12,IF($A$1=$T$1,U12,IF($A$1=$W$1,X12,IF($A$1=$Z$1,AA12,IF($A$1=$AC$1,AD12,IF($A$1=$AF$1,AG12,IF($A$1=$AI$1,AJ12)))))))))))) -> 1.260301e+08 | AR12: =W12*0.4 -> 63465218 | AS12: =AD12*0.4 -> 50412040 | AT12: =AS12-AR12 -> -13053178 | AV12: 2.5849199e+08 | AW12: =AV12-AI12 -> 3.2590704
A13: Yusen İnci Loj. | B13: ='A -Döviz'!B13 -> 6610337 | C13: ='A -Döviz'!C13 -> 6014583.7 | E13: =B13+'A -Döviz'!E13 -> 13441489 | F13: =C13+'A -Döviz'!F13 -> 11704515 | G13: =F13/E13-1 -> -0.12922482 | H13: =E13+'A -Döviz'!H13 -> 20205629 | I13: =F13+'A -Döviz'!I13 -> 18129619 | K13: =H13+'A -Döviz'!K13 -> 26930895 | L13: =I13+'A -Döviz'!L13 -> 23219247 | N13: =K13+'A -Döviz'!N13 -> 33830827 | O13: =L13+'A -Döviz'!O13 -> 28841513 | Q13: =N13+'A -Döviz'!Q13 -> 39481218 | R13: =O13+'A -Döviz'!R13 -> 33216110 | T13: =Q13+'A -Döviz'!T13 -> 46365908 | U13: =R13+'A -Döviz'!U13 -> 38512458 | W13: =T13+'A -Döviz'!W13 -> 52419152 | X13: =U13+'A -Döviz'!X13 -> 43084303 | Z13: =W13+'A -Döviz'!Z13 -> 58377379 | AA13: =X13+'A -Döviz'!AA13 -> 48487948 | AB13: =Z13/AA13-1 -> 0.20395646 | AC13: =Z13+'A -Döviz'!AC13 -> 65993756 | AD13: =AA13+'A -Döviz'!AD13 -> 48487948 | AF13: =AC13+'A -Döviz'!AF13 -> 72372260 | AG13: =AD13+'A -Döviz'!AG13 -> 48487948 | AI13: =AF13+'A -Döviz'!AI13 -> 78667168 | AJ13: =AG13+'A -Döviz'!AJ13 -> 48487948 | AL13: =AP13-AO13 -> -9889430.5 | AM13: =AP13/AO13-1 -> -0.16940518 | AN13: =AL13*0.4 -> -3955772.2 | AO13: =IF($A$1=$B$1,B13,IF($A$1=$E$1,E13,IF($A$1=$H$1,H13,IF($A$1=$K$1,K13,IF($A$1=$N$1,N13,IF($A$1=$Q$1,Q13,IF($A$1=$T$1,T13,IF($A$1=$W$1,W13,IF($A$1=$Z$1,Z13,IF($A$1=$AC$1,AC13,IF($A$1=$AF$1,AF13,IF($A$1=$AI$1,AI13)))))))))))) -> 58377379 | AP13: =IF($A$1=$B$1,C13,IF($A$1=$E$1,F13,IF($A$1=$H$1,I13,IF($A$1=$K$1,L13,IF($A$1=$N$1,O13,IF($A$1=$Q$1,R13,IF($A$1=$T$1,U13,IF($A$1=$W$1,X13,IF($A$1=$Z$1,AA13,IF($A$1=$AC$1,AD13,IF($A$1=$AF$1,AG13,IF($A$1=$AI$1,AJ13)))))))))))) -> 48487948 | AR13: =W13*0.4 -> 20967661 | AS13: =AD13*0.4 -> 19395179 | AT13: =AS13-AR13 -> -1572481.6 | AV13: 78339112 | AW13: =AV13-AI13 -> -328056.22 | AX13: 135771921
A14: Jantaş | B14: ='A -Döviz'!B14 -> 10048793 | C14: ='A -Döviz'!C14 -> 11605520 | E14: =B14+'A -Döviz'!E14 -> 20876073 | F14: =C14+'A -Döviz'!F14 -> 23148653 | G14: =F14/E14-1 -> 0.10886051 | H14: =E14+'A -Döviz'!H14 -> 33467134 | I14: =F14+'A -Döviz'!I14 -> 35571772 | K14: =H14+'A -Döviz'!K14 -> 44399589 | L14: =I14+'A -Döviz'!L14 -> 47664967 | N14: =K14+'A -Döviz'!N14 -> 56076554 | O14: =L14+'A -Döviz'!O14 -> 60323061 | Q14: =N14+'A -Döviz'!Q14 -> 67914651 | R14: =O14+'A -Döviz'!R14 -> 72800154 | T14: =Q14+'A -Döviz'!T14 -> 77326943 | U14: =R14+'A -Döviz'!U14 -> 83570932 | W14: =T14+'A -Döviz'!W14 -> 86731790 | X14: =U14+'A -Döviz'!X14 -> 93135529 | Z14: =W14+'A -Döviz'!Z14 -> 1.005876e+08 | AA14: =X14+'A -Döviz'!AA14 -> 1.0495021e+08 | AB14: =Z14/AA14-1 -> -0.041568348 | AC14: =Z14+'A -Döviz'!AC14 -> 1.125853e+08 | AD14: =AA14+'A -Döviz'!AD14 -> 1.0495021e+08 | AF14: =AC14+'A -Döviz'!AF14 -> 1.240135e+08 | AG14: =AD14+'A -Döviz'!AG14 -> 1.0495021e+08 | AI14: =AF14+'A -Döviz'!AI14 -> 1.3399974e+08 | AJ14: =AG14+'A -Döviz'!AJ14 -> 1.0495021e+08 | AL14: =AP14-AO14 -> 4362606.8 | AM14: =AP14/AO14-1 -> 0.043371218 | AN14: =AL14*0.4 -> 1745042.7 | AO14: =IF($A$1=$B$1,B14,IF($A$1=$E$1,E14,IF($A$1=$H$1,H14,IF($A$1=$K$1,K14,IF($A$1=$N$1,N14,IF($A$1=$Q$1,Q14,IF($A$1=$T$1,T14,IF($A$1=$W$1,W14,IF($A$1=$Z$1,Z14,IF($A$1=$AC$1,AC14,IF($A$1=$AF$1,AF14,IF($A$1=$AI$1,AI14)))))))))))) -> 1.005876e+08 | AP14: =IF($A$1=$B$1,C14,IF($A$1=$E$1,F14,IF($A$1=$H$1,I14,IF($A$1=$K$1,L14,IF($A$1=$N$1,O14,IF($A$1=$Q$1,R14,IF($A$1=$T$1,U14,IF($A$1=$W$1,X14,IF($A$1=$Z$1,AA14,IF($A$1=$AC$1,AD14,IF($A$1=$AF$1,AG14,IF($A$1=$AI$1,AJ14)))))))))))) -> 1.0495021e+08 | AR14: =W14*0.4 -> 34692716 | AS14: =AD14*0.4 -> 41980083 | AT14: =AS14-AR14 -> 7287367 | AV14: 1.3399974e+08 | AW14: =AV14-AI14 -> 0 | AX14: =AX13/30.77 -> 4412477.1
A15: Çelik | B15: ='A -Döviz'!B15 -> 7577608.3 | C15: ='A -Döviz'!C15 -> 7830554.3 | E15: =B15+'A -Döviz'!E15 -> 13680675 | F15: =C15+'A -Döviz'!F15 -> 16563383 | G15: =F15/E15-1 -> 0.21071388 | H15: =E15+'A -Döviz'!H15 -> 21663747 | I15: =F15+'A -Döviz'!I15 -> 25512815 | K15: =H15+'A -Döviz'!K15 -> 29658504 | L15: =I15+'A -Döviz'!L15 -> 34289255 | N15: =K15+'A -Döviz'!N15 -> 37534029 | O15: =L15+'A -Döviz'!O15 -> 42382920 | Q15: =N15+'A -Döviz'!Q15 -> 44473923 | R15: =O15+'A -Döviz'!R15 -> 49626109 | T15: =Q15+'A -Döviz'!T15 -> 51021535 | U15: =R15+'A -Döviz'!U15 -> 57673592 | W15: =T15+'A -Döviz'!W15 -> 56892292 | X15: =U15+'A -Döviz'!X15 -> 64146362 | Z15: =W15+'A -Döviz'!Z15 -> 65186161 | AA15: =X15+'A -Döviz'!AA15 -> 73735729 | AB15: =Z15/AA15-1 -> -0.11594878 | AC15: =Z15+'A -Döviz'!AC15 -> 73043536 | AD15: =AA15+'A -Döviz'!AD15 -> 73735729 | AF15: =AC15+'A -Döviz'!AF15 -> 80331597 | AG15: =AD15+'A -Döviz'!AG15 -> 73735729 | AI15: =AF15+'A -Döviz'!AI15 -> 85847861 | AJ15: =AG15+'A -Döviz'!AJ15 -> 73735729 | AL15: =AP15-AO15 -> 8549568.1 | AM15: =AP15/AO15-1 -> 0.13115618 | AN15: =AL15*0.4 -> 3419827.2 | AO15: =IF($A$1=$B$1,B15,IF($A$1=$E$1,E15,IF($A$1=$H$1,H15,IF($A$1=$K$1,K15,IF($A$1=$N$1,N15,IF($A$1=$Q$1,Q15,IF($A$1=$T$1,T15,IF($A$1=$W$1,W15,IF($A$1=$Z$1,Z15,IF($A$1=$AC$1,AC15,IF($A$1=$AF$1,AF15,IF($A$1=$AI$1,AI15)))))))))))) -> 65186161 | AP15: =IF($A$1=$B$1,C15,IF($A$1=$E$1,F15,IF($A$1=$H$1,I15,IF($A$1=$K$1,L15,IF($A$1=$N$1,O15,IF($A$1=$Q$1,R15,IF($A$1=$T$1,U15,IF($A$1=$W$1,X15,IF($A$1=$Z$1,AA15,IF($A$1=$AC$1,AD15,IF($A$1=$AF$1,AG15,IF($A$1=$AI$1,AJ15)))))))))))) -> 73735729 | AR15: =W15*0.4 -> 22756917 | AS15: =AD15*0.4 -> 29494292 | AT15: =AS15-AR15 -> 6737374.9 | AV15: 85847861 | AW15: =AV15-AI15 -> -4.4703484e-07
A16: Alüminyum | B16: ='A -Döviz'!B16 -> 19304354 | C16: ='A -Döviz'!C16 -> 22219414 | E16: =B16+'A -Döviz'!E16 -> 39652478 | F16: =C16+'A -Döviz'!F16 -> 42101743 | G16: =F16/E16-1 -> 0.061768251 | H16: =E16+'A -Döviz'!H16 -> 61998371 | I16: =F16+'A -Döviz'!I16 -> 64092690 | K16: =H16+'A -Döviz'!K16 -> 81345212 | L16: =I16+'A -Döviz'!L16 -> 86151603 | N16: =K16+'A -Döviz'!N16 -> 1.0317707e+08 | O16: =L16+'A -Döviz'!O16 -> 1.106893e+08 | Q16: =N16+'A -Döviz'!Q16 -> 1.2472234e+08 | R16: =O16+'A -Döviz'!R16 -> 1.3170738e+08 | T16: =Q16+'A -Döviz'!T16 -> 1.4613477e+08 | U16: =R16+'A -Döviz'!U16 -> 1.5333682e+08 | W16: =T16+'A -Döviz'!W16 -> 1.6277396e+08 | X16: =U16+'A -Döviz'!X16 -> 1.6839907e+08 | Z16: =W16+'A -Döviz'!Z16 -> 1.8700486e+08 | AA16: =X16+'A -Döviz'!AA16 -> 1.9088172e+08 | AB16: =Z16/AA16-1 -> -0.020310235 | AC16: =Z16+'A -Döviz'!AC16 -> 2.0928473e+08 | AD16: =AA16+'A -Döviz'!AD16 -> 1.9088172e+08 | AF16: =AC16+'A -Döviz'!AF16 -> 2.3029191e+08 | AG16: =AD16+'A -Döviz'!AG16 -> 1.9088172e+08 | AI16: =AF16+'A -Döviz'!AI16 -> 2.4768298e+08 | AJ16: =AG16+'A -Döviz'!AJ16 -> 1.9088172e+08 | AL16: =AP16-AO16 -> 3876852.5 | AM16: =AP16/AO16-1 -> 0.020731292 | AN16: =AL16*0.4 -> 1550741 | AO16: =IF($A$1=$B$1,B16,IF($A$1=$E$1,E16,IF($A$1=$H$1,H16,IF($A$1=$K$1,K16,IF($A$1=$N$1,N16,IF($A$1=$Q$1,Q16,IF($A$1=$T$1,T16,IF($A$1=$W$1,W16,IF($A$1=$Z$1,Z16,IF($A$1=$AC$1,AC16,IF($A$1=$AF$1,AF16,IF($A$1=$AI$1,AI16)))))))))))) -> 1.8700486e+08 | AP16: =IF($A$1=$B$1,C16,IF($A$1=$E$1,F16,IF($A$1=$H$1,I16,IF($A$1=$K$1,L16,IF($A$1=$N$1,O16,IF($A$1=$Q$1,R16,IF($A$1=$T$1,U16,IF($A$1=$W$1,X16,IF($A$1=$Z$1,AA16,IF($A$1=$AC$1,AD16,IF($A$1=$AF$1,AG16,IF($A$1=$AI$1,AJ16)))))))))))) -> 1.9088172e+08 | AR16: =W16*0.4 -> 65109586 | AS16: =AD16*0.4 -> 76352687 | AT16: =AS16-AR16 -> 11243101 | AV16: 2.4768298e+08 | AW16: =AV16-AI16 -> 0
L17: =L18-L16 -> 24537397 | AO17: =IF($A$1=$B$1,B17,IF($A$1=$E$1,E17,IF($A$1=$H$1,H17,IF($A$1=$K$1,K17,IF($A$1=$N$1,N17,IF($A$1=$Q$1,Q17,IF($A$1=$T$1,T17,IF($A$1=$W$1,W17,IF($A$1=$Z$1,Z17,IF($A$1=$AC$1,AC17,IF($A$1=$AF$1,AF17,IF($A$1=$AI$1,AI17)))))))))))) -> 0 | AP17: =IF($A$1=$B$1,C17,IF($A$1=$E$1,F17,IF($A$1=$H$1,I17,IF($A$1=$K$1,L17,IF($A$1=$N$1,O17,IF($A$1=$Q$1,R17,IF($A$1=$T$1,U17,IF($A$1=$W$1,X17,IF($A$1=$Z$1,AA17,IF($A$1=$AC$1,AD17,IF($A$1=$AF$1,AG17,IF($A$1=$AI$1,AJ17)))))))))))) -> 0
L18: 110689000 | AO18: =IF($A$1=$B$1,B18,IF($A$1=$E$1,E18,IF($A$1=$H$1,H18,IF($A$1=$K$1,K18,IF($A$1=$N$1,N18,IF($A$1=$Q$1,Q18,IF($A$1=$T$1,T18,IF($A$1=$W$1,W18,IF($A$1=$Z$1,Z18,IF($A$1=$AC$1,AC18,IF($A$1=$AF$1,AF18,IF($A$1=$AI$1,AI18)))))))))))) -> 0 | AP18: =IF($A$1=$B$1,C18,IF($A$1=$E$1,F18,IF($A$1=$H$1,I18,IF($A$1=$K$1,L18,IF($A$1=$N$1,O18,IF($A$1=$Q$1,R18,IF($A$1=$T$1,U18,IF($A$1=$W$1,X18,IF($A$1=$Z$1,AA18,IF($A$1=$AC$1,AD18,IF($A$1=$AF$1,AG18,IF($A$1=$AI$1,AJ18)))))))))))) -> 0
A19: SHARE OF SALES (%)
A20: İnci Holding | B20: =B9/B6 -> 0.025900517 | C20: =C9/C6 -> 0.024979718 | E20: =E9/E6 -> 0.025823191 | F20: =F9/F6 -> 0.025820638 | H20: =H9/H6 -> 0.025905039 | I20: =I9/I6 -> 0.026615282 | K20: =K9/K6 -> 0.025852529 | L20: =L9/L6 -> 0.026445368 | N20: =N9/N6 -> 0.025881534 | O20: =O9/O6 -> 0.02665925 | Q20: =Q9/Q6 -> 0.025932214 | R20: =R9/R6 -> 0.026879144 | T20: =T9/T6 -> 0.02584681 | U20: =U9/U6 -> 0.026872855 | W20: =W9/W6 -> 0.02580636 | X20: =X9/X6 -> 0.02694168 | Z20: =Z9/Z6 -> 0.025910949 | AA20: =AA9/AA6 -> 0.027298315 | AC20: =AC9/AC6 -> 0.025897974 | AD20: =AD9/AD6 -> 0.027298315 | AF20: =AF9/AF6 -> 0.025885512 | AG20: =AG9/AG6 -> 0.027298315 | AI20: =AI9/AI6 -> 0.025839499 | AJ20: =AJ9/AJ6 -> 0.027298315 | AL20: =AP20-AO20 -> 0.0013873656 | AO20: =IF($A$1=$B$1,B20,IF($A$1=$E$1,E20,IF($A$1=$H$1,H20,IF($A$1=$K$1,K20,IF($A$1=$N$1,N20,IF($A$1=$Q$1,Q20,IF($A$1=$T$1,T20,IF($A$1=$W$1,W20,IF($A$1=$Z$1,Z20,IF($A$1=$AC$1,AC20,IF($A$1=$AF$1,AF20,IF($A$1=$AI$1,AI20)))))))))))) -> 0.025910949 | AP20: =IF($A$1=$B$1,C20,IF($A$1=$E$1,F20,IF($A$1=$H$1,I20,IF($A$1=$K$1,L20,IF($A$1=$N$1,O20,IF($A$1=$Q$1,R20,IF($A$1=$T$1,U20,IF($A$1=$W$1,X20,IF($A$1=$Z$1,AA20,IF($A$1=$AC$1,AD20,IF($A$1=$AF$1,AG20,IF($A$1=$AI$1,AJ20)))))))))))) -> 0.027298315
A21: ISM | B21: =B10/B6 -> 0.030223169 | C21: =C10/C6 -> 0.029195216 | E21: =E10/E6 -> 0.032345718 | F21: =F10/F6 -> 0.031736481 | H21: =H10/H6 -> 0.032121726 | I21: =I10/I6 -> 0.029472201 | K21: =K10/K6 -> 0.033266336 | L21: =L10/L6 -> 0.026639761 | N21: =N10/N6 -> 0.033257925 | O21: =O10/O6 -> 0.026291612 | Q21: =Q10/Q6 -> 0.033535939 | R21: =R10/R6 -> 0.026352858 | T21: =T10/T6 -> 0.032818143 | U21: =U10/U6 -> 0.026231688 | W21: =W10/W6 -> 0.031659792 | X21: =X10/X6 -> 0.025881579 | Z21: =Z10/Z6 -> 0.030105372 | AA21: =AA10/AA6 -> 0.024947442 | AC21: =AC10/AC6 -> 0.028569886 | AD21: =AD10/AD6 -> 0.024947442 | AF21: =AF10/AF6 -> 0.027289408 | AG21: =AG10/AG6 -> 0.024947442 | AI21: =AI10/AI6 -> 0.026305279 | AJ21: =AJ10/AJ6 -> 0.024947442 | AL21: =AP21-AO21 -> -0.0051579306 | AO21: =IF($A$1=$B$1,B21,IF($A$1=$E$1,E21,IF($A$1=$H$1,H21,IF($A$1=$K$1,K21,IF($A$1=$N$1,N21,IF($A$1=$Q$1,Q21,IF($A$1=$T$1,T21,IF($A$1=$W$1,W21,IF($A$1=$Z$1,Z21,IF($A$1=$AC$1,AC21,IF($A$1=$AF$1,AF21,IF($A$1=$AI$1,AI21)))))))))))) -> 0.030105372 | AP21: =IF($A$1=$B$1,C21,IF($A$1=$E$1,F21,IF($A$1=$H$1,I21,IF($A$1=$K$1,L21,IF($A$1=$N$1,O21,IF($A$1=$Q$1,R21,IF($A$1=$T$1,U21,IF($A$1=$W$1,X21,IF($A$1=$Z$1,AA21,IF($A$1=$AC$1,AD21,IF($A$1=$AF$1,AG21,IF($A$1=$AI$1,AJ21)))))))))))) -> 0.024947442
A22: İncitaş | B22: =B11/B6 -> 0.036016437 | C22: =C11/C6 -> 0.032042444 | E22: =E11/E6 -> 0.035573789 | F22: =F11/F6 -> 0.035023134 | H22: =H11/H6 -> 0.037715656 | I22: =I11/I6 -> 0.041324205 | K22: =K11/K6 -> 0.039883602 | L22: =L11/L6 -> 0.04280666 | N22: =N11/N6 -> 0.041631377 | O22: =O11/O6 -> 0.039498505 | Q22: =Q11/Q6 -> 0.043010154 | R22: =R11/R6 -> 0.039271417 | T22: =T11/T6 -> 0.045450366 | U22: =U11/U6 -> 0.03853368 | W22: =W11/W6 -> 0.046491174 | X22: =X11/X6 -> 0.038472178 | Z22: =Z11/Z6 -> 0.046060781 | AA22: =AA11/AA6 -> 0.037989193 | AC22: =AC11/AC6 -> 0.045838798 | AD22: =AD11/AD6 -> 0.037989193 | AF22: =AF11/AF6 -> 0.046682856 | AG22: =AG11/AG6 -> 0.037989193 | AI22: =AI11/AI6 -> 0.047076935 | AJ22: =AJ11/AJ6 -> 0.037989193 | AL22: =AP22-AO22 -> -0.0080715883 | AO22: =IF($A$1=$B$1,B22,IF($A$1=$E$1,E22,IF($A$1=$H$1,H22,IF($A$1=$K$1,K22,IF($A$1=$N$1,N22,IF($A$1=$Q$1,Q22,IF($A$1=$T$1,T22,IF($A$1=$W$1,W22,IF($A$1=$Z$1,Z22,IF($A$1=$AC$1,AC22,IF($A$1=$AF$1,AF22,IF($A$1=$AI$1,AI22)))))))))))) -> 0.046060781 | AP22: =IF($A$1=$B$1,C22,IF($A$1=$E$1,F22,IF($A$1=$H$1,I22,IF($A$1=$K$1,L22,IF($A$1=$N$1,O22,IF($A$1=$Q$1,R22,IF($A$1=$T$1,U22,IF($A$1=$W$1,X22,IF($A$1=$Z$1,AA22,IF($A$1=$AC$1,AD22,IF($A$1=$AF$1,AG22,IF($A$1=$AI$1,AJ22)))))))))))) -> 0.037989193
A23: İnci GS Yuasa | B23: =B12*0.5/B6 -> 0.34606626 | C23: =C12*0.5/C6 -> 0.35320815 | E23: =E12*0.5/E6 -> 0.34602629 | F23: =F12*0.5/F6 -> 0.31823241 | H23: =H12*0.5/H6 -> 0.33926268 | I23: =I12*0.5/I6 -> 0.28843597 | K23: =K12*0.5/K6 -> 0.33832854 | L23: =L12*0.5/L6 -> 0.27543054 | N23: =N12*0.5/N6 -> 0.33264621 | O23: =O12*0.5/O6 -> 0.2706896 | Q23: =Q12*0.5/Q6 -> 0.33084647 | R23: =R12*0.5/R6 -> 0.25799777 | T23: =T12*0.5/T6 -> 0.33606362 | U23: =U12*0.5/U6 -> 0.26413286 | W23: =W12*0.5/W6 -> 0.34341615 | X23: =X12*0.5/X6 -> 0.27050258 | Z23: =Z12*0.5/Z6 -> 0.34334797 | AA23: =AA12*0.5/AA6 -> 0.26341848 | AC23: =AC12*0.4/AC6 -> 0.27875309 | AD23: =AD12*0.4/AD6 -> 0.21073478 | AF23: =AF12*0.4/AF6 -> 0.28296933 | AG23: =AG12*0.4/AG6 -> 0.21073478 | AI23: =AI12*0.5/AI6 -> 0.36169837 | AJ23: =AJ12*0.5/AJ6 -> 0.26341848 | AL23: =AP23-AO23 -> -0.0799295 | AO23: =IF($A$1=$B$1,B23,IF($A$1=$E$1,E23,IF($A$1=$H$1,H23,IF($A$1=$K$1,K23,IF($A$1=$N$1,N23,IF($A$1=$Q$1,Q23,IF($A$1=$T$1,T23,IF($A$1=$W$1,W23,IF($A$1=$Z$1,Z23,IF($A$1=$AC$1,AC23,IF($A$1=$AF$1,AF23,IF($A$1=$AI$1,AI23)))))))))))) -> 0.34334797 | AP23: =IF($A$1=$B$1,C23,IF($A$1=$E$1,F23,IF($A$1=$H$1,I23,IF($A$1=$K$1,L23,IF($A$1=$N$1,O23,IF($A$1=$Q$1,R23,IF($A$1=$T$1,U23,IF($A$1=$W$1,X23,IF($A$1=$Z$1,AA23,IF($A$1=$AC$1,AD23,IF($A$1=$AF$1,AG23,IF($A$1=$AI$1,AJ23)))))))))))) -> 0.26341848
A24: Yusen İnci Loj. | B24: =B13*0.4/B6 -> 0.095798424 | C24: =C13*0.4/C6 -> 0.079641207 | E24: =E13*0.4/E6 -> 0.096525861 | F24: =F13*0.4/F6 -> 0.081707043 | H24: =H13*0.4/H6 -> 0.093108762 | I24: =I13*0.4/I6 -> 0.084993779 | K24: =K13*0.4/K6 -> 0.093100898 | L24: =L13*0.4/L6 -> 0.082981701 | N24: =N13*0.4/N6 -> 0.092875079 | O24: =O13*0.4/O6 -> 0.082272619 | Q24: =Q13*0.4/Q6 -> 0.090333274 | R24: =R13*0.4/R6 -> 0.081043261 | T24: =T13*0.4/T6 -> 0.090612646 | U24: =U13*0.4/U6 -> 0.080593876 | W24: =W13*0.4/W6 -> 0.090766359 | X24: =X13*0.4/X6 -> 0.080884436 | Z24: =Z13*0.4/Z6 -> 0.088490453 | AA24: =AA13*0.4/AA6 -> 0.08107664 | AC24: =AC13*0.4/AC6 -> 0.088907634 | AD24: =AD13*0.4/AD6 -> 0.08107664 | AF24: =AF13*0.4/AF6 -> 0.088097397 | AG24: =AG13*0.4/AG6 -> 0.08107664 | AI24: =AI13*0.4/AI6 -> 0.088060869 | AJ24: =AJ13*0.4/AJ6 -> 0.08107664 | AL24: =AP24-AO24 -> -0.0074138131 | AO24: =IF($A$1=$B$1,B24,IF($A$1=$E$1,E24,IF($A$1=$H$1,H24,IF($A$1=$K$1,K24,IF($A$1=$N$1,N24,IF($A$1=$Q$1,Q24,IF($A$1=$T$1,T24,IF($A$1=$W$1,W24,IF($A$1=$Z$1,Z24,IF($A$1=$AC$1,AC24,IF($A$1=$AF$1,AF24,IF($A$1=$AI$1,AI24)))))))))))) -> 0.088490453 | AP24: =IF($A$1=$B$1,C24,IF($A$1=$E$1,F24,IF($A$1=$H$1,I24,IF($A$1=$K$1,L24,IF($A$1=$N$1,O24,IF($A$1=$Q$1,R24,IF($A$1=$T$1,U24,IF($A$1=$W$1,X24,IF($A$1=$Z$1,AA24,IF($A$1=$AC$1,AD24,IF($A$1=$AF$1,AG24,IF($A$1=$AI$1,AJ24)))))))))))) -> 0.08107664
A25: Jantaş | B25: =B14*0.4/B6 -> 0.14562927 | C25: =C14*0.4/C6 -> 0.15367275 | E25: =E14*0.4/E6 -> 0.14991501 | F25: =F14*0.4/F6 -> 0.16159644 | H25: =H14*0.4/H6 -> 0.15421858 | I25: =I14*0.4/I6 -> 0.16676464 | K25: =K14*0.4/K6 -> 0.15349069 | L25: =L14*0.4/L6 -> 0.17034661 | N25: =N14*0.4/N6 -> 0.15394582 | O25: =O14*0.4/O6 -> 0.17207614 | Q25: =Q14*0.4/Q6 -> 0.15538915 | R25: =R14*0.4/R6 -> 0.1776235 | T25: =T14*0.4/T6 -> 0.15111963 | U25: =U14*0.4/U6 -> 0.1748864 | W25: =W14*0.4/W6 -> 0.15018039 | X25: =X14*0.4/X6 -> 0.17484825 | Z25: =Z14*0.4/Z6 -> 0.15247417 | AA25: =AA14*0.4/AA6 -> 0.17548712 | AC25: =AC14*0.4/AC6 -> 0.15167636 | AD25: =AD14*0.4/AD6 -> 0.17548712 | AF25: =AF14*0.4/AF6 -> 0.15095932 | AG25: =AG14*0.4/AG6 -> 0.17548712 | AI25: =AI14*0.4/AI6 -> 0.15000074 | AJ25: =AJ14*0.4/AJ6 -> 0.17548712 | AL25: =AP25-AO25 -> 0.023012946 | AO25: =IF($A$1=$B$1,B25,IF($A$1=$E$1,E25,IF($A$1=$H$1,H25,IF($A$1=$K$1,K25,IF($A$1=$N$1,N25,IF($A$1=$Q$1,Q25,IF($A$1=$T$1,T25,IF($A$1=$W$1,W25,IF($A$1=$Z$1,Z25,IF($A$1=$AC$1,AC25,IF($A$1=$AF$1,AF25,IF($A$1=$AI$1,AI25)))))))))))) -> 0.15247417 | AP25: =IF($A$1=$B$1,C25,IF($A$1=$E$1,F25,IF($A$1=$H$1,I25,IF($A$1=$K$1,L25,IF($A$1=$N$1,O25,IF($A$1=$Q$1,R25,IF($A$1=$T$1,U25,IF($A$1=$W$1,X25,IF($A$1=$Z$1,AA25,IF($A$1=$AC$1,AD25,IF($A$1=$AF$1,AG25,IF($A$1=$AI$1,AJ25)))))))))))) -> 0.17548712
